{
  "type": "Feature",
  "properties": {
    "gn:admin1_code":"05",
    "gn:asciiname":"Cuchilla Enserrada",
    "gn:country_code":"HN",
    "gn:dem":652,
    "gn:feature_class":"P",
    "gn:feature_code":"PPL",
    "gn:name":"Cuchilla Enserrada",
    "gn:population":0,
    "gn:timezone":"America/Tegucigalpa",
    "iso:country":"HN",
    "wof:name":"Cuchilla Enserrada",
    "wof:placetype":"locality"
},
  "geometry": {"coordinates":[-88.88333,15.01667],"type":"Point"}
}