{
  "type": "Feature",
  "properties": {
    "gn:admin1_code":"02",
    "gn:asciiname":"Plan de Acosta",
    "gn:country_code":"HN",
    "gn:dem":629,
    "gn:feature_class":"P",
    "gn:feature_code":"PPL",
    "gn:name":"Plan de Acosta",
    "gn:population":0,
    "gn:timezone":"America/Tegucigalpa",
    "iso:country":"HN",
    "wof:name":"Plan de Acosta",
    "wof:placetype":"locality"
},
  "geometry": {"coordinates":[-87.03721999999998,13.26056],"type":"Point"}
}