{
  "type": "Feature",
  "properties": {
    "gn:admin1_code":"02",
    "gn:asciiname":"La Vuelta del Muerto",
    "gn:country_code":"HN",
    "gn:dem":8,
    "gn:feature_class":"P",
    "gn:feature_code":"PPL",
    "gn:name":"La Vuelta del Muerto",
    "gn:population":0,
    "gn:timezone":"America/Tegucigalpa",
    "iso:country":"HN",
    "wof:name":"La Vuelta del Muerto",
    "wof:placetype":"locality"
},
  "geometry": {"coordinates":[-87.39944,13.16083],"type":"Point"}
}