{
  "type": "Feature",
  "properties": {
    "gn:admin1_code":"02",
    "gn:asciiname":"El Jicaral",
    "gn:country_code":"HN",
    "gn:dem":139,
    "gn:feature_class":"P",
    "gn:feature_code":"PPL",
    "gn:name":"El Jicaral",
    "gn:population":0,
    "gn:timezone":"America/Tegucigalpa",
    "iso:country":"HN",
    "wof:name":"El Jicaral",
    "wof:placetype":"locality"
},
  "geometry": {"coordinates":[-87.38221999999998,13.66917],"type":"Point"}
}