{
  "type": "Feature",
  "properties": {
    "gn:admin1_code":"18",
    "gn:asciiname":"La Union",
    "gn:country_code":"HN",
    "gn:dem":879,
    "gn:feature_class":"P",
    "gn:feature_code":"PPL",
    "gn:name":"La Uni\u00f3n",
    "gn:population":0,
    "gn:timezone":"America/Tegucigalpa",
    "iso:country":"HN",
    "wof:name":"La Union",
    "wof:placetype":"locality"
},
  "geometry": {"coordinates":[-87.51666999999998,15.08333],"type":"Point"}
}