{
  "type": "Feature",
  "properties": {
    "gn:admin1_code":"12",
    "gn:asciiname":"Canas",
    "gn:country_code":"HN",
    "gn:dem":345,
    "gn:feature_class":"P",
    "gn:feature_code":"PPL",
    "gn:name":"Ca\u00f1as",
    "gn:population":0,
    "gn:timezone":"America/Tegucigalpa",
    "iso:country":"HN",
    "name:ceb_x_preferred":[
        "Canas"
    ],
    "name:deu_x_preferred":[
        "Canas"
    ],
    "name:nld_x_preferred":[
        "Canas"
    ],
    "name:por_x_preferred":[
        "Canas"
    ],
    "name:ron_x_preferred":[
        "Canas"
    ],
    "name:rus_x_preferred":[
        "\u041a\u0430\u043d\u0430\u0441"
    ],
    "name:swe_x_preferred":[
        "Canas"
    ],
    "wof:name":"Canas",
    "wof:placetype":"locality"
},
  "geometry": {"coordinates":[-87.66667,13.88333],"type":"Point"}
}