{
  "type": "Feature",
  "properties": {
    "gn:admin1_code":"08",
    "gn:asciiname":"Colonia La Rosa",
    "gn:country_code":"HN",
    "gn:dem":1011,
    "gn:feature_class":"P",
    "gn:feature_code":"PPL",
    "gn:name":"Colonia La Rosa",
    "gn:population":0,
    "gn:timezone":"America/Tegucigalpa",
    "iso:country":"HN",
    "wof:name":"Colonia La Rosa",
    "wof:placetype":"locality"
},
  "geometry": {"coordinates":[-87.22583,14.06575],"type":"Point"}
}