{
  "type": "Feature",
  "properties": {
    "gn:admin1_code":"01",
    "gn:asciiname":"Zambuco",
    "gn:cc2":"HN",
    "gn:country_code":"HN",
    "gn:dem":9,
    "gn:feature_class":"P",
    "gn:feature_code":"PPL",
    "gn:name":"Zambuco",
    "gn:population":0,
    "gn:timezone":"America/Tegucigalpa",
    "iso:country":"HN",
    "name:und_x_variant":[
        "Sambuco",
        "Zambuco"
    ],
    "wof:name":"Zambuco",
    "wof:placetype":"locality"
},
  "geometry": {"coordinates":[-87.26666999999998,15.76667],"type":"Point"}
}