{
  "type": "Feature",
  "properties": {
    "gn:admin1_code":"02",
    "gn:asciiname":"La Culebra",
    "gn:country_code":"HN",
    "gn:dem":165,
    "gn:feature_class":"P",
    "gn:feature_code":"PPL",
    "gn:name":"La Culebra",
    "gn:population":0,
    "gn:timezone":"America/Tegucigalpa",
    "iso:country":"HN",
    "wof:name":"La Culebra",
    "wof:placetype":"locality"
},
  "geometry": {"coordinates":[-87.35972,13.61417],"type":"Point"}
}