{
  "type": "Feature",
  "properties": {
    "gn:admin1_code":"13",
    "gn:asciiname":"Gualcincora",
    "gn:cc2":"HN",
    "gn:country_code":"HN",
    "gn:dem":318,
    "gn:feature_class":"P",
    "gn:feature_code":"PPL",
    "gn:name":"Gualcincora",
    "gn:population":0,
    "gn:timezone":"America/Tegucigalpa",
    "iso:country":"HN",
    "name:und_x_variant":[
        "Guatincora",
        "Guaquincora",
        "Gualcincora"
    ],
    "wof:name":"Gualcincora",
    "wof:placetype":"locality"
},
  "geometry": {"coordinates":[-88.53333000000001,14.01667],"type":"Point"}
}