{
  "type": "Feature",
  "properties": {
    "gn:admin1_code":"07",
    "gn:asciiname":"El Portillo",
    "gn:country_code":"HN",
    "gn:dem":799,
    "gn:feature_class":"P",
    "gn:feature_code":"PPL",
    "gn:name":"El Portillo",
    "gn:population":0,
    "gn:timezone":"America/Tegucigalpa",
    "iso:country":"HN",
    "wof:name":"El Portillo",
    "wof:placetype":"locality"
},
  "geometry": {"coordinates":[-87.18389000000001,13.62667],"type":"Point"}
}