{
  "type": "Feature",
  "properties": {
    "gn:admin1_code":"17",
    "gn:asciiname":"Las Trojitas",
    "gn:country_code":"HN",
    "gn:dem":457,
    "gn:feature_class":"P",
    "gn:feature_code":"PPL",
    "gn:name":"Las Trojitas",
    "gn:population":0,
    "gn:timezone":"America/Tegucigalpa",
    "iso:country":"HN",
    "wof:name":"Las Trojitas",
    "wof:placetype":"locality"
},
  "geometry": {"coordinates":[-87.63333,13.76667],"type":"Point"}
}