{
  "type": "Feature",
  "properties": {
    "gn:admin1_code":"04",
    "gn:asciiname":"Ventanas",
    "gn:country_code":"HN",
    "gn:dem":1020,
    "gn:feature_class":"P",
    "gn:feature_code":"PPL",
    "gn:name":"Ventanas",
    "gn:population":0,
    "gn:timezone":"America/Tegucigalpa",
    "iso:country":"HN",
    "name:fas_x_preferred":[
        "\u0648\u0646\u062a\u0646\u0633"
    ],
    "name:pol_x_preferred":[
        "Ventanas"
    ],
    "name:que_x_preferred":[
        "Ventanas"
    ],
    "name:ron_x_preferred":[
        "Ventanas"
    ],
    "name:spa_x_preferred":[
        "Ventanas"
    ],
    "wof:name":"Ventanas",
    "wof:placetype":"locality"
},
  "geometry": {"coordinates":[-87.40000000000001,14.78333],"type":"Point"}
}