{
  "type": "Feature",
  "properties": {
    "gn:admin1_code":"06",
    "gn:asciiname":"Terrero",
    "gn:country_code":"HN",
    "gn:dem":804,
    "gn:feature_class":"P",
    "gn:feature_code":"PPL",
    "gn:name":"Terrero",
    "gn:population":0,
    "gn:timezone":"America/Tegucigalpa",
    "iso:country":"HN",
    "wof:name":"Terrero",
    "wof:placetype":"locality"
},
  "geometry": {"coordinates":[-88.05,15.08333],"type":"Point"}
}