{
  "type": "Feature",
  "properties": {
    "gn:admin1_code":"17",
    "gn:asciiname":"La Poza",
    "gn:country_code":"HN",
    "gn:dem":12,
    "gn:feature_class":"P",
    "gn:feature_code":"PPL",
    "gn:name":"La Poza",
    "gn:population":0,
    "gn:timezone":"America/Tegucigalpa",
    "iso:country":"HN",
    "wof:name":"La Poza",
    "wof:placetype":"locality"
},
  "geometry": {"coordinates":[-87.61583,13.25944],"type":"Point"}
}