{
  "type": "Feature",
  "properties": {
    "gn:admin1_code":"04",
    "gn:asciiname":"Las Pitas",
    "gn:country_code":"HN",
    "gn:dem":1090,
    "gn:feature_class":"P",
    "gn:feature_code":"PPL",
    "gn:name":"Las Pitas",
    "gn:population":0,
    "gn:timezone":"America/Tegucigalpa",
    "iso:country":"HN",
    "wof:name":"Las Pitas",
    "wof:placetype":"locality"
},
  "geometry": {"coordinates":[-87.55,14.11667],"type":"Point"}
}