{
  "type": "Feature",
  "properties": {
    "gn:admin1_code":"02",
    "gn:asciiname":"Limonar",
    "gn:country_code":"HN",
    "gn:dem":39,
    "gn:feature_class":"P",
    "gn:feature_code":"PPL",
    "gn:name":"Limonar",
    "gn:population":0,
    "gn:timezone":"America/Tegucigalpa",
    "iso:country":"HN",
    "name:fra_x_preferred":[
        "Limonar"
    ],
    "name:hat_x_preferred":[
        "Limonar"
    ],
    "name:ita_x_preferred":[
        "Limonar"
    ],
    "name:kat_x_preferred":[
        "\u10da\u10d8\u10db\u10dd\u10dc\u10d0\u10e0\u10d8"
    ],
    "name:por_x_preferred":[
        "Limonar"
    ],
    "name:sco_x_preferred":[
        "Limonar"
    ],
    "name:spa_x_preferred":[
        "Limonar"
    ],
    "name:vie_x_preferred":[
        "Limonar"
    ],
    "name:zho_x_preferred":[
        "\u5229\u83ab\u7d0d\u723e"
    ],
    "wof:name":"Limonar",
    "wof:placetype":"locality"
},
  "geometry": {"coordinates":[-87.29916999999998,13.34361],"type":"Point"}
}