{
  "type": "Feature",
  "properties": {
    "gn:admin1_code":"12",
    "gn:asciiname":"Talpetate",
    "gn:country_code":"HN",
    "gn:dem":1279,
    "gn:feature_class":"P",
    "gn:feature_code":"PPL",
    "gn:name":"Talpetate",
    "gn:population":0,
    "gn:timezone":"America/Tegucigalpa",
    "iso:country":"HN",
    "wof:name":"Talpetate",
    "wof:placetype":"locality"
},
  "geometry": {"coordinates":[-87.75,14.26667],"type":"Point"}
}