{
  "type": "Feature",
  "properties": {
    "gn:admin1_code":"08",
    "gn:asciiname":"Chaguite Arriba",
    "gn:country_code":"HN",
    "gn:dem":1003,
    "gn:feature_class":"P",
    "gn:feature_code":"PPL",
    "gn:name":"Chag\u00fcite Arriba",
    "gn:population":0,
    "gn:timezone":"America/Tegucigalpa",
    "iso:country":"HN",
    "wof:name":"Chaguite Arriba",
    "wof:placetype":"locality"
},
  "geometry": {"coordinates":[-87.01333000000002,13.94389],"type":"Point"}
}