{
  "type": "Feature",
  "properties": {
    "gn:admin1_code":"17",
    "gn:asciiname":"El Brasilar",
    "gn:cc2":"HN",
    "gn:country_code":"HN",
    "gn:dem":81,
    "gn:feature_class":"P",
    "gn:feature_code":"PPL",
    "gn:name":"El Brasilar",
    "gn:population":0,
    "gn:timezone":"America/Tegucigalpa",
    "iso:country":"HN",
    "name:und_x_variant":[
        "El Brasil",
        "El Brasilar"
    ],
    "wof:name":"El Brasilar",
    "wof:placetype":"locality"
},
  "geometry": {"coordinates":[-87.55028,13.59444],"type":"Point"}
}