{
  "type": "Feature",
  "properties": {
    "gn:admin1_code":"07",
    "gn:asciiname":"Jaguitas",
    "gn:country_code":"HN",
    "gn:dem":631,
    "gn:feature_class":"P",
    "gn:feature_code":"PPL",
    "gn:name":"Jag\u00fcitas",
    "gn:population":0,
    "gn:timezone":"America/Tegucigalpa",
    "iso:country":"HN",
    "wof:name":"Jaguitas",
    "wof:placetype":"locality"
},
  "geometry": {"coordinates":[-86.91667,14.08333],"type":"Point"}
}