{
  "type": "Feature",
  "properties": {
    "gn:admin1_code":"18",
    "gn:asciiname":"Macora",
    "gn:country_code":"HN",
    "gn:dem":113,
    "gn:feature_class":"P",
    "gn:feature_code":"PPL",
    "gn:name":"Macora",
    "gn:population":0,
    "gn:timezone":"America/Tegucigalpa",
    "iso:country":"HN",
    "wof:name":"Macora",
    "wof:placetype":"locality"
},
  "geometry": {"coordinates":[-86.46666999999999,15.45],"type":"Point"}
}