{
  "type": "Feature",
  "properties": {
    "gn:admin1_code":"02",
    "gn:asciiname":"Gualiqueme",
    "gn:country_code":"HN",
    "gn:dem":1249,
    "gn:feature_class":"P",
    "gn:feature_code":"PPL",
    "gn:name":"Gualiqueme",
    "gn:population":0,
    "gn:timezone":"America/Tegucigalpa",
    "iso:country":"HN",
    "wof:name":"Gualiqueme",
    "wof:placetype":"locality"
},
  "geometry": {"coordinates":[-86.88333,13.35],"type":"Point"}
}