{
  "type": "Feature",
  "properties": {
    "gn:admin1_code":"07",
    "gn:asciiname":"Quebrada Las Gallinas",
    "gn:country_code":"HN",
    "gn:dem":393,
    "gn:feature_class":"P",
    "gn:feature_code":"PPL",
    "gn:name":"Quebrada Las Gallinas",
    "gn:population":0,
    "gn:timezone":"America/Tegucigalpa",
    "iso:country":"HN",
    "wof:name":"Quebrada Las Gallinas",
    "wof:placetype":"locality"
},
  "geometry": {"coordinates":[-87.03333000000001,13.66667],"type":"Point"}
}