{
  "type": "Feature",
  "properties": {
    "gn:admin1_code":"13",
    "gn:asciiname":"Villa Hermosa",
    "gn:country_code":"HN",
    "gn:dem":469,
    "gn:feature_class":"P",
    "gn:feature_code":"PPL",
    "gn:name":"Villa Hermosa",
    "gn:population":0,
    "gn:timezone":"America/Tegucigalpa",
    "iso:country":"HN",
    "name:ita_x_preferred":[
        "Villa Hermosa"
    ],
    "name:por_x_preferred":[
        "Villa Hermosa"
    ],
    "name:spa_x_preferred":[
        "Villa Hermosa"
    ],
    "name:zho_x_preferred":[
        "\u57c3\u723e\u83ab\u85a9\u93ae"
    ],
    "wof:name":"Villa Hermosa",
    "wof:placetype":"locality"
},
  "geometry": {"coordinates":[-88.66667,14.76667],"type":"Point"}
}