{
  "type": "Feature",
  "properties": {
    "iso:country":"HN",
    "name:und_x_variant":[
        "Ingenio Agalteca"
    ],
    "qs:gn_country":"HN",
    "qs:gn_fcode":"PPL",
    "qs:gn_pop":1029,
    "qs:name":"Agalteca",
    "qs:name_adm0":"Honduras",
    "qs:name_adm1":"Santa B\u00e1rbara",
    "qs:photos":0,
    "qs:photos_1k":0,
    "qs:photos_9k":0,
    "qs:photos_9r":0,
    "qs:photos_all":0,
    "qs:photos_sr":0,
    "qs:placetype":"Town",
    "qs:pop_sr":"3",
    "qs:woe_adm0":23424841,
    "wof:name":"Agalteca",
    "wof:placetype":"locality",
    "wof:population":1029
},
  "geometry": {"coordinates":[-87.26667,14.45],"type":"Point"}
}