{
  "type": "Feature",
  "properties": {
    "gn:admin1_code":"04",
    "gn:asciiname":"El Cacao",
    "gn:country_code":"HN",
    "gn:dem":892,
    "gn:feature_class":"P",
    "gn:feature_code":"PPL",
    "gn:name":"El Cacao",
    "gn:population":0,
    "gn:timezone":"America/Tegucigalpa",
    "iso:country":"HN",
    "name:ceb_x_preferred":[
        "El Cacao"
    ],
    "name:ita_x_preferred":[
        "El Cacao"
    ],
    "name:swe_x_preferred":[
        "El Cacao"
    ],
    "wof:name":"El Cacao",
    "wof:placetype":"locality"
},
  "geometry": {"coordinates":[-87.76666999999998,14.75],"type":"Point"}
}