{
  "type": "Feature",
  "properties": {
    "gn:admin1_code":"03",
    "gn:asciiname":"Balfate",
    "gn:cc2":"HN",
    "gn:country_code":"HN",
    "gn:dem":9,
    "gn:feature_class":"P",
    "gn:feature_code":"PPL",
    "gn:name":"Balfate",
    "gn:population":0,
    "gn:timezone":"America/Tegucigalpa",
    "iso:country":"HN",
    "name:ceb_x_preferred":[
        "Balfate"
    ],
    "name:fra_x_preferred":[
        "Balfate"
    ],
    "name:ita_x_preferred":[
        "Balfate"
    ],
    "name:nld_x_preferred":[
        "Balfate"
    ],
    "name:pol_x_preferred":[
        "Balfate"
    ],
    "name:por_x_preferred":[
        "Balfate"
    ],
    "name:spa_x_preferred":[
        "Balfate"
    ],
    "name:swe_x_preferred":[
        "Balfate"
    ],
    "name:und_x_variant":[
        "Belfate"
    ],
    "name:zho_x_preferred":[
        "\u5df4\u723e\u6cd5\u7279"
    ],
    "wof:name":"Balfate",
    "wof:placetype":"locality"
},
  "geometry": {"coordinates":[-86.38871999999998,15.77057],"type":"Point"}
}