{
  "type": "Feature",
  "properties": {
    "gn:admin1_code":"03",
    "gn:asciiname":"Balfate",
    "gn:cc2":"HN",
    "gn:country_code":"HN",
    "gn:dem":9,
    "gn:feature_class":"P",
    "gn:feature_code":"PPL",
    "gn:name":"Balfate",
    "gn:population":0,
    "gn:timezone":"America/Tegucigalpa",
    "iso:country":"HN",
    "name:und_x_variant":[
        "Belfate",
        "Balfate"
    ],
    "wof:name":"Balfate",
    "wof:placetype":"locality"
},
  "geometry": {"coordinates":[-86.38871999999998,15.77057],"type":"Point"}
}