{
  "type": "Feature",
  "properties": {
    "gn:admin1_code":"02",
    "gn:asciiname":"Los Espabeles",
    "gn:country_code":"HN",
    "gn:dem":6,
    "gn:feature_class":"P",
    "gn:feature_code":"PPL",
    "gn:name":"Los Espabeles",
    "gn:population":0,
    "gn:timezone":"America/Tegucigalpa",
    "iso:country":"HN",
    "wof:name":"Los Espabeles",
    "wof:placetype":"locality"
},
  "geometry": {"coordinates":[-87.41471999999997,13.29528],"type":"Point"}
}