{
  "type": "Feature",
  "properties": {
    "gn:admin1_code":"02",
    "gn:asciiname":"Los Maicillales",
    "gn:cc2":"HN",
    "gn:country_code":"HN",
    "gn:dem":790,
    "gn:feature_class":"P",
    "gn:feature_code":"PPL",
    "gn:name":"Los Maicillales",
    "gn:population":0,
    "gn:timezone":"America/Tegucigalpa",
    "iso:country":"HN",
    "name:und_x_variant":[
        "Maicillales",
        "Los Maicillales"
    ],
    "wof:name":"Los Maicillales",
    "wof:placetype":"locality"
},
  "geometry": {"coordinates":[-86.90000000000001,13.31667],"type":"Point"}
}