{
  "type": "Feature",
  "properties": {
    "gn:admin1_code":"17",
    "gn:asciiname":"Isla Exposicion",
    "gn:country_code":"HN",
    "gn:dem":68,
    "gn:feature_class":"P",
    "gn:feature_code":"PPL",
    "gn:name":"Isla Exposici\u00f3n",
    "gn:population":0,
    "gn:timezone":"America/Tegucigalpa",
    "iso:country":"HN",
    "wof:name":"Isla Exposicion",
    "wof:placetype":"locality"
},
  "geometry": {"coordinates":[-87.66667,13.31667],"type":"Point"}
}