{
  "type": "Feature",
  "properties": {
    "gn:admin1_code":"17",
    "gn:asciiname":"El Volcancillo",
    "gn:country_code":"HN",
    "gn:dem":168,
    "gn:feature_class":"P",
    "gn:feature_code":"PPL",
    "gn:name":"El Volcancillo",
    "gn:population":0,
    "gn:timezone":"America/Tegucigalpa",
    "iso:country":"HN",
    "wof:name":"El Volcancillo",
    "wof:placetype":"locality"
},
  "geometry": {"coordinates":[-87.65944,13.58694],"type":"Point"}
}