{
  "type": "Feature",
  "properties": {
    "gn:admin1_code":"01",
    "gn:asciiname":"La Ensenada",
    "gn:cc2":"HN",
    "gn:country_code":"HN",
    "gn:dem":2,
    "gn:feature_class":"P",
    "gn:feature_code":"PPL",
    "gn:name":"La Ensenada",
    "gn:population":0,
    "gn:timezone":"America/Tegucigalpa",
    "iso:country":"HN",
    "name:ita_x_preferred":[
        "La Ensenada"
    ],
    "name:spa_x_preferred":[
        "La Ensenada"
    ],
    "name:und_x_variant":[
        "La Encenada"
    ],
    "name:zho_x_preferred":[
        "\u62c9\u6069\u585e\u7d0d\u9054"
    ],
    "wof:name":"La Ensenada",
    "wof:placetype":"locality"
},
  "geometry": {"coordinates":[-87.06667,15.73333],"type":"Point"}
}