{
  "type": "Feature",
  "properties": {
    "gn:admin1_code":"17",
    "gn:asciiname":"Cerro Grande",
    "gn:country_code":"HN",
    "gn:dem":152,
    "gn:feature_class":"P",
    "gn:feature_code":"PPL",
    "gn:name":"Cerro Grande",
    "gn:population":0,
    "gn:timezone":"America/Tegucigalpa",
    "iso:country":"HN",
    "name:ceb_x_preferred":[
        "Cerro Grande"
    ],
    "name:deu_x_preferred":[
        "Cerro Grande"
    ],
    "name:spa_x_preferred":[
        "Cerro Grande"
    ],
    "name:swe_x_preferred":[
        "Cerro Grande"
    ],
    "wof:name":"Cerro Grande",
    "wof:placetype":"locality"
},
  "geometry": {"coordinates":[-87.53083000000002,13.66611],"type":"Point"}
}