{
  "type": "Feature",
  "properties": {
    "gn:admin1_code":"18",
    "gn:asciiname":"Sisique",
    "gn:country_code":"HN",
    "gn:dem":1471,
    "gn:feature_class":"P",
    "gn:feature_code":"PPL",
    "gn:name":"Sisique",
    "gn:population":0,
    "gn:timezone":"America/Tegucigalpa",
    "iso:country":"HN",
    "wof:name":"Sisique",
    "wof:placetype":"locality"
},
  "geometry": {"coordinates":[-86.95,15.18333],"type":"Point"}
}