{
  "type": "Feature",
  "properties": {
    "gn:admin1_code":"18",
    "gn:asciiname":"Corinto",
    "gn:country_code":"HN",
    "gn:dem":933,
    "gn:feature_class":"P",
    "gn:feature_code":"PPL",
    "gn:name":"Corinto",
    "gn:population":0,
    "gn:timezone":"America/Tegucigalpa",
    "iso:country":"HN",
    "name:ceb_x_preferred":[
        "Corinto"
    ],
    "name:deu_x_preferred":[
        "Corinto"
    ],
    "name:epo_x_preferred":[
        "Corinto"
    ],
    "name:fra_x_preferred":[
        "Corinto"
    ],
    "name:ita_x_preferred":[
        "Corinto"
    ],
    "name:jpn_x_preferred":[
        "\u30b3\u30ea\u30f3\u30c8"
    ],
    "name:lit_x_preferred":[
        "Korintas"
    ],
    "name:nld_x_preferred":[
        "Corinto"
    ],
    "name:por_x_preferred":[
        "Corinto"
    ],
    "name:spa_x_preferred":[
        "Corinto"
    ],
    "name:swe_x_preferred":[
        "Corinto"
    ],
    "wof:name":"Corinto",
    "wof:placetype":"locality"
},
  "geometry": {"coordinates":[-87.13333,15.31667],"type":"Point"}
}