{
  "type": "Feature",
  "properties": {
    "gn:admin1_code":"06",
    "gn:asciiname":"Jaguas",
    "gn:country_code":"HN",
    "gn:dem":295,
    "gn:feature_class":"P",
    "gn:feature_code":"PPL",
    "gn:name":"Jaguas",
    "gn:population":0,
    "gn:timezone":"America/Tegucigalpa",
    "iso:country":"HN",
    "wof:name":"Jaguas",
    "wof:placetype":"locality"
},
  "geometry": {"coordinates":[-87.91667,15.36667],"type":"Point"}
}