{
  "type": "Feature",
  "properties": {
    "gn:admin1_code":"06",
    "gn:asciiname":"Terreritos de La Libertad",
    "gn:cc2":"HN",
    "gn:country_code":"HN",
    "gn:dem":468,
    "gn:feature_class":"P",
    "gn:feature_code":"PPL",
    "gn:name":"Terreritos de La Libertad",
    "gn:population":0,
    "gn:timezone":"America/Tegucigalpa",
    "iso:country":"HN",
    "name:und_x_variant":[
        "La Libertad",
        "Terreritos",
        "Terrerito",
        "Terreritos de La Libertad"
    ],
    "wof:name":"Terreritos de La Libertad",
    "wof:placetype":"locality"
},
  "geometry": {"coordinates":[-87.83333,15.01667],"type":"Point"}
}