{
  "type": "Feature",
  "properties": {
    "gn:admin1_code":"09",
    "gn:asciiname":"Casautara",
    "gn:cc2":"HN",
    "gn:country_code":"HN",
    "gn:dem":3,
    "gn:feature_class":"P",
    "gn:feature_code":"PPL",
    "gn:name":"Casautara",
    "gn:population":0,
    "gn:timezone":"America/Tegucigalpa",
    "iso:country":"HN",
    "name:und_x_variant":[
        "Kasautara",
        "Casautara"
    ],
    "wof:name":"Casautara",
    "wof:placetype":"locality"
},
  "geometry": {"coordinates":[-83.25,15.03333],"type":"Point"}
}