{
  "type": "Feature",
  "properties": {
    "gn:admin1_code":"17",
    "gn:asciiname":"Caragual",
    "gn:country_code":"HN",
    "gn:dem":487,
    "gn:feature_class":"P",
    "gn:feature_code":"PPL",
    "gn:name":"Caragual",
    "gn:population":0,
    "gn:timezone":"America/Tegucigalpa",
    "iso:country":"HN",
    "wof:name":"Caragual",
    "wof:placetype":"locality"
},
  "geometry": {"coordinates":[-87.45166999999999,13.60583],"type":"Point"}
}