{
  "type": "Feature",
  "properties": {
    "gn:admin1_code":"02",
    "gn:asciiname":"Los Martel",
    "gn:country_code":"HN",
    "gn:dem":206,
    "gn:feature_class":"P",
    "gn:feature_code":"PPL",
    "gn:name":"Los Martel",
    "gn:population":0,
    "gn:timezone":"America/Tegucigalpa",
    "iso:country":"HN",
    "wof:name":"Los Martel",
    "wof:placetype":"locality"
},
  "geometry": {"coordinates":[-87.29222,13.58583],"type":"Point"}
}