{
  "type": "Feature",
  "properties": {
    "gn:admin1_code":"09",
    "gn:asciiname":"Esterbrook",
    "gn:country_code":"HN",
    "gn:dem":3,
    "gn:feature_class":"P",
    "gn:feature_code":"PPL",
    "gn:name":"Esterbrook",
    "gn:population":0,
    "gn:timezone":"America/Tegucigalpa",
    "iso:country":"HN",
    "wof:name":"Esterbrook",
    "wof:placetype":"locality"
},
  "geometry": {"coordinates":[-84.59999999999999,15.78333],"type":"Point"}
}