{
  "type": "Feature",
  "properties": {
    "gn:admin1_code":"18",
    "gn:asciiname":"El Rodeo",
    "gn:cc2":"HN",
    "gn:country_code":"HN",
    "gn:dem":780,
    "gn:feature_class":"P",
    "gn:feature_code":"PPL",
    "gn:name":"El Rodeo",
    "gn:population":0,
    "gn:timezone":"America/Tegucigalpa",
    "iso:country":"HN",
    "name:ceb_x_preferred":[
        "El Rodeo"
    ],
    "name:deu_x_preferred":[
        "El Rodeo"
    ],
    "name:spa_x_preferred":[
        "El Rodeo"
    ],
    "name:srp_x_preferred":[
        "\u0415\u043b \u0420\u043e\u0434\u0435\u043e"
    ],
    "name:swe_x_preferred":[
        "El Rodeo"
    ],
    "name:und_x_variant":[
        "Rodeo",
        "El Rodeo"
    ],
    "wof:name":"El Rodeo",
    "wof:placetype":"locality"
},
  "geometry": {"coordinates":[-87.33333,15.33333],"type":"Point"}
}