{
  "type": "Feature",
  "properties": {
    "gn:admin1_code":"12",
    "gn:asciiname":"Las Pipas",
    "gn:country_code":"HN",
    "gn:dem":1214,
    "gn:feature_class":"P",
    "gn:feature_code":"PPL",
    "gn:name":"Las Pipas",
    "gn:population":0,
    "gn:timezone":"America/Tegucigalpa",
    "iso:country":"HN",
    "wof:name":"Las Pipas",
    "wof:placetype":"locality"
},
  "geometry": {"coordinates":[-87.81667,13.95306],"type":"Point"}
}