{
  "type": "Feature",
  "properties": {
    "gn:admin1_code":"07",
    "gn:asciiname":"El Guarumal",
    "gn:cc2":"HN",
    "gn:country_code":"HN",
    "gn:dem":440,
    "gn:feature_class":"P",
    "gn:feature_code":"PPL",
    "gn:name":"El Guarumal",
    "gn:population":0,
    "gn:timezone":"America/Tegucigalpa",
    "iso:country":"HN",
    "name:und_x_variant":[
        "Guarumal",
        "El Guarumal"
    ],
    "wof:name":"El Guarumal",
    "wof:placetype":"locality"
},
  "geometry": {"coordinates":[-87.0425,13.61111],"type":"Point"}
}