{
  "type": "Feature",
  "properties": {
    "gn:admin1_code":"17",
    "gn:asciiname":"Zaracuco",
    "gn:country_code":"HN",
    "gn:dem":370,
    "gn:feature_class":"P",
    "gn:feature_code":"PPL",
    "gn:name":"Zaracuco",
    "gn:population":0,
    "gn:timezone":"America/Tegucigalpa",
    "iso:country":"HN",
    "wof:name":"Zaracuco",
    "wof:placetype":"locality"
},
  "geometry": {"coordinates":[-87.66667,13.75],"type":"Point"}
}