{
  "type": "Feature",
  "properties": {
    "gn:admin1_code":"09",
    "gn:asciiname":"Yolu",
    "gn:country_code":"HN",
    "gn:dem":72,
    "gn:feature_class":"P",
    "gn:feature_code":"PPL",
    "gn:name":"Yolu",
    "gn:population":0,
    "gn:timezone":"America/Tegucigalpa",
    "iso:country":"HN",
    "wof:name":"Yolu",
    "wof:placetype":"locality"
},
  "geometry": {"coordinates":[-83.91667,14.98333],"type":"Point"}
}