{
  "type": "Feature",
  "properties": {
    "gn:admin1_code":"02",
    "gn:asciiname":"Las Brisas",
    "gn:country_code":"HN",
    "gn:dem":1067,
    "gn:feature_class":"P",
    "gn:feature_code":"PPL",
    "gn:name":"Las Brisas",
    "gn:population":0,
    "gn:timezone":"America/Tegucigalpa",
    "iso:country":"HN",
    "name:fra_x_preferred":[
        "Las Brisas"
    ],
    "wof:name":"Las Brisas",
    "wof:placetype":"locality"
},
  "geometry": {"coordinates":[-86.83333,13.43333],"type":"Point"}
}