{
  "type": "Feature",
  "properties": {
    "gn:admin1_code":"18",
    "gn:asciiname":"La Majada",
    "gn:cc2":"HN",
    "gn:country_code":"HN",
    "gn:dem":675,
    "gn:feature_class":"P",
    "gn:feature_code":"PPL",
    "gn:name":"La Majada",
    "gn:population":0,
    "gn:timezone":"America/Tegucigalpa",
    "iso:country":"HN",
    "name:und_x_variant":[
        "Majada",
        "La Majada"
    ],
    "wof:name":"La Majada",
    "wof:placetype":"locality"
},
  "geometry": {"coordinates":[-87.75,15.28333],"type":"Point"}
}