{
  "type": "Feature",
  "properties": {
    "gn:admin1_code":"01",
    "gn:asciiname":"Jilamito Nuevo",
    "gn:country_code":"HN",
    "gn:dem":31,
    "gn:feature_class":"P",
    "gn:feature_code":"PPL",
    "gn:name":"Jilamito Nuevo",
    "gn:population":0,
    "gn:timezone":"America/Tegucigalpa",
    "iso:country":"HN",
    "wof:name":"Jilamito Nuevo",
    "wof:placetype":"locality"
},
  "geometry": {"coordinates":[-87.33888,15.62228],"type":"Point"}
}