{
  "type": "Feature",
  "properties": {
    "gn:admin1_code":"10",
    "gn:asciiname":"Piedras Negras",
    "gn:country_code":"HN",
    "gn:dem":640,
    "gn:feature_class":"P",
    "gn:feature_code":"PPL",
    "gn:name":"Piedras Negras",
    "gn:population":0,
    "gn:timezone":"America/Tegucigalpa",
    "iso:country":"HN",
    "name:ceb_x_preferred":[
        "Piedras Negras"
    ],
    "name:deu_x_preferred":[
        "Piedras Negras"
    ],
    "name:fas_x_preferred":[
        "\u067e\u06cc\u062f\u0631\u0627\u0633 \u0646\u06af\u0631\u0627\u0633"
    ],
    "name:fra_x_preferred":[
        "Piedras Negras"
    ],
    "name:ita_x_preferred":[
        "Piedras Negras"
    ],
    "name:nld_x_preferred":[
        "Piedras Negras"
    ],
    "name:spa_x_preferred":[
        "Piedras Negras"
    ],
    "name:swe_x_preferred":[
        "Piedras Negras"
    ],
    "name:vie_x_preferred":[
        "Piedras Negras"
    ],
    "wof:name":"Piedras Negras",
    "wof:placetype":"locality"
},
  "geometry": {"coordinates":[-88.05,14.51667],"type":"Point"}
}