{
  "type": "Feature",
  "properties": {
    "iso:country":"HN",
    "name:ceb_x_preferred":[
        "El Para\u00edso"
    ],
    "name:deu_x_preferred":[
        "El Para\u00edso"
    ],
    "name:eng_x_preferred":[
        "El Para\u00edso"
    ],
    "name:eus_x_preferred":[
        "El Para\u00edso"
    ],
    "name:fra_x_preferred":[
        "El Para\u00edso"
    ],
    "name:ita_x_preferred":[
        "El Para\u00edso"
    ],
    "name:nan_x_preferred":[
        "El Para\u00edso"
    ],
    "name:nld_x_preferred":[
        "El Para\u00edso"
    ],
    "name:pol_x_preferred":[
        "El Para\u00edso"
    ],
    "name:por_x_preferred":[
        "El Para\u00edso"
    ],
    "name:spa_x_preferred":[
        "El Para\u00edso"
    ],
    "name:swe_x_preferred":[
        "El Para\u00edso"
    ],
    "name:zho_x_preferred":[
        "\u57c3\u723e\u5e15\u62c9\u4f0a\u7d22"
    ],
    "qs:gn_country":"HN",
    "qs:gn_fcode":"PPL",
    "qs:gn_pop":18779,
    "qs:name":"El Para\u00edso",
    "qs:name_adm0":"Honduras",
    "qs:name_adm1":"El Para\u00edso",
    "qs:photos":19,
    "qs:photos_1k":4,
    "qs:photos_9k":1,
    "qs:photos_9r":1,
    "qs:photos_all":19,
    "qs:photos_sr":1,
    "qs:placetype":"Town",
    "qs:pop_sr":"6",
    "qs:woe_adm0":23424841,
    "wof:name":"El Para\u00edso",
    "wof:placetype":"locality",
    "wof:population":18779
},
  "geometry": {"coordinates":[-86.55,13.86667],"type":"Point"}
}