{
  "type": "Feature",
  "properties": {
    "gn:admin1_code":"18",
    "gn:asciiname":"Mataderos",
    "gn:country_code":"HN",
    "gn:dem":620,
    "gn:feature_class":"P",
    "gn:feature_code":"PPL",
    "gn:name":"Mataderos",
    "gn:population":0,
    "gn:timezone":"America/Tegucigalpa",
    "iso:country":"HN",
    "name:deu_x_preferred":[
        "Mataderos"
    ],
    "name:fra_x_preferred":[
        "Mataderos"
    ],
    "name:ita_x_preferred":[
        "Mataderos"
    ],
    "name:lat_x_preferred":[
        "Mataderos"
    ],
    "name:lit_x_preferred":[
        "Mataderosas"
    ],
    "name:por_x_preferred":[
        "Mataderos"
    ],
    "name:ron_x_preferred":[
        "Mataderos"
    ],
    "name:rus_x_preferred":[
        "\u041c\u0430\u0442\u0430\u0434\u0435\u0440\u043e\u0441"
    ],
    "name:spa_x_preferred":[
        "Mataderos"
    ],
    "wof:name":"Mataderos",
    "wof:placetype":"locality"
},
  "geometry": {"coordinates":[-87.31667,15.31667],"type":"Point"}
}