{
  "type": "Feature",
  "properties": {
    "gn:admin1_code":"13",
    "gn:asciiname":"Los Liros",
    "gn:country_code":"HN",
    "gn:dem":1627,
    "gn:feature_class":"P",
    "gn:feature_code":"PPL",
    "gn:name":"Los Liros",
    "gn:population":0,
    "gn:timezone":"America/Tegucigalpa",
    "iso:country":"HN",
    "wof:name":"Los Liros",
    "wof:placetype":"locality"
},
  "geometry": {"coordinates":[-88.3663,14.52227],"type":"Point"}
}