{
  "type": "Feature",
  "properties": {
    "gn:admin1_code":"08",
    "gn:asciiname":"La Estancia",
    "gn:country_code":"HN",
    "gn:dem":1625,
    "gn:feature_class":"P",
    "gn:feature_code":"PPL",
    "gn:name":"La Estancia",
    "gn:population":0,
    "gn:timezone":"America/Tegucigalpa",
    "iso:country":"HN",
    "name:ceb_x_preferred":[
        "La Estancia"
    ],
    "name:deu_x_preferred":[
        "La Estancia"
    ],
    "name:spa_x_preferred":[
        "La Estancia"
    ],
    "name:swe_x_preferred":[
        "La Estancia"
    ],
    "wof:name":"La Estancia",
    "wof:placetype":"locality"
},
  "geometry": {"coordinates":[-87.1375,13.97583],"type":"Point"}
}