{
  "type": "Feature",
  "properties": {
    "gn:admin1_code":"10",
    "gn:asciiname":"El Caulote",
    "gn:cc2":"HN",
    "gn:country_code":"HN",
    "gn:dem":322,
    "gn:feature_class":"P",
    "gn:feature_code":"PPL",
    "gn:name":"El Caulote",
    "gn:population":0,
    "gn:timezone":"America/Tegucigalpa",
    "iso:country":"HN",
    "name:und_x_variant":[
        "Caulote",
        "El Caulote"
    ],
    "wof:name":"El Caulote",
    "wof:placetype":"locality"
},
  "geometry": {"coordinates":[-88.31667,13.83333],"type":"Point"}
}