{
  "type": "Feature",
  "properties": {
    "gn:admin1_code":"09",
    "gn:asciiname":"Uhi",
    "gn:cc2":"HN",
    "gn:country_code":"HN",
    "gn:dem":3,
    "gn:feature_class":"P",
    "gn:feature_code":"PPL",
    "gn:name":"Uh\u00ed",
    "gn:population":0,
    "gn:timezone":"America/Tegucigalpa",
    "iso:country":"HN",
    "name:und_x_variant":[
        "Huji",
        "Unji",
        "Hnji",
        "Uj\u00ed",
        "Hnj",
        "Hoji",
        "Uh\u00ed"
    ],
    "wof:name":"Uhi",
    "wof:placetype":"locality"
},
  "geometry": {"coordinates":[-83.91667,15.48333],"type":"Point"}
}