{
  "type": "Feature",
  "properties": {
    "gn:admin1_code":"07",
    "gn:asciiname":"Cerro Bonito",
    "gn:country_code":"HN",
    "gn:dem":539,
    "gn:feature_class":"P",
    "gn:feature_code":"PPL",
    "gn:name":"Cerro Bonito",
    "gn:population":0,
    "gn:timezone":"America/Tegucigalpa",
    "iso:country":"HN",
    "wof:name":"Cerro Bonito",
    "wof:placetype":"locality"
},
  "geometry": {"coordinates":[-87.07111,13.65806],"type":"Point"}
}