{
  "type": "Feature",
  "properties": {
    "gn:admin1_code":"02",
    "gn:asciiname":"La Redonda",
    "gn:country_code":"HN",
    "gn:dem":53,
    "gn:feature_class":"P",
    "gn:feature_code":"PPL",
    "gn:name":"La Redonda",
    "gn:population":0,
    "gn:timezone":"America/Tegucigalpa",
    "iso:country":"HN",
    "name:arg_x_preferred":[
        "La Redonda"
    ],
    "name:ast_x_preferred":[
        "La Redonda"
    ],
    "name:cat_x_preferred":[
        "La Redonda"
    ],
    "name:eus_x_preferred":[
        "La Redonda"
    ],
    "name:fra_x_preferred":[
        "La Redonda"
    ],
    "name:haw_x_preferred":[
        "La Redonda"
    ],
    "name:hun_x_preferred":[
        "La Redonda"
    ],
    "name:hye_x_preferred":[
        "\u053c\u0561 \u054c\u0565\u0564\u0578\u0576\u0564\u0561"
    ],
    "name:ina_x_preferred":[
        "La Redonda"
    ],
    "name:ita_x_preferred":[
        "La Redonda"
    ],
    "name:kaz_x_preferred":[
        "\u041b\u0430-\u0420\u0435\u0434\u043e\u043d\u0434\u0430"
    ],
    "name:msa_x_preferred":[
        "La Redonda"
    ],
    "name:nld_x_preferred":[
        "La Redonda"
    ],
    "name:oci_x_preferred":[
        "La Redonda"
    ],
    "name:pol_x_preferred":[
        "La Redonda"
    ],
    "name:por_x_preferred":[
        "La Redonda"
    ],
    "name:rus_x_preferred":[
        "\u041b\u0430-\u0420\u0435\u0434\u043e\u043d\u0434\u0430"
    ],
    "name:spa_x_preferred":[
        "La Redonda"
    ],
    "name:ukr_x_preferred":[
        "\u041b\u0430-\u0420\u0435\u0434\u043e\u043d\u0434\u0430"
    ],
    "name:uzb_x_preferred":[
        "La Redonda"
    ],
    "name:vie_x_preferred":[
        "La Redonda"
    ],
    "name:war_x_preferred":[
        "La Redonda"
    ],
    "name:zho_x_preferred":[
        "\u62c9\u96f7\u4e1c\u8fbe"
    ],
    "wof:name":"La Redonda",
    "wof:placetype":"locality"
},
  "geometry": {"coordinates":[-87.20889,13.33917],"type":"Point"}
}