{
  "type": "Feature",
  "properties": {
    "gn:admin1_code":"02",
    "gn:asciiname":"Tapatoca",
    "gn:country_code":"HN",
    "gn:dem":166,
    "gn:feature_class":"P",
    "gn:feature_code":"PPL",
    "gn:name":"Tapatoca",
    "gn:population":0,
    "gn:timezone":"America/Tegucigalpa",
    "iso:country":"HN",
    "wof:name":"Tapatoca",
    "wof:placetype":"locality"
},
  "geometry": {"coordinates":[-87.3125,13.48667],"type":"Point"}
}