{
  "type": "Feature",
  "properties": {
    "gn:admin1_code":"08",
    "gn:asciiname":"La Presa",
    "gn:cc2":"HN",
    "gn:country_code":"HN",
    "gn:dem":744,
    "gn:feature_class":"P",
    "gn:feature_code":"PPL",
    "gn:name":"La Presa",
    "gn:population":0,
    "gn:timezone":"America/Tegucigalpa",
    "iso:country":"HN",
    "name:und_x_variant":[
        "La Preza",
        "La Presa"
    ],
    "wof:name":"La Presa",
    "wof:placetype":"locality"
},
  "geometry": {"coordinates":[-87.18333,14.48333],"type":"Point"}
}