{
  "type": "Feature",
  "properties": {
    "gn:admin1_code":"02",
    "gn:asciiname":"Hacienda El Eden",
    "gn:country_code":"HN",
    "gn:dem":29,
    "gn:feature_class":"P",
    "gn:feature_code":"PPL",
    "gn:name":"Hacienda El Eden",
    "gn:population":0,
    "gn:timezone":"America/Tegucigalpa",
    "iso:country":"HN",
    "wof:name":"Hacienda El Eden",
    "wof:placetype":"locality"
},
  "geometry": {"coordinates":[-87.19221999999998,13.23417],"type":"Point"}
}