{
  "type": "Feature",
  "properties": {
    "gn:admin1_code":"07",
    "gn:asciiname":"El Jobal",
    "gn:country_code":"HN",
    "gn:dem":438,
    "gn:feature_class":"P",
    "gn:feature_code":"PPL",
    "gn:name":"El Jobal",
    "gn:population":0,
    "gn:timezone":"America/Tegucigalpa",
    "iso:country":"HN",
    "wof:name":"El Jobal",
    "wof:placetype":"locality"
},
  "geometry": {"coordinates":[-87.02806,13.59889],"type":"Point"}
}