{
  "type": "Feature",
  "properties": {
    "gn:admin1_code":"13",
    "gn:asciiname":"Llano Chiquito",
    "gn:country_code":"HN",
    "gn:dem":966,
    "gn:feature_class":"P",
    "gn:feature_code":"PPL",
    "gn:name":"Llano Chiquito",
    "gn:population":0,
    "gn:timezone":"America/Tegucigalpa",
    "iso:country":"HN",
    "wof:name":"Llano Chiquito",
    "wof:placetype":"locality"
},
  "geometry": {"coordinates":[-88.56667,14.11667],"type":"Point"}
}