{
  "type": "Feature",
  "properties": {
    "gn:admin1_code":"15",
    "gn:asciiname":"El Destino",
    "gn:country_code":"HN",
    "gn:dem":1056,
    "gn:feature_class":"P",
    "gn:feature_code":"PPL",
    "gn:name":"El Destino",
    "gn:population":0,
    "gn:timezone":"America/Tegucigalpa",
    "iso:country":"HN",
    "wof:name":"El Destino",
    "wof:placetype":"locality"
},
  "geometry": {"coordinates":[-86.01666999999998,14.85],"type":"Point"}
}