{
  "type": "Feature",
  "properties": {
    "gn:admin1_code":"17",
    "gn:asciiname":"El Hueco",
    "gn:country_code":"HN",
    "gn:dem":269,
    "gn:feature_class":"P",
    "gn:feature_code":"PPL",
    "gn:name":"El Hueco",
    "gn:population":0,
    "gn:timezone":"America/Tegucigalpa",
    "iso:country":"HN",
    "wof:name":"El Hueco",
    "wof:placetype":"locality"
},
  "geometry": {"coordinates":[-87.71278000000002,13.84389],"type":"Point"}
}