{
  "type": "Feature",
  "properties": {
    "gn:admin1_code":"15",
    "gn:asciiname":"Linderos",
    "gn:country_code":"HN",
    "gn:dem":1218,
    "gn:feature_class":"P",
    "gn:feature_code":"PPL",
    "gn:name":"Linderos",
    "gn:population":0,
    "gn:timezone":"America/Tegucigalpa",
    "iso:country":"HN",
    "wof:name":"Linderos",
    "wof:placetype":"locality"
},
  "geometry": {"coordinates":[-86.71666999999999,14.56667],"type":"Point"}
}