{
  "type": "Feature",
  "properties": {
    "gn:admin1_code":"08",
    "gn:asciiname":"Monteado",
    "gn:cc2":"HN",
    "gn:country_code":"HN",
    "gn:dem":954,
    "gn:feature_class":"P",
    "gn:feature_code":"PPL",
    "gn:name":"Monteado",
    "gn:population":0,
    "gn:timezone":"America/Tegucigalpa",
    "iso:country":"HN",
    "name:und_x_variant":[
        "El Manteado",
        "El Monteado",
        "Monteado"
    ],
    "wof:name":"Monteado",
    "wof:placetype":"locality"
},
  "geometry": {"coordinates":[-87.03333000000001,14.21667],"type":"Point"}
}