{
  "type": "Feature",
  "properties": {
    "gn:admin1_code":"02",
    "gn:asciiname":"El Guapinol",
    "gn:country_code":"HN",
    "gn:dem":106,
    "gn:feature_class":"P",
    "gn:feature_code":"PPL",
    "gn:name":"El Guapinol",
    "gn:population":0,
    "gn:timezone":"America/Tegucigalpa",
    "iso:country":"HN",
    "wof:name":"El Guapinol",
    "wof:placetype":"locality"
},
  "geometry": {"coordinates":[-87.29306,13.39222],"type":"Point"}
}