{
  "type": "Feature",
  "properties": {
    "gn:admin1_code":"18",
    "gn:asciiname":"Boca Mame",
    "gn:cc2":"HN",
    "gn:country_code":"HN",
    "gn:dem":117,
    "gn:feature_class":"P",
    "gn:feature_code":"PPL",
    "gn:name":"Boca Mame",
    "gn:population":0,
    "gn:timezone":"America/Tegucigalpa",
    "iso:country":"HN",
    "name:und_x_variant":[
        "Mame",
        "Bocomame",
        "Boca Mame"
    ],
    "wof:name":"Boca Mame",
    "wof:placetype":"locality"
},
  "geometry": {"coordinates":[-86.41667,15.46667],"type":"Point"}
}