{
  "type": "Feature",
  "properties": {
    "gn:admin1_code":"01",
    "gn:asciiname":"Danto Barra",
    "gn:country_code":"HN",
    "gn:dem":-9999,
    "gn:feature_class":"P",
    "gn:feature_code":"PPL",
    "gn:name":"Danto Barra",
    "gn:population":0,
    "gn:timezone":"America/Tegucigalpa",
    "iso:country":"HN",
    "wof:name":"Danto Barra",
    "wof:placetype":"locality"
},
  "geometry": {"coordinates":[-86.84999999999999,15.78333],"type":"Point"}
}