{
  "type": "Feature",
  "properties": {
    "gn:admin1_code":"18",
    "gn:asciiname":"Campo Rojo",
    "gn:country_code":"HN",
    "gn:dem":263,
    "gn:feature_class":"P",
    "gn:feature_code":"PPL",
    "gn:name":"Campo Rojo",
    "gn:population":0,
    "gn:timezone":"America/Tegucigalpa",
    "iso:country":"HN",
    "wof:name":"Campo Rojo",
    "wof:placetype":"locality"
},
  "geometry": {"coordinates":[-86.73333000000002,15.35],"type":"Point"}
}