{
  "type": "Feature",
  "properties": {
    "gn:admin1_code":"08",
    "gn:asciiname":"El Aguacate",
    "gn:cc2":"HN",
    "gn:country_code":"HN",
    "gn:dem":1308,
    "gn:feature_class":"P",
    "gn:feature_code":"PPL",
    "gn:name":"El Aguacate",
    "gn:population":0,
    "gn:timezone":"America/Tegucigalpa",
    "iso:country":"HN",
    "name:und_x_variant":[
        "Aguacate",
        "El Aguacate"
    ],
    "wof:name":"El Aguacate",
    "wof:placetype":"locality"
},
  "geometry": {"coordinates":[-87.55667,13.98611],"type":"Point"}
}