{
  "type": "Feature",
  "properties": {
    "gn:admin1_code":"02",
    "gn:asciiname":"Hacienda La Flor",
    "gn:country_code":"HN",
    "gn:dem":11,
    "gn:feature_class":"P",
    "gn:feature_code":"PPL",
    "gn:name":"Hacienda La Flor",
    "gn:population":0,
    "gn:timezone":"America/Tegucigalpa",
    "iso:country":"HN",
    "wof:name":"Hacienda La Flor",
    "wof:placetype":"locality"
},
  "geometry": {"coordinates":[-87.06778,13.005],"type":"Point"}
}