{
  "type": "Feature",
  "properties": {
    "gn:admin1_code":"04",
    "gn:asciiname":"Mata Palo",
    "gn:country_code":"HN",
    "gn:dem":485,
    "gn:feature_class":"P",
    "gn:feature_code":"PPL",
    "gn:name":"Mata Palo",
    "gn:population":0,
    "gn:timezone":"America/Tegucigalpa",
    "iso:country":"HN",
    "wof:name":"Mata Palo",
    "wof:placetype":"locality"
},
  "geometry": {"coordinates":[-87.76666999999998,14.76667],"type":"Point"}
}