{
  "type": "Feature",
  "properties": {
    "gn:admin1_code":"02",
    "gn:asciiname":"El Jicarito",
    "gn:country_code":"HN",
    "gn:dem":22,
    "gn:feature_class":"P",
    "gn:feature_code":"PPL",
    "gn:name":"El Jicar\u00edto",
    "gn:population":0,
    "gn:timezone":"America/Tegucigalpa",
    "iso:country":"HN",
    "wof:name":"El Jicarito",
    "wof:placetype":"locality"
},
  "geometry": {"coordinates":[-87.43805999999999,13.26694],"type":"Point"}
}