{
  "type": "Feature",
  "properties": {
    "gn:admin1_code":"01",
    "gn:asciiname":"Cabo de Hornos",
    "gn:cc2":"HN",
    "gn:country_code":"HN",
    "gn:dem":7,
    "gn:feature_class":"P",
    "gn:feature_code":"PPL",
    "gn:name":"Cabo de Hornos",
    "gn:population":0,
    "gn:timezone":"America/Tegucigalpa",
    "iso:country":"HN",
    "name:und_x_variant":[
        "Danto Cabo Hornos",
        "Cabo de Hornos"
    ],
    "wof:name":"Cabo de Hornos",
    "wof:placetype":"locality"
},
  "geometry": {"coordinates":[-86.8167,15.7667],"type":"Point"}
}