{
  "type": "Feature",
  "properties": {
    "gn:admin1_code":"08",
    "gn:asciiname":"La Joya del Tanque",
    "gn:country_code":"HN",
    "gn:dem":1291,
    "gn:feature_class":"P",
    "gn:feature_code":"PPL",
    "gn:name":"La Joya del Tanque",
    "gn:population":0,
    "gn:timezone":"America/Tegucigalpa",
    "iso:country":"HN",
    "wof:name":"La Joya del Tanque",
    "wof:placetype":"locality"
},
  "geometry": {"coordinates":[-87.18194,13.85361],"type":"Point"}
}