{
  "type": "Feature",
  "properties": {
    "iso:country":"HN",
    "name:chi_x_preferred":[
        "\u62c9\u5229\u4f2f\u5854\u5fb7"
    ],
    "name:dut_x_preferred":[
        "La Libertad"
    ],
    "name:eng_x_preferred":[
        "La Libertad"
    ],
    "name:fre_x_preferred":[
        "La Libertad"
    ],
    "name:ita_x_preferred":[
        "La Libertad"
    ],
    "name:pol_x_preferred":[
        "La Libertad"
    ],
    "name:por_x_preferred":[
        "La Libertad"
    ],
    "name:spa_x_preferred":[
        "La Libertad"
    ],
    "name:swe_x_preferred":[
        "La Libertad"
    ],
    "qs:gn_country":"HN",
    "qs:gn_fcode":"PPL",
    "qs:gn_pop":4673,
    "qs:name":"La Libertad",
    "qs:name_adm0":"Honduras",
    "qs:name_adm1":"Comayagua",
    "qs:photos":0,
    "qs:photos_1k":0,
    "qs:photos_9k":1,
    "qs:photos_9r":1,
    "qs:photos_all":2,
    "qs:photos_sr":0,
    "qs:placetype":"Town",
    "qs:pop_sr":"4",
    "qs:woe_adm0":23424841,
    "wof:name":"La Libertad",
    "wof:placetype":"locality",
    "wof:population":4673
},
  "geometry": {"coordinates":[-87.61667,14.75],"type":"Point"}
}