{
  "type": "Feature",
  "properties": {
    "iso:country":"HN",
    "name:ara_x_preferred":[
        "\u0644\u0627 \u0644\u064a\u0628\u0631\u062a\u0627\u062f"
    ],
    "name:ben_x_preferred":[
        "\u09b2\u09be \u09b2\u09bf\u09ac\u09be\u09b0\u09cd\u099f\u09be\u09a6"
    ],
    "name:ceb_x_preferred":[
        "La Libertad"
    ],
    "name:ell_x_preferred":[
        "\u039b\u03b1 \u039b\u03b9\u03bc\u03c0\u03b5\u03c1\u03c4\u03ac\u03b4"
    ],
    "name:eng_x_preferred":[
        "La Libertad"
    ],
    "name:eus_x_preferred":[
        "La Libertad"
    ],
    "name:fas_x_preferred":[
        "\u0644\u0627 \u0644\u06cc\u0628\u0631\u062a\u0627\u062f"
    ],
    "name:fra_x_preferred":[
        "La Libertad"
    ],
    "name:heb_x_preferred":[
        "\u05dc\u05d4 \u05dc\u05d9\u05d1\u05e8\u05d8\u05d3"
    ],
    "name:hin_x_preferred":[
        "\u0932\u093e \u0932\u093f\u092c\u0930\u094d\u091f\u093e\u0921"
    ],
    "name:hun_x_preferred":[
        "La Libertad"
    ],
    "name:ind_x_preferred":[
        "La Libertad"
    ],
    "name:ita_x_preferred":[
        "La Libertad"
    ],
    "name:kor_x_preferred":[
        "\ub77c \ub9ac\ubca0\ub974\ud0c0\ub4dc"
    ],
    "name:nan_x_preferred":[
        "La Libertad"
    ],
    "name:nld_x_preferred":[
        "La Libertad"
    ],
    "name:pol_x_preferred":[
        "La Libertad"
    ],
    "name:por_x_preferred":[
        "La Libertad"
    ],
    "name:rus_x_preferred":[
        "\u041b\u0430-\u041b\u0438\u0431\u0435\u0440\u0442\u0430\u0434"
    ],
    "name:spa_x_preferred":[
        "La Libertad"
    ],
    "name:swe_x_preferred":[
        "La Libertad"
    ],
    "name:tur_x_preferred":[
        "La Libertad"
    ],
    "name:ukr_x_preferred":[
        "\u041b\u0430-\u041b\u0456\u0431\u0435\u0440\u0442\u0430\u0434"
    ],
    "name:urd_x_preferred":[
        "\u0644\u0627 \u0644\u0628\u0631\u062a\u0627\u062f"
    ],
    "name:vie_x_preferred":[
        "La Libertad"
    ],
    "name:zho_x_preferred":[
        "\u62c9\u5229\u4f2f\u5854\u5fb7"
    ],
    "qs:gn_country":"HN",
    "qs:gn_fcode":"PPL",
    "qs:gn_pop":4673,
    "qs:name":"La Libertad",
    "qs:name_adm0":"Honduras",
    "qs:name_adm1":"Comayagua",
    "qs:photos":0,
    "qs:photos_1k":0,
    "qs:photos_9k":1,
    "qs:photos_9r":1,
    "qs:photos_all":2,
    "qs:photos_sr":0,
    "qs:placetype":"Town",
    "qs:pop_sr":"4",
    "qs:woe_adm0":23424841,
    "wof:name":"La Libertad",
    "wof:placetype":"locality",
    "wof:population":4673
},
  "geometry": {"coordinates":[-87.61667,14.75],"type":"Point"}
}