{
  "type": "Feature",
  "properties": {
    "gn:admin1_code":"07",
    "gn:asciiname":"Limones",
    "gn:country_code":"HN",
    "gn:dem":767,
    "gn:feature_class":"P",
    "gn:feature_code":"PPL",
    "gn:name":"Limones",
    "gn:population":0,
    "gn:timezone":"America/Tegucigalpa",
    "iso:country":"HN",
    "wof:name":"Limones",
    "wof:placetype":"locality"
},
  "geometry": {"coordinates":[-86.65000000000001,13.86667],"type":"Point"}
}