{
  "type": "Feature",
  "properties": {
    "gn:admin1_code":"07",
    "gn:asciiname":"Limones",
    "gn:country_code":"HN",
    "gn:dem":767,
    "gn:feature_class":"P",
    "gn:feature_code":"PPL",
    "gn:name":"Limones",
    "gn:population":0,
    "gn:timezone":"America/Tegucigalpa",
    "iso:country":"HN",
    "name:ceb_x_preferred":[
        "Limones"
    ],
    "name:srp_x_preferred":[
        "\u041b\u0438\u043c\u043e\u043d\u0435\u0441"
    ],
    "name:swe_x_preferred":[
        "Limones"
    ],
    "wof:name":"Limones",
    "wof:placetype":"locality"
},
  "geometry": {"coordinates":[-86.65000000000001,13.86667],"type":"Point"}
}