{
  "type": "Feature",
  "properties": {
    "gn:admin1_code":"05",
    "gn:asciiname":"Jimilile",
    "gn:cc2":"HN",
    "gn:country_code":"HN",
    "gn:dem":909,
    "gn:feature_class":"P",
    "gn:feature_code":"PPL",
    "gn:name":"Jimilile",
    "gn:population":0,
    "gn:timezone":"America/Tegucigalpa",
    "iso:country":"HN",
    "name:und_x_variant":[
        "Jinilile",
        "Jimilile"
    ],
    "wof:name":"Jimilile",
    "wof:placetype":"locality"
},
  "geometry": {"coordinates":[-88.86667,14.56667],"type":"Point"}
}