{
  "type": "Feature",
  "properties": {
    "gn:admin1_code":"04",
    "gn:asciiname":"El Caobanal",
    "gn:cc2":"HN",
    "gn:country_code":"HN",
    "gn:dem":1105,
    "gn:feature_class":"P",
    "gn:feature_code":"PPL",
    "gn:name":"El Caobanal",
    "gn:population":0,
    "gn:timezone":"America/Tegucigalpa",
    "iso:country":"HN",
    "name:und_x_variant":[
        "Caobanal",
        "El Caobanal"
    ],
    "wof:name":"El Caobanal",
    "wof:placetype":"locality"
},
  "geometry": {"coordinates":[-87.83333,14.56667],"type":"Point"}
}