{
  "type": "Feature",
  "properties": {
    "gn:asciiname":"Siksayali",
    "gn:country_code":"HN",
    "gn:dem":112,
    "gn:feature_class":"P",
    "gn:feature_code":"PPL",
    "gn:name":"Siksayali",
    "gn:population":0,
    "gn:timezone":"America/Tegucigalpa",
    "iso:country":"HN",
    "name:und_x_variant":[
        "Sika Yari",
        "Siksayari",
        "Siksayali"
    ],
    "wof:name":"Siksayali",
    "wof:placetype":"locality"
},
  "geometry": {"coordinates":[-84.98744000000001,14.73705],"type":"Point"}
}