{
  "type": "Feature",
  "properties": {
    "gn:admin1_code":"16",
    "gn:asciiname":"El Ocotal",
    "gn:cc2":"HN",
    "gn:country_code":"HN",
    "gn:dem":343,
    "gn:feature_class":"P",
    "gn:feature_code":"PPL",
    "gn:name":"El Ocotal",
    "gn:population":0,
    "gn:timezone":"America/Tegucigalpa",
    "iso:country":"HN",
    "name:und_x_variant":[
        "Ocotal",
        "El Ocotal"
    ],
    "wof:name":"El Ocotal",
    "wof:placetype":"locality"
},
  "geometry": {"coordinates":[-88.28333000000001,14.85],"type":"Point"}
}