{
  "type": "Feature",
  "properties": {
    "gn:admin1_code":"03",
    "gn:asciiname":"Jalaca",
    "gn:country_code":"HN",
    "gn:dem":20,
    "gn:feature_class":"P",
    "gn:feature_code":"PPL",
    "gn:name":"Jalaca",
    "gn:population":0,
    "gn:timezone":"America/Tegucigalpa",
    "iso:country":"HN",
    "wof:name":"Jalaca",
    "wof:placetype":"locality"
},
  "geometry": {"coordinates":[-85.88333,15.75],"type":"Point"}
}