{
  "type": "Feature",
  "properties": {
    "gn:admin1_code":"12",
    "gn:asciiname":"Los Laureles",
    "gn:country_code":"HN",
    "gn:dem":462,
    "gn:feature_class":"P",
    "gn:feature_code":"PPL",
    "gn:name":"Los Laureles",
    "gn:population":0,
    "gn:timezone":"America/Tegucigalpa",
    "iso:country":"HN",
    "wof:name":"Los Laureles",
    "wof:placetype":"locality"
},
  "geometry": {"coordinates":[-87.64889000000002,13.88806],"type":"Point"}
}