{
  "type": "Feature",
  "properties": {
    "gn:admin1_code":"08",
    "gn:asciiname":"El Cimarron",
    "gn:country_code":"HN",
    "gn:dem":531,
    "gn:feature_class":"P",
    "gn:feature_code":"PPL",
    "gn:name":"El Cimarr\u00f3n",
    "gn:population":0,
    "gn:timezone":"America/Tegucigalpa",
    "iso:country":"HN",
    "wof:name":"El Cimarron",
    "wof:placetype":"locality"
},
  "geometry": {"coordinates":[-87.56778,13.71083],"type":"Point"}
}