{
  "type": "Feature",
  "properties": {
    "gn:admin1_code":"02",
    "gn:asciiname":"El Ojochal",
    "gn:cc2":"HN",
    "gn:country_code":"HN",
    "gn:dem":8,
    "gn:feature_class":"P",
    "gn:feature_code":"PPL",
    "gn:name":"El Ojochal",
    "gn:population":0,
    "gn:timezone":"America/Tegucigalpa",
    "iso:country":"HN",
    "name:und_x_variant":[
        "El Ajochal",
        "El Ojochal"
    ],
    "wof:name":"El Ojochal",
    "wof:placetype":"locality"
},
  "geometry": {"coordinates":[-87.38889,13.16528],"type":"Point"}
}