{
  "type": "Feature",
  "properties": {
    "gn:admin1_code":"08",
    "gn:asciiname":"La Pina",
    "gn:country_code":"HN",
    "gn:dem":966,
    "gn:feature_class":"P",
    "gn:feature_code":"PPL",
    "gn:name":"La Pi\u00f1a",
    "gn:population":0,
    "gn:timezone":"America/Tegucigalpa",
    "iso:country":"HN",
    "wof:name":"La Pina",
    "wof:placetype":"locality"
},
  "geometry": {"coordinates":[-87.5025,13.97361],"type":"Point"}
}