{
  "type": "Feature",
  "properties": {
    "gn:admin1_code":"08",
    "gn:asciiname":"Las Pinuelas",
    "gn:cc2":"HN",
    "gn:country_code":"HN",
    "gn:dem":775,
    "gn:feature_class":"P",
    "gn:feature_code":"PPL",
    "gn:name":"Las Pi\u00f1uelas",
    "gn:population":0,
    "gn:timezone":"America/Tegucigalpa",
    "iso:country":"HN",
    "name:und_x_variant":[
        "Pi\u00f1uela",
        "Los Pi\u00f1uelas",
        "Las Pi\u00f1uelas"
    ],
    "wof:name":"Las Pinuelas",
    "wof:placetype":"locality"
},
  "geometry": {"coordinates":[-87.185,13.79389],"type":"Point"}
}