{
  "type": "Feature",
  "properties": {
    "gn:admin1_code":"17",
    "gn:asciiname":"El Burio",
    "gn:country_code":"HN",
    "gn:dem":298,
    "gn:feature_class":"P",
    "gn:feature_code":"PPL",
    "gn:name":"El Bur\u00edo",
    "gn:population":0,
    "gn:timezone":"America/Tegucigalpa",
    "iso:country":"HN",
    "wof:name":"El Burio",
    "wof:placetype":"locality"
},
  "geometry": {"coordinates":[-87.61166999999998,13.66111],"type":"Point"}
}