{
  "type": "Feature",
  "properties": {
    "gn:admin1_code":"07",
    "gn:asciiname":"Matapalo",
    "gn:cc2":"HN",
    "gn:country_code":"HN",
    "gn:dem":335,
    "gn:feature_class":"P",
    "gn:feature_code":"PPL",
    "gn:name":"Matapalo",
    "gn:population":0,
    "gn:timezone":"America/Tegucigalpa",
    "iso:country":"HN",
    "name:und_x_variant":[
        "El Mata Palo",
        "Matapalo"
    ],
    "wof:name":"Matapalo",
    "wof:placetype":"locality"
},
  "geometry": {"coordinates":[-87.15000000000001,13.53333],"type":"Point"}
}