{
  "type": "Feature",
  "properties": {
    "gn:admin1_code":"15",
    "gn:asciiname":"Agua Zarca",
    "gn:country_code":"HN",
    "gn:dem":899,
    "gn:feature_class":"P",
    "gn:feature_code":"PPL",
    "gn:name":"Agua Zarca",
    "gn:population":0,
    "gn:timezone":"America/Tegucigalpa",
    "iso:country":"HN",
    "wof:name":"Agua Zarca",
    "wof:placetype":"locality"
},
  "geometry": {"coordinates":[-86.43333,14.66667],"type":"Point"}
}