{
  "type": "Feature",
  "properties": {
    "gn:admin1_code":"04",
    "gn:asciiname":"El Tintel",
    "gn:cc2":"HN",
    "gn:country_code":"HN",
    "gn:dem":1499,
    "gn:feature_class":"P",
    "gn:feature_code":"PPL",
    "gn:name":"El Tintel",
    "gn:population":0,
    "gn:timezone":"America/Tegucigalpa",
    "iso:country":"HN",
    "name:und_x_variant":[
        "Tintel",
        "El Tintel"
    ],
    "wof:name":"El Tintel",
    "wof:placetype":"locality"
},
  "geometry": {"coordinates":[-87.51666999999998,14.41667],"type":"Point"}
}