{
  "type": "Feature",
  "properties": {
    "gn:admin1_code":"17",
    "gn:asciiname":"Paso de Velas",
    "gn:cc2":"HN",
    "gn:country_code":"HN",
    "gn:dem":10,
    "gn:feature_class":"P",
    "gn:feature_code":"PPL",
    "gn:name":"Paso de Velas",
    "gn:population":0,
    "gn:timezone":"America/Tegucigalpa",
    "iso:country":"HN",
    "name:und_x_variant":[
        "Paso Velas",
        "Paso de Velas"
    ],
    "wof:name":"Paso de Velas",
    "wof:placetype":"locality"
},
  "geometry": {"coordinates":[-87.55139,13.43667],"type":"Point"}
}