{
  "type": "Feature",
  "properties": {
    "gn:admin1_code":"06",
    "gn:asciiname":"Colonia La Paz",
    "gn:country_code":"HN",
    "gn:dem":97,
    "gn:feature_class":"P",
    "gn:feature_code":"PPL",
    "gn:name":"Colonia La Paz",
    "gn:population":0,
    "gn:timezone":"America/Tegucigalpa",
    "iso:country":"HN",
    "wof:name":"Colonia La Paz",
    "wof:placetype":"locality"
},
  "geometry": {"coordinates":[-87.98075,15.04125],"type":"Point"}
}