{
  "type": "Feature",
  "properties": {
    "gn:admin1_code":"08",
    "gn:asciiname":"Mezcales",
    "gn:cc2":"HN",
    "gn:country_code":"HN",
    "gn:dem":607,
    "gn:feature_class":"P",
    "gn:feature_code":"PPL",
    "gn:name":"Mezcales",
    "gn:population":0,
    "gn:timezone":"America/Tegucigalpa",
    "iso:country":"HN",
    "name:und_x_variant":[
        "Mescales",
        "Mezcales"
    ],
    "wof:name":"Mezcales",
    "wof:placetype":"locality"
},
  "geometry": {"coordinates":[-87.21666999999999,14.75],"type":"Point"}
}