{
  "type": "Feature",
  "properties": {
    "gn:admin1_code":"10",
    "gn:asciiname":"El Culucon",
    "gn:cc2":"HN",
    "gn:country_code":"HN",
    "gn:dem":134,
    "gn:feature_class":"P",
    "gn:feature_code":"PPL",
    "gn:name":"El Culuc\u00f3n",
    "gn:population":0,
    "gn:timezone":"America/Tegucigalpa",
    "iso:country":"HN",
    "name:und_x_variant":[
        "Cutuc\u00f3n",
        "El Culuc\u00f3n"
    ],
    "wof:name":"El Culucon",
    "wof:placetype":"locality"
},
  "geometry": {"coordinates":[-88.40000000000001,13.88333],"type":"Point"}
}