{
  "type": "Feature",
  "properties": {
    "gn:admin1_code":"09",
    "gn:asciiname":"Swabila",
    "gn:country_code":"HN",
    "gn:dem":5,
    "gn:feature_class":"P",
    "gn:feature_code":"PPL",
    "gn:name":"Swabila",
    "gn:population":0,
    "gn:timezone":"America/Tegucigalpa",
    "iso:country":"HN",
    "wof:name":"Swabila",
    "wof:placetype":"locality"
},
  "geometry": {"coordinates":[-83.59999999999999,15.08333],"type":"Point"}
}