{
  "type": "Feature",
  "properties": {
    "gn:admin1_code":"18",
    "gn:asciiname":"El Chorro",
    "gn:cc2":"HN",
    "gn:country_code":"HN",
    "gn:dem":461,
    "gn:feature_class":"P",
    "gn:feature_code":"PPL",
    "gn:name":"El Chorro",
    "gn:population":0,
    "gn:timezone":"America/Tegucigalpa",
    "iso:country":"HN",
    "name:und_x_variant":[
        "Chorro",
        "El Chorro"
    ],
    "wof:name":"El Chorro",
    "wof:placetype":"locality"
},
  "geometry": {"coordinates":[-87.28333000000001,14.91667],"type":"Point"}
}