{
  "type": "Feature",
  "properties": {
    "gn:admin1_code":"05",
    "gn:asciiname":"El Matasano",
    "gn:cc2":"HN",
    "gn:country_code":"HN",
    "gn:dem":1270,
    "gn:feature_class":"P",
    "gn:feature_code":"PPL",
    "gn:name":"El Matasano",
    "gn:population":0,
    "gn:timezone":"America/Tegucigalpa",
    "iso:country":"HN",
    "name:und_x_variant":[
        "El Matazano",
        "El Matasano"
    ],
    "wof:name":"El Matasano",
    "wof:placetype":"locality"
},
  "geometry": {"coordinates":[-88.78333000000001,14.65],"type":"Point"}
}