{
  "type": "Feature",
  "properties": {
    "gn:admin1_code":"08",
    "gn:asciiname":"Concepcion de Rio Grande",
    "gn:cc2":"HN",
    "gn:country_code":"HN",
    "gn:dem":1107,
    "gn:feature_class":"P",
    "gn:feature_code":"PPL",
    "gn:name":"Concepci\u00f3n de R\u00edo Grande",
    "gn:population":0,
    "gn:timezone":"America/Tegucigalpa",
    "iso:country":"HN",
    "name:und_x_variant":[
        "Concepci\u00f3n del Rio Grande",
        "Concepci\u00f3n R\u00edo Grande",
        "Concepci\u00f3n de R\u00edo Grande"
    ],
    "wof:name":"Concepcion de Rio Grande",
    "wof:placetype":"locality"
},
  "geometry": {"coordinates":[-87.28278,13.99278],"type":"Point"}
}