{
  "type": "Feature",
  "properties": {
    "gn:admin1_code":"02",
    "gn:asciiname":"La Canita",
    "gn:country_code":"HN",
    "gn:dem":384,
    "gn:feature_class":"P",
    "gn:feature_code":"PPL",
    "gn:name":"La Ca\u00f1ita",
    "gn:population":0,
    "gn:timezone":"America/Tegucigalpa",
    "iso:country":"HN",
    "wof:name":"La Canita",
    "wof:placetype":"locality"
},
  "geometry": {"coordinates":[-87.02500000000001,13.465],"type":"Point"}
}