{
  "type": "Feature",
  "properties": {
    "gn:admin1_code":"12",
    "gn:asciiname":"Portillo de La Cruz",
    "gn:country_code":"HN",
    "gn:dem":409,
    "gn:feature_class":"P",
    "gn:feature_code":"PPL",
    "gn:name":"Portillo de La Cruz",
    "gn:population":0,
    "gn:timezone":"America/Tegucigalpa",
    "iso:country":"HN",
    "wof:name":"Portillo de La Cruz",
    "wof:placetype":"locality"
},
  "geometry": {"coordinates":[-87.68583000000002,13.93139],"type":"Point"}
}