{
  "type": "Feature",
  "properties": {
    "gn:admin1_code":"08",
    "gn:asciiname":"Zarzalosa",
    "gn:cc2":"HN",
    "gn:country_code":"HN",
    "gn:dem":910,
    "gn:feature_class":"P",
    "gn:feature_code":"PPL",
    "gn:name":"Zarzalosa",
    "gn:population":0,
    "gn:timezone":"America/Tegucigalpa",
    "iso:country":"HN",
    "name:und_x_variant":[
        "El Portillo Zarzalosa",
        "Zarzalosa"
    ],
    "wof:name":"Zarzalosa",
    "wof:placetype":"locality"
},
  "geometry": {"coordinates":[-87.08333,14.36667],"type":"Point"}
}