{
  "type": "Feature",
  "properties": {
    "gn:admin1_code":"13",
    "gn:asciiname":"El Cipres",
    "gn:country_code":"HN",
    "gn:dem":545,
    "gn:feature_class":"P",
    "gn:feature_code":"PPL",
    "gn:name":"El Cipr\u00e9s",
    "gn:population":0,
    "gn:timezone":"America/Tegucigalpa",
    "iso:country":"HN",
    "wof:name":"El Cipres",
    "wof:placetype":"locality"
},
  "geometry": {"coordinates":[-88.90000000000001,14.18333],"type":"Point"}
}