{
  "type": "Feature",
  "properties": {
    "gn:admin1_code":"02",
    "gn:asciiname":"Guacimal",
    "gn:country_code":"HN",
    "gn:dem":479,
    "gn:feature_class":"P",
    "gn:feature_code":"PPL",
    "gn:name":"Guacimal",
    "gn:population":0,
    "gn:timezone":"America/Tegucigalpa",
    "iso:country":"HN",
    "wof:name":"Guacimal",
    "wof:placetype":"locality"
},
  "geometry": {"coordinates":[-87.01666999999998,13.21667],"type":"Point"}
}