{
  "type": "Feature",
  "properties": {
    "gn:admin1_code":"08",
    "gn:asciiname":"Joya de Quebrachos",
    "gn:cc2":"HN",
    "gn:country_code":"HN",
    "gn:dem":969,
    "gn:feature_class":"P",
    "gn:feature_code":"PPL",
    "gn:name":"Joya de Quebrachos",
    "gn:population":0,
    "gn:timezone":"America/Tegucigalpa",
    "iso:country":"HN",
    "name:und_x_variant":[
        "Yoya de Quebrachos",
        "Joya de Quebracho",
        "Joya de Quebrachos"
    ],
    "wof:name":"Joya de Quebrachos",
    "wof:placetype":"locality"
},
  "geometry": {"coordinates":[-86.96666999999999,14.78333],"type":"Point"}
}