{
  "type": "Feature",
  "properties": {
    "gn:admin1_code":"02",
    "gn:asciiname":"Mata Palo",
    "gn:cc2":"HN",
    "gn:country_code":"HN",
    "gn:dem":381,
    "gn:feature_class":"P",
    "gn:feature_code":"PPL",
    "gn:name":"Mata Palo",
    "gn:population":0,
    "gn:timezone":"America/Tegucigalpa",
    "iso:country":"HN",
    "name:und_x_variant":[
        "El Matapalo",
        "Matapalo",
        "Mata Palo"
    ],
    "wof:name":"Mata Palo",
    "wof:placetype":"locality"
},
  "geometry": {"coordinates":[-87.13389000000002,13.54833],"type":"Point"}
}