{
  "type": "Feature",
  "properties": {
    "gn:admin1_code":"14",
    "gn:asciiname":"Las Vegas",
    "gn:country_code":"HN",
    "gn:dem":1031,
    "gn:feature_class":"P",
    "gn:feature_code":"PPL",
    "gn:name":"Las Vegas",
    "gn:population":0,
    "gn:timezone":"America/Tegucigalpa",
    "iso:country":"HN",
    "wof:name":"Las Vegas",
    "wof:placetype":"locality"
},
  "geometry": {"coordinates":[-88.96666999999999,14.25],"type":"Point"}
}