{
  "type": "Feature",
  "properties": {
    "gn:admin1_code":"15",
    "gn:asciiname":"El Barrero",
    "gn:cc2":"HN",
    "gn:country_code":"HN",
    "gn:dem":647,
    "gn:feature_class":"P",
    "gn:feature_code":"PPL",
    "gn:name":"El Barrero",
    "gn:population":0,
    "gn:timezone":"America/Tegucigalpa",
    "iso:country":"HN",
    "name:ita_x_preferred":[
        "El Barrero"
    ],
    "name:spa_x_preferred":[
        "El Barrero"
    ],
    "name:und_x_variant":[
        "Barero",
        "El Barro"
    ],
    "name:zho_x_preferred":[
        "\u57c3\u5c14\u5df4\u96f7\u7f57"
    ],
    "wof:name":"El Barrero",
    "wof:placetype":"locality"
},
  "geometry": {"coordinates":[-86.05,15.21667],"type":"Point"}
}