{
  "type": "Feature",
  "properties": {
    "gn:country":"HN",
    "gn:fcode":"PPL",
    "gn:population":1465,
    "iso:country":"HN",
    "name:und_x_variant":[
        "Balsamo"
    ],
    "qs:name":"B\u00e1lsamo Oriental",
    "qs:photos_9r":0,
    "qs:photos_sr":0,
    "qs:pop_sr":"3",
    "wof:name":"B\u00e1lsamo Oriental",
    "wof:placetype":"locality",
    "wof:population":1465
},
  "geometry": {"coordinates":[-86.33333,15.48333],"type":"Point"}
}