{
  "type": "Feature",
  "properties": {
    "gn:admin1_code":"02",
    "gn:asciiname":"Hacienda Nueva Esperanza",
    "gn:country_code":"HN",
    "gn:dem":244,
    "gn:feature_class":"P",
    "gn:feature_code":"PPL",
    "gn:name":"Hacienda Nueva Esperanza",
    "gn:population":0,
    "gn:timezone":"America/Tegucigalpa",
    "iso:country":"HN",
    "wof:name":"Hacienda Nueva Esperanza",
    "wof:placetype":"locality"
},
  "geometry": {"coordinates":[-87.23333000000002,13.58111],"type":"Point"}
}