{
  "type": "Feature",
  "properties": {
    "gn:admin1_code":"13",
    "gn:asciiname":"El Rodeo de Quelacasque",
    "gn:cc2":"HN",
    "gn:country_code":"HN",
    "gn:dem":802,
    "gn:feature_class":"P",
    "gn:feature_code":"PPL",
    "gn:name":"El Rodeo de Quelacasque",
    "gn:population":0,
    "gn:timezone":"America/Tegucigalpa",
    "iso:country":"HN",
    "name:und_x_variant":[
        "Quelascasque",
        "El Rodeo Quelac\u00e1sque",
        "Quelacasque",
        "El Rodeo de Quelacasque"
    ],
    "wof:name":"El Rodeo de Quelacasque",
    "wof:placetype":"locality"
},
  "geometry": {"coordinates":[-88.55,14.63333],"type":"Point"}
}