{
  "type": "Feature",
  "properties": {
    "gn:admin1_code":"08",
    "gn:asciiname":"El Jicarito",
    "gn:country_code":"HN",
    "gn:dem":678,
    "gn:feature_class":"P",
    "gn:feature_code":"PPL",
    "gn:name":"El Jicarito",
    "gn:population":0,
    "gn:timezone":"America/Tegucigalpa",
    "iso:country":"HN",
    "wof:name":"El Jicarito",
    "wof:placetype":"locality"
},
  "geometry": {"coordinates":[-87.24694000000002,13.77528],"type":"Point"}
}