{
  "type": "Feature",
  "properties": {
    "gn:admin1_code":"17",
    "gn:asciiname":"Quebrada Grande",
    "gn:country_code":"HN",
    "gn:dem":274,
    "gn:feature_class":"P",
    "gn:feature_code":"PPL",
    "gn:name":"Quebrada Grande",
    "gn:population":0,
    "gn:timezone":"America/Tegucigalpa",
    "iso:country":"HN",
    "wof:name":"Quebrada Grande",
    "wof:placetype":"locality"
},
  "geometry": {"coordinates":[-87.59999999999999,13.68333],"type":"Point"}
}