{
  "type": "Feature",
  "properties": {
    "gn:admin1_code":"09",
    "gn:asciiname":"Titi",
    "gn:country_code":"HN",
    "gn:dem":5,
    "gn:feature_class":"P",
    "gn:feature_code":"PPL",
    "gn:name":"Titi",
    "gn:population":0,
    "gn:timezone":"America/Tegucigalpa",
    "iso:country":"HN",
    "name:cat_x_preferred":[
        "Tit\u00ed"
    ],
    "name:deu_x_preferred":[
        "Springaffen"
    ],
    "name:eus_x_preferred":[
        "Titi"
    ],
    "name:fas_x_preferred":[
        "\u062a\u06cc\u200c\u062a\u06cc"
    ],
    "name:fra_x_preferred":[
        "Callicebinae"
    ],
    "name:pol_x_preferred":[
        "Titi"
    ],
    "name:rus_x_preferred":[
        "Callicebinae"
    ],
    "name:spa_x_preferred":[
        "Callicebinae"
    ],
    "wof:name":"Titi",
    "wof:placetype":"locality"
},
  "geometry": {"coordinates":[-83.31667,15.08333],"type":"Point"}
}