{
  "type": "Feature",
  "properties": {
    "gn:admin1_code":"09",
    "gn:asciiname":"Titi",
    "gn:country_code":"HN",
    "gn:dem":5,
    "gn:feature_class":"P",
    "gn:feature_code":"PPL",
    "gn:name":"Titi",
    "gn:population":0,
    "gn:timezone":"America/Tegucigalpa",
    "iso:country":"HN",
    "wof:name":"Titi",
    "wof:placetype":"locality"
},
  "geometry": {"coordinates":[-83.31667,15.08333],"type":"Point"}
}