{
  "type": "Feature",
  "properties": {
    "gn:admin1_code":"13",
    "gn:asciiname":"Troja Quemada",
    "gn:country_code":"HN",
    "gn:dem":801,
    "gn:feature_class":"P",
    "gn:feature_code":"PPL",
    "gn:name":"Troja Quemada",
    "gn:population":0,
    "gn:timezone":"America/Tegucigalpa",
    "iso:country":"HN",
    "wof:name":"Troja Quemada",
    "wof:placetype":"locality"
},
  "geometry": {"coordinates":[-88.83333,14.18333],"type":"Point"}
}