{
  "type": "Feature",
  "properties": {
    "gn:admin1_code":"05",
    "gn:asciiname":"Boca del Monte",
    "gn:country_code":"HN",
    "gn:dem":1011,
    "gn:feature_class":"P",
    "gn:feature_code":"PPL",
    "gn:name":"Boca del Monte",
    "gn:population":0,
    "gn:timezone":"America/Tegucigalpa",
    "iso:country":"HN",
    "wof:name":"Boca del Monte",
    "wof:placetype":"locality"
},
  "geometry": {"coordinates":[-89.15000000000001,14.78333],"type":"Point"}
}