{
  "type": "Feature",
  "properties": {
    "gn:admin1_code":"15",
    "gn:asciiname":"Guamilon",
    "gn:country_code":"HN",
    "gn:dem":883,
    "gn:feature_class":"P",
    "gn:feature_code":"PPL",
    "gn:name":"Guamil\u00f3n",
    "gn:population":0,
    "gn:timezone":"America/Tegucigalpa",
    "iso:country":"HN",
    "wof:name":"Guamilon",
    "wof:placetype":"locality"
},
  "geometry": {"coordinates":[-86.76666999999998,14.95],"type":"Point"}
}