{
  "type": "Feature",
  "properties": {
    "gn:admin1_code":"03",
    "gn:asciiname":"Limoncito",
    "gn:country_code":"HN",
    "gn:dem":7,
    "gn:feature_class":"P",
    "gn:feature_code":"PPL",
    "gn:name":"Limoncito",
    "gn:population":0,
    "gn:timezone":"America/Tegucigalpa",
    "iso:country":"HN",
    "name:ceb_x_preferred":[
        "Limoncito"
    ],
    "name:deu_x_preferred":[
        "Limoncito"
    ],
    "name:zho_x_preferred":[
        "\u5229\u8499\u897f\u6258"
    ],
    "wof:name":"Limoncito",
    "wof:placetype":"locality"
},
  "geometry": {"coordinates":[-85.55,15.85],"type":"Point"}
}