{
  "type": "Feature",
  "properties": {
    "gn:admin1_code":"17",
    "gn:asciiname":"Horcones",
    "gn:cc2":"HN",
    "gn:country_code":"HN",
    "gn:dem":252,
    "gn:feature_class":"P",
    "gn:feature_code":"PPL",
    "gn:name":"Horcones",
    "gn:population":0,
    "gn:timezone":"America/Tegucigalpa",
    "iso:country":"HN",
    "name:und_x_variant":[
        "Los Horcones",
        "Horcones"
    ],
    "wof:name":"Horcones",
    "wof:placetype":"locality"
},
  "geometry": {"coordinates":[-87.65111,13.65139],"type":"Point"}
}