{
  "type": "Feature",
  "properties": {
    "gn:admin1_code":"02",
    "gn:asciiname":"San Rafael de Precepalma",
    "gn:country_code":"HN",
    "gn:dem":79,
    "gn:feature_class":"P",
    "gn:feature_code":"PPL",
    "gn:name":"San Rafael de Precepalma",
    "gn:population":0,
    "gn:timezone":"America/Tegucigalpa",
    "iso:country":"HN",
    "wof:name":"San Rafael de Precepalma",
    "wof:placetype":"locality"
},
  "geometry": {"coordinates":[-87.12971999999998,13.38889],"type":"Point"}
}