{
  "type": "Feature",
  "properties": {
    "gn:admin1_code":"04",
    "gn:asciiname":"Las Mesas",
    "gn:cc2":"HN",
    "gn:country_code":"HN",
    "gn:dem":1168,
    "gn:feature_class":"P",
    "gn:feature_code":"PPL",
    "gn:name":"Las Mesas",
    "gn:population":0,
    "gn:timezone":"America/Tegucigalpa",
    "iso:country":"HN",
    "name:und_x_variant":[
        "Los Mesas",
        "Las Mesas"
    ],
    "wof:name":"Las Mesas",
    "wof:placetype":"locality"
},
  "geometry": {"coordinates":[-87.53333000000001,14.11667],"type":"Point"}
}