{
  "type": "Feature",
  "properties": {
    "gn:admin1_code":"16",
    "gn:asciiname":"Copantio",
    "gn:country_code":"HN",
    "gn:dem":339,
    "gn:feature_class":"P",
    "gn:feature_code":"PPL",
    "gn:name":"Copantio",
    "gn:population":0,
    "gn:timezone":"America/Tegucigalpa",
    "iso:country":"HN",
    "wof:name":"Copantio",
    "wof:placetype":"locality"
},
  "geometry": {"coordinates":[-88.59999999999999,14.98333],"type":"Point"}
}