{
  "type": "Feature",
  "properties": {
    "gn:admin1_code":"05",
    "gn:asciiname":"Las Crucitas",
    "gn:country_code":"HN",
    "gn:dem":786,
    "gn:feature_class":"P",
    "gn:feature_code":"PPL",
    "gn:name":"Las Crucitas",
    "gn:population":0,
    "gn:timezone":"America/Tegucigalpa",
    "iso:country":"HN",
    "wof:name":"Las Crucitas",
    "wof:placetype":"locality"
},
  "geometry": {"coordinates":[-88.84999999999999,14.66667],"type":"Point"}
}