{
  "type": "Feature",
  "properties": {
    "gn:admin1_code":"13",
    "gn:asciiname":"Maneadero",
    "gn:country_code":"HN",
    "gn:dem":532,
    "gn:feature_class":"P",
    "gn:feature_code":"PPL",
    "gn:name":"Maneadero",
    "gn:population":0,
    "gn:timezone":"America/Tegucigalpa",
    "iso:country":"HN",
    "name:spa_x_preferred":[
        "Maneadero"
    ],
    "wof:name":"Maneadero",
    "wof:placetype":"locality"
},
  "geometry": {"coordinates":[-88.61667,14.11667],"type":"Point"}
}