{
  "type": "Feature",
  "properties": {
    "iso:country":"HN",
    "name:unk_x_variant":[
        "Planes"
    ],
    "qs:gn_country":"HN",
    "qs:gn_fcode":"PPL",
    "qs:gn_pop":1048,
    "qs:name":"San Juan de Planes",
    "qs:name_adm0":"Honduras",
    "qs:name_adm1":"Cop\u00e1n",
    "qs:photos":0,
    "qs:photos_1k":0,
    "qs:photos_9k":0,
    "qs:photos_9r":0,
    "qs:photos_all":0,
    "qs:photos_sr":0,
    "qs:placetype":"Town",
    "qs:pop_sr":"3",
    "qs:woe_adm0":23424841,
    "wof:name":"San Juan de Planes",
    "wof:placetype":"locality",
    "wof:population":1048
},
  "geometry": {"coordinates":[-88.78333000000001,14.93333],"type":"Point"}
}