{
  "type": "Feature",
  "properties": {
    "gn:admin1_code":"05",
    "gn:asciiname":"Piedras de Fuego",
    "gn:cc2":"HN",
    "gn:country_code":"HN",
    "gn:dem":951,
    "gn:feature_class":"P",
    "gn:feature_code":"PPL",
    "gn:name":"Piedras de Fuego",
    "gn:population":0,
    "gn:timezone":"America/Tegucigalpa",
    "iso:country":"HN",
    "name:und_x_variant":[
        "Piedra de Juego",
        "Piedras de Fuego"
    ],
    "wof:name":"Piedras de Fuego",
    "wof:placetype":"locality"
},
  "geometry": {"coordinates":[-88.86667,14.83333],"type":"Point"}
}