{
  "type": "Feature",
  "properties": {
    "gn:admin1_code":"12",
    "gn:asciiname":"El Zapote",
    "gn:country_code":"HN",
    "gn:dem":746,
    "gn:feature_class":"P",
    "gn:feature_code":"PPL",
    "gn:name":"El Zapote",
    "gn:population":0,
    "gn:timezone":"America/Tegucigalpa",
    "iso:country":"HN",
    "wof:name":"El Zapote",
    "wof:placetype":"locality"
},
  "geometry": {"coordinates":[-87.79583000000002,13.99944],"type":"Point"}
}