{
  "type": "Feature",
  "properties": {
    "gn:admin1_code":"02",
    "gn:asciiname":"El Bajio",
    "gn:country_code":"HN",
    "gn:dem":345,
    "gn:feature_class":"P",
    "gn:feature_code":"PPL",
    "gn:name":"El Baj\u00edo",
    "gn:population":0,
    "gn:timezone":"America/Tegucigalpa",
    "iso:country":"HN",
    "wof:name":"El Bajio",
    "wof:placetype":"locality"
},
  "geometry": {"coordinates":[-87.26528,13.65694],"type":"Point"}
}