{
  "type": "Feature",
  "properties": {
    "gn:admin1_code":"13",
    "gn:asciiname":"La Miande",
    "gn:cc2":"HN",
    "gn:country_code":"HN",
    "gn:dem":1654,
    "gn:feature_class":"P",
    "gn:feature_code":"PPL",
    "gn:name":"La Miande",
    "gn:population":0,
    "gn:timezone":"America/Tegucigalpa",
    "iso:country":"HN",
    "name:und_x_variant":[
        "Miande",
        "La Miande"
    ],
    "wof:name":"La Miande",
    "wof:placetype":"locality"
},
  "geometry": {"coordinates":[-88.68333,14.46667],"type":"Point"}
}