{
  "type": "Feature",
  "properties": {
    "gn:admin1_code":"02",
    "gn:asciiname":"El Chicharron",
    "gn:cc2":"HN",
    "gn:country_code":"HN",
    "gn:dem":288,
    "gn:feature_class":"P",
    "gn:feature_code":"PPL",
    "gn:name":"El Chicharr\u00f3n",
    "gn:population":0,
    "gn:timezone":"America/Tegucigalpa",
    "iso:country":"HN",
    "name:und_x_variant":[
        "Chicharron",
        "El Chicharr\u00f3n"
    ],
    "wof:name":"El Chicharron",
    "wof:placetype":"locality"
},
  "geometry": {"coordinates":[-86.88333,13.58333],"type":"Point"}
}