{
  "type": "Feature",
  "properties": {
    "gn:admin1_code":"12",
    "gn:asciiname":"Aguacatal",
    "gn:country_code":"HN",
    "gn:dem":1887,
    "gn:feature_class":"P",
    "gn:feature_code":"PPL",
    "gn:name":"Aguacatal",
    "gn:population":0,
    "gn:timezone":"America/Tegucigalpa",
    "iso:country":"HN",
    "wof:name":"Aguacatal",
    "wof:placetype":"locality"
},
  "geometry": {"coordinates":[-87.81667,14.15],"type":"Point"}
}