{
  "type": "Feature",
  "properties": {
    "gn:admin1_code":"06",
    "gn:asciiname":"Chaguiton",
    "gn:country_code":"HN",
    "gn:dem":611,
    "gn:feature_class":"P",
    "gn:feature_code":"PPL",
    "gn:name":"Chag\u00fcit\u00f3n",
    "gn:population":0,
    "gn:timezone":"America/Tegucigalpa",
    "iso:country":"HN",
    "wof:name":"Chaguiton",
    "wof:placetype":"locality"
},
  "geometry": {"coordinates":[-87.83333,14.98333],"type":"Point"}
}