{
  "type": "Feature",
  "properties": {
    "gn:admin1_code":"16",
    "gn:asciiname":"La Joya del Venado",
    "gn:country_code":"HN",
    "gn:dem":245,
    "gn:feature_class":"P",
    "gn:feature_code":"PPL",
    "gn:name":"La Joya del V\u00e9nado",
    "gn:population":0,
    "gn:timezone":"America/Tegucigalpa",
    "iso:country":"HN",
    "wof:name":"La Joya del Venado",
    "wof:placetype":"locality"
},
  "geometry": {"coordinates":[-88.53222,15.35417],"type":"Point"}
}