{
  "type": "Feature",
  "properties": {
    "gn:admin1_code":"08",
    "gn:asciiname":"El Llano del Jicaro",
    "gn:country_code":"HN",
    "gn:dem":870,
    "gn:feature_class":"P",
    "gn:feature_code":"PPL",
    "gn:name":"El Llano del J\u00edcaro",
    "gn:population":0,
    "gn:timezone":"America/Tegucigalpa",
    "iso:country":"HN",
    "wof:name":"El Llano del Jicaro",
    "wof:placetype":"locality"
},
  "geometry": {"coordinates":[-87.035,13.98361],"type":"Point"}
}