{
  "type": "Feature",
  "properties": {
    "gn:admin1_code":"14",
    "gn:asciiname":"Agua Caliente",
    "gn:country_code":"HN",
    "gn:dem":814,
    "gn:feature_class":"P",
    "gn:feature_code":"PPL",
    "gn:name":"Agua Caliente",
    "gn:population":0,
    "gn:timezone":"America/Tegucigalpa",
    "iso:country":"HN",
    "name:bre_x_preferred":[
        "Agua Caliente"
    ],
    "name:ceb_x_preferred":[
        "Agua Caliente"
    ],
    "name:deu_x_preferred":[
        "Agua Caliente"
    ],
    "name:spa_x_preferred":[
        "Agua Caliente"
    ],
    "name:swe_x_preferred":[
        "Agua Caliente"
    ],
    "wof:name":"Agua Caliente",
    "wof:placetype":"locality"
},
  "geometry": {"coordinates":[-89.13333,14.66667],"type":"Point"}
}