{
  "type": "Feature",
  "properties": {
    "gn:admin1_code":"13",
    "gn:asciiname":"El Manchon",
    "gn:cc2":"HN",
    "gn:country_code":"HN",
    "gn:dem":744,
    "gn:feature_class":"P",
    "gn:feature_code":"PPL",
    "gn:name":"El Manch\u00f3n",
    "gn:population":0,
    "gn:timezone":"America/Tegucigalpa",
    "iso:country":"HN",
    "name:und_x_variant":[
        "Manch\u00f3n",
        "El Manch\u00f3n"
    ],
    "wof:name":"El Manchon",
    "wof:placetype":"locality"
},
  "geometry": {"coordinates":[-88.56667,14.61667],"type":"Point"}
}