{
  "type": "Feature",
  "properties": {
    "gn:admin1_code":"06",
    "gn:asciiname":"Cieneguita",
    "gn:cc2":"HN",
    "gn:country_code":"HN",
    "gn:dem":228,
    "gn:feature_class":"P",
    "gn:feature_code":"PPL",
    "gn:name":"Cieneguita",
    "gn:population":0,
    "gn:timezone":"America/Tegucigalpa",
    "iso:country":"HN",
    "name:und_x_variant":[
        "Cienaguita",
        "Cienoguita",
        "Cieneguita"
    ],
    "wof:name":"Cieneguita",
    "wof:placetype":"locality"
},
  "geometry": {"coordinates":[-87.93333,15.75],"type":"Point"}
}