{
  "type": "Feature",
  "properties": {
    "gn:admin1_code":"14",
    "gn:asciiname":"Quebradas",
    "gn:country_code":"HN",
    "gn:dem":1207,
    "gn:feature_class":"P",
    "gn:feature_code":"PPL",
    "gn:name":"Quebradas",
    "gn:population":0,
    "gn:timezone":"America/Tegucigalpa",
    "iso:country":"HN",
    "wof:name":"Quebradas",
    "wof:placetype":"locality"
},
  "geometry": {"coordinates":[-89.11667,14.68333],"type":"Point"}
}