{
  "type": "Feature",
  "properties": {
    "gn:admin1_code":"17",
    "gn:asciiname":"Estacones",
    "gn:country_code":"HN",
    "gn:dem":152,
    "gn:feature_class":"P",
    "gn:feature_code":"PPL",
    "gn:name":"Estacones",
    "gn:population":0,
    "gn:timezone":"America/Tegucigalpa",
    "iso:country":"HN",
    "wof:name":"Estacones",
    "wof:placetype":"locality"
},
  "geometry": {"coordinates":[-87.51666999999998,13.58333],"type":"Point"}
}