{
  "type": "Feature",
  "properties": {
    "gn:admin1_code":"17",
    "gn:asciiname":"El Jicaro",
    "gn:country_code":"HN",
    "gn:dem":249,
    "gn:feature_class":"P",
    "gn:feature_code":"PPL",
    "gn:name":"El J\u00edcaro",
    "gn:population":0,
    "gn:timezone":"America/Tegucigalpa",
    "iso:country":"HN",
    "wof:name":"El Jicaro",
    "wof:placetype":"locality"
},
  "geometry": {"coordinates":[-87.67333000000001,13.72389],"type":"Point"}
}