{
  "type": "Feature",
  "properties": {
    "gn:admin1_code":"15",
    "gn:asciiname":"Dos Quebradas",
    "gn:country_code":"HN",
    "gn:dem":569,
    "gn:feature_class":"P",
    "gn:feature_code":"PPL",
    "gn:name":"Dos Quebradas",
    "gn:population":0,
    "gn:timezone":"America/Tegucigalpa",
    "iso:country":"HN",
    "wof:name":"Dos Quebradas",
    "wof:placetype":"locality"
},
  "geometry": {"coordinates":[-86.16667,14.86667],"type":"Point"}
}