{
  "type": "Feature",
  "properties": {
    "gn:admin1_code":"02",
    "gn:asciiname":"El Borbollon",
    "gn:country_code":"HN",
    "gn:dem":167,
    "gn:feature_class":"P",
    "gn:feature_code":"PPL",
    "gn:name":"El Borboll\u00f3n",
    "gn:population":0,
    "gn:timezone":"America/Tegucigalpa",
    "iso:country":"HN",
    "wof:name":"El Borbollon",
    "wof:placetype":"locality"
},
  "geometry": {"coordinates":[-87.39361,13.665],"type":"Point"}
}