{
  "type": "Feature",
  "properties": {
    "gn:admin1_code":"06",
    "gn:asciiname":"La Mina",
    "gn:country_code":"HN",
    "gn:dem":74,
    "gn:feature_class":"P",
    "gn:feature_code":"PPL",
    "gn:name":"La Mina",
    "gn:population":0,
    "gn:timezone":"America/Tegucigalpa",
    "iso:country":"HN",
    "name:ita_x_preferred":[
        "La Mina"
    ],
    "wof:name":"La Mina",
    "wof:placetype":"locality"
},
  "geometry": {"coordinates":[-88.01666999999998,15.26667],"type":"Point"}
}