{
  "type": "Feature",
  "properties": {
    "gn:admin1_code":"08",
    "gn:asciiname":"Tamal y Queso",
    "gn:country_code":"HN",
    "gn:dem":1019,
    "gn:feature_class":"P",
    "gn:feature_code":"PPL",
    "gn:name":"Tamal y Queso",
    "gn:population":0,
    "gn:timezone":"America/Tegucigalpa",
    "iso:country":"HN",
    "wof:name":"Tamal y Queso",
    "wof:placetype":"locality"
},
  "geometry": {"coordinates":[-87.28333000000001,14.28333],"type":"Point"}
}