{
  "type": "Feature",
  "properties": {
    "gn:admin1_code":"08",
    "gn:asciiname":"El Barrio Arriba",
    "gn:country_code":"HN",
    "gn:dem":1208,
    "gn:feature_class":"P",
    "gn:feature_code":"PPL",
    "gn:name":"El Barrio Arriba",
    "gn:population":0,
    "gn:timezone":"America/Tegucigalpa",
    "iso:country":"HN",
    "wof:name":"El Barrio Arriba",
    "wof:placetype":"locality"
},
  "geometry": {"coordinates":[-87.29666999999998,13.99917],"type":"Point"}
}