{
  "type": "Feature",
  "properties": {
    "gn:admin1_code":"05",
    "gn:asciiname":"El Copante",
    "gn:cc2":"HN",
    "gn:country_code":"HN",
    "gn:dem":894,
    "gn:feature_class":"P",
    "gn:feature_code":"PPL",
    "gn:name":"El Copante",
    "gn:population":0,
    "gn:timezone":"America/Tegucigalpa",
    "iso:country":"HN",
    "name:und_x_variant":[
        "Copante",
        "El Copante"
    ],
    "wof:name":"El Copante",
    "wof:placetype":"locality"
},
  "geometry": {"coordinates":[-88.73333000000002,14.96667],"type":"Point"}
}