{
  "type": "Feature",
  "properties": {
    "gn:admin1_code":"02",
    "gn:asciiname":"El Quebrachito",
    "gn:country_code":"HN",
    "gn:dem":671,
    "gn:feature_class":"P",
    "gn:feature_code":"PPL",
    "gn:name":"El Quebrachito",
    "gn:population":0,
    "gn:timezone":"America/Tegucigalpa",
    "iso:country":"HN",
    "wof:name":"El Quebrachito",
    "wof:placetype":"locality"
},
  "geometry": {"coordinates":[-87.03778,13.22056],"type":"Point"}
}