{
  "type": "Feature",
  "properties": {
    "gn:admin1_code":"15",
    "gn:asciiname":"La Danta",
    "gn:country_code":"HN",
    "gn:dem":1068,
    "gn:feature_class":"P",
    "gn:feature_code":"PPL",
    "gn:name":"La Danta",
    "gn:population":0,
    "gn:timezone":"America/Tegucigalpa",
    "iso:country":"HN",
    "wof:name":"La Danta",
    "wof:placetype":"locality"
},
  "geometry": {"coordinates":[-86.88333,15.03333],"type":"Point"}
}