{
  "type": "Feature",
  "properties": {
    "gn:admin1_code":"04",
    "gn:asciiname":"Mecetillas",
    "gn:country_code":"HN",
    "gn:dem":537,
    "gn:feature_class":"P",
    "gn:feature_code":"PPL",
    "gn:name":"Mecetillas",
    "gn:population":0,
    "gn:timezone":"America/Tegucigalpa",
    "iso:country":"HN",
    "wof:name":"Mecetillas",
    "wof:placetype":"locality"
},
  "geometry": {"coordinates":[-87.73333000000002,14.83333],"type":"Point"}
}