{
  "type": "Feature",
  "properties": {
    "gn:admin1_code":"08",
    "gn:asciiname":"Los Amates",
    "gn:country_code":"HN",
    "gn:dem":503,
    "gn:feature_class":"P",
    "gn:feature_code":"PPL",
    "gn:name":"Los Amates",
    "gn:population":0,
    "gn:timezone":"America/Tegucigalpa",
    "iso:country":"HN",
    "wof:name":"Los Amates",
    "wof:placetype":"locality"
},
  "geometry": {"coordinates":[-87.34778,13.75528],"type":"Point"}
}