{
  "type": "Feature",
  "properties": {
    "gn:admin1_code":"07",
    "gn:asciiname":"Guapinol",
    "gn:country_code":"HN",
    "gn:dem":677,
    "gn:feature_class":"P",
    "gn:feature_code":"PPL",
    "gn:name":"Guapinol",
    "gn:population":0,
    "gn:timezone":"America/Tegucigalpa",
    "iso:country":"HN",
    "wof:name":"Guapinol",
    "wof:placetype":"locality"
},
  "geometry": {"coordinates":[-86.84999999999999,14.08333],"type":"Point"}
}