{
  "type": "Feature",
  "properties": {
    "gn:admin1_code":"06",
    "gn:asciiname":"Amapa Nuevo",
    "gn:country_code":"HN",
    "gn:dem":375,
    "gn:feature_class":"P",
    "gn:feature_code":"PPL",
    "gn:name":"Amapa Nuevo",
    "gn:population":0,
    "gn:timezone":"America/Tegucigalpa",
    "iso:country":"HN",
    "wof:name":"Amapa Nuevo",
    "wof:placetype":"locality"
},
  "geometry": {"coordinates":[-88.01666999999998,15.03333],"type":"Point"}
}