{
  "type": "Feature",
  "properties": {
    "gn:admin1_code":"09",
    "gn:asciiname":"Tuburus",
    "gn:cc2":"HN",
    "gn:country_code":"HN",
    "gn:dem":6,
    "gn:feature_class":"P",
    "gn:feature_code":"PPL",
    "gn:name":"T\u00faburus",
    "gn:population":0,
    "gn:timezone":"America/Tegucigalpa",
    "iso:country":"HN",
    "name:und_x_variant":[
        "Turub\u00fas",
        "Tuburas",
        "T\u00faburus"
    ],
    "wof:name":"Tuburus",
    "wof:placetype":"locality"
},
  "geometry": {"coordinates":[-83.59999999999999,15.06667],"type":"Point"}
}