{
  "type": "Feature",
  "properties": {
    "gn:admin1_code":"18",
    "gn:asciiname":"El Sauzal",
    "gn:cc2":"HN",
    "gn:country_code":"HN",
    "gn:dem":644,
    "gn:feature_class":"P",
    "gn:feature_code":"PPL",
    "gn:name":"El Sauzal",
    "gn:population":0,
    "gn:timezone":"America/Tegucigalpa",
    "iso:country":"HN",
    "name:ara_x_preferred":[
        "\u0625\u0644 \u0633\u0627\u0648\u062b\u0627\u0644"
    ],
    "name:cat_x_preferred":[
        "El Sauzal"
    ],
    "name:ceb_x_preferred":[
        "Sauzal"
    ],
    "name:ces_x_preferred":[
        "El Sauzal"
    ],
    "name:deu_x_preferred":[
        "El Sauzal"
    ],
    "name:eus_x_preferred":[
        "El Sauzal"
    ],
    "name:fra_x_preferred":[
        "El Sauzal"
    ],
    "name:glg_x_preferred":[
        "El Sauzal"
    ],
    "name:hun_x_preferred":[
        "El Sauzal"
    ],
    "name:ita_x_preferred":[
        "El Sauzal"
    ],
    "name:lat_x_preferred":[
        "El Sauzal"
    ],
    "name:msa_x_preferred":[
        "El Sauzal"
    ],
    "name:nld_x_preferred":[
        "El Sauzal"
    ],
    "name:oci_x_preferred":[
        "El Sauzal"
    ],
    "name:pol_x_preferred":[
        "El Sauzal"
    ],
    "name:por_x_preferred":[
        "El Sauzal"
    ],
    "name:rus_x_preferred":[
        "\u042d\u043b\u044c-\u0421\u0430\u0443\u0441\u0430\u043b\u044c"
    ],
    "name:spa_x_preferred":[
        "El Sauzal"
    ],
    "name:sqi_x_preferred":[
        "El Sauzal"
    ],
    "name:swe_x_preferred":[
        "Sauzal"
    ],
    "name:ukr_x_preferred":[
        "\u0415\u043b\u044c-\u0421\u0430\u0443\u0441\u0430\u043b\u044c"
    ],
    "name:und_x_variant":[
        "El Sausal",
        "El Sauzal"
    ],
    "name:uzb_x_preferred":[
        "El Sauzal"
    ],
    "name:war_x_preferred":[
        "El Sauzal"
    ],
    "name:zho_x_preferred":[
        "\u57c3\u5c14\u7ecd\u8428\u5c14"
    ],
    "wof:name":"El Sauzal",
    "wof:placetype":"locality"
},
  "geometry": {"coordinates":[-87.16667,15.11667],"type":"Point"}
}