{
  "type": "Feature",
  "properties": {
    "gn:admin1_code":"18",
    "gn:asciiname":"Pueblito",
    "gn:country_code":"HN",
    "gn:dem":638,
    "gn:feature_class":"P",
    "gn:feature_code":"PPL",
    "gn:name":"Pueblito",
    "gn:population":0,
    "gn:timezone":"America/Tegucigalpa",
    "iso:country":"HN",
    "wof:name":"Pueblito",
    "wof:placetype":"locality"
},
  "geometry": {"coordinates":[-87.21666999999999,15.08333],"type":"Point"}
}