{
  "type": "Feature",
  "properties": {
    "gn:admin1_code":"08",
    "gn:asciiname":"Limones",
    "gn:country_code":"HN",
    "gn:dem":609,
    "gn:feature_class":"P",
    "gn:feature_code":"PPL",
    "gn:name":"Limones",
    "gn:population":0,
    "gn:timezone":"America/Tegucigalpa",
    "iso:country":"HN",
    "name:ceb_x_preferred":[
        "Limones"
    ],
    "name:srp_x_preferred":[
        "\u041b\u0438\u043c\u043e\u043d\u0435\u0441"
    ],
    "name:swe_x_preferred":[
        "Limones"
    ],
    "wof:name":"Limones",
    "wof:placetype":"locality"
},
  "geometry": {"coordinates":[-87.09999999999999,14.66667],"type":"Point"}
}