{
  "type": "Feature",
  "properties": {
    "iso:country":"HN",
    "name:und_x_variant":[
        "French Harbour"
    ],
    "qs:gn_country":"HN",
    "qs:gn_fcode":"PPL",
    "qs:gn_pop":2698,
    "qs:name":"French Harbor",
    "qs:name_adm0":"Honduras",
    "qs:name_adm1":"Islas de la Bah\u00eda",
    "qs:photos":1893,
    "qs:photos_1k":384,
    "qs:photos_9k":8,
    "qs:photos_9r":9,
    "qs:photos_all":1893,
    "qs:photos_sr":15,
    "qs:placetype":"Town",
    "qs:pop_sr":"4",
    "qs:woe_adm0":23424841,
    "wof:name":"French Harbor",
    "wof:placetype":"locality",
    "wof:population":2698
},
  "geometry": {"coordinates":[-86.43333,16.35],"type":"Point"}
}