{
  "type": "Feature",
  "properties": {
    "gn:admin1_code":"13",
    "gn:asciiname":"Quebrada La Penca",
    "gn:cc2":"HN",
    "gn:country_code":"HN",
    "gn:dem":1062,
    "gn:feature_class":"P",
    "gn:feature_code":"PPL",
    "gn:name":"Quebrada La Penca",
    "gn:population":0,
    "gn:timezone":"America/Tegucigalpa",
    "iso:country":"HN",
    "name:und_x_variant":[
        "La Penca",
        "Quebrada La Penca"
    ],
    "wof:name":"Quebrada La Penca",
    "wof:placetype":"locality"
},
  "geometry": {"coordinates":[-88.45,14.56667],"type":"Point"}
}