{
  "type": "Feature",
  "properties": {
    "gn:admin1_code":"07",
    "gn:asciiname":"Guajiniquil",
    "gn:country_code":"HN",
    "gn:dem":874,
    "gn:feature_class":"P",
    "gn:feature_code":"PPL",
    "gn:name":"Guajiniquil",
    "gn:population":0,
    "gn:timezone":"America/Tegucigalpa",
    "iso:country":"HN",
    "wof:name":"Guajiniquil",
    "wof:placetype":"locality"
},
  "geometry": {"coordinates":[-87.1375,13.65306],"type":"Point"}
}