{
  "type": "Feature",
  "properties": {
    "gn:admin1_code":"10",
    "gn:asciiname":"Las Cinco Crucitas",
    "gn:country_code":"HN",
    "gn:dem":1774,
    "gn:feature_class":"P",
    "gn:feature_code":"PPL",
    "gn:name":"Las Cinco Crucitas",
    "gn:population":0,
    "gn:timezone":"America/Tegucigalpa",
    "iso:country":"HN",
    "wof:name":"Las Cinco Crucitas",
    "wof:placetype":"locality"
},
  "geometry": {"coordinates":[-88.06667,14.33333],"type":"Point"}
}