{
  "type": "Feature",
  "properties": {
    "gn:admin1_code":"16",
    "gn:asciiname":"Agua Helada",
    "gn:country_code":"HN",
    "gn:dem":291,
    "gn:feature_class":"P",
    "gn:feature_code":"PPL",
    "gn:name":"Agua Helada",
    "gn:population":0,
    "gn:timezone":"America/Tegucigalpa",
    "iso:country":"HN",
    "wof:name":"Agua Helada",
    "wof:placetype":"locality"
},
  "geometry": {"coordinates":[-88.34999999999999,15.28333],"type":"Point"}
}