{
  "type": "Feature",
  "properties": {
    "gn:country":"HN",
    "gn:fcode":"PPL",
    "gn:pop":1103,
    "iso:country":"HN",
    "qs:name":"Prieta",
    "qs:photos_9r":0,
    "qs:photos_sr":0,
    "qs:pop_sr":"3",
    "wof:name":"Prieta",
    "wof:placetype":"locality",
    "wof:population":1103
},
  "geometry": {"coordinates":[-86.18333,15.58333],"type":"Point"}
}