{
  "type": "Feature",
  "properties": {
    "gn:admin1_code":"09",
    "gn:asciiname":"Kropunta",
    "gn:cc2":"HN",
    "gn:country_code":"HN",
    "gn:dem":9,
    "gn:feature_class":"P",
    "gn:feature_code":"PPL",
    "gn:name":"Kropunta",
    "gn:population":0,
    "gn:timezone":"America/Tegucigalpa",
    "iso:country":"HN",
    "name:und_x_variant":[
        "Cruputa",
        "Cropunta",
        "Kropunta"
    ],
    "wof:name":"Kropunta",
    "wof:placetype":"locality"
},
  "geometry": {"coordinates":[-84.31667,15.51667],"type":"Point"}
}