{
  "type": "Feature",
  "properties": {
    "gn:admin1_code":"08",
    "gn:asciiname":"La Magnolia",
    "gn:country_code":"HN",
    "gn:dem":1103,
    "gn:feature_class":"P",
    "gn:feature_code":"PPL",
    "gn:name":"La Magnolia",
    "gn:population":0,
    "gn:timezone":"America/Tegucigalpa",
    "iso:country":"HN",
    "wof:name":"La Magnolia",
    "wof:placetype":"locality"
},
  "geometry": {"coordinates":[-87.19861,13.81167],"type":"Point"}
}