{
  "type": "Feature",
  "properties": {
    "gn:admin1_code":"04",
    "gn:asciiname":"El Higuero",
    "gn:cc2":"HN",
    "gn:country_code":"HN",
    "gn:dem":714,
    "gn:feature_class":"P",
    "gn:feature_code":"PPL",
    "gn:name":"El Higuero",
    "gn:population":0,
    "gn:timezone":"America/Tegucigalpa",
    "iso:country":"HN",
    "name:und_x_variant":[
        "Higuero",
        "El Higuero"
    ],
    "wof:name":"El Higuero",
    "wof:placetype":"locality"
},
  "geometry": {"coordinates":[-87.71666999999999,14.56667],"type":"Point"}
}