{
  "type": "Feature",
  "properties": {
    "gn:admin1_code":"05",
    "gn:asciiname":"El Playoncito",
    "gn:cc2":"HN",
    "gn:country_code":"HN",
    "gn:dem":1003,
    "gn:feature_class":"P",
    "gn:feature_code":"PPL",
    "gn:name":"El Playoncito",
    "gn:population":0,
    "gn:timezone":"America/Tegucigalpa",
    "iso:country":"HN",
    "name:und_x_variant":[
        "Playoncito",
        "Playonsito",
        "El Playoncito"
    ],
    "wof:name":"El Playoncito",
    "wof:placetype":"locality"
},
  "geometry": {"coordinates":[-89.06667,14.85],"type":"Point"}
}