{
  "type": "Feature",
  "properties": {
    "gn:admin1_code":"01",
    "gn:asciiname":"Frisco Dos",
    "gn:country_code":"HN",
    "gn:dem":16,
    "gn:feature_class":"P",
    "gn:feature_code":"PPL",
    "gn:name":"Frisco Dos",
    "gn:population":0,
    "gn:timezone":"America/Tegucigalpa",
    "iso:country":"HN",
    "wof:name":"Frisco Dos",
    "wof:placetype":"locality"
},
  "geometry": {"coordinates":[-87.11667,15.66667],"type":"Point"}
}