{
  "type": "Feature",
  "properties": {
    "gn:admin1_code":"07",
    "gn:asciiname":"Las Casillas",
    "gn:country_code":"HN",
    "gn:dem":269,
    "gn:feature_class":"P",
    "gn:feature_code":"PPL",
    "gn:name":"Las Casillas",
    "gn:population":0,
    "gn:timezone":"America/Tegucigalpa",
    "iso:country":"HN",
    "wof:name":"Las Casillas",
    "wof:placetype":"locality"
},
  "geometry": {"coordinates":[-87.11499999999999,13.56944],"type":"Point"}
}