{
  "type": "Feature",
  "properties": {
    "gn:admin1_code":"16",
    "gn:asciiname":"Villa Luz",
    "gn:cc2":"HN",
    "gn:country_code":"HN",
    "gn:dem":684,
    "gn:feature_class":"P",
    "gn:feature_code":"PPL",
    "gn:name":"Villa Luz",
    "gn:population":0,
    "gn:timezone":"America/Tegucigalpa",
    "iso:country":"HN",
    "name:und_x_variant":[
        "V\u00eda Luz",
        "Villa Luz"
    ],
    "wof:name":"Villa Luz",
    "wof:placetype":"locality"
},
  "geometry": {"coordinates":[-88.40000000000001,15.05],"type":"Point"}
}