{
  "type": "Feature",
  "properties": {
    "gn:admin1_code":"08",
    "gn:asciiname":"Guanacaste",
    "gn:country_code":"HN",
    "gn:dem":832,
    "gn:feature_class":"P",
    "gn:feature_code":"PPL",
    "gn:name":"Guanacaste",
    "gn:population":0,
    "gn:timezone":"America/Tegucigalpa",
    "iso:country":"HN",
    "name:cat_x_preferred":[
        "Guanacaste"
    ],
    "name:ces_x_preferred":[
        "Guanacaste"
    ],
    "name:deu_x_preferred":[
        "Guanacaste"
    ],
    "name:fra_x_preferred":[
        "Guanacaste"
    ],
    "name:hrv_x_preferred":[
        "Guanacaste"
    ],
    "name:ita_x_preferred":[
        "Guanacaste"
    ],
    "name:nld_x_preferred":[
        "Guanacaste"
    ],
    "name:rus_x_preferred":[
        "\u0413\u0443\u0430\u043d\u0430\u043a\u0430\u0441\u0442\u0435"
    ],
    "name:swe_x_preferred":[
        "Guanacaste"
    ],
    "name:ukr_x_preferred":[
        "\u0413\u0443\u0430\u043d\u0430\u043a\u0430\u0441\u0442\u0435"
    ],
    "name:war_x_preferred":[
        "Guanacaste"
    ],
    "wof:name":"Guanacaste",
    "wof:placetype":"locality"
},
  "geometry": {"coordinates":[-87.09999999999999,14.53333],"type":"Point"}
}