{
  "type": "Feature",
  "properties": {
    "gn:admin1_code":"17",
    "gn:asciiname":"Punta Novillo",
    "gn:country_code":"HN",
    "gn:dem":24,
    "gn:feature_class":"P",
    "gn:feature_code":"PPL",
    "gn:name":"Punta Novillo",
    "gn:population":0,
    "gn:timezone":"America/Tegucigalpa",
    "iso:country":"HN",
    "wof:name":"Punta Novillo",
    "wof:placetype":"locality"
},
  "geometry": {"coordinates":[-87.65778,13.33694],"type":"Point"}
}