{
  "type": "Feature",
  "properties": {
    "gn:admin1_code":"06",
    "gn:asciiname":"Amapa",
    "gn:country_code":"HN",
    "gn:dem":145,
    "gn:feature_class":"P",
    "gn:feature_code":"PPL",
    "gn:name":"Amapa",
    "gn:population":0,
    "gn:timezone":"America/Tegucigalpa",
    "iso:country":"HN",
    "wof:name":"Amapa",
    "wof:placetype":"locality"
},
  "geometry": {"coordinates":[-87.98333000000002,15.03333],"type":"Point"}
}