{
  "type": "Feature",
  "properties": {
    "gn:admin1_code":"06",
    "gn:asciiname":"Amapa",
    "gn:country_code":"HN",
    "gn:dem":145,
    "gn:feature_class":"P",
    "gn:feature_code":"PPL",
    "gn:name":"Amapa",
    "gn:population":0,
    "gn:timezone":"America/Tegucigalpa",
    "iso:country":"HN",
    "name:ceb_x_preferred":[
        "Amapa"
    ],
    "name:sco_x_preferred":[
        "Amapa"
    ],
    "name:srp_x_preferred":[
        "\u0410\u043c\u0430\u043f\u0430"
    ],
    "name:swe_x_preferred":[
        "Amapa"
    ],
    "name:vie_x_preferred":[
        "Amapa"
    ],
    "wof:name":"Amapa",
    "wof:placetype":"locality"
},
  "geometry": {"coordinates":[-87.98333000000002,15.03333],"type":"Point"}
}