{
  "type": "Feature",
  "properties": {
    "gn:admin1_code":"06",
    "gn:asciiname":"El Crique",
    "gn:cc2":"HN",
    "gn:country_code":"HN",
    "gn:dem":66,
    "gn:feature_class":"P",
    "gn:feature_code":"PPL",
    "gn:name":"El Crique",
    "gn:population":0,
    "gn:timezone":"America/Tegucigalpa",
    "iso:country":"HN",
    "name:und_x_variant":[
        "El Orique",
        "El Crique"
    ],
    "wof:name":"El Crique",
    "wof:placetype":"locality"
},
  "geometry": {"coordinates":[-88.93333,15.38333],"type":"Point"}
}