{
  "type": "Feature",
  "properties": {
    "gn:admin1_code":"04",
    "gn:asciiname":"Ocotillal",
    "gn:country_code":"HN",
    "gn:dem":753,
    "gn:feature_class":"P",
    "gn:feature_code":"PPL",
    "gn:name":"Ocotillal",
    "gn:population":0,
    "gn:timezone":"America/Tegucigalpa",
    "iso:country":"HN",
    "wof:name":"Ocotillal",
    "wof:placetype":"locality"
},
  "geometry": {"coordinates":[-87.56667,14.58333],"type":"Point"}
}