{
  "type": "Feature",
  "properties": {
    "gn:country":"HN",
    "gn:fcode":"PPL",
    "gn:population":1000,
    "iso:country":"HN",
    "qs:name":"Las Mercedes",
    "qs:photos_9r":0,
    "qs:photos_sr":0,
    "qs:pop_sr":"2",
    "wd:wordcount":175,
    "wof:name":"Las Mercedes",
    "wof:placetype":"locality",
    "wof:population":1000
},
  "geometry": {"coordinates":[-87.56667,14.28333],"type":"Point"}
}