{
  "type": "Feature",
  "properties": {
    "gn:admin1_code":"18",
    "gn:asciiname":"El Convento",
    "gn:cc2":"HN",
    "gn:country_code":"HN",
    "gn:dem":1005,
    "gn:feature_class":"P",
    "gn:feature_code":"PPL",
    "gn:name":"El Convento",
    "gn:population":0,
    "gn:timezone":"America/Tegucigalpa",
    "iso:country":"HN",
    "name:und_x_variant":[
        "Convento",
        "El Convento"
    ],
    "wof:name":"El Convento",
    "wof:placetype":"locality"
},
  "geometry": {"coordinates":[-86.90000000000001,14.81667],"type":"Point"}
}