{
  "type": "Feature",
  "properties": {
    "gn:admin1_code":"06",
    "gn:asciiname":"Cuyamelito",
    "gn:country_code":"HN",
    "gn:dem":16,
    "gn:feature_class":"P",
    "gn:feature_code":"PPL",
    "gn:name":"Cuyamelito",
    "gn:population":0,
    "gn:timezone":"America/Tegucigalpa",
    "iso:country":"HN",
    "wof:name":"Cuyamelito",
    "wof:placetype":"locality"
},
  "geometry": {"coordinates":[-88.31667,15.61667],"type":"Point"}
}