{
  "type": "Feature",
  "properties": {
    "gn:admin1_code":"02",
    "gn:asciiname":"Las Pozas",
    "gn:country_code":"HN",
    "gn:dem":481,
    "gn:feature_class":"P",
    "gn:feature_code":"PPL",
    "gn:name":"Las Pozas",
    "gn:population":0,
    "gn:timezone":"America/Tegucigalpa",
    "iso:country":"HN",
    "name:ces_x_preferred":[
        "Las Pozas"
    ],
    "name:fra_x_preferred":[
        "Las Pozas"
    ],
    "name:hun_x_preferred":[
        "Las Pozas"
    ],
    "name:rus_x_preferred":[
        "\u041b\u0430\u0441-\u041f\u043e\u0441\u0430\u0441"
    ],
    "name:spa_x_preferred":[
        "Las Pozas"
    ],
    "name:ukr_x_preferred":[
        "\u041b\u0430\u0441-\u041f\u043e\u0441\u0430\u0441"
    ],
    "wof:name":"Las Pozas",
    "wof:placetype":"locality"
},
  "geometry": {"coordinates":[-87.19806,13.46056],"type":"Point"}
}