{
  "type": "Feature",
  "properties": {
    "gn:admin1_code":"13",
    "gn:asciiname":"La Colmena",
    "gn:country_code":"HN",
    "gn:dem":644,
    "gn:feature_class":"P",
    "gn:feature_code":"PPL",
    "gn:name":"La Colmena",
    "gn:population":0,
    "gn:timezone":"America/Tegucigalpa",
    "iso:country":"HN",
    "name:ceb_x_preferred":[
        "La Colmena"
    ],
    "name:fra_x_preferred":[
        "La Colmena"
    ],
    "name:glg_x_preferred":[
        "La colmena"
    ],
    "name:nld_x_preferred":[
        "La colmena"
    ],
    "name:spa_x_preferred":[
        "La colmena"
    ],
    "name:swe_x_preferred":[
        "La Colmena"
    ],
    "wof:name":"La Colmena",
    "wof:placetype":"locality"
},
  "geometry": {"coordinates":[-88.61667,14.13333],"type":"Point"}
}