{
  "type": "Feature",
  "properties": {
    "gn:admin1_code":"02",
    "gn:asciiname":"Las Lomitas",
    "gn:country_code":"HN",
    "gn:dem":1116,
    "gn:feature_class":"P",
    "gn:feature_code":"PPL",
    "gn:name":"Las Lomitas",
    "gn:population":0,
    "gn:timezone":"America/Tegucigalpa",
    "iso:country":"HN",
    "name:pol_x_preferred":[
        "Las Lomitas"
    ],
    "name:spa_x_preferred":[
        "Las Lomitas"
    ],
    "name:urd_x_preferred":[
        "\u0644\u0627\u0633 \u0644\u0648\u0645\u06cc\u0679\u0627\u0633"
    ],
    "wof:name":"Las Lomitas",
    "wof:placetype":"locality"
},
  "geometry": {"coordinates":[-86.93333,13.41667],"type":"Point"}
}