{
  "type": "Feature",
  "properties": {
    "gn:admin1_code":"08",
    "gn:asciiname":"El Suyatillo",
    "gn:country_code":"HN",
    "gn:dem":937,
    "gn:feature_class":"P",
    "gn:feature_code":"PPL",
    "gn:name":"El Suyatillo",
    "gn:population":0,
    "gn:timezone":"America/Tegucigalpa",
    "iso:country":"HN",
    "wof:name":"El Suyatillo",
    "wof:placetype":"locality"
},
  "geometry": {"coordinates":[-87.14917,13.68167],"type":"Point"}
}