{
  "type": "Feature",
  "properties": {
    "gn:admin1_code":"02",
    "gn:asciiname":"Macuelizo",
    "gn:country_code":"HN",
    "gn:dem":284,
    "gn:feature_class":"P",
    "gn:feature_code":"PPL",
    "gn:name":"Macuelizo",
    "gn:population":0,
    "gn:timezone":"America/Tegucigalpa",
    "iso:country":"HN",
    "name:fra_x_preferred":[
        "Macuelizo"
    ],
    "name:ita_x_preferred":[
        "Macuelizo"
    ],
    "name:nld_x_preferred":[
        "Macuelizo"
    ],
    "name:por_x_preferred":[
        "Macuelizo"
    ],
    "name:spa_x_preferred":[
        "Macuelizo"
    ],
    "name:vie_x_preferred":[
        "Macuelizo"
    ],
    "name:zho_x_preferred":[
        "\u99ac\u5eab\u57c3\u5229\u7d22"
    ],
    "wof:name":"Macuelizo",
    "wof:placetype":"locality"
},
  "geometry": {"coordinates":[-87.39166999999998,13.74528],"type":"Point"}
}