{
  "type": "Feature",
  "properties": {
    "gn:admin1_code":"15",
    "gn:asciiname":"San Pedro",
    "gn:country_code":"HN",
    "gn:dem":484,
    "gn:feature_class":"P",
    "gn:feature_code":"PPL",
    "gn:name":"San Pedro",
    "gn:population":0,
    "gn:timezone":"America/Tegucigalpa",
    "iso:country":"HN",
    "wof:name":"San Pedro",
    "wof:placetype":"locality"
},
  "geometry": {"coordinates":[-86.25,14.63333],"type":"Point"}
}