{
  "type": "Feature",
  "properties": {
    "gn:admin1_code":"11",
    "gn:asciiname":"El Soldado",
    "gn:country_code":"HN",
    "gn:dem":-9999,
    "gn:feature_class":"P",
    "gn:feature_code":"PPL",
    "gn:name":"El Soldado",
    "gn:population":0,
    "gn:timezone":"America/Tegucigalpa",
    "iso:country":"HN",
    "wof:name":"El Soldado",
    "wof:placetype":"locality"
},
  "geometry": {"coordinates":[-85.91667,16.48333],"type":"Point"}
}