{
  "type": "Feature",
  "properties": {
    "gn:country":"HN",
    "gn:fcode":"PPL",
    "gn:population":1139,
    "iso:country":"HN",
    "name:und_x_variant":[
        "La Bueso"
    ],
    "qs_pg:aaroncc":"HN",
    "qs_pg:gn_country":"HN",
    "qs_pg:gn_fcode":"PPL",
    "qs_pg:gn_pop":1139,
    "qs_pg:name":"La Huesa",
    "qs_pg:photos_9r":0,
    "qs_pg:photos_sr":0,
    "qs_pg:pop_sr":3,
    "qs_pg:qs_pg_placetype":"locality",
    "wof:name":"La Huesa",
    "wof:placetype":"locality",
    "wof:population":1139
},
  "geometry": {"coordinates":[-87.88333,15.58333],"type":"Point"}
}