{
  "type": "Feature",
  "properties": {
    "gn:admin1_code":"16",
    "gn:asciiname":"Potreritos",
    "gn:country_code":"HN",
    "gn:dem":286,
    "gn:feature_class":"P",
    "gn:feature_code":"PPL",
    "gn:name":"Potreritos",
    "gn:population":0,
    "gn:timezone":"America/Tegucigalpa",
    "iso:country":"HN",
    "wof:name":"Potreritos",
    "wof:placetype":"locality"
},
  "geometry": {"coordinates":[-88.55694,15.3475],"type":"Point"}
}