{
  "type": "Feature",
  "properties": {
    "gn:admin1_code":"01",
    "gn:asciiname":"Descombros",
    "gn:cc2":"HN",
    "gn:country_code":"HN",
    "gn:dem":563,
    "gn:feature_class":"P",
    "gn:feature_code":"PPL",
    "gn:name":"Descombros",
    "gn:population":0,
    "gn:timezone":"America/Tegucigalpa",
    "iso:country":"HN",
    "name:und_x_variant":[
        "Descombro",
        "Descombros"
    ],
    "wof:name":"Descombros",
    "wof:placetype":"locality"
},
  "geometry": {"coordinates":[-86.41667,15.58333],"type":"Point"}
}