{
  "type": "Feature",
  "properties": {
    "gn:country":"HN",
    "gn:fcode":"PPL",
    "gn:pop":798,
    "iso:country":"HN",
    "qs:name":"El Tizatillo",
    "qs:photos_9r":0,
    "qs:photos_sr":0,
    "qs:pop_sr":"2",
    "wof:name":"El Tizatillo",
    "wof:placetype":"locality",
    "wof:population":798
},
  "geometry": {"coordinates":[-87.19499999999999,13.99944],"type":"Point"}
}