{
  "type": "Feature",
  "properties": {
    "gn:admin1_code":"12",
    "gn:asciiname":"Ingrula",
    "gn:cc2":"HN",
    "gn:country_code":"HN",
    "gn:dem":2136,
    "gn:feature_class":"P",
    "gn:feature_code":"PPL",
    "gn:name":"Ingrula",
    "gn:population":0,
    "gn:timezone":"America/Tegucigalpa",
    "iso:country":"HN",
    "name:und_x_variant":[
        "Ingurula",
        "Ingrula"
    ],
    "wof:name":"Ingrula",
    "wof:placetype":"locality"
},
  "geometry": {"coordinates":[-87.84999999999999,14.13333],"type":"Point"}
}