{
  "type": "Feature",
  "properties": {
    "gn:admin1_code":"12",
    "gn:asciiname":"El Mezcal",
    "gn:country_code":"HN",
    "gn:dem":1174,
    "gn:feature_class":"P",
    "gn:feature_code":"PPL",
    "gn:name":"El Mezcal",
    "gn:population":0,
    "gn:timezone":"America/Tegucigalpa",
    "iso:country":"HN",
    "wof:name":"El Mezcal",
    "wof:placetype":"locality"
},
  "geometry": {"coordinates":[-87.76916999999997,13.99944],"type":"Point"}
}