{
  "type": "Feature",
  "properties": {
    "gn:admin1_code":"13",
    "gn:asciiname":"Yucual",
    "gn:cc2":"HN",
    "gn:country_code":"HN",
    "gn:dem":1091,
    "gn:feature_class":"P",
    "gn:feature_code":"PPL",
    "gn:name":"Yucual",
    "gn:population":0,
    "gn:timezone":"America/Tegucigalpa",
    "iso:country":"HN",
    "name:und_x_variant":[
        "Yucal",
        "Yucual"
    ],
    "wof:name":"Yucual",
    "wof:placetype":"locality"
},
  "geometry": {"coordinates":[-88.53333000000001,14.11667],"type":"Point"}
}