{
  "type": "Feature",
  "properties": {
    "gn:admin1_code":"06",
    "gn:asciiname":"El Cipres",
    "gn:country_code":"HN",
    "gn:dem":351,
    "gn:feature_class":"P",
    "gn:feature_code":"PPL",
    "gn:name":"El Cipr\u00e9s",
    "gn:population":0,
    "gn:timezone":"America/Tegucigalpa",
    "iso:country":"HN",
    "wof:name":"El Cipres",
    "wof:placetype":"locality"
},
  "geometry": {"coordinates":[-87.91678,14.98596],"type":"Point"}
}