{
  "type": "Feature",
  "properties": {
    "gn:admin1_code":"08",
    "gn:asciiname":"El Pelillal",
    "gn:country_code":"HN",
    "gn:dem":1539,
    "gn:feature_class":"P",
    "gn:feature_code":"PPL",
    "gn:name":"El Pelillal",
    "gn:population":0,
    "gn:timezone":"America/Tegucigalpa",
    "iso:country":"HN",
    "wof:name":"El Pelillal",
    "wof:placetype":"locality"
},
  "geometry": {"coordinates":[-87.56667,14.06667],"type":"Point"}
}