{
  "type": "Feature",
  "properties": {
    "gn:admin1_code":"08",
    "gn:asciiname":"El Espino",
    "gn:cc2":"HN",
    "gn:country_code":"HN",
    "gn:dem":1320,
    "gn:feature_class":"P",
    "gn:feature_code":"PPL",
    "gn:name":"El Espino",
    "gn:population":0,
    "gn:timezone":"America/Tegucigalpa",
    "iso:country":"HN",
    "name:und_x_variant":[
        "Espino",
        "El Espino"
    ],
    "wof:name":"El Espino",
    "wof:placetype":"locality"
},
  "geometry": {"coordinates":[-87.01666999999998,13.85],"type":"Point"}
}