{
  "type": "Feature",
  "properties": {
    "gn:admin1_code":"10",
    "gn:asciiname":"Cangual",
    "gn:country_code":"HN",
    "gn:dem":1885,
    "gn:feature_class":"P",
    "gn:feature_code":"PPL",
    "gn:name":"Cangual",
    "gn:population":0,
    "gn:timezone":"America/Tegucigalpa",
    "iso:country":"HN",
    "wof:name":"Cangual",
    "wof:placetype":"locality"
},
  "geometry": {"coordinates":[-88.33333,14.43333],"type":"Point"}
}