{
  "type": "Feature",
  "properties": {
    "gn:admin1_code":"08",
    "gn:asciiname":"El Tranquilo",
    "gn:cc2":"HN",
    "gn:country_code":"HN",
    "gn:dem":2073,
    "gn:feature_class":"P",
    "gn:feature_code":"PPL",
    "gn:name":"El Tranquilo",
    "gn:population":0,
    "gn:timezone":"America/Tegucigalpa",
    "iso:country":"HN",
    "name:und_x_variant":[
        "Tranquilo",
        "El Tranquilo"
    ],
    "wof:name":"El Tranquilo",
    "wof:placetype":"locality"
},
  "geometry": {"coordinates":[-87.05,14.96667],"type":"Point"}
}