{
  "type": "Feature",
  "properties": {
    "gn:admin1_code":"06",
    "gn:asciiname":"El Guanal",
    "gn:cc2":"HN",
    "gn:country_code":"HN",
    "gn:dem":188,
    "gn:feature_class":"P",
    "gn:feature_code":"PPL",
    "gn:name":"El Guanal",
    "gn:population":0,
    "gn:timezone":"America/Tegucigalpa",
    "iso:country":"HN",
    "name:und_x_variant":[
        "Guanal",
        "El Guanal"
    ],
    "wof:name":"El Guanal",
    "wof:placetype":"locality"
},
  "geometry": {"coordinates":[-88.09999999999999,15.15],"type":"Point"}
}