{
  "type": "Feature",
  "properties": {
    "gn:admin1_code":"16",
    "gn:asciiname":"La Quebrada",
    "gn:country_code":"HN",
    "gn:dem":543,
    "gn:feature_class":"P",
    "gn:feature_code":"PPL",
    "gn:name":"La Quebrada",
    "gn:population":0,
    "gn:timezone":"America/Tegucigalpa",
    "iso:country":"HN",
    "wof:name":"La Quebrada",
    "wof:placetype":"locality"
},
  "geometry": {"coordinates":[-88.56667,15.13333],"type":"Point"}
}