{
  "type": "Feature",
  "properties": {
    "gn:admin1_code":"07",
    "gn:asciiname":"Los Arabos",
    "gn:country_code":"HN",
    "gn:dem":484,
    "gn:feature_class":"P",
    "gn:feature_code":"PPL",
    "gn:name":"Los Arabos",
    "gn:population":0,
    "gn:timezone":"America/Tegucigalpa",
    "iso:country":"HN",
    "name:fra_x_preferred":[
        "Los Arabos"
    ],
    "name:ita_x_preferred":[
        "Los Arabos"
    ],
    "name:kat_x_preferred":[
        "\u10da\u10dd\u10e1-\u10d0\u10e0\u10d0\u10d1\u10dd\u10e1\u10d8"
    ],
    "name:oci_x_preferred":[
        "Los Arabos"
    ],
    "name:por_x_preferred":[
        "Los Arabos"
    ],
    "name:sco_x_preferred":[
        "Los Arabos"
    ],
    "name:spa_x_preferred":[
        "Los Arabos"
    ],
    "name:vie_x_preferred":[
        "Los Arabos"
    ],
    "name:zho_x_preferred":[
        "\u6d1b\u65af\u963f\u62c9\u6c83\u65af"
    ],
    "wof:name":"Los Arabos",
    "wof:placetype":"locality"
},
  "geometry": {"coordinates":[-87.06917,13.66194],"type":"Point"}
}