{
  "type": "Feature",
  "properties": {
    "gn:admin1_code":"07",
    "gn:asciiname":"Los Arabos",
    "gn:country_code":"HN",
    "gn:dem":484,
    "gn:feature_class":"P",
    "gn:feature_code":"PPL",
    "gn:name":"Los Arabos",
    "gn:population":0,
    "gn:timezone":"America/Tegucigalpa",
    "iso:country":"HN",
    "wof:name":"Los Arabos",
    "wof:placetype":"locality"
},
  "geometry": {"coordinates":[-87.06917,13.66194],"type":"Point"}
}