{
  "type": "Feature",
  "properties": {
    "gn:admin1_code":"02",
    "gn:asciiname":"Hacienda Santa Fe",
    "gn:country_code":"HN",
    "gn:dem":37,
    "gn:feature_class":"P",
    "gn:feature_code":"PPL",
    "gn:name":"Hacienda Santa Fe",
    "gn:population":0,
    "gn:timezone":"America/Tegucigalpa",
    "iso:country":"HN",
    "wof:name":"Hacienda Santa Fe",
    "wof:placetype":"locality"
},
  "geometry": {"coordinates":[-87.25083000000002,13.31333],"type":"Point"}
}