{
  "type": "Feature",
  "properties": {
    "gn:admin1_code":"18",
    "gn:asciiname":"Tegucigalpa",
    "gn:country_code":"HN",
    "gn:dem":1295,
    "gn:feature_class":"P",
    "gn:feature_code":"PPL",
    "gn:name":"Tegucigalpa",
    "gn:population":0,
    "gn:timezone":"America/Tegucigalpa",
    "iso:country":"HN",
    "wof:name":"Tegucigalpa",
    "wof:placetype":"locality"
},
  "geometry": {"coordinates":[-87.46666999999999,15.13333],"type":"Point"}
}