{
  "type": "Feature",
  "properties": {
    "gn:admin1_code":"18",
    "gn:asciiname":"San Jose el Negrito",
    "gn:cc2":"HN",
    "gn:country_code":"HN",
    "gn:dem":451,
    "gn:feature_class":"P",
    "gn:feature_code":"PPL",
    "gn:name":"San Jos\u00e9 el Negrito",
    "gn:population":0,
    "gn:timezone":"America/Tegucigalpa",
    "iso:country":"HN",
    "name:und_x_variant":[
        "San Jos\u00e9",
        "San Jos\u00e9 el Negrito"
    ],
    "wof:name":"San Jose el Negrito",
    "wof:placetype":"locality"
},
  "geometry": {"coordinates":[-87.68333,15.41667],"type":"Point"}
}