{
  "type": "Feature",
  "properties": {
    "gn:admin1_code":"13",
    "gn:asciiname":"Guatismon",
    "gn:cc2":"HN",
    "gn:country_code":"HN",
    "gn:dem":614,
    "gn:feature_class":"P",
    "gn:feature_code":"PPL",
    "gn:name":"Guatism\u00f3n",
    "gn:population":0,
    "gn:timezone":"America/Tegucigalpa",
    "iso:country":"HN",
    "name:und_x_variant":[
        "Guatisman",
        "Guatism\u00f3n"
    ],
    "wof:name":"Guatismon",
    "wof:placetype":"locality"
},
  "geometry": {"coordinates":[-88.41667,14.13333],"type":"Point"}
}