{
  "type": "Feature",
  "properties": {
    "gn:admin1_code":"18",
    "gn:asciiname":"Urraco Sur",
    "gn:cc2":"HN",
    "gn:country_code":"HN",
    "gn:dem":332,
    "gn:feature_class":"P",
    "gn:feature_code":"PPL",
    "gn:name":"Urraco Sur",
    "gn:population":0,
    "gn:timezone":"America/Tegucigalpa",
    "iso:country":"HN",
    "name:und_x_variant":[
        "Urraco",
        "Urraco Sur"
    ],
    "wof:name":"Urraco Sur",
    "wof:placetype":"locality"
},
  "geometry": {"coordinates":[-87.84999999999999,15.23333],"type":"Point"}
}