{
  "type": "Feature",
  "properties": {
    "gn:admin1_code":"18",
    "gn:asciiname":"El Chamuscado",
    "gn:cc2":"HN",
    "gn:country_code":"HN",
    "gn:dem":576,
    "gn:feature_class":"P",
    "gn:feature_code":"PPL",
    "gn:name":"El Chamuscado",
    "gn:population":0,
    "gn:timezone":"America/Tegucigalpa",
    "iso:country":"HN",
    "name:und_x_variant":[
        "Chamuscado",
        "El Chamuscado"
    ],
    "wof:name":"El Chamuscado",
    "wof:placetype":"locality"
},
  "geometry": {"coordinates":[-87.23333000000002,15.25],"type":"Point"}
}