{
  "type": "Feature",
  "properties": {
    "gn:admin1_code":"02",
    "gn:asciiname":"El Jicaro",
    "gn:cc2":"HN",
    "gn:country_code":"HN",
    "gn:dem":313,
    "gn:feature_class":"P",
    "gn:feature_code":"PPL",
    "gn:name":"El J\u00edcaro",
    "gn:population":0,
    "gn:timezone":"America/Tegucigalpa",
    "iso:country":"HN",
    "name:und_x_variant":[
        "Los Jicaros",
        "El J\u00edcaro"
    ],
    "wof:name":"El Jicaro",
    "wof:placetype":"locality"
},
  "geometry": {"coordinates":[-87.04639,13.45472],"type":"Point"}
}