{
  "type": "Feature",
  "properties": {
    "gn:admin1_code":"13",
    "gn:asciiname":"Potrerillos",
    "gn:country_code":"HN",
    "gn:dem":692,
    "gn:feature_class":"P",
    "gn:feature_code":"PPL",
    "gn:name":"Potrerillos",
    "gn:population":0,
    "gn:timezone":"America/Tegucigalpa",
    "iso:country":"HN",
    "name:ceb_x_preferred":[
        "Potrerillos"
    ],
    "name:deu_x_preferred":[
        "Potrerillos"
    ],
    "name:fra_x_preferred":[
        "Potrerillos"
    ],
    "name:ita_x_preferred":[
        "Potrerillos"
    ],
    "name:nld_x_preferred":[
        "Potrerillos"
    ],
    "name:pol_x_preferred":[
        "Potrerillos"
    ],
    "name:por_x_preferred":[
        "Potrerillos"
    ],
    "name:spa_x_preferred":[
        "Potrerillos"
    ],
    "name:swe_x_preferred":[
        "Potrerillos"
    ],
    "wof:name":"Potrerillos",
    "wof:placetype":"locality"
},
  "geometry": {"coordinates":[-88.61667,14.63333],"type":"Point"}
}