{
  "type": "Feature",
  "properties": {
    "gn:admin1_code":"04",
    "gn:asciiname":"Rancho Chiquito",
    "gn:country_code":"HN",
    "gn:dem":988,
    "gn:feature_class":"P",
    "gn:feature_code":"PPL",
    "gn:name":"Rancho Chiquito",
    "gn:population":0,
    "gn:timezone":"America/Tegucigalpa",
    "iso:country":"HN",
    "wof:name":"Rancho Chiquito",
    "wof:placetype":"locality"
},
  "geometry": {"coordinates":[-87.51666999999998,14.28333],"type":"Point"}
}