{
  "type": "Feature",
  "properties": {
    "gn:country":"HN",
    "gn:fcode":"PPL",
    "gn:population":1066,
    "iso:country":"HN",
    "qs_pg:aaroncc":"HN",
    "qs_pg:gn_country":"HN",
    "qs_pg:gn_fcode":"PPL",
    "qs_pg:gn_pop":1066,
    "qs_pg:name":"San Francisco de Cones",
    "qs_pg:photos_9r":0,
    "qs_pg:photos_sr":0,
    "qs_pg:pop_sr":3,
    "qs_pg:qs_pg_placetype":"locality",
    "wof:name":"San Francisco de Cones",
    "wof:placetype":"locality",
    "wof:population":1066
},
  "geometry": {"coordinates":[-88.90000000000001,14.51667],"type":"Point"}
}