{
  "type": "Feature",
  "properties": {
    "gn:admin1_code":"08",
    "gn:asciiname":"Aceituno Pando",
    "gn:country_code":"HN",
    "gn:dem":540,
    "gn:feature_class":"P",
    "gn:feature_code":"PPL",
    "gn:name":"Aceituno Pando",
    "gn:population":0,
    "gn:timezone":"America/Tegucigalpa",
    "iso:country":"HN",
    "wof:name":"Aceituno Pando",
    "wof:placetype":"locality"
},
  "geometry": {"coordinates":[-87.56222,13.77667],"type":"Point"}
}