{
  "type": "Feature",
  "properties": {
    "gn:admin1_code":"07",
    "gn:asciiname":"Guayambre",
    "gn:country_code":"HN",
    "gn:dem":444,
    "gn:feature_class":"P",
    "gn:feature_code":"PPL",
    "gn:name":"Guayambre",
    "gn:population":0,
    "gn:timezone":"America/Tegucigalpa",
    "iso:country":"HN",
    "wof:name":"Guayambre",
    "wof:placetype":"locality"
},
  "geometry": {"coordinates":[-86.36667,14.03333],"type":"Point"}
}