{
  "type": "Feature",
  "properties": {
    "gn:asciiname":"Lucinda",
    "gn:country_code":"HN",
    "gn:dem":5,
    "gn:feature_class":"P",
    "gn:feature_code":"PPLL",
    "gn:name":"Lucinda",
    "gn:population":0,
    "gn:timezone":"America/Tegucigalpa",
    "iso:country":"HN",
    "wof:name":"Lucinda",
    "wof:placetype":"locality"
},
  "geometry": {"coordinates":[-86.38086,15.77684],"type":"Point"}
}