{
  "type": "Feature",
  "properties": {
    "gn:admin1_code":"07",
    "gn:asciiname":"Portillo del Hato Grande",
    "gn:country_code":"HN",
    "gn:dem":1059,
    "gn:feature_class":"P",
    "gn:feature_code":"PPL",
    "gn:name":"Portillo del Hato Grande",
    "gn:population":0,
    "gn:timezone":"America/Tegucigalpa",
    "iso:country":"HN",
    "wof:name":"Portillo del Hato Grande",
    "wof:placetype":"locality"
},
  "geometry": {"coordinates":[-87.04944,13.70833],"type":"Point"}
}