{
  "type": "Feature",
  "properties": {
    "gn:admin1_code":"01",
    "gn:asciiname":"Naranjal",
    "gn:cc2":"HN",
    "gn:country_code":"HN",
    "gn:dem":28,
    "gn:feature_class":"P",
    "gn:feature_code":"PPL",
    "gn:name":"Naranjal",
    "gn:population":0,
    "gn:timezone":"America/Tegucigalpa",
    "iso:country":"HN",
    "name:ceb_x_preferred":[
        "Naranjal"
    ],
    "name:deu_x_preferred":[
        "Naranjal"
    ],
    "name:pol_x_preferred":[
        "Naranjal"
    ],
    "name:spa_x_preferred":[
        "Naranjal"
    ],
    "name:swe_x_preferred":[
        "Naranjal"
    ],
    "name:und_x_variant":[
        "El Naranjal",
        "Naranjel"
    ],
    "wof:name":"Naranjal",
    "wof:placetype":"locality"
},
  "geometry": {"coordinates":[-87.08333,15.63333],"type":"Point"}
}