{
  "type": "Feature",
  "properties": {
    "gn:admin1_code":"06",
    "gn:asciiname":"Omonita Campo",
    "gn:country_code":"HN",
    "gn:dem":30,
    "gn:feature_class":"P",
    "gn:feature_code":"PPL",
    "gn:name":"Omonita Campo",
    "gn:population":0,
    "gn:timezone":"America/Tegucigalpa",
    "iso:country":"HN",
    "wof:name":"Omonita Campo",
    "wof:placetype":"locality"
},
  "geometry": {"coordinates":[-87.84999999999999,15.38333],"type":"Point"}
}