{
  "type": "Feature",
  "properties": {
    "gn:admin1_code":"10",
    "gn:asciiname":"El Quebrachal",
    "gn:cc2":"HN",
    "gn:country_code":"HN",
    "gn:dem":467,
    "gn:feature_class":"P",
    "gn:feature_code":"PPL",
    "gn:name":"El Quebrachal",
    "gn:population":0,
    "gn:timezone":"America/Tegucigalpa",
    "iso:country":"HN",
    "name:und_x_variant":[
        "Quebrachal",
        "El Quebrachal"
    ],
    "wof:name":"El Quebrachal",
    "wof:placetype":"locality"
},
  "geometry": {"coordinates":[-88.26666999999998,13.91667],"type":"Point"}
}