{
  "type": "Feature",
  "properties": {
    "gn:admin1_code":"07",
    "gn:asciiname":"Los Chorros",
    "gn:country_code":"HN",
    "gn:dem":734,
    "gn:feature_class":"P",
    "gn:feature_code":"PPL",
    "gn:name":"Los Chorros",
    "gn:population":0,
    "gn:timezone":"America/Tegucigalpa",
    "iso:country":"HN",
    "wof:name":"Los Chorros",
    "wof:placetype":"locality"
},
  "geometry": {"coordinates":[-87.18944,13.68083],"type":"Point"}
}