{
  "type": "Feature",
  "properties": {
    "gn:admin1_code":"02",
    "gn:asciiname":"Omoa",
    "gn:country_code":"HN",
    "gn:dem":573,
    "gn:feature_class":"P",
    "gn:feature_code":"PPL",
    "gn:name":"Omoa",
    "gn:population":0,
    "gn:timezone":"America/Tegucigalpa",
    "iso:country":"HN",
    "name:ara_x_preferred":[
        "\u0623\u0648\u0645\u0648\u0627"
    ],
    "name:deu_x_preferred":[
        "Omoa"
    ],
    "name:fin_x_preferred":[
        "Omoa"
    ],
    "name:fra_x_preferred":[
        "Omoa"
    ],
    "name:ita_x_preferred":[
        "Omoa"
    ],
    "name:lit_x_preferred":[
        "Omoa"
    ],
    "name:nld_x_preferred":[
        "Omoa"
    ],
    "name:pol_x_preferred":[
        "Omoa"
    ],
    "name:por_x_preferred":[
        "Omoa"
    ],
    "name:spa_x_preferred":[
        "Omoa"
    ],
    "name:zho_x_preferred":[
        "\u5967\u83ab\u963f"
    ],
    "wof:name":"Omoa",
    "wof:placetype":"locality"
},
  "geometry": {"coordinates":[-87.01694000000001,13.21417],"type":"Point"}
}