{
  "type": "Feature",
  "properties": {
    "gn:admin1_code":"08",
    "gn:asciiname":"El Aguacatal",
    "gn:cc2":"HN",
    "gn:country_code":"HN",
    "gn:dem":1388,
    "gn:feature_class":"P",
    "gn:feature_code":"PPL",
    "gn:name":"El Aguacatal",
    "gn:population":0,
    "gn:timezone":"America/Tegucigalpa",
    "iso:country":"HN",
    "name:und_x_variant":[
        "Aguacatal",
        "El Aguacatal"
    ],
    "wof:name":"El Aguacatal",
    "wof:placetype":"locality"
},
  "geometry": {"coordinates":[-87.37222,13.99222],"type":"Point"}
}