{
  "type": "Feature",
  "properties": {
    "gn:admin1_code":"07",
    "gn:asciiname":"Jocoton",
    "gn:country_code":"HN",
    "gn:dem":812,
    "gn:feature_class":"P",
    "gn:feature_code":"PPL",
    "gn:name":"Jocot\u00f3n",
    "gn:population":0,
    "gn:timezone":"America/Tegucigalpa",
    "iso:country":"HN",
    "wof:name":"Jocoton",
    "wof:placetype":"locality"
},
  "geometry": {"coordinates":[-87.04805999999998,13.64056],"type":"Point"}
}