{
  "type": "Feature",
  "properties": {
    "gn:admin1_code":"08",
    "gn:asciiname":"Las Jaguitas",
    "gn:cc2":"HN",
    "gn:country_code":"HN",
    "gn:dem":966,
    "gn:feature_class":"P",
    "gn:feature_code":"PPL",
    "gn:name":"Las Jag\u00fcitas",
    "gn:population":0,
    "gn:timezone":"America/Tegucigalpa",
    "iso:country":"HN",
    "name:und_x_variant":[
        "La Jag\u00fcita",
        "Las Jag\u00fcitas"
    ],
    "wof:name":"Las Jaguitas",
    "wof:placetype":"locality"
},
  "geometry": {"coordinates":[-87.05861,13.89111],"type":"Point"}
}