{
  "type": "Feature",
  "properties": {
    "gn:admin1_code":"18",
    "gn:asciiname":"Yaguala",
    "gn:cc2":"HN",
    "gn:country_code":"HN",
    "gn:dem":737,
    "gn:feature_class":"P",
    "gn:feature_code":"PPL",
    "gn:name":"Yaguala",
    "gn:population":0,
    "gn:timezone":"America/Tegucigalpa",
    "iso:country":"HN",
    "name:und_x_variant":[
        "Yagual",
        "Yaguala"
    ],
    "wof:name":"Yaguala",
    "wof:placetype":"locality"
},
  "geometry": {"coordinates":[-86.76666999999998,15.31667],"type":"Point"}
}