{
  "type": "Feature",
  "properties": {
    "gn:admin1_code":"04",
    "gn:asciiname":"La Penita",
    "gn:cc2":"HN",
    "gn:country_code":"HN",
    "gn:dem":969,
    "gn:feature_class":"P",
    "gn:feature_code":"PPL",
    "gn:name":"La Pe\u00f1ita",
    "gn:population":0,
    "gn:timezone":"America/Tegucigalpa",
    "iso:country":"HN",
    "name:und_x_variant":[
        "La Pi\u00f1ita",
        "La Pe\u00f1ita"
    ],
    "wof:name":"La Penita",
    "wof:placetype":"locality"
},
  "geometry": {"coordinates":[-87.61667,14.16667],"type":"Point"}
}