{
  "type": "Feature",
  "properties": {
    "gn:admin1_code":"05",
    "gn:asciiname":"Banaderos",
    "gn:country_code":"HN",
    "gn:dem":1412,
    "gn:feature_class":"P",
    "gn:feature_code":"PPL",
    "gn:name":"Ba\u00f1aderos",
    "gn:population":0,
    "gn:timezone":"America/Tegucigalpa",
    "iso:country":"HN",
    "wof:name":"Banaderos",
    "wof:placetype":"locality"
},
  "geometry": {"coordinates":[-88.93333,14.86667],"type":"Point"}
}