{
  "type": "Feature",
  "properties": {
    "gn:admin1_code":"08",
    "gn:asciiname":"San Lorenzo Abajo",
    "gn:country_code":"HN",
    "gn:dem":735,
    "gn:feature_class":"P",
    "gn:feature_code":"PPL",
    "gn:name":"San Lorenzo Abajo",
    "gn:population":0,
    "gn:timezone":"America/Tegucigalpa",
    "iso:country":"HN",
    "wof:name":"San Lorenzo Abajo",
    "wof:placetype":"locality"
},
  "geometry": {"coordinates":[-87.07971999999999,13.88028],"type":"Point"}
}