{
  "type": "Feature",
  "properties": {
    "gn:admin1_code":"05",
    "gn:asciiname":"Otuta",
    "gn:country_code":"HN",
    "gn:dem":837,
    "gn:feature_class":"P",
    "gn:feature_code":"PPL",
    "gn:name":"Otuta",
    "gn:population":0,
    "gn:timezone":"America/Tegucigalpa",
    "iso:country":"HN",
    "wof:name":"Otuta",
    "wof:placetype":"locality"
},
  "geometry": {"coordinates":[-89.06667,14.91667],"type":"Point"}
}