{
  "type": "Feature",
  "properties": {
    "gn:admin1_code":"16",
    "gn:asciiname":"Quebrada Desplayada",
    "gn:country_code":"HN",
    "gn:dem":1531,
    "gn:feature_class":"P",
    "gn:feature_code":"PPL",
    "gn:name":"Quebrada Desplayada",
    "gn:population":0,
    "gn:timezone":"America/Tegucigalpa",
    "iso:country":"HN",
    "wof:name":"Quebrada Desplayada",
    "wof:placetype":"locality"
},
  "geometry": {"coordinates":[-88.41667,14.83333],"type":"Point"}
}