{
  "type": "Feature",
  "properties": {
    "gn:admin1_code":"04",
    "gn:asciiname":"Mescales",
    "gn:cc2":"HN",
    "gn:country_code":"HN",
    "gn:dem":462,
    "gn:feature_class":"P",
    "gn:feature_code":"PPL",
    "gn:name":"Mescales",
    "gn:population":0,
    "gn:timezone":"America/Tegucigalpa",
    "iso:country":"HN",
    "name:und_x_variant":[
        "Mezcales",
        "Mescales"
    ],
    "wof:name":"Mescales",
    "wof:placetype":"locality"
},
  "geometry": {"coordinates":[-87.65000000000001,14.63333],"type":"Point"}
}