{
  "type": "Feature",
  "properties": {
    "gn:admin1_code":"02",
    "gn:asciiname":"El Quebrachal",
    "gn:country_code":"HN",
    "gn:dem":447,
    "gn:feature_class":"P",
    "gn:feature_code":"PPL",
    "gn:name":"El Quebrachal",
    "gn:population":0,
    "gn:timezone":"America/Tegucigalpa",
    "iso:country":"HN",
    "name:ceb_x_preferred":[
        "El Quebrachal"
    ],
    "name:por_x_preferred":[
        "El Quebrachal"
    ],
    "name:spa_x_preferred":[
        "El Quebrachal"
    ],
    "name:swe_x_preferred":[
        "El Quebrachal"
    ],
    "wof:name":"El Quebrachal",
    "wof:placetype":"locality"
},
  "geometry": {"coordinates":[-87.2225,13.47444],"type":"Point"}
}