{
  "type": "Feature",
  "properties": {
    "gn:admin1_code":"08",
    "gn:asciiname":"Joyas de Carballo",
    "gn:cc2":"HN",
    "gn:country_code":"HN",
    "gn:dem":1151,
    "gn:feature_class":"P",
    "gn:feature_code":"PPL",
    "gn:name":"Joyas de Carballo",
    "gn:population":0,
    "gn:timezone":"America/Tegucigalpa",
    "iso:country":"HN",
    "name:und_x_variant":[
        "Joyas Carballo",
        "Joyas de Carballo"
    ],
    "wof:name":"Joyas de Carballo",
    "wof:placetype":"locality"
},
  "geometry": {"coordinates":[-86.91667,14.35],"type":"Point"}
}