{
  "type": "Feature",
  "properties": {
    "gn:admin1_code":"08",
    "gn:asciiname":"Cueva Pintada",
    "gn:country_code":"HN",
    "gn:dem":1399,
    "gn:feature_class":"P",
    "gn:feature_code":"PPL",
    "gn:name":"Cueva Pintada",
    "gn:population":0,
    "gn:timezone":"America/Tegucigalpa",
    "iso:country":"HN",
    "wof:name":"Cueva Pintada",
    "wof:placetype":"locality"
},
  "geometry": {"coordinates":[-87.21556,13.93083],"type":"Point"}
}