{
  "type": "Feature",
  "properties": {
    "gn:admin1_code":"02",
    "gn:asciiname":"Los Araditos",
    "gn:country_code":"HN",
    "gn:dem":502,
    "gn:feature_class":"P",
    "gn:feature_code":"PPL",
    "gn:name":"Los Araditos",
    "gn:population":0,
    "gn:timezone":"America/Tegucigalpa",
    "iso:country":"HN",
    "wof:name":"Los Araditos",
    "wof:placetype":"locality"
},
  "geometry": {"coordinates":[-87.15611,13.50861],"type":"Point"}
}