{
  "type": "Feature",
  "properties": {
    "gn:admin1_code":"01",
    "gn:asciiname":"Tarritos",
    "gn:country_code":"HN",
    "gn:dem":31,
    "gn:feature_class":"P",
    "gn:feature_code":"PPL",
    "gn:name":"Tarritos",
    "gn:population":0,
    "gn:timezone":"America/Tegucigalpa",
    "iso:country":"HN",
    "wof:name":"Tarritos",
    "wof:placetype":"locality"
},
  "geometry": {"coordinates":[-87.16667,15.61667],"type":"Point"}
}