{
  "type": "Feature",
  "properties": {
    "gn:admin1_code":"01",
    "gn:asciiname":"Tripoli",
    "gn:country_code":"HN",
    "gn:dem":15,
    "gn:feature_class":"P",
    "gn:feature_code":"PPL",
    "gn:name":"Tr\u00edpoli",
    "gn:population":0,
    "gn:timezone":"America/Tegucigalpa",
    "iso:country":"HN",
    "wof:name":"Tripoli",
    "wof:placetype":"locality"
},
  "geometry": {"coordinates":[-87.15000000000001,15.68333],"type":"Point"}
}