{
  "type": "Feature",
  "properties": {
    "gn:admin1_code":"15",
    "gn:asciiname":"Aguacatales",
    "gn:cc2":"HN",
    "gn:country_code":"HN",
    "gn:dem":1271,
    "gn:feature_class":"P",
    "gn:feature_code":"PPL",
    "gn:name":"Aguacatales",
    "gn:population":0,
    "gn:timezone":"America/Tegucigalpa",
    "iso:country":"HN",
    "name:und_x_variant":[
        "Aguacatal",
        "Aguacatales"
    ],
    "wof:name":"Aguacatales",
    "wof:placetype":"locality"
},
  "geometry": {"coordinates":[-86.16667,15.31667],"type":"Point"}
}