{
  "type": "Feature",
  "properties": {
    "gn:admin1_code":"02",
    "gn:asciiname":"La Cueva del Tigre",
    "gn:cc2":"HN",
    "gn:country_code":"HN",
    "gn:dem":1403,
    "gn:feature_class":"P",
    "gn:feature_code":"PPL",
    "gn:name":"La Cueva del Tigre",
    "gn:population":0,
    "gn:timezone":"America/Tegucigalpa",
    "iso:country":"HN",
    "name:und_x_variant":[
        "La Cueva de Tigre",
        "La Cueva del Tigre"
    ],
    "wof:name":"La Cueva del Tigre",
    "wof:placetype":"locality"
},
  "geometry": {"coordinates":[-86.76666999999998,13.38333],"type":"Point"}
}