{
  "type": "Feature",
  "properties": {
    "gn:admin1_code":"02",
    "gn:asciiname":"El Carrizal",
    "gn:country_code":"HN",
    "gn:dem":424,
    "gn:feature_class":"P",
    "gn:feature_code":"PPL",
    "gn:name":"El Carrizal",
    "gn:population":0,
    "gn:timezone":"America/Tegucigalpa",
    "iso:country":"HN",
    "wof:name":"El Carrizal",
    "wof:placetype":"locality"
},
  "geometry": {"coordinates":[-87.25583,13.48528],"type":"Point"}
}