{
  "type": "Feature",
  "properties": {
    "gn:admin1_code":"07",
    "gn:asciiname":"Salamar",
    "gn:country_code":"HN",
    "gn:dem":1123,
    "gn:feature_class":"P",
    "gn:feature_code":"PPL",
    "gn:name":"Salamar",
    "gn:population":0,
    "gn:timezone":"America/Tegucigalpa",
    "iso:country":"HN",
    "wof:name":"Salamar",
    "wof:placetype":"locality"
},
  "geometry": {"coordinates":[-86.51666999999998,13.86667],"type":"Point"}
}