{
  "type": "Feature",
  "properties": {
    "gn:admin1_code":"05",
    "gn:asciiname":"Las Pavas",
    "gn:country_code":"HN",
    "gn:dem":1038,
    "gn:feature_class":"P",
    "gn:feature_code":"PPL",
    "gn:name":"Las Pavas",
    "gn:population":0,
    "gn:timezone":"America/Tegucigalpa",
    "iso:country":"HN",
    "wof:name":"Las Pavas",
    "wof:placetype":"locality"
},
  "geometry": {"coordinates":[-88.93333,14.91667],"type":"Point"}
}