{
  "type": "Feature",
  "properties": {
    "gn:admin1_code":"18",
    "gn:asciiname":"Rio Abajo",
    "gn:country_code":"HN",
    "gn:dem":285,
    "gn:feature_class":"P",
    "gn:feature_code":"PPL",
    "gn:name":"R\u00edo Abajo",
    "gn:population":0,
    "gn:timezone":"America/Tegucigalpa",
    "iso:country":"HN",
    "wof:name":"Rio Abajo",
    "wof:placetype":"locality"
},
  "geometry": {"coordinates":[-87.01666999999998,15.36667],"type":"Point"}
}