{
  "type": "Feature",
  "properties": {
    "gn:admin1_code":"12",
    "gn:asciiname":"Mercedes de Oriente",
    "gn:country_code":"HN",
    "gn:dem":1019,
    "gn:feature_class":"P",
    "gn:feature_code":"PPL",
    "gn:name":"Mercedes de Oriente",
    "gn:population":0,
    "gn:timezone":"America/Tegucigalpa",
    "iso:country":"HN",
    "wof:name":"Mercedes de Oriente",
    "wof:placetype":"locality"
},
  "geometry": {"coordinates":[-87.77583,13.91028],"type":"Point"}
}