{
  "type": "Feature",
  "properties": {
    "gn:admin1_code":"08",
    "gn:asciiname":"El Jicaral",
    "gn:country_code":"HN",
    "gn:dem":647,
    "gn:feature_class":"P",
    "gn:feature_code":"PPL",
    "gn:name":"El Jicaral",
    "gn:population":0,
    "gn:timezone":"America/Tegucigalpa",
    "iso:country":"HN",
    "wof:name":"El Jicaral",
    "wof:placetype":"locality"
},
  "geometry": {"coordinates":[-87.45444000000001,13.83861],"type":"Point"}
}