{
  "type": "Feature",
  "properties": {
    "gn:admin1_code":"04",
    "gn:asciiname":"La Laguneta",
    "gn:cc2":"HN",
    "gn:country_code":"HN",
    "gn:dem":987,
    "gn:feature_class":"P",
    "gn:feature_code":"PPL",
    "gn:name":"La Laguneta",
    "gn:population":0,
    "gn:timezone":"America/Tegucigalpa",
    "iso:country":"HN",
    "name:und_x_variant":[
        "La Laguna",
        "La Laguneta"
    ],
    "wof:name":"La Laguneta",
    "wof:placetype":"locality"
},
  "geometry": {"coordinates":[-87.66667,14.16667],"type":"Point"}
}