{
  "type": "Feature",
  "properties": {
    "gn:admin1_code":"18",
    "gn:asciiname":"El Salitre",
    "gn:country_code":"HN",
    "gn:dem":732,
    "gn:feature_class":"P",
    "gn:feature_code":"PPL",
    "gn:name":"El Salitre",
    "gn:population":0,
    "gn:timezone":"America/Tegucigalpa",
    "iso:country":"HN",
    "wof:name":"El Salitre",
    "wof:placetype":"locality"
},
  "geometry": {"coordinates":[-87.31667,15.21667],"type":"Point"}
}