{
  "type": "Feature",
  "properties": {
    "gn:admin1_code":"18",
    "gn:asciiname":"La Cebadilla",
    "gn:country_code":"HN",
    "gn:dem":312,
    "gn:feature_class":"P",
    "gn:feature_code":"PPL",
    "gn:name":"La Cebadilla",
    "gn:population":0,
    "gn:timezone":"America/Tegucigalpa",
    "iso:country":"HN",
    "wof:name":"La Cebadilla",
    "wof:placetype":"locality"
},
  "geometry": {"coordinates":[-86.98333000000002,15.43333],"type":"Point"}
}