{
  "type": "Feature",
  "properties": {
    "gn:admin1_code":"07",
    "gn:asciiname":"Managua",
    "gn:country_code":"HN",
    "gn:dem":570,
    "gn:feature_class":"P",
    "gn:feature_code":"PPL",
    "gn:name":"Managua",
    "gn:population":0,
    "gn:timezone":"America/Tegucigalpa",
    "iso:country":"HN",
    "wof:name":"Managua",
    "wof:placetype":"locality"
},
  "geometry": {"coordinates":[-87.09639,13.61028],"type":"Point"}
}