{
  "type": "Feature",
  "properties": {
    "gn:admin1_code":"02",
    "gn:asciiname":"Las Uvas",
    "gn:country_code":"HN",
    "gn:dem":145,
    "gn:feature_class":"P",
    "gn:feature_code":"PPL",
    "gn:name":"Las Uvas",
    "gn:population":0,
    "gn:timezone":"America/Tegucigalpa",
    "iso:country":"HN",
    "wof:name":"Las Uvas",
    "wof:placetype":"locality"
},
  "geometry": {"coordinates":[-87.02249999999999,13.1325],"type":"Point"}
}