{
  "type": "Feature",
  "properties": {
    "gn:admin1_code":"07",
    "gn:asciiname":"La Sidra",
    "gn:country_code":"HN",
    "gn:dem":525,
    "gn:feature_class":"P",
    "gn:feature_code":"PPL",
    "gn:name":"La Sidra",
    "gn:population":0,
    "gn:timezone":"America/Tegucigalpa",
    "iso:country":"HN",
    "name:ast_x_preferred":[
        "La Sidra"
    ],
    "name:glg_x_preferred":[
        "La Sidra"
    ],
    "wof:name":"La Sidra",
    "wof:placetype":"locality"
},
  "geometry": {"coordinates":[-87.01666999999998,13.51667],"type":"Point"}
}