{
  "type": "Feature",
  "properties": {
    "gn:admin1_code":"08",
    "gn:asciiname":"Colonia Zapote Centro",
    "gn:country_code":"HN",
    "gn:dem":994,
    "gn:feature_class":"P",
    "gn:feature_code":"PPL",
    "gn:name":"Colonia Zapote Centro",
    "gn:population":0,
    "gn:timezone":"America/Tegucigalpa",
    "iso:country":"HN",
    "wof:name":"Colonia Zapote Centro",
    "wof:placetype":"locality"
},
  "geometry": {"coordinates":[-87.22583,14.10361],"type":"Point"}
}