{
  "type": "Feature",
  "properties": {
    "gn:admin1_code":"17",
    "gn:asciiname":"El Espinito",
    "gn:country_code":"HN",
    "gn:dem":348,
    "gn:feature_class":"P",
    "gn:feature_code":"PPL",
    "gn:name":"El Espinito",
    "gn:population":0,
    "gn:timezone":"America/Tegucigalpa",
    "iso:country":"HN",
    "wof:name":"El Espinito",
    "wof:placetype":"locality"
},
  "geometry": {"coordinates":[-87.72028,13.84528],"type":"Point"}
}