{
  "type": "Feature",
  "properties": {
    "gn:admin1_code":"09",
    "gn:asciiname":"Awawas Rapido",
    "gn:country_code":"HN",
    "gn:dem":116,
    "gn:feature_class":"P",
    "gn:feature_code":"PPL",
    "gn:name":"Awawas R\u00e1pido",
    "gn:population":0,
    "gn:timezone":"America/Tegucigalpa",
    "iso:country":"HN",
    "wof:name":"Awawas Rapido",
    "wof:placetype":"locality"
},
  "geometry": {"coordinates":[-84.91667,14.78333],"type":"Point"}
}