{
  "type": "Feature",
  "properties": {
    "gn:admin1_code":"15",
    "gn:asciiname":"El Rancho",
    "gn:cc2":"HN",
    "gn:country_code":"HN",
    "gn:dem":743,
    "gn:feature_class":"P",
    "gn:feature_code":"PPL",
    "gn:name":"El Rancho",
    "gn:population":0,
    "gn:timezone":"America/Tegucigalpa",
    "iso:country":"HN",
    "name:ceb_x_preferred":[
        "El Rancho"
    ],
    "name:deu_x_preferred":[
        "El Rancho"
    ],
    "name:ita_x_preferred":[
        "El Rancho"
    ],
    "name:spa_x_preferred":[
        "El Rancho"
    ],
    "name:srp_x_preferred":[
        "\u0415\u043b \u0420\u0430\u043d\u0447\u043e"
    ],
    "name:swe_x_preferred":[
        "El Rancho"
    ],
    "name:ukr_x_preferred":[
        "\u0415\u043b\u044c-\u0420\u0430\u043d\u0447\u043e"
    ],
    "name:und_x_variant":[
        "Rancho"
    ],
    "wof:name":"El Rancho",
    "wof:placetype":"locality"
},
  "geometry": {"coordinates":[-85.75,15.01667],"type":"Point"}
}