{
  "type": "Feature",
  "properties": {
    "gn:admin1_code":"13",
    "gn:asciiname":"El Porvenir de Ojuera",
    "gn:cc2":"HN",
    "gn:country_code":"HN",
    "gn:dem":1562,
    "gn:feature_class":"P",
    "gn:feature_code":"PPL",
    "gn:name":"El Porvenir de Ojuera",
    "gn:population":0,
    "gn:timezone":"America/Tegucigalpa",
    "iso:country":"HN",
    "name:und_x_variant":[
        "Ojuera",
        "El Porvenir de Ojuera"
    ],
    "wof:name":"El Porvenir de Ojuera",
    "wof:placetype":"locality"
},
  "geometry": {"coordinates":[-88.38333,14.53333],"type":"Point"}
}