{
  "type": "Feature",
  "properties": {
    "gn:admin1_code":"17",
    "gn:asciiname":"Tierra Morena",
    "gn:country_code":"HN",
    "gn:dem":229,
    "gn:feature_class":"P",
    "gn:feature_code":"PPL",
    "gn:name":"Tierra Morena",
    "gn:population":0,
    "gn:timezone":"America/Tegucigalpa",
    "iso:country":"HN",
    "wof:name":"Tierra Morena",
    "wof:placetype":"locality"
},
  "geometry": {"coordinates":[-87.45889,13.57611],"type":"Point"}
}