{
  "type": "Feature",
  "properties": {
    "gn:admin1_code":"08",
    "gn:asciiname":"El Portillo de Siales",
    "gn:cc2":"HN",
    "gn:country_code":"HN",
    "gn:dem":943,
    "gn:feature_class":"P",
    "gn:feature_code":"PPL",
    "gn:name":"El Portillo de Siales",
    "gn:population":0,
    "gn:timezone":"America/Tegucigalpa",
    "iso:country":"HN",
    "name:und_x_variant":[
        "Portillo de Siale",
        "El Portillo de Siales"
    ],
    "wof:name":"El Portillo de Siales",
    "wof:placetype":"locality"
},
  "geometry": {"coordinates":[-87.03333000000001,14.83333],"type":"Point"}
}