{
  "type": "Feature",
  "properties": {
    "gn:admin1_code":"18",
    "gn:asciiname":"Calichito",
    "gn:country_code":"HN",
    "gn:dem":674,
    "gn:feature_class":"P",
    "gn:feature_code":"PPL",
    "gn:name":"Calichito",
    "gn:population":0,
    "gn:timezone":"America/Tegucigalpa",
    "iso:country":"HN",
    "wof:name":"Calichito",
    "wof:placetype":"locality"
},
  "geometry": {"coordinates":[-87.48333000000002,14.88333],"type":"Point"}
}