{
  "type": "Feature",
  "properties": {
    "gn:admin1_code":"08",
    "gn:asciiname":"Canyuco",
    "gn:country_code":"HN",
    "gn:dem":1524,
    "gn:feature_class":"P",
    "gn:feature_code":"PPL",
    "gn:name":"Canyuco",
    "gn:population":0,
    "gn:timezone":"America/Tegucigalpa",
    "iso:country":"HN",
    "wof:name":"Canyuco",
    "wof:placetype":"locality"
},
  "geometry": {"coordinates":[-87.34999999999999,13.93333],"type":"Point"}
}