{
  "type": "Feature",
  "properties": {
    "gn:admin1_code":"18",
    "gn:asciiname":"Chorrera",
    "gn:country_code":"HN",
    "gn:dem":156,
    "gn:feature_class":"P",
    "gn:feature_code":"PPL",
    "gn:name":"Chorrera",
    "gn:population":0,
    "gn:timezone":"America/Tegucigalpa",
    "iso:country":"HN",
    "wof:name":"Chorrera",
    "wof:placetype":"locality"
},
  "geometry": {"coordinates":[-86.71666999999999,15.41667],"type":"Point"}
}