{
  "type": "Feature",
  "properties": {
    "gn:admin1_code":"13",
    "gn:asciiname":"Corta Cabezas",
    "gn:country_code":"HN",
    "gn:dem":1371,
    "gn:feature_class":"P",
    "gn:feature_code":"PPL",
    "gn:name":"Corta Cabezas",
    "gn:population":0,
    "gn:timezone":"America/Tegucigalpa",
    "iso:country":"HN",
    "wof:name":"Corta Cabezas",
    "wof:placetype":"locality"
},
  "geometry": {"coordinates":[-88.48333000000002,14.13333],"type":"Point"}
}