{
  "type": "Feature",
  "properties": {
    "gn:admin1_code":"10",
    "gn:asciiname":"El Espino",
    "gn:country_code":"HN",
    "gn:dem":288,
    "gn:feature_class":"P",
    "gn:feature_code":"PPL",
    "gn:name":"El Espino",
    "gn:population":0,
    "gn:timezone":"America/Tegucigalpa",
    "iso:country":"HN",
    "name:ceb_x_preferred":[
        "El Espino"
    ],
    "name:deu_x_preferred":[
        "El Espino"
    ],
    "name:ita_x_preferred":[
        "El Espino"
    ],
    "name:srp_x_preferred":[
        "\u0415\u043b \u0415\u0441\u043f\u0438\u043d\u043e"
    ],
    "name:swe_x_preferred":[
        "El Espino"
    ],
    "wof:name":"El Espino",
    "wof:placetype":"locality"
},
  "geometry": {"coordinates":[-88.31667,13.88333],"type":"Point"}
}