{
  "type": "Feature",
  "properties": {
    "gn:admin1_code":"07",
    "gn:asciiname":"Hoya Grande",
    "gn:cc2":"HN",
    "gn:country_code":"HN",
    "gn:dem":1188,
    "gn:feature_class":"P",
    "gn:feature_code":"PPL",
    "gn:name":"Hoya Grande",
    "gn:population":0,
    "gn:timezone":"America/Tegucigalpa",
    "iso:country":"HN",
    "name:und_x_variant":[
        "Hoja Grande",
        "Joya Grande",
        "Holla Grande",
        "Hoya Grande"
    ],
    "wof:name":"Hoya Grande",
    "wof:placetype":"locality"
},
  "geometry": {"coordinates":[-86.78333000000001,14.13333],"type":"Point"}
}