{
  "type": "Feature",
  "properties": {
    "gn:admin1_code":"02",
    "gn:asciiname":"Hacienda Las Anonas",
    "gn:country_code":"HN",
    "gn:dem":8,
    "gn:feature_class":"P",
    "gn:feature_code":"PPL",
    "gn:name":"Hacienda Las An\u00f3nas",
    "gn:population":0,
    "gn:timezone":"America/Tegucigalpa",
    "iso:country":"HN",
    "wof:name":"Hacienda Las Anonas",
    "wof:placetype":"locality"
},
  "geometry": {"coordinates":[-87.30556,13.21],"type":"Point"}
}