{
  "type": "Feature",
  "properties": {
    "gn:admin1_code":"14",
    "gn:asciiname":"Los Ranchos",
    "gn:country_code":"HN",
    "gn:dem":1454,
    "gn:feature_class":"P",
    "gn:feature_code":"PPL",
    "gn:name":"Los Ranchos",
    "gn:population":0,
    "gn:timezone":"America/Tegucigalpa",
    "iso:country":"HN",
    "name:ceb_x_preferred":[
        "Los Ranchos"
    ],
    "name:swe_x_preferred":[
        "Los Ranchos"
    ],
    "wof:name":"Los Ranchos",
    "wof:placetype":"locality"
},
  "geometry": {"coordinates":[-89.06667,14.51667],"type":"Point"}
}