{
  "type": "Feature",
  "properties": {
    "gn:admin1_code":"12",
    "gn:asciiname":"Las Papayas",
    "gn:country_code":"HN",
    "gn:dem":642,
    "gn:feature_class":"P",
    "gn:feature_code":"PPL",
    "gn:name":"Las Papayas",
    "gn:population":0,
    "gn:timezone":"America/Tegucigalpa",
    "iso:country":"HN",
    "wof:name":"Las Papayas",
    "wof:placetype":"locality"
},
  "geometry": {"coordinates":[-87.95278,13.91306],"type":"Point"}
}