{
  "type": "Feature",
  "properties": {
    "gn:admin1_code":"02",
    "gn:asciiname":"La Enea",
    "gn:cc2":"HN",
    "gn:country_code":"HN",
    "gn:dem":355,
    "gn:feature_class":"P",
    "gn:feature_code":"PPL",
    "gn:name":"La Enea",
    "gn:population":0,
    "gn:timezone":"America/Tegucigalpa",
    "iso:country":"HN",
    "name:und_x_variant":[
        "Enea",
        "La Enea"
    ],
    "wof:name":"La Enea",
    "wof:placetype":"locality"
},
  "geometry": {"coordinates":[-86.91667,13.61667],"type":"Point"}
}