{
  "type": "Feature",
  "properties": {
    "gn:admin1_code":"02",
    "gn:asciiname":"La Enea",
    "gn:cc2":"HN",
    "gn:country_code":"HN",
    "gn:dem":355,
    "gn:feature_class":"P",
    "gn:feature_code":"PPL",
    "gn:name":"La Enea",
    "gn:population":0,
    "gn:timezone":"America/Tegucigalpa",
    "iso:country":"HN",
    "name:ita_x_preferred":[
        "La Enea"
    ],
    "name:spa_x_preferred":[
        "La Enea"
    ],
    "name:und_x_variant":[
        "Enea"
    ],
    "name:zho_x_preferred":[
        "\u62c9\u57c3\u5167\u963f"
    ],
    "wof:name":"La Enea",
    "wof:placetype":"locality"
},
  "geometry": {"coordinates":[-86.91667,13.61667],"type":"Point"}
}