{
  "type": "Feature",
  "properties": {
    "gn:admin1_code":"17",
    "gn:asciiname":"El Portillo de San Antonio",
    "gn:cc2":"HN",
    "gn:country_code":"HN",
    "gn:dem":217,
    "gn:feature_class":"P",
    "gn:feature_code":"PPL",
    "gn:name":"El Portillo de San Antonio",
    "gn:population":0,
    "gn:timezone":"America/Tegucigalpa",
    "iso:country":"HN",
    "name:und_x_variant":[
        "El Portillo",
        "El Portillo de San Antonio"
    ],
    "wof:name":"El Portillo de San Antonio",
    "wof:placetype":"locality"
},
  "geometry": {"coordinates":[-87.58055999999998,13.61028],"type":"Point"}
}