{
  "type": "Feature",
  "properties": {
    "gn:admin1_code":"04",
    "gn:asciiname":"Plan de Ramon",
    "gn:country_code":"HN",
    "gn:dem":852,
    "gn:feature_class":"P",
    "gn:feature_code":"PPL",
    "gn:name":"Plan de Ram\u00f3n",
    "gn:population":0,
    "gn:timezone":"America/Tegucigalpa",
    "iso:country":"HN",
    "wof:name":"Plan de Ramon",
    "wof:placetype":"locality"
},
  "geometry": {"coordinates":[-87.58333,14.75],"type":"Point"}
}