{
  "type": "Feature",
  "properties": {
    "gn:admin1_code":"08",
    "gn:asciiname":"Los Encuentros",
    "gn:country_code":"HN",
    "gn:dem":1517,
    "gn:feature_class":"P",
    "gn:feature_code":"PPL",
    "gn:name":"Los Encuentros",
    "gn:population":0,
    "gn:timezone":"America/Tegucigalpa",
    "iso:country":"HN",
    "wof:name":"Los Encuentros",
    "wof:placetype":"locality"
},
  "geometry": {"coordinates":[-87.14139,13.98472],"type":"Point"}
}