{
  "type": "Feature",
  "properties": {
    "gn:admin1_code":"10",
    "gn:asciiname":"El Espinal",
    "gn:cc2":"HN",
    "gn:country_code":"HN",
    "gn:dem":1353,
    "gn:feature_class":"P",
    "gn:feature_code":"PPL",
    "gn:name":"El Espinal",
    "gn:population":0,
    "gn:timezone":"America/Tegucigalpa",
    "iso:country":"HN",
    "name:cat_x_preferred":[
        "L'Espinal"
    ],
    "name:ceb_x_preferred":[
        "El Espinal"
    ],
    "name:ita_x_preferred":[
        "El Espinal"
    ],
    "name:spa_x_preferred":[
        "El Espinal"
    ],
    "name:srp_x_preferred":[
        "\u0415\u043b \u0415\u0441\u043f\u0438\u043d\u0430\u043b"
    ],
    "name:swe_x_preferred":[
        "El Espinal"
    ],
    "name:und_x_variant":[
        "La Retumbadora",
        "El Espinal"
    ],
    "wof:name":"El Espinal",
    "wof:placetype":"locality"
},
  "geometry": {"coordinates":[-88.46666999999999,14.38333],"type":"Point"}
}