{
  "type": "Feature",
  "properties": {
    "gn:admin1_code":"17",
    "gn:asciiname":"La Danta",
    "gn:country_code":"HN",
    "gn:dem":445,
    "gn:feature_class":"P",
    "gn:feature_code":"PPL",
    "gn:name":"La Danta",
    "gn:population":0,
    "gn:timezone":"America/Tegucigalpa",
    "iso:country":"HN",
    "wof:name":"La Danta",
    "wof:placetype":"locality"
},
  "geometry": {"coordinates":[-87.43139000000002,13.62389],"type":"Point"}
}