{
  "type": "Feature",
  "properties": {
    "gn:admin1_code":"08",
    "gn:asciiname":"Santa Marta",
    "gn:cc2":"HN",
    "gn:country_code":"HN",
    "gn:dem":608,
    "gn:feature_class":"P",
    "gn:feature_code":"PPL",
    "gn:name":"Santa Marta",
    "gn:population":0,
    "gn:timezone":"America/Tegucigalpa",
    "iso:country":"HN",
    "name:und_x_variant":[
        "Santa Martha",
        "Santa Marta"
    ],
    "wof:name":"Santa Marta",
    "wof:placetype":"locality"
},
  "geometry": {"coordinates":[-87.46833000000002,13.73417],"type":"Point"}
}