{
  "type": "Feature",
  "properties": {
    "gn:admin1_code":"04",
    "gn:asciiname":"La Laguna",
    "gn:country_code":"HN",
    "gn:dem":1063,
    "gn:feature_class":"P",
    "gn:feature_code":"PPL",
    "gn:name":"La Laguna",
    "gn:population":0,
    "gn:timezone":"America/Tegucigalpa",
    "iso:country":"HN",
    "wof:name":"La Laguna",
    "wof:placetype":"locality"
},
  "geometry": {"coordinates":[-87.81667,14.58333],"type":"Point"}
}