{
  "type": "Feature",
  "properties": {
    "gn:admin1_code":"02",
    "gn:asciiname":"Licanto",
    "gn:country_code":"HN",
    "gn:dem":78,
    "gn:feature_class":"P",
    "gn:feature_code":"PPL",
    "gn:name":"Licanto",
    "gn:population":0,
    "gn:timezone":"America/Tegucigalpa",
    "iso:country":"HN",
    "wof:name":"Licanto",
    "wof:placetype":"locality"
},
  "geometry": {"coordinates":[-87.16306,13.37528],"type":"Point"}
}