{
  "type": "Feature",
  "properties": {
    "gn:admin1_code":"08",
    "gn:asciiname":"El Matasano",
    "gn:country_code":"HN",
    "gn:dem":1129,
    "gn:feature_class":"P",
    "gn:feature_code":"PPL",
    "gn:name":"El Matasano",
    "gn:population":0,
    "gn:timezone":"America/Tegucigalpa",
    "iso:country":"HN",
    "wof:name":"El Matasano",
    "wof:placetype":"locality"
},
  "geometry": {"coordinates":[-87.34999999999999,14.16667],"type":"Point"}
}