{
  "type": "Feature",
  "properties": {
    "gn:admin1_code":"12",
    "gn:asciiname":"San Jose del Bramadero",
    "gn:country_code":"HN",
    "gn:dem":892,
    "gn:feature_class":"P",
    "gn:feature_code":"PPL",
    "gn:name":"San Jos\u00e9 del Bramadero",
    "gn:population":0,
    "gn:timezone":"America/Tegucigalpa",
    "iso:country":"HN",
    "wof:name":"San Jose del Bramadero",
    "wof:placetype":"locality"
},
  "geometry": {"coordinates":[-87.78971999999997,13.99333],"type":"Point"}
}