{
  "type": "Feature",
  "properties": {
    "gn:admin1_code":"08",
    "gn:asciiname":"San Matias",
    "gn:country_code":"HN",
    "gn:dem":1317,
    "gn:feature_class":"P",
    "gn:feature_code":"PPL",
    "gn:name":"San Mat\u00edas",
    "gn:population":0,
    "gn:timezone":"America/Tegucigalpa",
    "iso:country":"HN",
    "wof:name":"San Matias",
    "wof:placetype":"locality"
},
  "geometry": {"coordinates":[-87.34999999999999,14.13333],"type":"Point"}
}