{
  "type": "Feature",
  "properties": {
    "gn:admin1_code":"07",
    "gn:asciiname":"El Rodeito",
    "gn:country_code":"HN",
    "gn:dem":551,
    "gn:feature_class":"P",
    "gn:feature_code":"PPL",
    "gn:name":"El Rode\u00edto",
    "gn:population":0,
    "gn:timezone":"America/Tegucigalpa",
    "iso:country":"HN",
    "wof:name":"El Rodeito",
    "wof:placetype":"locality"
},
  "geometry": {"coordinates":[-87.09999999999999,13.56667],"type":"Point"}
}