{
  "type": "Feature",
  "properties": {
    "gn:admin1_code":"02",
    "gn:asciiname":"Hacienda La Florida",
    "gn:cc2":"HN",
    "gn:country_code":"HN",
    "gn:dem":6,
    "gn:feature_class":"P",
    "gn:feature_code":"PPL",
    "gn:name":"Hacienda La Florida",
    "gn:population":0,
    "gn:timezone":"America/Tegucigalpa",
    "iso:country":"HN",
    "name:und_x_variant":[
        "La Florida",
        "Hacienda La Florida"
    ],
    "wof:name":"Hacienda La Florida",
    "wof:placetype":"locality"
},
  "geometry": {"coordinates":[-87.36944,13.15972],"type":"Point"}
}