{
  "type": "Feature",
  "properties": {
    "gn:admin1_code":"15",
    "gn:asciiname":"Jucurunca",
    "gn:country_code":"HN",
    "gn:dem":919,
    "gn:feature_class":"P",
    "gn:feature_code":"PPL",
    "gn:name":"Jucurunca",
    "gn:population":0,
    "gn:timezone":"America/Tegucigalpa",
    "iso:country":"HN",
    "wof:name":"Jucurunca",
    "wof:placetype":"locality"
},
  "geometry": {"coordinates":[-86.84999999999999,14.76667],"type":"Point"}
}