{
  "type": "Feature",
  "properties": {
    "gn:admin1_code":"07",
    "gn:asciiname":"El Barro",
    "gn:country_code":"HN",
    "gn:dem":763,
    "gn:feature_class":"P",
    "gn:feature_code":"PPL",
    "gn:name":"El Barro",
    "gn:population":0,
    "gn:timezone":"America/Tegucigalpa",
    "iso:country":"HN",
    "wof:name":"El Barro",
    "wof:placetype":"locality"
},
  "geometry": {"coordinates":[-86.86667,13.78333],"type":"Point"}
}