{
  "type": "Feature",
  "properties": {
    "gn:admin1_code":"13",
    "gn:asciiname":"Los Metales",
    "gn:country_code":"HN",
    "gn:dem":398,
    "gn:feature_class":"P",
    "gn:feature_code":"PPL",
    "gn:name":"Los Metales",
    "gn:population":0,
    "gn:timezone":"America/Tegucigalpa",
    "iso:country":"HN",
    "wof:name":"Los Metales",
    "wof:placetype":"locality"
},
  "geometry": {"coordinates":[-88.59999999999999,14.08333],"type":"Point"}
}