{
  "type": "Feature",
  "properties": {
    "gn:admin1_code":"02",
    "gn:asciiname":"Los Cerritos",
    "gn:country_code":"HN",
    "gn:dem":656,
    "gn:feature_class":"P",
    "gn:feature_code":"PPL",
    "gn:name":"Los Cerritos",
    "gn:population":0,
    "gn:timezone":"America/Tegucigalpa",
    "iso:country":"HN",
    "wof:name":"Los Cerritos",
    "wof:placetype":"locality"
},
  "geometry": {"coordinates":[-87.00221999999999,13.40167],"type":"Point"}
}