{
  "type": "Feature",
  "properties": {
    "iso:country":"HN",
    "name:chi_x_preferred":[
        "\u8056\u5f17\u862d\u897f\u65af\u79d1\u5fb7\u8c9d\u585e\u62c9"
    ],
    "name:dut_x_preferred":[
        "San Francisco de Becerra"
    ],
    "name:eng_x_preferred":[
        "San Francisco de Becerra"
    ],
    "name:fre_x_preferred":[
        "San Francisco de Becerra"
    ],
    "name:ita_x_preferred":[
        "San Francisco de Becerra"
    ],
    "name:jpn_x_preferred":[
        "\u30b5\u30f3\u30fb\u30d5\u30e9\u30f3\u30b7\u30b9\u30b3\u30fb\u30c7\u30fb\u30d9\u30bb\u30fc\u30e9"
    ],
    "name:nld_x_preferred":[
        "San Francisco de Becerra"
    ],
    "name:por_x_preferred":[
        "San Francisco de Becerra"
    ],
    "name:spa_x_preferred":[
        "San Francisco de Becerra"
    ],
    "name:swe_x_preferred":[
        "San Francisco de Becerra"
    ],
    "name:unk_x_variant":[
        "San Francisco Becerra"
    ],
    "name:zho_x_preferred":[
        "\u8056\u5f17\u862d\u897f\u65af\u79d1\u5fb7\u8c9d\u585e\u62c9"
    ],
    "qs:gn_country":"HN",
    "qs:gn_fcode":"PPL",
    "qs:gn_pop":2411,
    "qs:name":"San Francisco de Becerra",
    "qs:name_adm0":"Honduras",
    "qs:name_adm1":"Olancho",
    "qs:photos":0,
    "qs:photos_1k":0,
    "qs:photos_9k":0,
    "qs:photos_9r":0,
    "qs:photos_all":0,
    "qs:photos_sr":0,
    "qs:placetype":"Town",
    "qs:pop_sr":"4",
    "qs:woe_adm0":23424841,
    "wof:name":"San Francisco de Becerra",
    "wof:placetype":"locality",
    "wof:population":2411
},
  "geometry": {"coordinates":[-86.09999999999999,14.63333],"type":"Point"}
}