{
  "type": "Feature",
  "properties": {
    "gn:admin1_code":"10",
    "gn:asciiname":"El Tejar",
    "gn:country_code":"HN",
    "gn:dem":1820,
    "gn:feature_class":"P",
    "gn:feature_code":"PPL",
    "gn:name":"El Tejar",
    "gn:population":0,
    "gn:timezone":"America/Tegucigalpa",
    "iso:country":"HN",
    "name:ceb_x_preferred":[
        "El Tejar"
    ],
    "name:fra_x_preferred":[
        "El Tejar"
    ],
    "name:ita_x_preferred":[
        "El Tejar"
    ],
    "name:spa_x_preferred":[
        "El Tejar"
    ],
    "name:swe_x_preferred":[
        "El Tejar"
    ],
    "wof:name":"El Tejar",
    "wof:placetype":"locality"
},
  "geometry": {"coordinates":[-88.18333,14.23333],"type":"Point"}
}