{
  "type": "Feature",
  "properties": {
    "gn:admin1_code":"16",
    "gn:asciiname":"Pitones Altos",
    "gn:country_code":"HN",
    "gn:dem":288,
    "gn:feature_class":"P",
    "gn:feature_code":"PPL",
    "gn:name":"Pitones Altos",
    "gn:population":0,
    "gn:timezone":"America/Tegucigalpa",
    "iso:country":"HN",
    "wof:name":"Pitones Altos",
    "wof:placetype":"locality"
},
  "geometry": {"coordinates":[-88.23333000000002,15.15],"type":"Point"}
}