{
  "type": "Feature",
  "properties": {
    "gn:admin1_code":"05",
    "gn:asciiname":"Motagua",
    "gn:country_code":"HN",
    "gn:dem":988,
    "gn:feature_class":"P",
    "gn:feature_code":"PPL",
    "gn:name":"Motagua",
    "gn:population":0,
    "gn:timezone":"America/Tegucigalpa",
    "iso:country":"HN",
    "wof:name":"Motagua",
    "wof:placetype":"locality"
},
  "geometry": {"coordinates":[-89.05,14.78333],"type":"Point"}
}