{
  "type": "Feature",
  "properties": {
    "gn:admin1_code":"13",
    "gn:asciiname":"Rio Blanco",
    "gn:country_code":"HN",
    "gn:dem":961,
    "gn:feature_class":"P",
    "gn:feature_code":"PPL",
    "gn:name":"R\u00edo Blanco",
    "gn:population":0,
    "gn:timezone":"America/Tegucigalpa",
    "iso:country":"HN",
    "wof:name":"Rio Blanco",
    "wof:placetype":"locality"
},
  "geometry": {"coordinates":[-88.45,14.71667],"type":"Point"}
}