{
  "type": "Feature",
  "properties": {
    "gn:admin1_code":"09",
    "gn:asciiname":"Mistruk",
    "gn:cc2":"HN",
    "gn:country_code":"HN",
    "gn:dem":8,
    "gn:feature_class":"P",
    "gn:feature_code":"PPL",
    "gn:name":"Mistruk",
    "gn:population":0,
    "gn:timezone":"America/Tegucigalpa",
    "iso:country":"HN",
    "name:und_x_variant":[
        "Mistric",
        "Mistruc",
        "Mistuc",
        "Mistruck",
        "Mistruk"
    ],
    "wof:name":"Mistruk",
    "wof:placetype":"locality"
},
  "geometry": {"coordinates":[-83.88333,15.23333],"type":"Point"}
}