{
  "type": "Feature",
  "properties": {
    "gn:admin1_code":"05",
    "gn:asciiname":"La Bufa",
    "gn:cc2":"HN",
    "gn:country_code":"HN",
    "gn:dem":815,
    "gn:feature_class":"P",
    "gn:feature_code":"PPL",
    "gn:name":"La Bufa",
    "gn:population":0,
    "gn:timezone":"America/Tegucigalpa",
    "iso:country":"HN",
    "name:und_x_variant":[
        "Bufa",
        "La Bufa"
    ],
    "wof:name":"La Bufa",
    "wof:placetype":"locality"
},
  "geometry": {"coordinates":[-88.93333,14.73333],"type":"Point"}
}