{
  "type": "Feature",
  "properties": {
    "gn:admin1_code":"13",
    "gn:asciiname":"Villa Verde",
    "gn:country_code":"HN",
    "gn:dem":1401,
    "gn:feature_class":"P",
    "gn:feature_code":"PPL",
    "gn:name":"Villa Verde",
    "gn:population":0,
    "gn:timezone":"America/Tegucigalpa",
    "iso:country":"HN",
    "wof:name":"Villa Verde",
    "wof:placetype":"locality"
},
  "geometry": {"coordinates":[-88.63333,14.56667],"type":"Point"}
}