{
  "type": "Feature",
  "properties": {
    "gn:admin1_code":"18",
    "gn:asciiname":"Teguajal",
    "gn:country_code":"HN",
    "gn:dem":443,
    "gn:feature_class":"P",
    "gn:feature_code":"PPL",
    "gn:name":"Teguajal",
    "gn:population":0,
    "gn:timezone":"America/Tegucigalpa",
    "iso:country":"HN",
    "wof:name":"Teguajal",
    "wof:placetype":"locality"
},
  "geometry": {"coordinates":[-86.76666999999998,15.35],"type":"Point"}
}