{
  "type": "Feature",
  "properties": {
    "gn:admin1_code":"08",
    "gn:asciiname":"Sanguijuela",
    "gn:country_code":"HN",
    "gn:dem":1117,
    "gn:feature_class":"P",
    "gn:feature_code":"PPL",
    "gn:name":"Sanguijuela",
    "gn:population":0,
    "gn:timezone":"America/Tegucigalpa",
    "iso:country":"HN",
    "wof:name":"Sanguijuela",
    "wof:placetype":"locality"
},
  "geometry": {"coordinates":[-86.75,14.38333],"type":"Point"}
}