{
  "type": "Feature",
  "properties": {
    "gn:admin1_code":"16",
    "gn:asciiname":"Vuelta Grande",
    "gn:country_code":"HN",
    "gn:dem":826,
    "gn:feature_class":"P",
    "gn:feature_code":"PPL",
    "gn:name":"Vuelta Grande",
    "gn:population":0,
    "gn:timezone":"America/Tegucigalpa",
    "iso:country":"HN",
    "wof:name":"Vuelta Grande",
    "wof:placetype":"locality"
},
  "geometry": {"coordinates":[-88.5925,15.3425],"type":"Point"}
}