{
  "type": "Feature",
  "properties": {
    "gn:admin1_code":"05",
    "gn:asciiname":"Concepcion",
    "gn:cc2":"HN",
    "gn:country_code":"HN",
    "gn:dem":1068,
    "gn:feature_class":"P",
    "gn:feature_code":"PPL",
    "gn:name":"Concepci\u00f3n",
    "gn:population":0,
    "gn:timezone":"America/Tegucigalpa",
    "iso:country":"HN",
    "name:und_x_variant":[
        "Concepci\u00f3n de Piedras",
        "Concepcion Piedras",
        "Concepci\u00f3n"
    ],
    "wof:name":"Concepcion",
    "wof:placetype":"locality"
},
  "geometry": {"coordinates":[-88.84999999999999,14.83333],"type":"Point"}
}