{
  "type": "Feature",
  "properties": {
    "gn:admin1_code":"05",
    "gn:asciiname":"Concepcion",
    "gn:cc2":"HN",
    "gn:country_code":"HN",
    "gn:dem":1068,
    "gn:feature_class":"P",
    "gn:feature_code":"PPL",
    "gn:name":"Concepci\u00f3n",
    "gn:population":0,
    "gn:timezone":"America/Tegucigalpa",
    "iso:country":"HN",
    "name:fra_x_preferred":[
        "Concepci\u00f3n"
    ],
    "name:ita_x_preferred":[
        "Concepci\u00f3n"
    ],
    "name:nld_x_preferred":[
        "Concepci\u00f3n"
    ],
    "name:pol_x_preferred":[
        "Concepci\u00f3n"
    ],
    "name:por_x_preferred":[
        "Concepci\u00f3n"
    ],
    "name:spa_x_preferred":[
        "Concepci\u00f3n"
    ],
    "name:und_x_variant":[
        "Concepci\u00f3n de Piedras",
        "Concepcion Piedras"
    ],
    "name:zho_x_preferred":[
        "\u5eb7\u585e\u666e\u897f\u7fc1"
    ],
    "wof:name":"Concepcion",
    "wof:placetype":"locality"
},
  "geometry": {"coordinates":[-88.84999999999999,14.83333],"type":"Point"}
}