{
  "type": "Feature",
  "properties": {
    "gn:admin1_code":"08",
    "gn:asciiname":"Hacienda Santa Cruz",
    "gn:country_code":"HN",
    "gn:dem":980,
    "gn:feature_class":"P",
    "gn:feature_code":"PPL",
    "gn:name":"Hacienda Santa Cruz",
    "gn:population":0,
    "gn:timezone":"America/Tegucigalpa",
    "iso:country":"HN",
    "wof:name":"Hacienda Santa Cruz",
    "wof:placetype":"locality"
},
  "geometry": {"coordinates":[-87.05,13.95],"type":"Point"}
}