{
  "type": "Feature",
  "properties": {
    "iso:country":"HN",
    "name:ceb_x_preferred":[
        "Intibuc\u00e1"
    ],
    "name:deu_x_preferred":[
        "Intibuc\u00e1"
    ],
    "name:eng_x_preferred":[
        "Intibuc\u00e1"
    ],
    "name:eus_x_preferred":[
        "Intibuc\u00e1"
    ],
    "name:fra_x_preferred":[
        "Intibuc\u00e1"
    ],
    "name:ita_x_preferred":[
        "Intibuc\u00e1"
    ],
    "name:nan_x_preferred":[
        "Intibuc\u00e1"
    ],
    "name:nld_x_preferred":[
        "Intibuc\u00e1"
    ],
    "name:pol_x_preferred":[
        "Intibuc\u00e1"
    ],
    "name:por_x_preferred":[
        "Intibuc\u00e1"
    ],
    "name:spa_x_preferred":[
        "Intibuc\u00e1"
    ],
    "name:swe_x_preferred":[
        "Intibuc\u00e1"
    ],
    "qs:gn_country":"HN",
    "qs:gn_fcode":"PPL",
    "qs:gn_pop":13741,
    "qs:name":"Intibuc\u00e1",
    "qs:name_adm0":"Honduras",
    "qs:name_adm1":"Intibuc\u00e1",
    "qs:photos":346,
    "qs:photos_1k":70,
    "qs:photos_9k":2,
    "qs:photos_9r":5,
    "qs:photos_all":346,
    "qs:photos_sr":5,
    "qs:placetype":"Town",
    "qs:pop_sr":"6",
    "qs:woe_adm0":23424841,
    "wof:name":"Intibuc\u00e1",
    "wof:placetype":"locality",
    "wof:population":13741
},
  "geometry": {"coordinates":[-88.16667,14.31667],"type":"Point"}
}