{
  "type": "Feature",
  "properties": {
    "gn:admin1_code":"02",
    "gn:asciiname":"La Manzana",
    "gn:country_code":"HN",
    "gn:dem":493,
    "gn:feature_class":"P",
    "gn:feature_code":"PPL",
    "gn:name":"La Manzana",
    "gn:population":0,
    "gn:timezone":"America/Tegucigalpa",
    "iso:country":"HN",
    "wof:name":"La Manzana",
    "wof:placetype":"locality"
},
  "geometry": {"coordinates":[-87.03333000000001,13.36667],"type":"Point"}
}