{
  "type": "Feature",
  "properties": {
    "gn:admin1_code":"13",
    "gn:asciiname":"San Sebastian",
    "gn:country_code":"HN",
    "gn:dem":631,
    "gn:feature_class":"P",
    "gn:feature_code":"PPL",
    "gn:name":"San Sebasti\u00e1n",
    "gn:population":0,
    "gn:timezone":"America/Tegucigalpa",
    "iso:country":"HN",
    "wof:name":"San Sebastian",
    "wof:placetype":"locality"
},
  "geometry": {"coordinates":[-88.43333,14.08333],"type":"Point"}
}