{
  "type": "Feature",
  "properties": {
    "gn:admin1_code":"08",
    "gn:asciiname":"Milpa Vieja",
    "gn:country_code":"HN",
    "gn:dem":1368,
    "gn:feature_class":"P",
    "gn:feature_code":"PPL",
    "gn:name":"Milpa Vieja",
    "gn:population":0,
    "gn:timezone":"America/Tegucigalpa",
    "iso:country":"HN",
    "wof:name":"Milpa Vieja",
    "wof:placetype":"locality"
},
  "geometry": {"coordinates":[-87.07250000000001,13.98778],"type":"Point"}
}