{
  "type": "Feature",
  "properties": {
    "gn:admin1_code":"17",
    "gn:asciiname":"Amates",
    "gn:country_code":"HN",
    "gn:dem":192,
    "gn:feature_class":"P",
    "gn:feature_code":"PPL",
    "gn:name":"Amates",
    "gn:population":0,
    "gn:timezone":"America/Tegucigalpa",
    "iso:country":"HN",
    "wof:name":"Amates",
    "wof:placetype":"locality"
},
  "geometry": {"coordinates":[-87.51666999999998,13.66667],"type":"Point"}
}