{
  "type": "Feature",
  "properties": {
    "gn:admin1_code":"13",
    "gn:asciiname":"El Gusano",
    "gn:country_code":"HN",
    "gn:dem":1289,
    "gn:feature_class":"P",
    "gn:feature_code":"PPL",
    "gn:name":"El Gusano",
    "gn:population":0,
    "gn:timezone":"America/Tegucigalpa",
    "iso:country":"HN",
    "wof:name":"El Gusano",
    "wof:placetype":"locality"
},
  "geometry": {"coordinates":[-88.58333,14.33333],"type":"Point"}
}