{
  "type": "Feature",
  "properties": {
    "gn:admin1_code":"08",
    "gn:asciiname":"Plan del Rancho",
    "gn:country_code":"HN",
    "gn:dem":1168,
    "gn:feature_class":"P",
    "gn:feature_code":"PPL",
    "gn:name":"Plan del Rancho",
    "gn:population":0,
    "gn:timezone":"America/Tegucigalpa",
    "iso:country":"HN",
    "wof:name":"Plan del Rancho",
    "wof:placetype":"locality"
},
  "geometry": {"coordinates":[-87.58889000000001,13.85778],"type":"Point"}
}