{
  "type": "Feature",
  "properties": {
    "gn:admin1_code":"06",
    "gn:asciiname":"Medina",
    "gn:country_code":"HN",
    "gn:dem":398,
    "gn:feature_class":"P",
    "gn:feature_code":"PPL",
    "gn:name":"Medina",
    "gn:population":0,
    "gn:timezone":"America/Tegucigalpa",
    "iso:country":"HN",
    "wof:name":"Medina",
    "wof:placetype":"locality"
},
  "geometry": {"coordinates":[-87.90000000000001,15.76667],"type":"Point"}
}