{
  "type": "Feature",
  "properties": {
    "gn:admin1_code":"03",
    "gn:asciiname":"La Puntilla",
    "gn:country_code":"HN",
    "gn:dem":-9999,
    "gn:feature_class":"P",
    "gn:feature_code":"PPL",
    "gn:name":"La Puntilla",
    "gn:population":0,
    "gn:timezone":"America/Tegucigalpa",
    "iso:country":"HN",
    "name:ceb_x_preferred":[
        "La Puntilla"
    ],
    "name:deu_x_preferred":[
        "La Puntilla"
    ],
    "name:spa_x_preferred":[
        "La Puntilla"
    ],
    "name:swe_x_preferred":[
        "La Puntilla"
    ],
    "wof:name":"La Puntilla",
    "wof:placetype":"locality"
},
  "geometry": {"coordinates":[-86.01666999999998,16.01667],"type":"Point"}
}