{
  "type": "Feature",
  "properties": {
    "gn:admin1_code":"08",
    "gn:asciiname":"El Canto",
    "gn:country_code":"HN",
    "gn:dem":1623,
    "gn:feature_class":"P",
    "gn:feature_code":"PPL",
    "gn:name":"El Canto",
    "gn:population":0,
    "gn:timezone":"America/Tegucigalpa",
    "iso:country":"HN",
    "wof:name":"El Canto",
    "wof:placetype":"locality"
},
  "geometry": {"coordinates":[-87.14028,13.96667],"type":"Point"}
}