{
  "type": "Feature",
  "properties": {
    "gn:admin1_code":"07",
    "gn:asciiname":"San Cristobal",
    "gn:country_code":"HN",
    "gn:dem":1307,
    "gn:feature_class":"P",
    "gn:feature_code":"PPL",
    "gn:name":"San Crist\u00f3bal",
    "gn:population":0,
    "gn:timezone":"America/Tegucigalpa",
    "iso:country":"HN",
    "wof:name":"San Cristobal",
    "wof:placetype":"locality"
},
  "geometry": {"coordinates":[-86.58333,14.08333],"type":"Point"}
}