{
  "type": "Feature",
  "properties": {
    "gn:admin1_code":"13",
    "gn:asciiname":"Rostrojo Grande",
    "gn:cc2":"HN",
    "gn:country_code":"HN",
    "gn:dem":973,
    "gn:feature_class":"P",
    "gn:feature_code":"PPL",
    "gn:name":"Rostrojo Grande",
    "gn:population":0,
    "gn:timezone":"America/Tegucigalpa",
    "iso:country":"HN",
    "name:und_x_variant":[
        "El Caulotal",
        "Rastrojo",
        "Rostrojo Grande"
    ],
    "wof:name":"Rostrojo Grande",
    "wof:placetype":"locality"
},
  "geometry": {"coordinates":[-88.78333000000001,14.68333],"type":"Point"}
}