{
  "type": "Feature",
  "properties": {
    "gn:admin1_code":"02",
    "gn:asciiname":"Las Lajitas",
    "gn:country_code":"HN",
    "gn:dem":852,
    "gn:feature_class":"P",
    "gn:feature_code":"PPL",
    "gn:name":"Las Lajitas",
    "gn:population":0,
    "gn:timezone":"America/Tegucigalpa",
    "iso:country":"HN",
    "wof:name":"Las Lajitas",
    "wof:placetype":"locality"
},
  "geometry": {"coordinates":[-87.18944,13.51861],"type":"Point"}
}