{
  "type": "Feature",
  "properties": {
    "gn:admin1_code":"05",
    "gn:asciiname":"Higueral",
    "gn:country_code":"HN",
    "gn:dem":847,
    "gn:feature_class":"P",
    "gn:feature_code":"PPL",
    "gn:name":"Higueral",
    "gn:population":0,
    "gn:timezone":"America/Tegucigalpa",
    "iso:country":"HN",
    "wof:name":"Higueral",
    "wof:placetype":"locality"
},
  "geometry": {"coordinates":[-88.93333,14.76667],"type":"Point"}
}