{
  "type": "Feature",
  "properties": {
    "gn:admin1_code":"08",
    "gn:asciiname":"Upare",
    "gn:country_code":"HN",
    "gn:dem":1676,
    "gn:feature_class":"P",
    "gn:feature_code":"PPL",
    "gn:name":"Upare",
    "gn:population":0,
    "gn:timezone":"America/Tegucigalpa",
    "iso:country":"HN",
    "wof:name":"Upare",
    "wof:placetype":"locality"
},
  "geometry": {"coordinates":[-87.33333,14.03333],"type":"Point"}
}