{
  "type": "Feature",
  "properties": {
    "gn:admin1_code":"08",
    "gn:asciiname":"Oseguera",
    "gn:country_code":"HN",
    "gn:dem":342,
    "gn:feature_class":"P",
    "gn:feature_code":"PPL",
    "gn:name":"Oseguera",
    "gn:population":0,
    "gn:timezone":"America/Tegucigalpa",
    "iso:country":"HN",
    "wof:name":"Oseguera",
    "wof:placetype":"locality"
},
  "geometry": {"coordinates":[-87.39749999999999,13.81222],"type":"Point"}
}