{
  "type": "Feature",
  "properties": {
    "gn:admin1_code":"06",
    "gn:asciiname":"Caracol",
    "gn:cc2":"HN",
    "gn:country_code":"HN",
    "gn:dem":22,
    "gn:feature_class":"P",
    "gn:feature_code":"PPL",
    "gn:name":"Caracol",
    "gn:population":0,
    "gn:timezone":"America/Tegucigalpa",
    "iso:country":"HN",
    "name:und_x_variant":[
        "Curocol",
        "Caracol"
    ],
    "wof:name":"Caracol",
    "wof:placetype":"locality"
},
  "geometry": {"coordinates":[-88.23333000000002,15.63333],"type":"Point"}
}