{
  "type": "Feature",
  "properties": {
    "gn:admin1_code":"05",
    "gn:asciiname":"Vega de las Chanchas",
    "gn:country_code":"HN",
    "gn:dem":525,
    "gn:feature_class":"P",
    "gn:feature_code":"PPL",
    "gn:name":"Vega de las Chanchas",
    "gn:population":0,
    "gn:timezone":"America/Tegucigalpa",
    "iso:country":"HN",
    "wof:name":"Vega de las Chanchas",
    "wof:placetype":"locality"
},
  "geometry": {"coordinates":[-88.66667,14.71667],"type":"Point"}
}