{
  "type": "Feature",
  "properties": {
    "gn:admin1_code":"17",
    "gn:asciiname":"Jicaro Pintado",
    "gn:country_code":"HN",
    "gn:dem":508,
    "gn:feature_class":"P",
    "gn:feature_code":"PPL",
    "gn:name":"J\u00edcaro Pintado",
    "gn:population":0,
    "gn:timezone":"America/Tegucigalpa",
    "iso:country":"HN",
    "wof:name":"Jicaro Pintado",
    "wof:placetype":"locality"
},
  "geometry": {"coordinates":[-87.61667,13.71667],"type":"Point"}
}