{
  "type": "Feature",
  "properties": {
    "gn:admin1_code":"17",
    "gn:asciiname":"San Andres",
    "gn:country_code":"HN",
    "gn:dem":78,
    "gn:feature_class":"P",
    "gn:feature_code":"PPL",
    "gn:name":"San Andr\u00e9s",
    "gn:population":0,
    "gn:timezone":"America/Tegucigalpa",
    "iso:country":"HN",
    "wof:name":"San Andres",
    "wof:placetype":"locality"
},
  "geometry": {"coordinates":[-87.73278000000001,13.58694],"type":"Point"}
}