{
  "type": "Feature",
  "properties": {
    "gn:admin1_code":"02",
    "gn:asciiname":"Llano Grande",
    "gn:country_code":"HN",
    "gn:dem":44,
    "gn:feature_class":"P",
    "gn:feature_code":"PPL",
    "gn:name":"Llano Grande",
    "gn:population":0,
    "gn:timezone":"America/Tegucigalpa",
    "iso:country":"HN",
    "name:ceb_x_preferred":[
        "Llano Grande"
    ],
    "name:deu_x_preferred":[
        "Llano Grande"
    ],
    "name:fra_x_preferred":[
        "Llano Grande"
    ],
    "name:ita_x_preferred":[
        "Llano Grande"
    ],
    "name:spa_x_preferred":[
        "Llano Grande"
    ],
    "name:swe_x_preferred":[
        "Llano Grande"
    ],
    "wof:name":"Llano Grande",
    "wof:placetype":"locality"
},
  "geometry": {"coordinates":[-87.06,13.07667],"type":"Point"}
}