{
  "type": "Feature",
  "properties": {
    "gn:admin1_code":"02",
    "gn:asciiname":"La Galera",
    "gn:cc2":"HN",
    "gn:country_code":"HN",
    "gn:dem":550,
    "gn:feature_class":"P",
    "gn:feature_code":"PPL",
    "gn:name":"La Galera",
    "gn:population":0,
    "gn:timezone":"America/Tegucigalpa",
    "iso:country":"HN",
    "name:und_x_variant":[
        "Galera",
        "La Galera"
    ],
    "wof:name":"La Galera",
    "wof:placetype":"locality"
},
  "geometry": {"coordinates":[-87.04639,13.36889],"type":"Point"}
}