{
  "type": "Feature",
  "properties": {
    "gn:admin1_code":"17",
    "gn:asciiname":"El Tun Tun",
    "gn:cc2":"HN",
    "gn:country_code":"HN",
    "gn:dem":101,
    "gn:feature_class":"P",
    "gn:feature_code":"PPL",
    "gn:name":"El Tun Tun",
    "gn:population":0,
    "gn:timezone":"America/Tegucigalpa",
    "iso:country":"HN",
    "name:und_x_variant":[
        "El Tunt\u00fan",
        "El Tun Tun"
    ],
    "wof:name":"El Tun Tun",
    "wof:placetype":"locality"
},
  "geometry": {"coordinates":[-87.74139,13.6275],"type":"Point"}
}