{
  "type": "Feature",
  "properties": {
    "gn:admin1_code":"18",
    "gn:asciiname":"Cerrito del Mal Nombre",
    "gn:cc2":"HN",
    "gn:country_code":"HN",
    "gn:dem":675,
    "gn:feature_class":"P",
    "gn:feature_code":"PPL",
    "gn:name":"Cerrito del Mal Nombre",
    "gn:population":0,
    "gn:timezone":"America/Tegucigalpa",
    "iso:country":"HN",
    "name:und_x_variant":[
        "Cerrito de Mal Nombra",
        "Cerrito del Mal Nombre"
    ],
    "wof:name":"Cerrito del Mal Nombre",
    "wof:placetype":"locality"
},
  "geometry": {"coordinates":[-87.11667,15.13333],"type":"Point"}
}