{
  "type": "Feature",
  "properties": {
    "gn:admin1_code":"12",
    "gn:asciiname":"Zacate Blanco",
    "gn:cc2":"HN",
    "gn:country_code":"HN",
    "gn:dem":1902,
    "gn:feature_class":"P",
    "gn:feature_code":"PPL",
    "gn:name":"Zacate Blanco",
    "gn:population":0,
    "gn:timezone":"America/Tegucigalpa",
    "iso:country":"HN",
    "name:und_x_variant":[
        "Zacate Grande",
        "Zacate Blanco"
    ],
    "wof:name":"Zacate Blanco",
    "wof:placetype":"locality"
},
  "geometry": {"coordinates":[-88.05,14.06667],"type":"Point"}
}