{
  "type": "Feature",
  "properties": {
    "gn:admin1_code":"05",
    "gn:asciiname":"La Vereda",
    "gn:country_code":"HN",
    "gn:dem":1018,
    "gn:feature_class":"P",
    "gn:feature_code":"PPL",
    "gn:name":"La Vereda",
    "gn:population":0,
    "gn:timezone":"America/Tegucigalpa",
    "iso:country":"HN",
    "wof:name":"La Vereda",
    "wof:placetype":"locality"
},
  "geometry": {"coordinates":[-88.83333,14.56667],"type":"Point"}
}