{
  "type": "Feature",
  "properties": {
    "gn:admin1_code":"08",
    "gn:asciiname":"El Chaguiton",
    "gn:country_code":"HN",
    "gn:dem":603,
    "gn:feature_class":"P",
    "gn:feature_code":"PPL",
    "gn:name":"El Chag\u00fcit\u00f3n",
    "gn:population":0,
    "gn:timezone":"America/Tegucigalpa",
    "iso:country":"HN",
    "wof:name":"El Chaguiton",
    "wof:placetype":"locality"
},
  "geometry": {"coordinates":[-87.50305999999998,13.82778],"type":"Point"}
}