{
  "type": "Feature",
  "properties": {
    "gn:admin1_code":"08",
    "gn:asciiname":"Agua Fria",
    "gn:country_code":"HN",
    "gn:dem":1348,
    "gn:feature_class":"P",
    "gn:feature_code":"PPL",
    "gn:name":"Agua Fr\u00eda",
    "gn:population":0,
    "gn:timezone":"America/Tegucigalpa",
    "iso:country":"HN",
    "name:ceb_x_preferred":[
        "Agua Fria"
    ],
    "name:deu_x_preferred":[
        "Agua Fria"
    ],
    "name:swe_x_preferred":[
        "Agua Fria"
    ],
    "wof:name":"Agua Fria",
    "wof:placetype":"locality"
},
  "geometry": {"coordinates":[-87.23999999999999,13.91833],"type":"Point"}
}