{
  "type": "Feature",
  "properties": {
    "gn:admin1_code":"02",
    "gn:asciiname":"Las Trojas",
    "gn:country_code":"HN",
    "gn:dem":726,
    "gn:feature_class":"P",
    "gn:feature_code":"PPL",
    "gn:name":"Las Trojas",
    "gn:population":0,
    "gn:timezone":"America/Tegucigalpa",
    "iso:country":"HN",
    "wof:name":"Las Trojas",
    "wof:placetype":"locality"
},
  "geometry": {"coordinates":[-86.96666999999999,13.41667],"type":"Point"}
}