{
  "type": "Feature",
  "properties": {
    "iso:country":"HN",
    "qs:gn_country":"HN",
    "qs:gn_fcode":"PPL",
    "qs:gn_pop":1471,
    "qs:name":"San Sebasti\u00e1n",
    "qs:name_adm0":"Honduras",
    "qs:name_adm1":"Comayagua",
    "qs:photos":0,
    "qs:photos_1k":0,
    "qs:photos_9k":0,
    "qs:photos_9r":0,
    "qs:photos_all":0,
    "qs:photos_sr":0,
    "qs:placetype":"Town",
    "qs:pop_sr":"3",
    "qs:woe_adm0":23424841,
    "wof:name":"San Sebasti\u00e1n",
    "wof:placetype":"locality",
    "wof:population":1471
},
  "geometry": {"coordinates":[-87.63333,14.25],"type":"Point"}
}