{
  "type": "Feature",
  "properties": {
    "gn:admin1_code":"17",
    "gn:asciiname":"Portillo del Oro",
    "gn:country_code":"HN",
    "gn:dem":270,
    "gn:feature_class":"P",
    "gn:feature_code":"PPL",
    "gn:name":"Portillo del Oro",
    "gn:population":0,
    "gn:timezone":"America/Tegucigalpa",
    "iso:country":"HN",
    "wof:name":"Portillo del Oro",
    "wof:placetype":"locality"
},
  "geometry": {"coordinates":[-87.64221999999999,13.68278],"type":"Point"}
}