{
  "type": "Feature",
  "properties": {
    "gn:admin1_code":"16",
    "gn:asciiname":"Jutiapa",
    "gn:country_code":"HN",
    "gn:dem":647,
    "gn:feature_class":"P",
    "gn:feature_code":"PPL",
    "gn:name":"Jutiapa",
    "gn:population":0,
    "gn:timezone":"America/Tegucigalpa",
    "iso:country":"HN",
    "name:ara_x_preferred":[
        "\u062e\u0648\u062a\u064a\u0627\u0628\u0627"
    ],
    "name:deu_x_preferred":[
        "Jutiapa"
    ],
    "name:eus_x_preferred":[
        "Jutiapa"
    ],
    "name:fra_x_preferred":[
        "Jutiapa"
    ],
    "name:ind_x_preferred":[
        "Jutiapa"
    ],
    "name:ita_x_preferred":[
        "Jutiapa"
    ],
    "name:kor_x_preferred":[
        "\ud6c4\ud2f0\uc544\ud30c"
    ],
    "name:lit_x_preferred":[
        "Chutiapa"
    ],
    "name:nld_x_preferred":[
        "Jutiapa"
    ],
    "name:pol_x_preferred":[
        "Jutiapa"
    ],
    "name:por_x_preferred":[
        "Jutiapa"
    ],
    "name:sme_x_preferred":[
        "Jutiapa"
    ],
    "name:spa_x_preferred":[
        "Jutiapa"
    ],
    "name:zho_x_preferred":[
        "\u80e1\u8482\u4e9e\u5e15"
    ],
    "wof:name":"Jutiapa",
    "wof:placetype":"locality"
},
  "geometry": {"coordinates":[-88.01666999999998,14.83333],"type":"Point"}
}