{
  "type": "Feature",
  "properties": {
    "gn:admin1_code":"16",
    "gn:asciiname":"Jutiapa",
    "gn:country_code":"HN",
    "gn:dem":647,
    "gn:feature_class":"P",
    "gn:feature_code":"PPL",
    "gn:name":"Jutiapa",
    "gn:population":0,
    "gn:timezone":"America/Tegucigalpa",
    "iso:country":"HN",
    "wof:name":"Jutiapa",
    "wof:placetype":"locality"
},
  "geometry": {"coordinates":[-88.01666999999998,14.83333],"type":"Point"}
}