{
  "type": "Feature",
  "properties": {
    "iso:country":"HN",
    "qs:gn_country":"HN",
    "qs:gn_fcode":"PPL",
    "qs:gn_pop":0,
    "qs:name":"Los Cayitos",
    "qs:name_adm0":"Honduras",
    "qs:name_adm1":"Islas de la Bah\u00eda",
    "qs:photos":1004,
    "qs:photos_1k":203,
    "qs:photos_9k":4,
    "qs:photos_9r":7,
    "qs:photos_all":1004,
    "qs:photos_sr":11,
    "qs:placetype":"Town",
    "qs:pop_sr":"0",
    "qs:woe_adm0":23424841,
    "wof:name":"Los Cayitos",
    "wof:placetype":"locality"
},
  "geometry": {"coordinates":[-86.98333,16.05],"type":"Point"}
}