{
  "type": "Feature",
  "properties": {
    "gn:admin1_code":"07",
    "gn:asciiname":"El Matiaral",
    "gn:country_code":"HN",
    "gn:dem":266,
    "gn:feature_class":"P",
    "gn:feature_code":"PPL",
    "gn:name":"El Matiaral",
    "gn:population":0,
    "gn:timezone":"America/Tegucigalpa",
    "iso:country":"HN",
    "wof:name":"El Matiaral",
    "wof:placetype":"locality"
},
  "geometry": {"coordinates":[-87.07528000000001,13.54278],"type":"Point"}
}