{
  "type": "Feature",
  "properties": {
    "gn:admin1_code":"02",
    "gn:asciiname":"La Palanca",
    "gn:country_code":"HN",
    "gn:dem":308,
    "gn:feature_class":"P",
    "gn:feature_code":"PPL",
    "gn:name":"La Palanca",
    "gn:population":0,
    "gn:timezone":"America/Tegucigalpa",
    "iso:country":"HN",
    "wof:name":"La Palanca",
    "wof:placetype":"locality"
},
  "geometry": {"coordinates":[-87.05,13.28333],"type":"Point"}
}