{
  "type": "Feature",
  "properties": {
    "gn:admin1_code":"14",
    "gn:asciiname":"Chichicuilote",
    "gn:country_code":"HN",
    "gn:dem":1659,
    "gn:feature_class":"P",
    "gn:feature_code":"PPL",
    "gn:name":"Chichicuilote",
    "gn:population":0,
    "gn:timezone":"America/Tegucigalpa",
    "iso:country":"HN",
    "wof:name":"Chichicuilote",
    "wof:placetype":"locality"
},
  "geometry": {"coordinates":[-88.76666999999998,14.48333],"type":"Point"}
}