{
  "type": "Feature",
  "properties": {
    "gn:admin1_code":"02",
    "gn:asciiname":"El Rodeito",
    "gn:cc2":"HN",
    "gn:country_code":"HN",
    "gn:dem":1164,
    "gn:feature_class":"P",
    "gn:feature_code":"PPL",
    "gn:name":"El Rode\u00edto",
    "gn:population":0,
    "gn:timezone":"America/Tegucigalpa",
    "iso:country":"HN",
    "name:und_x_variant":[
        "El Rodellito",
        "El Rode\u00edto"
    ],
    "wof:name":"El Rodeito",
    "wof:placetype":"locality"
},
  "geometry": {"coordinates":[-86.83333,13.36667],"type":"Point"}
}