{
  "type": "Feature",
  "properties": {
    "gn:admin1_code":"05",
    "gn:asciiname":"Las Canas",
    "gn:country_code":"HN",
    "gn:dem":1154,
    "gn:feature_class":"P",
    "gn:feature_code":"PPL",
    "gn:name":"Las Ca\u00f1as",
    "gn:population":0,
    "gn:timezone":"America/Tegucigalpa",
    "iso:country":"HN",
    "wof:name":"Las Canas",
    "wof:placetype":"locality"
},
  "geometry": {"coordinates":[-88.76666999999998,14.75],"type":"Point"}
}