{
  "type": "Feature",
  "properties": {
    "gn:admin1_code":"07",
    "gn:asciiname":"El Chingo",
    "gn:country_code":"HN",
    "gn:dem":471,
    "gn:feature_class":"P",
    "gn:feature_code":"PPL",
    "gn:name":"El Chingo",
    "gn:population":0,
    "gn:timezone":"America/Tegucigalpa",
    "iso:country":"HN",
    "wof:name":"El Chingo",
    "wof:placetype":"locality"
},
  "geometry": {"coordinates":[-87.01721999999999,13.60139],"type":"Point"}
}