{
  "type": "Feature",
  "properties": {
    "iso:country":"HN",
    "name:cat_x_preferred":[
        "Tela"
    ],
    "name:chi_x_preferred":[
        "\u7279\u62c9"
    ],
    "name:dut_x_preferred":[
        "Tela"
    ],
    "name:eng_x_preferred":[
        "Tela"
    ],
    "name:fin_x_preferred":[
        "Tela"
    ],
    "name:fre_x_preferred":[
        "Tela"
    ],
    "name:ger_x_preferred":[
        "Tela"
    ],
    "name:hun_x_preferred":[
        "Tela"
    ],
    "name:ita_x_preferred":[
        "Tela"
    ],
    "name:jpn_x_preferred":[
        "\u30c6\u30e9"
    ],
    "name:lit_x_preferred":[
        "Tela"
    ],
    "name:nan_x_preferred":[
        "Tela"
    ],
    "name:pol_x_preferred":[
        "Tela"
    ],
    "name:por_x_preferred":[
        "Tela"
    ],
    "name:rus_x_preferred":[
        "\u0422\u0435\u043b\u0430"
    ],
    "name:spa_x_preferred":[
        "Tela"
    ],
    "name:swe_x_preferred":[
        "Tela"
    ],
    "name:ukr_x_preferred":[
        "\u0422\u0435\u043b\u0430"
    ],
    "qs:gn_country":"HN",
    "qs:gn_fcode":"PPL",
    "qs:gn_pop":29325,
    "qs:name":"Tela",
    "qs:name_adm0":"Honduras",
    "qs:name_adm1":"Atl\u00e1ntida",
    "qs:photos":1673,
    "qs:photos_1k":339,
    "qs:photos_9k":7,
    "qs:photos_9r":8,
    "qs:photos_all":1673,
    "qs:photos_sr":14,
    "qs:placetype":"Town",
    "qs:pop_sr":"7",
    "qs:woe_adm0":23424841,
    "wd:wordcount":1567,
    "wof:name":"Tela",
    "wof:placetype":"locality",
    "wof:population":29325
},
  "geometry": {"coordinates":[-87.45,15.78333],"type":"Point"}
}