{
  "type": "Feature",
  "properties": {
    "gn:admin1_code":"18",
    "gn:asciiname":"El Mango",
    "gn:cc2":"HN",
    "gn:country_code":"HN",
    "gn:dem":699,
    "gn:feature_class":"P",
    "gn:feature_code":"PPL",
    "gn:name":"El Mango",
    "gn:population":0,
    "gn:timezone":"America/Tegucigalpa",
    "iso:country":"HN",
    "name:und_x_variant":[
        "Mango",
        "El Mango"
    ],
    "wof:name":"El Mango",
    "wof:placetype":"locality"
},
  "geometry": {"coordinates":[-87.53333000000001,15.03333],"type":"Point"}
}