{
  "type": "Feature",
  "properties": {
    "gn:admin1_code":"02",
    "gn:asciiname":"Los Calpules",
    "gn:country_code":"HN",
    "gn:dem":65,
    "gn:feature_class":"P",
    "gn:feature_code":"PPL",
    "gn:name":"Los Calpules",
    "gn:population":0,
    "gn:timezone":"America/Tegucigalpa",
    "iso:country":"HN",
    "wof:name":"Los Calpules",
    "wof:placetype":"locality"
},
  "geometry": {"coordinates":[-86.98333000000002,13.08333],"type":"Point"}
}