{
  "type": "Feature",
  "properties": {
    "gn:admin1_code":"04",
    "gn:asciiname":"La Calera",
    "gn:cc2":"HN",
    "gn:country_code":"HN",
    "gn:dem":1209,
    "gn:feature_class":"P",
    "gn:feature_code":"PPL",
    "gn:name":"La Calera",
    "gn:population":0,
    "gn:timezone":"America/Tegucigalpa",
    "iso:country":"HN",
    "name:und_x_variant":[
        "Calderas",
        "La Calera"
    ],
    "wof:name":"La Calera",
    "wof:placetype":"locality"
},
  "geometry": {"coordinates":[-87.86667,14.56667],"type":"Point"}
}