{
  "type": "Feature",
  "properties": {
    "gn:admin1_code":"13",
    "gn:asciiname":"Hacienda Vieja",
    "gn:country_code":"HN",
    "gn:dem":1127,
    "gn:feature_class":"P",
    "gn:feature_code":"PPL",
    "gn:name":"Hacienda Vieja",
    "gn:population":0,
    "gn:timezone":"America/Tegucigalpa",
    "iso:country":"HN",
    "wof:name":"Hacienda Vieja",
    "wof:placetype":"locality"
},
  "geometry": {"coordinates":[-88.63333,14.36667],"type":"Point"}
}