{
  "type": "Feature",
  "properties": {
    "gn:admin1_code":"12",
    "gn:asciiname":"Musula",
    "gn:cc2":"HN",
    "gn:country_code":"HN",
    "gn:dem":1653,
    "gn:feature_class":"P",
    "gn:feature_code":"PPL",
    "gn:name":"Musula",
    "gn:population":0,
    "gn:timezone":"America/Tegucigalpa",
    "iso:country":"HN",
    "name:und_x_variant":[
        "Muzula",
        "Musula"
    ],
    "wof:name":"Musula",
    "wof:placetype":"locality"
},
  "geometry": {"coordinates":[-88.03333000000001,14.11667],"type":"Point"}
}