{
  "type": "Feature",
  "properties": {
    "gn:country":"HN",
    "gn:fcode":"PPL",
    "gn:population":947,
    "iso:country":"HN",
    "qs:name":"El Ermitano",
    "qs:photos_9r":0,
    "qs:photos_sr":0,
    "qs:pop_sr":"2",
    "wd:wordcount":57,
    "wof:name":"El Ermitano",
    "wof:placetype":"locality",
    "wof:population":947
},
  "geometry": {"coordinates":[-88.68333,15.25],"type":"Point"}
}