{
  "type": "Feature",
  "properties": {
    "gn:admin1_code":"03",
    "gn:asciiname":"Vuelta Grande",
    "gn:cc2":"HN",
    "gn:country_code":"HN",
    "gn:dem":3,
    "gn:feature_class":"P",
    "gn:feature_code":"PPL",
    "gn:name":"Vuelta Grande",
    "gn:population":0,
    "gn:timezone":"America/Tegucigalpa",
    "iso:country":"HN",
    "name:und_x_variant":[
        "Caser\u00edo Vuelta Grande",
        "Vuelta Grande"
    ],
    "wof:name":"Vuelta Grande",
    "wof:placetype":"locality"
},
  "geometry": {"coordinates":[-85.76666999999998,15.95],"type":"Point"}
}