{
  "type": "Feature",
  "properties": {
    "gn:admin1_code":"17",
    "gn:asciiname":"Las Placitas",
    "gn:cc2":"HN",
    "gn:country_code":"HN",
    "gn:dem":8,
    "gn:feature_class":"P",
    "gn:feature_code":"PPL",
    "gn:name":"Las Placitas",
    "gn:population":0,
    "gn:timezone":"America/Tegucigalpa",
    "iso:country":"HN",
    "name:und_x_variant":[
        "Placitas",
        "Lo Placita",
        "Las Placitas"
    ],
    "wof:name":"Las Placitas",
    "wof:placetype":"locality"
},
  "geometry": {"coordinates":[-87.56028000000001,13.40694],"type":"Point"}
}