{
  "type": "Feature",
  "properties": {
    "gn:admin1_code":"02",
    "gn:asciiname":"La Garza",
    "gn:country_code":"HN",
    "gn:dem":389,
    "gn:feature_class":"P",
    "gn:feature_code":"PPL",
    "gn:name":"La Garza",
    "gn:population":0,
    "gn:timezone":"America/Tegucigalpa",
    "iso:country":"HN",
    "wof:name":"La Garza",
    "wof:placetype":"locality"
},
  "geometry": {"coordinates":[-87.04000000000001,13.51306],"type":"Point"}
}