{
  "type": "Feature",
  "properties": {
    "gn:admin1_code":"08",
    "gn:asciiname":"Cerro Los Burros",
    "gn:country_code":"HN",
    "gn:dem":1117,
    "gn:feature_class":"P",
    "gn:feature_code":"PPL",
    "gn:name":"Cerro Los Burros",
    "gn:population":0,
    "gn:timezone":"America/Tegucigalpa",
    "iso:country":"HN",
    "wof:name":"Cerro Los Burros",
    "wof:placetype":"locality"
},
  "geometry": {"coordinates":[-87.27583,13.80556],"type":"Point"}
}