{
  "type": "Feature",
  "properties": {
    "gn:admin1_code":"06",
    "gn:asciiname":"Picachitos",
    "gn:cc2":"HN",
    "gn:country_code":"HN",
    "gn:dem":925,
    "gn:feature_class":"P",
    "gn:feature_code":"PPL",
    "gn:name":"Picachitos",
    "gn:population":0,
    "gn:timezone":"America/Tegucigalpa",
    "iso:country":"HN",
    "name:und_x_variant":[
        "Picachito",
        "Picachitos"
    ],
    "wof:name":"Picachitos",
    "wof:placetype":"locality"
},
  "geometry": {"coordinates":[-87.91667,14.85],"type":"Point"}
}