{
  "type": "Feature",
  "properties": {
    "gn:admin1_code":"18",
    "gn:asciiname":"Colonia 19 de junio",
    "gn:country_code":"HN",
    "gn:dem":64,
    "gn:feature_class":"P",
    "gn:feature_code":"PPL",
    "gn:name":"Colonia 19 de junio",
    "gn:population":0,
    "gn:timezone":"America/Tegucigalpa",
    "iso:country":"HN",
    "wof:name":"Colonia 19 de junio",
    "wof:placetype":"locality"
},
  "geometry": {"coordinates":[-87.79179000000001,15.39646],"type":"Point"}
}