{
  "type": "Feature",
  "properties": {
    "gn:admin1_code":"08",
    "gn:asciiname":"El Uviel",
    "gn:cc2":"HN",
    "gn:country_code":"HN",
    "gn:dem":949,
    "gn:feature_class":"P",
    "gn:feature_code":"PPL",
    "gn:name":"El Uviel",
    "gn:population":0,
    "gn:timezone":"America/Tegucigalpa",
    "iso:country":"HN",
    "name:und_x_variant":[
        "Ubiel",
        "El Ubiel",
        "El Uviel"
    ],
    "wof:name":"El Uviel",
    "wof:placetype":"locality"
},
  "geometry": {"coordinates":[-87.28721999999998,13.81167],"type":"Point"}
}