{
  "type": "Feature",
  "properties": {
    "gn:admin1_code":"13",
    "gn:asciiname":"El Morral",
    "gn:cc2":"HN",
    "gn:country_code":"HN",
    "gn:dem":179,
    "gn:feature_class":"P",
    "gn:feature_code":"PPL",
    "gn:name":"El Morral",
    "gn:population":0,
    "gn:timezone":"America/Tegucigalpa",
    "iso:country":"HN",
    "name:und_x_variant":[
        "El Moral",
        "El Morral"
    ],
    "wof:name":"El Morral",
    "wof:placetype":"locality"
},
  "geometry": {"coordinates":[-88.66667,14.05],"type":"Point"}
}