{
  "type": "Feature",
  "properties": {
    "gn:admin1_code":"16",
    "gn:asciiname":"Maiz Blanco",
    "gn:country_code":"HN",
    "gn:dem":1224,
    "gn:feature_class":"P",
    "gn:feature_code":"PPL",
    "gn:name":"Ma\u00edz Blanco",
    "gn:population":0,
    "gn:timezone":"America/Tegucigalpa",
    "iso:country":"HN",
    "wof:name":"Maiz Blanco",
    "wof:placetype":"locality"
},
  "geometry": {"coordinates":[-88.31667,14.75],"type":"Point"}
}