{
  "type": "Feature",
  "properties": {
    "gn:admin1_code":"07",
    "gn:asciiname":"El Naranjo",
    "gn:cc2":"HN",
    "gn:country_code":"HN",
    "gn:dem":541,
    "gn:feature_class":"P",
    "gn:feature_code":"PPL",
    "gn:name":"El Naranjo",
    "gn:population":0,
    "gn:timezone":"America/Tegucigalpa",
    "iso:country":"HN",
    "name:und_x_variant":[
        "Naranjo",
        "El Naranjo"
    ],
    "wof:name":"El Naranjo",
    "wof:placetype":"locality"
},
  "geometry": {"coordinates":[-87.08471999999998,13.71278],"type":"Point"}
}