{
  "type": "Feature",
  "properties": {
    "gn:admin1_code":"16",
    "gn:asciiname":"Playa Grande",
    "gn:country_code":"HN",
    "gn:dem":373,
    "gn:feature_class":"P",
    "gn:feature_code":"PPL",
    "gn:name":"Playa Grande",
    "gn:population":0,
    "gn:timezone":"America/Tegucigalpa",
    "iso:country":"HN",
    "name:ceb_x_preferred":[
        "Playa Grande"
    ],
    "name:fra_x_preferred":[
        "Playa Grande"
    ],
    "name:spa_x_preferred":[
        "Playa Grande"
    ],
    "name:swe_x_preferred":[
        "Playa Grande"
    ],
    "wof:name":"Playa Grande",
    "wof:placetype":"locality"
},
  "geometry": {"coordinates":[-88.28333000000001,14.95],"type":"Point"}
}