{
  "type": "Feature",
  "properties": {
    "gn:admin1_code":"13",
    "gn:asciiname":"La Jagua",
    "gn:cc2":"HN",
    "gn:country_code":"HN",
    "gn:dem":598,
    "gn:feature_class":"P",
    "gn:feature_code":"PPL",
    "gn:name":"La Jagua",
    "gn:population":0,
    "gn:timezone":"America/Tegucigalpa",
    "iso:country":"HN",
    "name:und_x_variant":[
        "Jagua",
        "La Jagua"
    ],
    "wof:name":"La Jagua",
    "wof:placetype":"locality"
},
  "geometry": {"coordinates":[-88.65000000000001,14.18333],"type":"Point"}
}