{
  "type": "Feature",
  "properties": {
    "gn:admin1_code":"02",
    "gn:asciiname":"El Lavadero",
    "gn:cc2":"HN",
    "gn:country_code":"HN",
    "gn:dem":768,
    "gn:feature_class":"P",
    "gn:feature_code":"PPL",
    "gn:name":"El Lavadero",
    "gn:population":0,
    "gn:timezone":"America/Tegucigalpa",
    "iso:country":"HN",
    "name:und_x_variant":[
        "Lavandero",
        "El Lavadero"
    ],
    "wof:name":"El Lavadero",
    "wof:placetype":"locality"
},
  "geometry": {"coordinates":[-86.98333000000002,13.35],"type":"Point"}
}