{
  "type": "Feature",
  "properties": {
    "gn:admin1_code":"10",
    "gn:asciiname":"Cofradia",
    "gn:country_code":"HN",
    "gn:dem":1316,
    "gn:feature_class":"P",
    "gn:feature_code":"PPL",
    "gn:name":"Cofrad\u00eda",
    "gn:population":0,
    "gn:timezone":"America/Tegucigalpa",
    "iso:country":"HN",
    "wof:name":"Cofradia",
    "wof:placetype":"locality"
},
  "geometry": {"coordinates":[-88.33333,14.31667],"type":"Point"}
}