{
  "type": "Feature",
  "properties": {
    "gn:admin1_code":"08",
    "gn:asciiname":"Yiguilapa",
    "gn:country_code":"HN",
    "gn:dem":324,
    "gn:feature_class":"P",
    "gn:feature_code":"PPL",
    "gn:name":"Yig\u00fcilapa",
    "gn:population":0,
    "gn:timezone":"America/Tegucigalpa",
    "iso:country":"HN",
    "wof:name":"Yiguilapa",
    "wof:placetype":"locality"
},
  "geometry": {"coordinates":[-87.39,13.7775],"type":"Point"}
}