{
  "type": "Feature",
  "properties": {
    "gn:admin1_code":"01",
    "gn:asciiname":"Campo Nuevo",
    "gn:country_code":"HN",
    "gn:dem":117,
    "gn:feature_class":"P",
    "gn:feature_code":"PPL",
    "gn:name":"Campo Nuevo",
    "gn:population":0,
    "gn:timezone":"America/Tegucigalpa",
    "iso:country":"HN",
    "wof:name":"Campo Nuevo",
    "wof:placetype":"locality"
},
  "geometry": {"coordinates":[-87.25,15.73333],"type":"Point"}
}