{
  "type": "Feature",
  "properties": {
    "gn:admin1_code":"08",
    "gn:asciiname":"Amarateca",
    "gn:cc2":"HN",
    "gn:country_code":"HN",
    "gn:dem":983,
    "gn:feature_class":"P",
    "gn:feature_code":"PPL",
    "gn:name":"Amarateca",
    "gn:population":0,
    "gn:timezone":"America/Tegucigalpa",
    "iso:country":"HN",
    "name:und_x_variant":[
        "R\u00edo Fr\u00edo",
        "Amarateca"
    ],
    "wof:name":"Amarateca",
    "wof:placetype":"locality"
},
  "geometry": {"coordinates":[-87.36667,14.23333],"type":"Point"}
}