{
  "type": "Feature",
  "properties": {
    "gn:admin1_code":"05",
    "gn:asciiname":"El Plan del Jarro",
    "gn:country_code":"HN",
    "gn:dem":1542,
    "gn:feature_class":"P",
    "gn:feature_code":"PPL",
    "gn:name":"El Plan del Jarro",
    "gn:population":0,
    "gn:timezone":"America/Tegucigalpa",
    "iso:country":"HN",
    "wof:name":"El Plan del Jarro",
    "wof:placetype":"locality"
},
  "geometry": {"coordinates":[-89.01666999999998,14.73333],"type":"Point"}
}