{
  "type": "Feature",
  "properties": {
    "gn:admin1_code":"04",
    "gn:asciiname":"Minas de San Antonio",
    "gn:cc2":"HN",
    "gn:country_code":"HN",
    "gn:dem":1156,
    "gn:feature_class":"P",
    "gn:feature_code":"PPL",
    "gn:name":"Minas de San Antonio",
    "gn:population":0,
    "gn:timezone":"America/Tegucigalpa",
    "iso:country":"HN",
    "name:und_x_variant":[
        "San Antonio",
        "Minas de San Antonio"
    ],
    "wof:name":"Minas de San Antonio",
    "wof:placetype":"locality"
},
  "geometry": {"coordinates":[-87.38333,14.81667],"type":"Point"}
}