{
  "type": "Feature",
  "properties": {
    "gn:admin1_code":"12",
    "gn:asciiname":"Gaspa Nuevo",
    "gn:country_code":"HN",
    "gn:dem":958,
    "gn:feature_class":"P",
    "gn:feature_code":"PPL",
    "gn:name":"Gaspa Nuevo",
    "gn:population":0,
    "gn:timezone":"America/Tegucigalpa",
    "iso:country":"HN",
    "wof:name":"Gaspa Nuevo",
    "wof:placetype":"locality"
},
  "geometry": {"coordinates":[-87.95,13.98333],"type":"Point"}
}