{
  "type": "Feature",
  "properties": {
    "gn:admin1_code":"04",
    "gn:asciiname":"Valle Bonito",
    "gn:country_code":"HN",
    "gn:dem":990,
    "gn:feature_class":"P",
    "gn:feature_code":"PPL",
    "gn:name":"Valle Bonito",
    "gn:population":0,
    "gn:timezone":"America/Tegucigalpa",
    "iso:country":"HN",
    "wof:name":"Valle Bonito",
    "wof:placetype":"locality"
},
  "geometry": {"coordinates":[-87.53333000000001,14.86667],"type":"Point"}
}