{
  "type": "Feature",
  "properties": {
    "gn:admin1_code":"08",
    "gn:asciiname":"Zinguizapa",
    "gn:country_code":"HN",
    "gn:dem":857,
    "gn:feature_class":"P",
    "gn:feature_code":"PPL",
    "gn:name":"Zinguizapa",
    "gn:population":0,
    "gn:timezone":"America/Tegucigalpa",
    "iso:country":"HN",
    "wof:name":"Zinguizapa",
    "wof:placetype":"locality"
},
  "geometry": {"coordinates":[-87.31667,14.46667],"type":"Point"}
}