{
  "type": "Feature",
  "properties": {
    "gn:admin1_code":"02",
    "gn:asciiname":"Los Hatillos",
    "gn:country_code":"HN",
    "gn:dem":233,
    "gn:feature_class":"P",
    "gn:feature_code":"PPL",
    "gn:name":"Los Hatillos",
    "gn:population":0,
    "gn:timezone":"America/Tegucigalpa",
    "iso:country":"HN",
    "name:ita_x_preferred":[
        "Los Hatillos"
    ],
    "name:spa_x_preferred":[
        "Los Hatillos"
    ],
    "name:zho_x_preferred":[
        "\u6d1b\u65af\u963f\u8482\u7565\u65af"
    ],
    "wof:name":"Los Hatillos",
    "wof:placetype":"locality"
},
  "geometry": {"coordinates":[-87.18139000000002,13.45083],"type":"Point"}
}