{
  "type": "Feature",
  "properties": {
    "gn:admin1_code":"08",
    "gn:asciiname":"Talanguita",
    "gn:country_code":"HN",
    "gn:dem":754,
    "gn:feature_class":"P",
    "gn:feature_code":"PPL",
    "gn:name":"Talanguita",
    "gn:population":0,
    "gn:timezone":"America/Tegucigalpa",
    "iso:country":"HN",
    "wof:name":"Talanguita",
    "wof:placetype":"locality"
},
  "geometry": {"coordinates":[-87.16667,14.48333],"type":"Point"}
}