{
  "type": "Feature",
  "properties": {
    "gn:country":"HN",
    "gn:fcode":"PPL",
    "gn:pop":1079,
    "iso:country":"HN",
    "name:unk_x_variant":[
        "Aserradero"
    ],
    "qs:name":"Agua Azul",
    "qs:photos_9r":0,
    "qs:photos_sr":0,
    "qs:pop_sr":"3",
    "wd:wordcount":247,
    "wof:name":"Agua Azul",
    "wof:placetype":"locality",
    "wof:population":1079
},
  "geometry": {"coordinates":[-87.96666999999999,14.91667],"type":"Point"}
}