{
  "type": "Feature",
  "properties": {
    "gn:admin1_code":"13",
    "gn:asciiname":"El Agua Caliente",
    "gn:cc2":"HN",
    "gn:country_code":"HN",
    "gn:dem":1170,
    "gn:feature_class":"P",
    "gn:feature_code":"PPL",
    "gn:name":"El Agua Caliente",
    "gn:population":0,
    "gn:timezone":"America/Tegucigalpa",
    "iso:country":"HN",
    "name:und_x_variant":[
        "Auga Caliente",
        "El Agua Caliente"
    ],
    "wof:name":"El Agua Caliente",
    "wof:placetype":"locality"
},
  "geometry": {"coordinates":[-88.45,14.28333],"type":"Point"}
}