{
  "type": "Feature",
  "properties": {
    "gn:admin1_code":"06",
    "gn:asciiname":"Ocotillo",
    "gn:country_code":"HN",
    "gn:dem":566,
    "gn:feature_class":"P",
    "gn:feature_code":"PPL",
    "gn:name":"Ocotillo",
    "gn:population":0,
    "gn:timezone":"America/Tegucigalpa",
    "iso:country":"HN",
    "wof:name":"Ocotillo",
    "wof:placetype":"locality"
},
  "geometry": {"coordinates":[-87.93333,14.95],"type":"Point"}
}