{
  "type": "Feature",
  "properties": {
    "gn:admin1_code":"18",
    "gn:asciiname":"Pijol",
    "gn:country_code":"HN",
    "gn:dem":233,
    "gn:feature_class":"P",
    "gn:feature_code":"PPL",
    "gn:name":"Pijol",
    "gn:population":0,
    "gn:timezone":"America/Tegucigalpa",
    "iso:country":"HN",
    "wof:name":"Pijol",
    "wof:placetype":"locality"
},
  "geometry": {"coordinates":[-87.61667,15.25],"type":"Point"}
}