{
  "type": "Feature",
  "properties": {
    "gn:admin1_code":"02",
    "gn:asciiname":"El Talnete",
    "gn:cc2":"HN",
    "gn:country_code":"HN",
    "gn:dem":449,
    "gn:feature_class":"P",
    "gn:feature_code":"PPL",
    "gn:name":"El Talnete",
    "gn:population":0,
    "gn:timezone":"America/Tegucigalpa",
    "iso:country":"HN",
    "name:und_x_variant":[
        "Los Talnetes",
        "El Talnete"
    ],
    "wof:name":"El Talnete",
    "wof:placetype":"locality"
},
  "geometry": {"coordinates":[-87.04444000000002,13.35167],"type":"Point"}
}