{
  "type": "Feature",
  "properties": {
    "gn:admin1_code":"08",
    "gn:asciiname":"Villa Santa",
    "gn:country_code":"HN",
    "gn:dem":409,
    "gn:feature_class":"P",
    "gn:feature_code":"PPL",
    "gn:name":"Villa Santa",
    "gn:population":0,
    "gn:timezone":"America/Tegucigalpa",
    "iso:country":"HN",
    "wof:name":"Villa Santa",
    "wof:placetype":"locality"
},
  "geometry": {"coordinates":[-87.38972,13.83083],"type":"Point"}
}