{
  "type": "Feature",
  "properties": {
    "gn:admin1_code":"14",
    "gn:asciiname":"El Penasco",
    "gn:cc2":"HN",
    "gn:country_code":"HN",
    "gn:dem":831,
    "gn:feature_class":"P",
    "gn:feature_code":"PPL",
    "gn:name":"El Pe\u00f1asco",
    "gn:population":0,
    "gn:timezone":"America/Tegucigalpa",
    "iso:country":"HN",
    "name:und_x_variant":[
        "Pe\u00f1asco",
        "El Pe\u00f1asco"
    ],
    "wof:name":"El Penasco",
    "wof:placetype":"locality"
},
  "geometry": {"coordinates":[-89.18333,14.48333],"type":"Point"}
}