{
  "type": "Feature",
  "properties": {
    "gn:admin1_code":"15",
    "gn:asciiname":"Uriocal",
    "gn:country_code":"HN",
    "gn:dem":1129,
    "gn:feature_class":"P",
    "gn:feature_code":"PPL",
    "gn:name":"Uriocal",
    "gn:population":0,
    "gn:timezone":"America/Tegucigalpa",
    "iso:country":"HN",
    "wof:name":"Uriocal",
    "wof:placetype":"locality"
},
  "geometry": {"coordinates":[-86.23333000000002,15.05],"type":"Point"}
}