{
  "type": "Feature",
  "properties": {
    "gn:admin1_code":"17",
    "gn:asciiname":"El Ciruelito",
    "gn:country_code":"HN",
    "gn:dem":197,
    "gn:feature_class":"P",
    "gn:feature_code":"PPL",
    "gn:name":"El Ciruelito",
    "gn:population":0,
    "gn:timezone":"America/Tegucigalpa",
    "iso:country":"HN",
    "wof:name":"El Ciruelito",
    "wof:placetype":"locality"
},
  "geometry": {"coordinates":[-87.69639000000002,13.83306],"type":"Point"}
}