{
  "type": "Feature",
  "properties": {
    "gn:admin1_code":"08",
    "gn:asciiname":"Mulular",
    "gn:cc2":"HN",
    "gn:country_code":"HN",
    "gn:dem":1196,
    "gn:feature_class":"P",
    "gn:feature_code":"PPL",
    "gn:name":"Mulular",
    "gn:population":0,
    "gn:timezone":"America/Tegucigalpa",
    "iso:country":"HN",
    "name:und_x_variant":[
        "Mumular",
        "Muladar",
        "Mulular"
    ],
    "wof:name":"Mulular",
    "wof:placetype":"locality"
},
  "geometry": {"coordinates":[-87.06667,14.25],"type":"Point"}
}