{
  "type": "Feature",
  "properties": {
    "gn:admin1_code":"10",
    "gn:asciiname":"Azacualpa",
    "gn:country_code":"HN",
    "gn:dem":870,
    "gn:feature_class":"P",
    "gn:feature_code":"PPL",
    "gn:name":"Azacualpa",
    "gn:population":0,
    "gn:timezone":"America/Tegucigalpa",
    "iso:country":"HN",
    "name:fra_x_preferred":[
        "Azacualpa"
    ],
    "name:ita_x_preferred":[
        "Azacualpa"
    ],
    "name:nld_x_preferred":[
        "Azacualpa"
    ],
    "name:por_x_preferred":[
        "Azacualpa"
    ],
    "name:spa_x_preferred":[
        "Azacualpa"
    ],
    "name:zho_x_preferred":[
        "\u963f\u85a9\u5eab\u963f\u723e\u5e15"
    ],
    "wof:name":"Azacualpa",
    "wof:placetype":"locality"
},
  "geometry": {"coordinates":[-87.98333000000002,14.35],"type":"Point"}
}