{
  "type": "Feature",
  "properties": {
    "gn:admin1_code":"14",
    "gn:asciiname":"El Joconal",
    "gn:cc2":"HN",
    "gn:country_code":"HN",
    "gn:dem":1452,
    "gn:feature_class":"P",
    "gn:feature_code":"PPL",
    "gn:name":"El Joconal",
    "gn:population":0,
    "gn:timezone":"America/Tegucigalpa",
    "iso:country":"HN",
    "name:und_x_variant":[
        "Joconal",
        "El Joconal"
    ],
    "wof:name":"El Joconal",
    "wof:placetype":"locality"
},
  "geometry": {"coordinates":[-89.06667,14.63333],"type":"Point"}
}