{
  "type": "Feature",
  "properties": {
    "gn:admin1_code":"08",
    "gn:asciiname":"El Papalon",
    "gn:country_code":"HN",
    "gn:dem":344,
    "gn:feature_class":"P",
    "gn:feature_code":"PPL",
    "gn:name":"El Papal\u00f3n",
    "gn:population":0,
    "gn:timezone":"America/Tegucigalpa",
    "iso:country":"HN",
    "wof:name":"El Papalon",
    "wof:placetype":"locality"
},
  "geometry": {"coordinates":[-87.48,13.74861],"type":"Point"}
}