{
  "type": "Feature",
  "properties": {
    "gn:admin1_code":"13",
    "gn:asciiname":"Las Quebradas",
    "gn:cc2":"HN",
    "gn:country_code":"HN",
    "gn:dem":1571,
    "gn:feature_class":"P",
    "gn:feature_code":"PPL",
    "gn:name":"Las Quebradas",
    "gn:population":0,
    "gn:timezone":"America/Tegucigalpa",
    "iso:country":"HN",
    "name:und_x_variant":[
        "Quebradas",
        "Las Quebradas"
    ],
    "wof:name":"Las Quebradas",
    "wof:placetype":"locality"
},
  "geometry": {"coordinates":[-88.38333,14.78333],"type":"Point"}
}