{
  "type": "Feature",
  "properties": {
    "gn:country":"HN",
    "gn:fcode":"PPL",
    "gn:population":1001,
    "iso:country":"HN",
    "qs:name":"La Criba",
    "qs:photos_9r":0,
    "qs:photos_sr":0,
    "qs:pop_sr":"3",
    "wof:name":"La Criba",
    "wof:placetype":"locality",
    "wof:population":1001
},
  "geometry": {"coordinates":[-87.41333,13.45361],"type":"Point"}
}