{
  "type": "Feature",
  "properties": {
    "gn:admin1_code":"15",
    "gn:asciiname":"El Ocotal",
    "gn:country_code":"HN",
    "gn:dem":790,
    "gn:feature_class":"P",
    "gn:feature_code":"PPL",
    "gn:name":"El Ocotal",
    "gn:population":0,
    "gn:timezone":"America/Tegucigalpa",
    "iso:country":"HN",
    "wof:name":"El Ocotal",
    "wof:placetype":"locality"
},
  "geometry": {"coordinates":[-86.53333000000001,14.83333],"type":"Point"}
}