{
  "type": "Feature",
  "properties": {
    "gn:admin1_code":"15",
    "gn:asciiname":"Camalotal",
    "gn:cc2":"HN",
    "gn:country_code":"HN",
    "gn:dem":730,
    "gn:feature_class":"P",
    "gn:feature_code":"PPL",
    "gn:name":"Camalotal",
    "gn:population":0,
    "gn:timezone":"America/Tegucigalpa",
    "iso:country":"HN",
    "name:und_x_variant":[
        "Camalotol",
        "Camalotal"
    ],
    "wof:name":"Camalotal",
    "wof:placetype":"locality"
},
  "geometry": {"coordinates":[-86.25,15.25],"type":"Point"}
}