{
  "type": "Feature",
  "properties": {
    "gn:admin1_code":"03",
    "gn:asciiname":"El Nanzal",
    "gn:cc2":"HN",
    "gn:country_code":"HN",
    "gn:dem":237,
    "gn:feature_class":"P",
    "gn:feature_code":"PPL",
    "gn:name":"El Nanzal",
    "gn:population":0,
    "gn:timezone":"America/Tegucigalpa",
    "iso:country":"HN",
    "name:und_x_variant":[
        "Nanzal",
        "El Nansal",
        "El Nanzal"
    ],
    "wof:name":"El Nanzal",
    "wof:placetype":"locality"
},
  "geometry": {"coordinates":[-86.16667,15.76667],"type":"Point"}
}