{
  "type": "Feature",
  "properties": {
    "gn:admin1_code":"12",
    "gn:asciiname":"Valle Nuevo",
    "gn:country_code":"HN",
    "gn:dem":1128,
    "gn:feature_class":"P",
    "gn:feature_code":"PPL",
    "gn:name":"Valle Nuevo",
    "gn:population":0,
    "gn:timezone":"America/Tegucigalpa",
    "iso:country":"HN",
    "wof:name":"Valle Nuevo",
    "wof:placetype":"locality"
},
  "geometry": {"coordinates":[-87.99694000000002,13.92667],"type":"Point"}
}