{
  "type": "Feature",
  "properties": {
    "gn:admin1_code":"12",
    "gn:asciiname":"La Cofradia",
    "gn:country_code":"HN",
    "gn:dem":359,
    "gn:feature_class":"P",
    "gn:feature_code":"PPL",
    "gn:name":"La Cofrad\u00eda",
    "gn:population":0,
    "gn:timezone":"America/Tegucigalpa",
    "iso:country":"HN",
    "wof:name":"La Cofradia",
    "wof:placetype":"locality"
},
  "geometry": {"coordinates":[-87.66417,13.86889],"type":"Point"}
}