{
  "type": "Feature",
  "properties": {
    "gn:admin1_code":"15",
    "gn:asciiname":"El Encino",
    "gn:country_code":"HN",
    "gn:dem":1150,
    "gn:feature_class":"P",
    "gn:feature_code":"PPL",
    "gn:name":"El Encino",
    "gn:population":0,
    "gn:timezone":"America/Tegucigalpa",
    "iso:country":"HN",
    "wof:name":"El Encino",
    "wof:placetype":"locality"
},
  "geometry": {"coordinates":[-86.51666999999998,15.25],"type":"Point"}
}