{
  "type": "Feature",
  "properties": {
    "gn:admin1_code":"18",
    "gn:asciiname":"Lagunita",
    "gn:country_code":"HN",
    "gn:dem":834,
    "gn:feature_class":"P",
    "gn:feature_code":"PPL",
    "gn:name":"Lagunita",
    "gn:population":0,
    "gn:timezone":"America/Tegucigalpa",
    "iso:country":"HN",
    "name:nld_x_preferred":[
        "Lagunita"
    ],
    "name:spa_x_preferred":[
        "Lagunita"
    ],
    "name:swe_x_preferred":[
        "Lagunita"
    ],
    "wof:name":"Lagunita",
    "wof:placetype":"locality"
},
  "geometry": {"coordinates":[-87.31667,15.25],"type":"Point"}
}