{
  "type": "Feature",
  "properties": {
    "gn:admin1_code":"17",
    "gn:asciiname":"El Penasco",
    "gn:country_code":"HN",
    "gn:dem":266,
    "gn:feature_class":"P",
    "gn:feature_code":"PPL",
    "gn:name":"El Penasco",
    "gn:population":0,
    "gn:timezone":"America/Tegucigalpa",
    "iso:country":"HN",
    "wof:name":"El Penasco",
    "wof:placetype":"locality"
},
  "geometry": {"coordinates":[-87.67278,13.75361],"type":"Point"}
}