{
  "type": "Feature",
  "properties": {
    "gn:admin1_code":"02",
    "gn:asciiname":"El Rincon de Los Limones",
    "gn:country_code":"HN",
    "gn:dem":163,
    "gn:feature_class":"P",
    "gn:feature_code":"PPL",
    "gn:name":"El Rinc\u00f3n de Los Limones",
    "gn:population":0,
    "gn:timezone":"America/Tegucigalpa",
    "iso:country":"HN",
    "wof:name":"El Rincon de Los Limones",
    "wof:placetype":"locality"
},
  "geometry": {"coordinates":[-87.39055999999999,13.55306],"type":"Point"}
}