{
  "type": "Feature",
  "properties": {
    "gn:admin1_code":"16",
    "gn:asciiname":"Caulotales",
    "gn:country_code":"HN",
    "gn:dem":1492,
    "gn:feature_class":"P",
    "gn:feature_code":"PPL",
    "gn:name":"Caulotales",
    "gn:population":0,
    "gn:timezone":"America/Tegucigalpa",
    "iso:country":"HN",
    "wof:name":"Caulotales",
    "wof:placetype":"locality"
},
  "geometry": {"coordinates":[-88.36667,14.81667],"type":"Point"}
}