{
  "type": "Feature",
  "properties": {
    "gn:admin1_code":"13",
    "gn:asciiname":"El Chiquirin",
    "gn:cc2":"HN",
    "gn:country_code":"HN",
    "gn:dem":1915,
    "gn:feature_class":"P",
    "gn:feature_code":"PPL",
    "gn:name":"El Chiquir\u00edn",
    "gn:population":0,
    "gn:timezone":"America/Tegucigalpa",
    "iso:country":"HN",
    "name:und_x_variant":[
        "Chiquir\u00edn",
        "Chiquir\u00edn (1)",
        "El Chiquir\u00edn"
    ],
    "wof:name":"El Chiquirin",
    "wof:placetype":"locality"
},
  "geometry": {"coordinates":[-88.66667,14.48333],"type":"Point"}
}