{
  "type": "Feature",
  "properties": {
    "gn:admin1_code":"17",
    "gn:asciiname":"El Tabacal",
    "gn:country_code":"HN",
    "gn:dem":60,
    "gn:feature_class":"P",
    "gn:feature_code":"PPL",
    "gn:name":"El Tabacal",
    "gn:population":0,
    "gn:timezone":"America/Tegucigalpa",
    "iso:country":"HN",
    "wof:name":"El Tabacal",
    "wof:placetype":"locality"
},
  "geometry": {"coordinates":[-87.43639,13.56278],"type":"Point"}
}