{
  "type": "Feature",
  "properties": {
    "gn:admin1_code":"08",
    "gn:asciiname":"Los Lagos",
    "gn:country_code":"HN",
    "gn:dem":1298,
    "gn:feature_class":"P",
    "gn:feature_code":"PPL",
    "gn:name":"Los Lagos",
    "gn:population":0,
    "gn:timezone":"America/Tegucigalpa",
    "iso:country":"HN",
    "name:bre_x_preferred":[
        "Los Lagos"
    ],
    "name:ceb_x_preferred":[
        "Los Lagos"
    ],
    "name:deu_x_preferred":[
        "Los Lagos"
    ],
    "name:hrv_x_preferred":[
        "Los Lagos"
    ],
    "name:ita_x_preferred":[
        "Los Lagos"
    ],
    "name:nld_x_preferred":[
        "Los Lagos"
    ],
    "name:rus_x_preferred":[
        "\u041b\u043e\u0441-\u041b\u0430\u0433\u043e\u0441"
    ],
    "name:sco_x_preferred":[
        "Los Lagos"
    ],
    "name:slk_x_preferred":[
        "Los Lagos"
    ],
    "name:spa_x_preferred":[
        "Los Lagos"
    ],
    "name:srp_x_preferred":[
        "\u041b\u043e\u0441 \u041b\u0430\u0433\u043e\u0441"
    ],
    "name:swe_x_preferred":[
        "Los Lagos"
    ],
    "wof:name":"Los Lagos",
    "wof:placetype":"locality"
},
  "geometry": {"coordinates":[-87.06667,14.11667],"type":"Point"}
}