{
  "type": "Feature",
  "properties": {
    "gn:admin1_code":"08",
    "gn:asciiname":"Los Lagos",
    "gn:country_code":"HN",
    "gn:dem":1298,
    "gn:feature_class":"P",
    "gn:feature_code":"PPL",
    "gn:name":"Los Lagos",
    "gn:population":0,
    "gn:timezone":"America/Tegucigalpa",
    "iso:country":"HN",
    "name:ara_x_preferred":[
        "\u0644\u0648\u0633 \u0644\u0627\u063a\u0648\u0633"
    ],
    "name:ben_x_preferred":[
        "\u09b2\u09b8 \u09b2\u09be\u0997\u09cb\u09b8"
    ],
    "name:bre_x_preferred":[
        "Los Lagos"
    ],
    "name:ceb_x_preferred":[
        "Los Lagos"
    ],
    "name:deu_x_preferred":[
        "Los Lagos"
    ],
    "name:ell_x_preferred":[
        "\u039b\u03bf\u03c2 \u039b\u03ac\u03b3\u03bf\u03c2"
    ],
    "name:heb_x_preferred":[
        "\u05dc\u05d5\u05e1 \u05dc\u05d2\u05d5\u05e1"
    ],
    "name:hin_x_preferred":[
        "\u0932\u094b\u0938 \u0932\u093e\u0917\u094b\u0938"
    ],
    "name:hrv_x_preferred":[
        "Los Lagos"
    ],
    "name:hun_x_preferred":[
        "Los Lagos"
    ],
    "name:ind_x_preferred":[
        "Los Lagos"
    ],
    "name:ita_x_preferred":[
        "Los Lagos"
    ],
    "name:jpn_x_preferred":[
        "\u30ed\u30b9\u30e9\u30b4\u30b9"
    ],
    "name:nld_x_preferred":[
        "Los Lagos"
    ],
    "name:rus_x_preferred":[
        "\u041b\u043e\u0441-\u041b\u0430\u0433\u043e\u0441"
    ],
    "name:sco_x_preferred":[
        "Los Lagos"
    ],
    "name:slk_x_preferred":[
        "Los Lagos"
    ],
    "name:spa_x_preferred":[
        "Los Lagos"
    ],
    "name:srp_x_preferred":[
        "\u041b\u043e\u0441 \u041b\u0430\u0433\u043e\u0441"
    ],
    "name:swe_x_preferred":[
        "Los Lagos"
    ],
    "name:tur_x_preferred":[
        "Los Lagos"
    ],
    "name:ukr_x_preferred":[
        "\u041b\u043e\u0441-\u041b\u0430\u0433\u043e\u0441"
    ],
    "name:urd_x_preferred":[
        "\u0644\u0627\u0633 \u0644\u0627\u06af\u0648\u0633"
    ],
    "name:vie_x_preferred":[
        "Los Lagos"
    ],
    "wof:name":"Los Lagos",
    "wof:placetype":"locality"
},
  "geometry": {"coordinates":[-87.06667,14.11667],"type":"Point"}
}