{
  "type": "Feature",
  "properties": {
    "gn:admin1_code":"16",
    "gn:asciiname":"La Laguneta",
    "gn:country_code":"HN",
    "gn:dem":428,
    "gn:feature_class":"P",
    "gn:feature_code":"PPL",
    "gn:name":"La Laguneta",
    "gn:population":0,
    "gn:timezone":"America/Tegucigalpa",
    "iso:country":"HN",
    "wof:name":"La Laguneta",
    "wof:placetype":"locality"
},
  "geometry": {"coordinates":[-88.15000000000001,14.78333],"type":"Point"}
}