{
  "type": "Feature",
  "properties": {
    "gn:admin1_code":"02",
    "gn:asciiname":"Chapeton",
    "gn:country_code":"HN",
    "gn:dem":12,
    "gn:feature_class":"P",
    "gn:feature_code":"PPL",
    "gn:name":"Chapet\u00f3n",
    "gn:population":0,
    "gn:timezone":"America/Tegucigalpa",
    "iso:country":"HN",
    "wof:name":"Chapeton",
    "wof:placetype":"locality"
},
  "geometry": {"coordinates":[-87.36389,13.22222],"type":"Point"}
}