{
  "type": "Feature",
  "properties": {
    "gn:admin1_code":"15",
    "gn:asciiname":"Los Prietos",
    "gn:country_code":"HN",
    "gn:dem":745,
    "gn:feature_class":"P",
    "gn:feature_code":"PPL",
    "gn:name":"Los Prietos",
    "gn:population":0,
    "gn:timezone":"America/Tegucigalpa",
    "iso:country":"HN",
    "wof:name":"Los Prietos",
    "wof:placetype":"locality"
},
  "geometry": {"coordinates":[-86.81667,15.11667],"type":"Point"}
}