{
  "type": "Feature",
  "properties": {
    "iso:country":"HN",
    "name:eng_x_preferred":[
        "Manto"
    ],
    "name:fra_x_preferred":[
        "Manto"
    ],
    "name:ita_x_preferred":[
        "Manto"
    ],
    "name:jpn_x_preferred":[
        "\u30de\u30f3\u30c8"
    ],
    "name:nan_x_preferred":[
        "Manto"
    ],
    "name:nld_x_preferred":[
        "Manto"
    ],
    "name:por_x_preferred":[
        "Manto"
    ],
    "name:spa_x_preferred":[
        "Manto"
    ],
    "name:swe_x_preferred":[
        "Manto"
    ],
    "name:zho_x_preferred":[
        "\u66fc\u5854"
    ],
    "qs:gn_country":"HN",
    "qs:gn_fcode":"PPL",
    "qs:gn_pop":1098,
    "qs:name":"Manto",
    "qs:name_adm0":"Honduras",
    "qs:name_adm1":"Olancho",
    "qs:photos":0,
    "qs:photos_1k":0,
    "qs:photos_9k":1,
    "qs:photos_9r":1,
    "qs:photos_all":20,
    "qs:photos_sr":0,
    "qs:placetype":"Town",
    "qs:pop_sr":"3",
    "qs:woe_adm0":23424841,
    "wd:wordcount":10,
    "wof:name":"Manto",
    "wof:placetype":"locality",
    "wof:population":1098
},
  "geometry": {"coordinates":[-86.38333,14.91667],"type":"Point"}
}