{
  "type": "Feature",
  "properties": {
    "gn:admin1_code":"18",
    "gn:asciiname":"El Urracal",
    "gn:cc2":"HN",
    "gn:country_code":"HN",
    "gn:dem":539,
    "gn:feature_class":"P",
    "gn:feature_code":"PPL",
    "gn:name":"El Urracal",
    "gn:population":0,
    "gn:timezone":"America/Tegucigalpa",
    "iso:country":"HN",
    "name:und_x_variant":[
        "Hurracal",
        "El Hurracal",
        "El Urracal"
    ],
    "wof:name":"El Urracal",
    "wof:placetype":"locality"
},
  "geometry": {"coordinates":[-86.90000000000001,15.26667],"type":"Point"}
}