{
  "type": "Feature",
  "properties": {
    "gn:admin1_code":"02",
    "gn:asciiname":"La Picota",
    "gn:country_code":"HN",
    "gn:dem":379,
    "gn:feature_class":"P",
    "gn:feature_code":"PPL",
    "gn:name":"La Picota",
    "gn:population":0,
    "gn:timezone":"America/Tegucigalpa",
    "iso:country":"HN",
    "wof:name":"La Picota",
    "wof:placetype":"locality"
},
  "geometry": {"coordinates":[-87.27194,13.43889],"type":"Point"}
}