{
  "type": "Feature",
  "properties": {
    "gn:admin1_code":"01",
    "gn:asciiname":"Cantor",
    "gn:cc2":"HN",
    "gn:country_code":"HN",
    "gn:dem":109,
    "gn:feature_class":"P",
    "gn:feature_code":"PPL",
    "gn:name":"Cantor",
    "gn:population":0,
    "gn:timezone":"America/Tegucigalpa",
    "iso:country":"HN",
    "name:spa_x_preferred":[
        "Cantor"
    ],
    "name:und_x_variant":[
        "Cantar"
    ],
    "wof:name":"Cantor",
    "wof:placetype":"locality"
},
  "geometry": {"coordinates":[-86.46666999999999,15.66667],"type":"Point"}
}