{
  "type": "Feature",
  "properties": {
    "gn:admin1_code":"07",
    "gn:asciiname":"El Zapotillo",
    "gn:cc2":"HN",
    "gn:country_code":"HN",
    "gn:dem":444,
    "gn:feature_class":"P",
    "gn:feature_code":"PPL",
    "gn:name":"El Zapotillo",
    "gn:population":0,
    "gn:timezone":"America/Tegucigalpa",
    "iso:country":"HN",
    "name:und_x_variant":[
        "Zapotillo",
        "El Zapotillo"
    ],
    "wof:name":"El Zapotillo",
    "wof:placetype":"locality"
},
  "geometry": {"coordinates":[-86.36667,14.03333],"type":"Point"}
}