{
  "type": "Feature",
  "properties": {
    "gn:admin1_code":"02",
    "gn:asciiname":"El Quebracho",
    "gn:country_code":"HN",
    "gn:dem":206,
    "gn:feature_class":"P",
    "gn:feature_code":"PPL",
    "gn:name":"El Quebracho",
    "gn:population":0,
    "gn:timezone":"America/Tegucigalpa",
    "iso:country":"HN",
    "wof:name":"El Quebracho",
    "wof:placetype":"locality"
},
  "geometry": {"coordinates":[-87.25139,13.57528],"type":"Point"}
}