{
  "type": "Feature",
  "properties": {
    "gn:admin1_code":"08",
    "gn:asciiname":"El Junquillo",
    "gn:cc2":"HN",
    "gn:country_code":"HN",
    "gn:dem":932,
    "gn:feature_class":"P",
    "gn:feature_code":"PPL",
    "gn:name":"El Junquillo",
    "gn:population":0,
    "gn:timezone":"America/Tegucigalpa",
    "iso:country":"HN",
    "name:und_x_variant":[
        "Junquillo",
        "El Junquillo"
    ],
    "wof:name":"El Junquillo",
    "wof:placetype":"locality"
},
  "geometry": {"coordinates":[-87.12666999999998,13.68611],"type":"Point"}
}