{
  "type": "Feature",
  "properties": {
    "gn:admin1_code":"05",
    "gn:asciiname":"Ticocla",
    "gn:country_code":"HN",
    "gn:dem":1208,
    "gn:feature_class":"P",
    "gn:feature_code":"PPL",
    "gn:name":"Ticocla",
    "gn:population":0,
    "gn:timezone":"America/Tegucigalpa",
    "iso:country":"HN",
    "wof:name":"Ticocla",
    "wof:placetype":"locality"
},
  "geometry": {"coordinates":[-88.96666999999999,14.76667],"type":"Point"}
}