{
  "type": "Feature",
  "properties": {
    "gn:admin1_code":"13",
    "gn:asciiname":"La Junta",
    "gn:country_code":"HN",
    "gn:dem":905,
    "gn:feature_class":"P",
    "gn:feature_code":"PPL",
    "gn:name":"La Junta",
    "gn:population":0,
    "gn:timezone":"America/Tegucigalpa",
    "iso:country":"HN",
    "wof:name":"La Junta",
    "wof:placetype":"locality"
},
  "geometry": {"coordinates":[-88.51666999999998,14.55],"type":"Point"}
}