{
  "type": "Feature",
  "properties": {
    "gn:admin1_code":"06",
    "gn:asciiname":"La Hicaca",
    "gn:cc2":"HN",
    "gn:country_code":"HN",
    "gn:dem":28,
    "gn:feature_class":"P",
    "gn:feature_code":"PPL",
    "gn:name":"La Hicaca",
    "gn:population":0,
    "gn:timezone":"America/Tegucigalpa",
    "iso:country":"HN",
    "name:und_x_variant":[
        "Hicaca",
        "La Hicaya",
        "La Hicaca"
    ],
    "wof:name":"La Hicaca",
    "wof:placetype":"locality"
},
  "geometry": {"coordinates":[-87.95,15.65],"type":"Point"}
}