{
  "type": "Feature",
  "properties": {
    "gn:admin1_code":"02",
    "gn:asciiname":"Las Pitas",
    "gn:country_code":"HN",
    "gn:dem":110,
    "gn:feature_class":"P",
    "gn:feature_code":"PPL",
    "gn:name":"Las Pitas",
    "gn:population":0,
    "gn:timezone":"America/Tegucigalpa",
    "iso:country":"HN",
    "wof:name":"Las Pitas",
    "wof:placetype":"locality"
},
  "geometry": {"coordinates":[-87.16722,13.38889],"type":"Point"}
}