{
  "type": "Feature",
  "properties": {
    "iso:country":"HN",
    "name:ceb_x_preferred":[
        "Aramecina"
    ],
    "name:eng_x_preferred":[
        "Aramecina"
    ],
    "name:fra_x_preferred":[
        "Aramecina"
    ],
    "name:ita_x_preferred":[
        "Aramecina"
    ],
    "name:jpn_x_preferred":[
        "\u30a2\u30e9\u30e1\u30b7\u30ca"
    ],
    "name:nan_x_preferred":[
        "Aramecina"
    ],
    "name:nld_x_preferred":[
        "Aramecina"
    ],
    "name:por_x_preferred":[
        "Aramecina"
    ],
    "name:spa_x_preferred":[
        "Aramecina"
    ],
    "name:swe_x_preferred":[
        "Aramecina"
    ],
    "name:zho_x_preferred":[
        "\u963f\u62c9\u6885\u897f\u7d0d"
    ],
    "qs:gn_country":"HN",
    "qs:gn_fcode":"PPL",
    "qs:gn_pop":1071,
    "qs:name":"Aramecina",
    "qs:name_adm0":"Honduras",
    "qs:name_adm1":"Valle",
    "qs:photos":0,
    "qs:photos_1k":0,
    "qs:photos_9k":1,
    "qs:photos_9r":1,
    "qs:photos_all":3,
    "qs:photos_sr":0,
    "qs:placetype":"Town",
    "qs:pop_sr":"3",
    "qs:woe_adm0":23424841,
    "wof:name":"Aramecina",
    "wof:placetype":"locality",
    "wof:population":1071
},
  "geometry": {"coordinates":[-87.71028,13.74222],"type":"Point"}
}