{
  "type": "Feature",
  "properties": {
    "gn:admin1_code":"08",
    "gn:asciiname":"Mala Lista",
    "gn:country_code":"HN",
    "gn:dem":784,
    "gn:feature_class":"P",
    "gn:feature_code":"PPL",
    "gn:name":"Mala Lista",
    "gn:population":0,
    "gn:timezone":"America/Tegucigalpa",
    "iso:country":"HN",
    "wof:name":"Mala Lista",
    "wof:placetype":"locality"
},
  "geometry": {"coordinates":[-87.16667,14.51667],"type":"Point"}
}