{
  "type": "Feature",
  "properties": {
    "gn:admin1_code":"05",
    "gn:asciiname":"Tierra Colorada",
    "gn:country_code":"HN",
    "gn:dem":1659,
    "gn:feature_class":"P",
    "gn:feature_code":"PPL",
    "gn:name":"Tierra Colorada",
    "gn:population":0,
    "gn:timezone":"America/Tegucigalpa",
    "iso:country":"HN",
    "wof:name":"Tierra Colorada",
    "wof:placetype":"locality"
},
  "geometry": {"coordinates":[-88.91667,15.06667],"type":"Point"}
}