{
  "type": "Feature",
  "properties": {
    "gn:admin1_code":"08",
    "gn:asciiname":"Cerro Colorado",
    "gn:country_code":"HN",
    "gn:dem":618,
    "gn:feature_class":"P",
    "gn:feature_code":"PPL",
    "gn:name":"Cerro Colorado",
    "gn:population":0,
    "gn:timezone":"America/Tegucigalpa",
    "iso:country":"HN",
    "wof:name":"Cerro Colorado",
    "wof:placetype":"locality"
},
  "geometry": {"coordinates":[-87.11667,13.81667],"type":"Point"}
}