{
  "type": "Feature",
  "properties": {
    "gn:admin1_code":"13",
    "gn:asciiname":"La Garza",
    "gn:country_code":"HN",
    "gn:dem":537,
    "gn:feature_class":"P",
    "gn:feature_code":"PPL",
    "gn:name":"La Garza",
    "gn:population":0,
    "gn:timezone":"America/Tegucigalpa",
    "iso:country":"HN",
    "wof:name":"La Garza",
    "wof:placetype":"locality"
},
  "geometry": {"coordinates":[-88.88333,14.18333],"type":"Point"}
}