{
  "type": "Feature",
  "properties": {
    "gn:admin1_code":"03",
    "gn:asciiname":"Parma",
    "gn:cc2":"HN",
    "gn:country_code":"HN",
    "gn:dem":119,
    "gn:feature_class":"P",
    "gn:feature_code":"PPL",
    "gn:name":"Parma",
    "gn:population":0,
    "gn:timezone":"America/Tegucigalpa",
    "iso:country":"HN",
    "name:und_x_variant":[
        "Parma Lorelay",
        "Parmas",
        "Parma"
    ],
    "wof:name":"Parma",
    "wof:placetype":"locality"
},
  "geometry": {"coordinates":[-86.18333,15.63333],"type":"Point"}
}