{
  "type": "Feature",
  "properties": {
    "gn:admin1_code":"08",
    "gn:asciiname":"Tujupi",
    "gn:country_code":"HN",
    "gn:dem":826,
    "gn:feature_class":"P",
    "gn:feature_code":"PPL",
    "gn:name":"Tujup\u00ed",
    "gn:population":0,
    "gn:timezone":"America/Tegucigalpa",
    "iso:country":"HN",
    "wof:name":"Tujupi",
    "wof:placetype":"locality"
},
  "geometry": {"coordinates":[-87.18056,13.715],"type":"Point"}
}