{
  "type": "Feature",
  "properties": {
    "gn:admin1_code":"07",
    "gn:asciiname":"Piedra de Campana",
    "gn:cc2":"HN",
    "gn:country_code":"HN",
    "gn:dem":466,
    "gn:feature_class":"P",
    "gn:feature_code":"PPL",
    "gn:name":"Piedra de Campana",
    "gn:population":0,
    "gn:timezone":"America/Tegucigalpa",
    "iso:country":"HN",
    "name:und_x_variant":[
        "Pidera Campana",
        "Piedra Campana",
        "Piedra de Campana"
    ],
    "wof:name":"Piedra de Campana",
    "wof:placetype":"locality"
},
  "geometry": {"coordinates":[-87.08055999999998,13.5575],"type":"Point"}
}