{
  "type": "Feature",
  "properties": {
    "gn:admin1_code":"07",
    "gn:asciiname":"La Lumbrera",
    "gn:country_code":"HN",
    "gn:dem":857,
    "gn:feature_class":"P",
    "gn:feature_code":"PPL",
    "gn:name":"La Lumbrera",
    "gn:population":0,
    "gn:timezone":"America/Tegucigalpa",
    "iso:country":"HN",
    "wof:name":"La Lumbrera",
    "wof:placetype":"locality"
},
  "geometry": {"coordinates":[-87.14778000000003,13.5975],"type":"Point"}
}