{
  "type": "Feature",
  "properties": {
    "gn:admin1_code":"02",
    "gn:asciiname":"El Cerro",
    "gn:country_code":"HN",
    "gn:dem":187,
    "gn:feature_class":"P",
    "gn:feature_code":"PPL",
    "gn:name":"El Cerro",
    "gn:population":0,
    "gn:timezone":"America/Tegucigalpa",
    "iso:country":"HN",
    "wof:name":"El Cerro",
    "wof:placetype":"locality"
},
  "geometry": {"coordinates":[-87.08333,13.26667],"type":"Point"}
}