{
  "type": "Feature",
  "properties": {
    "gn:admin1_code":"08",
    "gn:asciiname":"Las Tranquitas",
    "gn:country_code":"HN",
    "gn:dem":174,
    "gn:feature_class":"P",
    "gn:feature_code":"PPL",
    "gn:name":"Las Tranquitas",
    "gn:population":0,
    "gn:timezone":"America/Tegucigalpa",
    "iso:country":"HN",
    "wof:name":"Las Tranquitas",
    "wof:placetype":"locality"
},
  "geometry": {"coordinates":[-87.38,13.70889],"type":"Point"}
}