{
  "type": "Feature",
  "properties": {
    "iso:country":"HN",
    "name:und_x_variant":[
        "Butukawas"
    ],
    "qs:gn_country":"HN",
    "qs:gn_fcode":"PPL",
    "qs:gn_pop":1505,
    "qs:name":"Auas",
    "qs:name_adm0":"Honduras",
    "qs:name_adm1":"Gracias a Dios",
    "qs:photos":0,
    "qs:photos_1k":0,
    "qs:photos_9k":1,
    "qs:photos_9r":1,
    "qs:photos_all":1,
    "qs:photos_sr":0,
    "qs:placetype":"Town",
    "qs:pop_sr":"3",
    "qs:woe_adm0":23424841,
    "wof:name":"Auas",
    "wof:placetype":"locality",
    "wof:population":1505
},
  "geometry": {"coordinates":[-84.33333,15.48333],"type":"Point"}
}