{
  "type": "Feature",
  "properties": {
    "gn:admin1_code":"08",
    "gn:asciiname":"Los Tablones",
    "gn:cc2":"HN",
    "gn:country_code":"HN",
    "gn:dem":632,
    "gn:feature_class":"P",
    "gn:feature_code":"PPL",
    "gn:name":"Los Tablones",
    "gn:population":0,
    "gn:timezone":"America/Tegucigalpa",
    "iso:country":"HN",
    "name:und_x_variant":[
        "Tablones",
        "Los Tablones"
    ],
    "wof:name":"Los Tablones",
    "wof:placetype":"locality"
},
  "geometry": {"coordinates":[-87.43278000000002,13.7675],"type":"Point"}
}