{
  "type": "Feature",
  "properties": {
    "gn:admin1_code":"10",
    "gn:asciiname":"Cabeceras del Rio Negro",
    "gn:country_code":"HN",
    "gn:dem":1300,
    "gn:feature_class":"P",
    "gn:feature_code":"PPL",
    "gn:name":"Cabeceras del R\u00edo Negro",
    "gn:population":0,
    "gn:timezone":"America/Tegucigalpa",
    "iso:country":"HN",
    "wof:name":"Cabeceras del Rio Negro",
    "wof:placetype":"locality"
},
  "geometry": {"coordinates":[-88.28333000000001,14.51667],"type":"Point"}
}