{
  "type": "Feature",
  "properties": {
    "gn:admin1_code":"18",
    "gn:asciiname":"Las Flores Este",
    "gn:cc2":"HN",
    "gn:country_code":"HN",
    "gn:dem":203,
    "gn:feature_class":"P",
    "gn:feature_code":"PPL",
    "gn:name":"Las Flores Este",
    "gn:population":0,
    "gn:timezone":"America/Tegucigalpa",
    "iso:country":"HN",
    "name:und_x_variant":[
        "Las Flores",
        "Las Flores Este"
    ],
    "wof:name":"Las Flores Este",
    "wof:placetype":"locality"
},
  "geometry": {"coordinates":[-86.36667,15.53333],"type":"Point"}
}