{
  "type": "Feature",
  "properties": {
    "gn:admin1_code":"16",
    "gn:asciiname":"Las Flores",
    "gn:country_code":"HN",
    "gn:dem":848,
    "gn:feature_class":"P",
    "gn:feature_code":"PPL",
    "gn:name":"Las Flores",
    "gn:population":0,
    "gn:timezone":"America/Tegucigalpa",
    "iso:country":"HN",
    "wof:name":"Las Flores",
    "wof:placetype":"locality"
},
  "geometry": {"coordinates":[-88.60583000000003,15.39944],"type":"Point"}
}