{
  "type": "Feature",
  "properties": {
    "gn:admin1_code":"02",
    "gn:asciiname":"Fray Lazaro",
    "gn:country_code":"HN",
    "gn:dem":79,
    "gn:feature_class":"P",
    "gn:feature_code":"PPL",
    "gn:name":"Fray L\u00e1zaro",
    "gn:population":0,
    "gn:timezone":"America/Tegucigalpa",
    "iso:country":"HN",
    "wof:name":"Fray Lazaro",
    "wof:placetype":"locality"
},
  "geometry": {"coordinates":[-87.27417,13.36861],"type":"Point"}
}