{
  "type": "Feature",
  "properties": {
    "gn:admin1_code":"02",
    "gn:asciiname":"Hacienda El Limonar",
    "gn:country_code":"HN",
    "gn:dem":66,
    "gn:feature_class":"P",
    "gn:feature_code":"PPL",
    "gn:name":"Hacienda El Limonar",
    "gn:population":0,
    "gn:timezone":"America/Tegucigalpa",
    "iso:country":"HN",
    "wof:name":"Hacienda El Limonar",
    "wof:placetype":"locality"
},
  "geometry": {"coordinates":[-87.15167,13.36972],"type":"Point"}
}