{
  "type": "Feature",
  "properties": {
    "gn:admin1_code":"17",
    "gn:asciiname":"Moraicito",
    "gn:country_code":"HN",
    "gn:dem":62,
    "gn:feature_class":"P",
    "gn:feature_code":"PPL",
    "gn:name":"Moraicito",
    "gn:population":0,
    "gn:timezone":"America/Tegucigalpa",
    "iso:country":"HN",
    "wof:name":"Moraicito",
    "wof:placetype":"locality"
},
  "geometry": {"coordinates":[-87.41500000000001,13.55861],"type":"Point"}
}