{
  "type": "Feature",
  "properties": {
    "gn:admin1_code":"16",
    "gn:asciiname":"Los Hoyos",
    "gn:country_code":"HN",
    "gn:dem":1595,
    "gn:feature_class":"P",
    "gn:feature_code":"PPL",
    "gn:name":"Los Hoyos",
    "gn:population":0,
    "gn:timezone":"America/Tegucigalpa",
    "iso:country":"HN",
    "wof:name":"Los Hoyos",
    "wof:placetype":"locality"
},
  "geometry": {"coordinates":[-88.43333,14.83333],"type":"Point"}
}