{
  "type": "Feature",
  "properties": {
    "gn:admin1_code":"02",
    "gn:asciiname":"Hacienda Gracias a Dios",
    "gn:country_code":"HN",
    "gn:dem":34,
    "gn:feature_class":"P",
    "gn:feature_code":"PPL",
    "gn:name":"Hacienda Gracias a Dios",
    "gn:population":0,
    "gn:timezone":"America/Tegucigalpa",
    "iso:country":"HN",
    "wof:name":"Hacienda Gracias a Dios",
    "wof:placetype":"locality"
},
  "geometry": {"coordinates":[-87.25556,13.31889],"type":"Point"}
}