{
  "type": "Feature",
  "properties": {
    "gn:admin1_code":"12",
    "gn:asciiname":"Cansire",
    "gn:cc2":"HN",
    "gn:country_code":"HN",
    "gn:dem":998,
    "gn:feature_class":"P",
    "gn:feature_code":"PPL",
    "gn:name":"Cansire",
    "gn:population":0,
    "gn:timezone":"America/Tegucigalpa",
    "iso:country":"HN",
    "name:und_x_variant":[
        "Cancire",
        "Cansire"
    ],
    "wof:name":"Cansire",
    "wof:placetype":"locality"
},
  "geometry": {"coordinates":[-87.88333,14.33333],"type":"Point"}
}