{
  "type": "Feature",
  "properties": {
    "gn:admin1_code":"12",
    "gn:asciiname":"Santa Ana",
    "gn:cc2":"HN",
    "gn:country_code":"HN",
    "gn:dem":1640,
    "gn:feature_class":"P",
    "gn:feature_code":"PPL",
    "gn:name":"Santa Ana",
    "gn:population":0,
    "gn:timezone":"America/Tegucigalpa",
    "iso:country":"HN",
    "name:und_x_variant":[
        "Cacauterique",
        "Santa Ana de Cacauterique",
        "Santa Ana Cacaoterique",
        "Santa Ana Cacoterique",
        "Santa Ana"
    ],
    "wof:name":"Santa Ana",
    "wof:placetype":"locality"
},
  "geometry": {"coordinates":[-87.95,14.06667],"type":"Point"}
}