{
  "type": "Feature",
  "properties": {
    "gn:admin1_code":"02",
    "gn:asciiname":"Condega",
    "gn:country_code":"HN",
    "gn:dem":-9999,
    "gn:feature_class":"P",
    "gn:feature_code":"PPL",
    "gn:name":"Condega",
    "gn:population":0,
    "gn:timezone":"America/Tegucigalpa",
    "iso:country":"HN",
    "name:ceb_x_preferred":[
        "Condega"
    ],
    "name:deu_x_preferred":[
        "Condega"
    ],
    "name:ell_x_preferred":[
        "\u039a\u03bf\u03bd\u03c4\u03ad\u03b3\u03b1"
    ],
    "name:fra_x_preferred":[
        "Condega"
    ],
    "name:ita_x_preferred":[
        "Condega"
    ],
    "name:nld_x_preferred":[
        "Condega"
    ],
    "name:spa_x_preferred":[
        "Condega"
    ],
    "name:swe_x_preferred":[
        "Condega"
    ],
    "name:urd_x_preferred":[
        "\u06a9\u0648\u0646\u062f\u06cc\u06af\u0627"
    ],
    "name:vie_x_preferred":[
        "Condega"
    ],
    "name:zho_x_preferred":[
        "\u5b54\u5fb7\u52a0"
    ],
    "wof:name":"Condega",
    "wof:placetype":"locality"
},
  "geometry": {"coordinates":[-87.43028000000002,13.10333],"type":"Point"}
}