{
  "type": "Feature",
  "properties": {
    "gn:admin1_code":"02",
    "gn:asciiname":"Condega",
    "gn:country_code":"HN",
    "gn:dem":-9999,
    "gn:feature_class":"P",
    "gn:feature_code":"PPL",
    "gn:name":"Condega",
    "gn:population":0,
    "gn:timezone":"America/Tegucigalpa",
    "iso:country":"HN",
    "wof:name":"Condega",
    "wof:placetype":"locality"
},
  "geometry": {"coordinates":[-87.43028000000002,13.10333],"type":"Point"}
}