{
  "type": "Feature",
  "properties": {
    "gn:admin1_code":"10",
    "gn:asciiname":"Los Tablones",
    "gn:country_code":"HN",
    "gn:dem":322,
    "gn:feature_class":"P",
    "gn:feature_code":"PPL",
    "gn:name":"Los Tablones",
    "gn:population":0,
    "gn:timezone":"America/Tegucigalpa",
    "iso:country":"HN",
    "wof:name":"Los Tablones",
    "wof:placetype":"locality"
},
  "geometry": {"coordinates":[-88.31667,13.83333],"type":"Point"}
}