{
  "type": "Feature",
  "properties": {
    "gn:admin1_code":"08",
    "gn:asciiname":"San Patricio",
    "gn:country_code":"HN",
    "gn:dem":1024,
    "gn:feature_class":"P",
    "gn:feature_code":"PPL",
    "gn:name":"San Patricio",
    "gn:population":0,
    "gn:timezone":"America/Tegucigalpa",
    "iso:country":"HN",
    "name:ceb_x_preferred":[
        "San Patricio"
    ],
    "name:deu_x_preferred":[
        "San Patricio"
    ],
    "name:ita_x_preferred":[
        "San Patricio"
    ],
    "name:pol_x_preferred":[
        "San Patricio"
    ],
    "name:por_x_preferred":[
        "San Patricio"
    ],
    "name:spa_x_preferred":[
        "San Patricio"
    ],
    "name:srp_x_preferred":[
        "\u0421\u0430\u043d \u041f\u0430\u0442\u0440\u0438\u0448\u0438\u043e"
    ],
    "name:swe_x_preferred":[
        "San Patricio"
    ],
    "wof:name":"San Patricio",
    "wof:placetype":"locality"
},
  "geometry": {"coordinates":[-87.28333000000001,13.81667],"type":"Point"}
}