{
  "type": "Feature",
  "properties": {
    "gn:admin1_code":"08",
    "gn:asciiname":"Los Planes",
    "gn:country_code":"HN",
    "gn:dem":175,
    "gn:feature_class":"P",
    "gn:feature_code":"PPL",
    "gn:name":"Los Planes",
    "gn:population":0,
    "gn:timezone":"America/Tegucigalpa",
    "iso:country":"HN",
    "wof:name":"Los Planes",
    "wof:placetype":"locality"
},
  "geometry": {"coordinates":[-87.37833000000001,13.75417],"type":"Point"}
}