{
  "type": "Feature",
  "properties": {
    "gn:admin1_code":"08",
    "gn:asciiname":"Pacayas",
    "gn:country_code":"HN",
    "gn:dem":1311,
    "gn:feature_class":"P",
    "gn:feature_code":"PPL",
    "gn:name":"Pacayas",
    "gn:population":0,
    "gn:timezone":"America/Tegucigalpa",
    "iso:country":"HN",
    "wof:name":"Pacayas",
    "wof:placetype":"locality"
},
  "geometry": {"coordinates":[-86.93333,14.35],"type":"Point"}
}