{
  "type": "Feature",
  "properties": {
    "gn:admin1_code":"07",
    "gn:asciiname":"Junacatal",
    "gn:cc2":"HN",
    "gn:country_code":"HN",
    "gn:dem":1494,
    "gn:feature_class":"P",
    "gn:feature_code":"PPL",
    "gn:name":"Junacatal",
    "gn:population":0,
    "gn:timezone":"America/Tegucigalpa",
    "iso:country":"HN",
    "name:und_x_variant":[
        "El Junacatal",
        "Junacatal"
    ],
    "wof:name":"Junacatal",
    "wof:placetype":"locality"
},
  "geometry": {"coordinates":[-87.01416999999999,13.77972],"type":"Point"}
}