{
  "type": "Feature",
  "properties": {
    "gn:admin1_code":"02",
    "gn:asciiname":"El Jocomico",
    "gn:cc2":"HN",
    "gn:country_code":"HN",
    "gn:dem":288,
    "gn:feature_class":"P",
    "gn:feature_code":"PPL",
    "gn:name":"El Jocomico",
    "gn:population":0,
    "gn:timezone":"America/Tegucigalpa",
    "iso:country":"HN",
    "name:und_x_variant":[
        "Jocomico",
        "El Jocomico"
    ],
    "wof:name":"El Jocomico",
    "wof:placetype":"locality"
},
  "geometry": {"coordinates":[-86.88333,13.58333],"type":"Point"}
}