{
  "type": "Feature",
  "properties": {
    "gn:admin1_code":"13",
    "gn:asciiname":"Sanate",
    "gn:cc2":"HN",
    "gn:country_code":"HN",
    "gn:dem":987,
    "gn:feature_class":"P",
    "gn:feature_code":"PPL",
    "gn:name":"Sanate",
    "gn:population":0,
    "gn:timezone":"America/Tegucigalpa",
    "iso:country":"HN",
    "name:und_x_variant":[
        "Zanate",
        "Sanate"
    ],
    "wof:name":"Sanate",
    "wof:placetype":"locality"
},
  "geometry": {"coordinates":[-88.68333,14.31667],"type":"Point"}
}