{
  "type": "Feature",
  "properties": {
    "gn:admin1_code":"10",
    "gn:asciiname":"Hacienda Cosire",
    "gn:country_code":"HN",
    "gn:dem":1233,
    "gn:feature_class":"P",
    "gn:feature_code":"PPL",
    "gn:name":"Hacienda Cosire",
    "gn:population":0,
    "gn:timezone":"America/Tegucigalpa",
    "iso:country":"HN",
    "wof:name":"Hacienda Cosire",
    "wof:placetype":"locality"
},
  "geometry": {"coordinates":[-88.45,14.45],"type":"Point"}
}