{
  "type": "Feature",
  "properties": {
    "iso:country":"HN",
    "name:ceb_x_preferred":[
        "Vallecillo"
    ],
    "name:eng_x_preferred":[
        "Vallecillo"
    ],
    "name:eus_x_preferred":[
        "Vallecillo"
    ],
    "name:fra_x_preferred":[
        "Vallecillo"
    ],
    "name:ita_x_preferred":[
        "Vallecillo"
    ],
    "name:nan_x_preferred":[
        "Vallecillo"
    ],
    "name:nld_x_preferred":[
        "Vallecillo"
    ],
    "name:pol_x_preferred":[
        "Vallecillo"
    ],
    "name:spa_x_preferred":[
        "Vallecillo"
    ],
    "name:swe_x_preferred":[
        "Vallecillo"
    ],
    "name:zho_x_preferred":[
        "\u5df4\u8036\u897f\u7d04"
    ],
    "qs:gn_country":"HN",
    "qs:gn_fcode":"PPL",
    "qs:gn_pop":1986,
    "qs:name":"Vallecillo",
    "qs:name_adm0":"Honduras",
    "qs:name_adm1":"Francisco Moraz\u00e1n",
    "qs:photos":0,
    "qs:photos_1k":0,
    "qs:photos_9k":0,
    "qs:photos_9r":0,
    "qs:photos_all":0,
    "qs:photos_sr":0,
    "qs:placetype":"Town",
    "qs:pop_sr":"3",
    "qs:woe_adm0":23424841,
    "wof:name":"Vallecillo",
    "wof:placetype":"locality",
    "wof:population":1986
},
  "geometry": {"coordinates":[-87.40000000000001,14.51667],"type":"Point"}
}