{
  "type": "Feature",
  "properties": {
    "gn:admin1_code":"13",
    "gn:asciiname":"El Rancho de La Mision",
    "gn:cc2":"HN",
    "gn:country_code":"HN",
    "gn:dem":923,
    "gn:feature_class":"P",
    "gn:feature_code":"PPL",
    "gn:name":"El Rancho de La Misi\u00f3n",
    "gn:population":0,
    "gn:timezone":"America/Tegucigalpa",
    "iso:country":"HN",
    "name:und_x_variant":[
        "La Misi\u00f3",
        "El Rancho de La Misi\u00f3n"
    ],
    "wof:name":"El Rancho de La Mision",
    "wof:placetype":"locality"
},
  "geometry": {"coordinates":[-88.55,14.68333],"type":"Point"}
}