{
  "type": "Feature",
  "properties": {
    "gn:admin1_code":"17",
    "gn:asciiname":"El Tabloncito",
    "gn:cc2":"HN",
    "gn:country_code":"HN",
    "gn:dem":322,
    "gn:feature_class":"P",
    "gn:feature_code":"PPL",
    "gn:name":"El Tabloncito",
    "gn:population":0,
    "gn:timezone":"America/Tegucigalpa",
    "iso:country":"HN",
    "name:und_x_variant":[
        "El Tabl\u00f3n",
        "El Tabloncito"
    ],
    "wof:name":"El Tabloncito",
    "wof:placetype":"locality"
},
  "geometry": {"coordinates":[-87.64694,13.69139],"type":"Point"}
}