{
  "type": "Feature",
  "properties": {
    "gn:admin1_code":"13",
    "gn:asciiname":"Maria de la Cruz",
    "gn:country_code":"HN",
    "gn:dem":1130,
    "gn:feature_class":"P",
    "gn:feature_code":"PPL",
    "gn:name":"Mar\u00eda de la Cruz",
    "gn:population":0,
    "gn:timezone":"America/Tegucigalpa",
    "iso:country":"HN",
    "wof:name":"Maria de la Cruz",
    "wof:placetype":"locality"
},
  "geometry": {"coordinates":[-88.46666999999999,14.71667],"type":"Point"}
}