{
  "type": "Feature",
  "properties": {
    "gn:admin1_code":"02",
    "gn:asciiname":"El Gualiqueme",
    "gn:country_code":"HN",
    "gn:dem":414,
    "gn:feature_class":"P",
    "gn:feature_code":"PPL",
    "gn:name":"El Gualiqueme",
    "gn:population":0,
    "gn:timezone":"America/Tegucigalpa",
    "iso:country":"HN",
    "wof:name":"El Gualiqueme",
    "wof:placetype":"locality"
},
  "geometry": {"coordinates":[-87.21361,13.47111],"type":"Point"}
}