{
  "type": "Feature",
  "properties": {
    "iso:country":"HN",
    "qs:gn_country":"HN",
    "qs:gn_fcode":"PPL",
    "qs:gn_pop":1026,
    "qs:name":"San Fernando",
    "qs:name_adm0":"Honduras",
    "qs:name_adm1":"Ocotepeque",
    "qs:photos":0,
    "qs:photos_1k":0,
    "qs:photos_9k":1,
    "qs:photos_9r":1,
    "qs:photos_all":19,
    "qs:photos_sr":0,
    "qs:placetype":"Town",
    "qs:pop_sr":"3",
    "qs:woe_adm0":23424841,
    "wof:name":"San Fernando",
    "wof:placetype":"locality",
    "wof:population":1026
},
  "geometry": {"coordinates":[-89.11667,14.68333],"type":"Point"}
}