{
  "type": "Feature",
  "properties": {
    "iso:country":"HN",
    "name:bre_x_preferred":[
        "San Fernando"
    ],
    "name:bul_x_preferred":[
        "\u0421\u0430\u043d \u0424\u0435\u0440\u043d\u0430\u043d\u0434\u043e"
    ],
    "name:cat_x_preferred":[
        "San Fernando"
    ],
    "name:ceb_x_preferred":[
        "San Fernando"
    ],
    "name:ces_x_preferred":[
        "San Fernando"
    ],
    "name:deu_x_preferred":[
        "San Fernando"
    ],
    "name:epo_x_preferred":[
        "San Fernando"
    ],
    "name:eus_x_preferred":[
        "San Fernando"
    ],
    "name:fas_x_preferred":[
        "\u0633\u0627\u0646 \u0641\u0631\u0646\u0627\u0646\u062f\u0648"
    ],
    "name:fra_x_preferred":[
        "San Fernando"
    ],
    "name:glg_x_preferred":[
        "San Fernando"
    ],
    "name:heb_x_preferred":[
        "\u05e1\u05df \u05e4\u05e8\u05e0\u05e0\u05d3\u05d5"
    ],
    "name:hrv_x_preferred":[
        "San Fernando"
    ],
    "name:hun_x_preferred":[
        "San Fernando"
    ],
    "name:ilo_x_preferred":[
        "San Fernando"
    ],
    "name:ita_x_preferred":[
        "San Fernando"
    ],
    "name:jpn_x_preferred":[
        "\u30b5\u30f3\u30d5\u30a7\u30eb\u30ca\u30f3\u30c9"
    ],
    "name:kor_x_preferred":[
        "\uc0b0 \ud398\ub974\ub09c\ub3c4"
    ],
    "name:kor_x_variant":[
        "\uc0b0\ud398\ub974\ub09c\ub3c4"
    ],
    "name:lit_x_preferred":[
        "San Fernandas"
    ],
    "name:mlg_x_preferred":[
        "San Fernando"
    ],
    "name:msa_x_preferred":[
        "San Fernando"
    ],
    "name:nld_x_preferred":[
        "San Fernando"
    ],
    "name:nor_x_preferred":[
        "San Fernando"
    ],
    "name:pol_x_preferred":[
        "San Fernando"
    ],
    "name:por_x_preferred":[
        "S\u00e3o Fernando"
    ],
    "name:rus_x_preferred":[
        "\u0421\u0430\u043d-\u0424\u0435\u0440\u043d\u0430\u043d\u0434\u043e"
    ],
    "name:sco_x_preferred":[
        "San Fernando"
    ],
    "name:spa_x_preferred":[
        "San Fernando"
    ],
    "name:srp_x_preferred":[
        "\u0421\u0430\u043d \u0424\u0435\u0440\u043d\u0430\u043d\u0434\u043e"
    ],
    "name:swa_x_preferred":[
        "San Fernando"
    ],
    "name:swe_x_preferred":[
        "San Fernando"
    ],
    "name:tur_x_preferred":[
        "San Fernando"
    ],
    "name:ukr_x_preferred":[
        "\u0421\u0430\u043d-\u0424\u0435\u0440\u043d\u0430\u043d\u0434\u043e"
    ],
    "name:urd_x_preferred":[
        "\u0633\u0627\u0646 \u0641\u0631\u0646\u06cc\u0646\u062f\u0648"
    ],
    "name:vie_x_preferred":[
        "San Fernando"
    ],
    "name:war_x_preferred":[
        "San Fernando"
    ],
    "name:zho_cn_x_preferred":[
        "\u5723\u8d39\u5c14\u5357\u591a"
    ],
    "name:zho_tw_x_preferred":[
        "\u8056\u8cbb\u723e\u5357\u591a"
    ],
    "qs:gn_country":"HN",
    "qs:gn_fcode":"PPL",
    "qs:gn_pop":1026,
    "qs:name":"San Fernando",
    "qs:name_adm0":"Honduras",
    "qs:name_adm1":"Ocotepeque",
    "qs:photos":0,
    "qs:photos_1k":0,
    "qs:photos_9k":1,
    "qs:photos_9r":1,
    "qs:photos_all":19,
    "qs:photos_sr":0,
    "qs:placetype":"Town",
    "qs:pop_sr":"3",
    "qs:woe_adm0":23424841,
    "wof:name":"San Fernando",
    "wof:placetype":"locality",
    "wof:population":1026
},
  "geometry": {"coordinates":[-89.11667,14.68333],"type":"Point"}
}