{
  "type": "Feature",
  "properties": {
    "gn:admin1_code":"08",
    "gn:asciiname":"La Curena",
    "gn:country_code":"HN",
    "gn:dem":668,
    "gn:feature_class":"P",
    "gn:feature_code":"PPL",
    "gn:name":"La Cure\u00f1a",
    "gn:population":0,
    "gn:timezone":"America/Tegucigalpa",
    "iso:country":"HN",
    "wof:name":"La Curena",
    "wof:placetype":"locality"
},
  "geometry": {"coordinates":[-87.1125,13.83222],"type":"Point"}
}