{
  "type": "Feature",
  "properties": {
    "gn:admin1_code":"08",
    "gn:asciiname":"La Sabana",
    "gn:country_code":"HN",
    "gn:dem":714,
    "gn:feature_class":"P",
    "gn:feature_code":"PPL",
    "gn:name":"La Sabana",
    "gn:population":0,
    "gn:timezone":"America/Tegucigalpa",
    "iso:country":"HN",
    "name:ceb_x_preferred":[
        "La S\u00e1bana"
    ],
    "name:spa_x_preferred":[
        "La Sabana"
    ],
    "name:urd_x_preferred":[
        "\u0644\u0627 \u0633\u0627\u0628\u0627\u0646\u0627"
    ],
    "wof:name":"La Sabana",
    "wof:placetype":"locality"
},
  "geometry": {"coordinates":[-87.16333,13.80667],"type":"Point"}
}