{
  "type": "Feature",
  "properties": {
    "gn:admin1_code":"04",
    "gn:asciiname":"Guarajao Viejo",
    "gn:cc2":"HN",
    "gn:country_code":"HN",
    "gn:dem":1298,
    "gn:feature_class":"P",
    "gn:feature_code":"PPL",
    "gn:name":"Guarajao Viejo",
    "gn:population":0,
    "gn:timezone":"America/Tegucigalpa",
    "iso:country":"HN",
    "name:und_x_variant":[
        "Guarajao",
        "Guaraja Viejo",
        "Guarajao Viejo"
    ],
    "wof:name":"Guarajao Viejo",
    "wof:placetype":"locality"
},
  "geometry": {"coordinates":[-87.83333,14.68333],"type":"Point"}
}