{
  "type": "Feature",
  "properties": {
    "gn:admin1_code":"12",
    "gn:asciiname":"Estancia",
    "gn:country_code":"HN",
    "gn:dem":802,
    "gn:feature_class":"P",
    "gn:feature_code":"PPL",
    "gn:name":"Estancia",
    "gn:population":0,
    "gn:timezone":"America/Tegucigalpa",
    "iso:country":"HN",
    "name:cat_x_preferred":[
        "Estancia"
    ],
    "name:deu_x_preferred":[
        "Estancia"
    ],
    "name:fra_x_preferred":[
        "Estancia"
    ],
    "name:kor_x_preferred":[
        "\uc5d0\uc2a4\ud0c4\uc2dc\uc544"
    ],
    "name:pol_x_preferred":[
        "Estancja"
    ],
    "name:por_x_preferred":[
        "Est\u00e2ncia"
    ],
    "name:spa_x_preferred":[
        "Estancia"
    ],
    "name:swe_x_preferred":[
        "Estancia"
    ],
    "wof:name":"Estancia",
    "wof:placetype":"locality"
},
  "geometry": {"coordinates":[-87.91667,13.91667],"type":"Point"}
}