{
  "type": "Feature",
  "properties": {
    "gn:admin1_code":"08",
    "gn:asciiname":"El Sabacuante",
    "gn:country_code":"HN",
    "gn:dem":1309,
    "gn:feature_class":"P",
    "gn:feature_code":"PPL",
    "gn:name":"El Sabacuante",
    "gn:population":0,
    "gn:timezone":"America/Tegucigalpa",
    "iso:country":"HN",
    "wof:name":"El Sabacuante",
    "wof:placetype":"locality"
},
  "geometry": {"coordinates":[-87.16722,13.96667],"type":"Point"}
}