{
  "type": "Feature",
  "properties": {
    "gn:admin1_code":"13",
    "gn:asciiname":"La Escondida",
    "gn:cc2":"HN",
    "gn:country_code":"HN",
    "gn:dem":331,
    "gn:feature_class":"P",
    "gn:feature_code":"PPL",
    "gn:name":"La Escondida",
    "gn:population":0,
    "gn:timezone":"America/Tegucigalpa",
    "iso:country":"HN",
    "name:und_x_variant":[
        "San Sim\u00f3n",
        "La Escondida"
    ],
    "wof:name":"La Escondida",
    "wof:placetype":"locality"
},
  "geometry": {"coordinates":[-88.65000000000001,14.15],"type":"Point"}
}