{
  "type": "Feature",
  "properties": {
    "gn:admin1_code":"18",
    "gn:asciiname":"Vijagual",
    "gn:cc2":"HN",
    "gn:country_code":"HN",
    "gn:dem":354,
    "gn:feature_class":"P",
    "gn:feature_code":"PPL",
    "gn:name":"Vijagual",
    "gn:population":0,
    "gn:timezone":"America/Tegucigalpa",
    "iso:country":"HN",
    "name:und_x_variant":[
        "Bijaqual",
        "Vijagual"
    ],
    "wof:name":"Vijagual",
    "wof:placetype":"locality"
},
  "geometry": {"coordinates":[-87.58333,15.26667],"type":"Point"}
}