{
  "type": "Feature",
  "properties": {
    "gn:admin1_code":"17",
    "gn:asciiname":"El Jicarito",
    "gn:country_code":"HN",
    "gn:dem":295,
    "gn:feature_class":"P",
    "gn:feature_code":"PPL",
    "gn:name":"El Jicarito",
    "gn:population":0,
    "gn:timezone":"America/Tegucigalpa",
    "iso:country":"HN",
    "wof:name":"El Jicarito",
    "wof:placetype":"locality"
},
  "geometry": {"coordinates":[-87.58610999999998,13.64444],"type":"Point"}
}