{
  "type": "Feature",
  "properties": {
    "gn:admin1_code":"13",
    "gn:asciiname":"Santa Guadalupe",
    "gn:country_code":"HN",
    "gn:dem":865,
    "gn:feature_class":"P",
    "gn:feature_code":"PPL",
    "gn:name":"Santa Guadalupe",
    "gn:population":0,
    "gn:timezone":"America/Tegucigalpa",
    "iso:country":"HN",
    "wof:name":"Santa Guadalupe",
    "wof:placetype":"locality"
},
  "geometry": {"coordinates":[-88.73333000000002,14.18333],"type":"Point"}
}