{
  "type": "Feature",
  "properties": {
    "gn:admin1_code":"15",
    "gn:asciiname":"Quebrachal",
    "gn:country_code":"HN",
    "gn:dem":712,
    "gn:feature_class":"P",
    "gn:feature_code":"PPL",
    "gn:name":"Quebrachal",
    "gn:population":0,
    "gn:timezone":"America/Tegucigalpa",
    "iso:country":"HN",
    "wof:name":"Quebrachal",
    "wof:placetype":"locality"
},
  "geometry": {"coordinates":[-86.21666999999999,14.93333],"type":"Point"}
}