{
  "type": "Feature",
  "properties": {
    "gn:admin1_code":"04",
    "gn:asciiname":"Humuya",
    "gn:country_code":"HN",
    "gn:dem":643,
    "gn:feature_class":"P",
    "gn:feature_code":"PPL",
    "gn:name":"Humuya",
    "gn:population":0,
    "gn:timezone":"America/Tegucigalpa",
    "iso:country":"HN",
    "name:ceb_x_preferred":[
        "Humuya"
    ],
    "name:fra_x_preferred":[
        "Humuya"
    ],
    "name:ita_x_preferred":[
        "Humuya"
    ],
    "name:nld_x_preferred":[
        "Humuya"
    ],
    "name:pol_x_preferred":[
        "Humuya"
    ],
    "name:por_x_preferred":[
        "Humuya"
    ],
    "name:spa_x_preferred":[
        "Humuya"
    ],
    "name:swe_x_preferred":[
        "Humuya"
    ],
    "name:zho_x_preferred":[
        "\u80e1\u7a46\u4e9e"
    ],
    "wof:name":"Humuya",
    "wof:placetype":"locality"
},
  "geometry": {"coordinates":[-87.66667,14.25],"type":"Point"}
}