{
  "type": "Feature",
  "properties": {
    "gn:admin1_code":"04",
    "gn:asciiname":"Humuya",
    "gn:country_code":"HN",
    "gn:dem":643,
    "gn:feature_class":"P",
    "gn:feature_code":"PPL",
    "gn:name":"Humuya",
    "gn:population":0,
    "gn:timezone":"America/Tegucigalpa",
    "iso:country":"HN",
    "wof:name":"Humuya",
    "wof:placetype":"locality"
},
  "geometry": {"coordinates":[-87.66667,14.25],"type":"Point"}
}