{
  "type": "Feature",
  "properties": {
    "gn:admin1_code":"13",
    "gn:asciiname":"Toril Grande",
    "gn:country_code":"HN",
    "gn:dem":943,
    "gn:feature_class":"P",
    "gn:feature_code":"PPL",
    "gn:name":"Toril Grande",
    "gn:population":0,
    "gn:timezone":"America/Tegucigalpa",
    "iso:country":"HN",
    "wof:name":"Toril Grande",
    "wof:placetype":"locality"
},
  "geometry": {"coordinates":[-88.26666999999998,14.15],"type":"Point"}
}