{
  "type": "Feature",
  "properties": {
    "gn:admin1_code":"16",
    "gn:asciiname":"El Guanacaste",
    "gn:country_code":"HN",
    "gn:dem":476,
    "gn:feature_class":"P",
    "gn:feature_code":"PPL",
    "gn:name":"El Guanacaste",
    "gn:population":0,
    "gn:timezone":"America/Tegucigalpa",
    "iso:country":"HN",
    "wof:name":"El Guanacaste",
    "wof:placetype":"locality"
},
  "geometry": {"coordinates":[-88.53333000000001,15.16667],"type":"Point"}
}