{
  "type": "Feature",
  "properties": {
    "gn:admin1_code":"08",
    "gn:asciiname":"La Cruz Alta",
    "gn:cc2":"HN",
    "gn:country_code":"HN",
    "gn:dem":1066,
    "gn:feature_class":"P",
    "gn:feature_code":"PPL",
    "gn:name":"La Cruz Alta",
    "gn:population":0,
    "gn:timezone":"America/Tegucigalpa",
    "iso:country":"HN",
    "name:und_x_variant":[
        "Cruz Alta",
        "La Cruz Alta"
    ],
    "wof:name":"La Cruz Alta",
    "wof:placetype":"locality"
},
  "geometry": {"coordinates":[-87.28833,13.82833],"type":"Point"}
}