{
  "type": "Feature",
  "properties": {
    "gn:admin1_code":"16",
    "gn:asciiname":"Cerro Tamara",
    "gn:country_code":"HN",
    "gn:dem":411,
    "gn:feature_class":"P",
    "gn:feature_code":"PPL",
    "gn:name":"Cerro T\u00e1mara",
    "gn:population":0,
    "gn:timezone":"America/Tegucigalpa",
    "iso:country":"HN",
    "wof:name":"Cerro Tamara",
    "wof:placetype":"locality"
},
  "geometry": {"coordinates":[-88.23333000000002,15.08333],"type":"Point"}
}