{
  "type": "Feature",
  "properties": {
    "gn:admin1_code":"08",
    "gn:asciiname":"Los Banquitos",
    "gn:country_code":"HN",
    "gn:dem":1216,
    "gn:feature_class":"P",
    "gn:feature_code":"PPL",
    "gn:name":"Los Banquitos",
    "gn:population":0,
    "gn:timezone":"America/Tegucigalpa",
    "iso:country":"HN",
    "wof:name":"Los Banquitos",
    "wof:placetype":"locality"
},
  "geometry": {"coordinates":[-87.0125,13.90194],"type":"Point"}
}