{
  "type": "Feature",
  "properties": {
    "gn:admin1_code":"12",
    "gn:asciiname":"El Barreal",
    "gn:country_code":"HN",
    "gn:dem":558,
    "gn:feature_class":"P",
    "gn:feature_code":"PPL",
    "gn:name":"El Barreal",
    "gn:population":0,
    "gn:timezone":"America/Tegucigalpa",
    "iso:country":"HN",
    "wof:name":"El Barreal",
    "wof:placetype":"locality"
},
  "geometry": {"coordinates":[-87.73194000000002,13.9225],"type":"Point"}
}