{
  "type": "Feature",
  "properties": {
    "gn:admin1_code":"16",
    "gn:asciiname":"Posoma",
    "gn:cc2":"HN",
    "gn:country_code":"HN",
    "gn:dem":952,
    "gn:feature_class":"P",
    "gn:feature_code":"PPL",
    "gn:name":"Posoma",
    "gn:population":0,
    "gn:timezone":"America/Tegucigalpa",
    "iso:country":"HN",
    "name:und_x_variant":[
        "Pozoma",
        "Posoma"
    ],
    "wof:name":"Posoma",
    "wof:placetype":"locality"
},
  "geometry": {"coordinates":[-88.40000000000001,15.06667],"type":"Point"}
}