{
  "type": "Feature",
  "properties": {
    "gn:admin1_code":"14",
    "gn:asciiname":"Magueyal",
    "gn:cc2":"HN",
    "gn:country_code":"HN",
    "gn:dem":1875,
    "gn:feature_class":"P",
    "gn:feature_code":"PPL",
    "gn:name":"Magueyal",
    "gn:population":0,
    "gn:timezone":"America/Tegucigalpa",
    "iso:country":"HN",
    "name:und_x_variant":[
        "El Maguiyal",
        "El Magueyal",
        "El Mangueyal",
        "Magueyal"
    ],
    "wof:name":"Magueyal",
    "wof:placetype":"locality"
},
  "geometry": {"coordinates":[-88.81667,14.45],"type":"Point"}
}