{
  "type": "Feature",
  "properties": {
    "gn:admin1_code":"14",
    "gn:asciiname":"Los Amates",
    "gn:country_code":"HN",
    "gn:dem":1728,
    "gn:feature_class":"P",
    "gn:feature_code":"PPL",
    "gn:name":"Los Amates",
    "gn:population":0,
    "gn:timezone":"America/Tegucigalpa",
    "iso:country":"HN",
    "name:ceb_x_preferred":[
        "Los Amates"
    ],
    "name:deu_x_preferred":[
        "Los Amates"
    ],
    "name:fra_x_preferred":[
        "Los Amates"
    ],
    "name:ita_x_preferred":[
        "Los Amates"
    ],
    "name:pol_x_preferred":[
        "Los Amates"
    ],
    "name:por_x_preferred":[
        "Los Amates"
    ],
    "name:sco_x_preferred":[
        "Los Amates"
    ],
    "name:spa_x_preferred":[
        "Los Amates"
    ],
    "name:zho_x_preferred":[
        "\u6d1b\u65af\u963f\u99ac\u7279\u65af"
    ],
    "wof:name":"Los Amates",
    "wof:placetype":"locality"
},
  "geometry": {"coordinates":[-89.03333000000001,14.61667],"type":"Point"}
}