{
  "type": "Feature",
  "properties": {
    "iso:country":"HN",
    "name:chi_x_preferred":[
        "\u74dc\u91cc\u85a9\u99ac"
    ],
    "name:dut_x_preferred":[
        "Guarizama"
    ],
    "name:eng_x_preferred":[
        "Guarizama"
    ],
    "name:fre_x_preferred":[
        "Guarizama"
    ],
    "name:ita_x_preferred":[
        "Guarizama"
    ],
    "name:jpn_x_preferred":[
        "\u30b0\u30a2\u30ea\u30b5\u30fc\u30de"
    ],
    "name:nan_x_preferred":[
        "Guarizama"
    ],
    "name:nld_x_preferred":[
        "Guarizama"
    ],
    "name:por_x_preferred":[
        "Guarizama"
    ],
    "name:spa_x_preferred":[
        "Guarizama"
    ],
    "name:swe_x_preferred":[
        "Guarizama"
    ],
    "name:zho_x_preferred":[
        "\u74dc\u91cc\u85a9\u99ac"
    ],
    "qs:gn_country":"HN",
    "qs:gn_fcode":"PPL",
    "qs:gn_pop":1300,
    "qs:name":"Guarizama",
    "qs:name_adm0":"Honduras",
    "qs:name_adm1":"Olancho",
    "qs:photos":0,
    "qs:photos_1k":0,
    "qs:photos_9k":0,
    "qs:photos_9r":0,
    "qs:photos_all":0,
    "qs:photos_sr":0,
    "qs:placetype":"Town",
    "qs:pop_sr":"3",
    "qs:woe_adm0":23424841,
    "wof:name":"Guarizama",
    "wof:placetype":"locality",
    "wof:population":1300
},
  "geometry": {"coordinates":[-86.33333,14.91667],"type":"Point"}
}