{
  "type": "Feature",
  "properties": {
    "gn:admin1_code":"04",
    "gn:asciiname":"El Palmital",
    "gn:cc2":"HN",
    "gn:country_code":"HN",
    "gn:dem":920,
    "gn:feature_class":"P",
    "gn:feature_code":"PPL",
    "gn:name":"El Palmital",
    "gn:population":0,
    "gn:timezone":"America/Tegucigalpa",
    "iso:country":"HN",
    "name:und_x_variant":[
        "Palmital",
        "El Palmital"
    ],
    "wof:name":"El Palmital",
    "wof:placetype":"locality"
},
  "geometry": {"coordinates":[-87.81667,14.85],"type":"Point"}
}