{
  "type": "Feature",
  "properties": {
    "gn:admin1_code":"18",
    "gn:asciiname":"Agua Buena",
    "gn:cc2":"HN",
    "gn:country_code":"HN",
    "gn:dem":160,
    "gn:feature_class":"P",
    "gn:feature_code":"PPL",
    "gn:name":"Agua Buena",
    "gn:population":0,
    "gn:timezone":"America/Tegucigalpa",
    "iso:country":"HN",
    "name:und_x_variant":[
        "Agua Blanca",
        "Agua Buena"
    ],
    "wof:name":"Agua Buena",
    "wof:placetype":"locality"
},
  "geometry": {"coordinates":[-86.68333,15.45],"type":"Point"}
}