{
  "type": "Feature",
  "properties": {
    "gn:admin1_code":"17",
    "gn:asciiname":"Palin",
    "gn:country_code":"HN",
    "gn:dem":12,
    "gn:feature_class":"P",
    "gn:feature_code":"PPL",
    "gn:name":"Palin",
    "gn:population":0,
    "gn:timezone":"America/Tegucigalpa",
    "iso:country":"HN",
    "name:ces_x_preferred":[
        "Palin"
    ],
    "wof:name":"Palin",
    "wof:placetype":"locality"
},
  "geometry": {"coordinates":[-87.58917,13.33333],"type":"Point"}
}