{
  "type": "Feature",
  "properties": {
    "gn:admin1_code":"06",
    "gn:asciiname":"El Oval",
    "gn:cc2":"HN",
    "gn:country_code":"HN",
    "gn:dem":54,
    "gn:feature_class":"P",
    "gn:feature_code":"PPL",
    "gn:name":"El Oval",
    "gn:population":0,
    "gn:timezone":"America/Tegucigalpa",
    "iso:country":"HN",
    "name:und_x_variant":[
        "Obal",
        "El Oval"
    ],
    "wof:name":"El Oval",
    "wof:placetype":"locality"
},
  "geometry": {"coordinates":[-87.91667,15.15],"type":"Point"}
}