{
  "type": "Feature",
  "properties": {
    "gn:admin1_code":"09",
    "gn:asciiname":"Wiwili",
    "gn:country_code":"HN",
    "gn:dem":148,
    "gn:feature_class":"P",
    "gn:feature_code":"PPL",
    "gn:name":"Wiwili",
    "gn:population":0,
    "gn:timezone":"America/Tegucigalpa",
    "iso:country":"HN",
    "wof:name":"Wiwili",
    "wof:placetype":"locality"
},
  "geometry": {"coordinates":[-84.98333000000002,14.75],"type":"Point"}
}