{
  "type": "Feature",
  "properties": {
    "gn:admin1_code":"16",
    "gn:asciiname":"La Esperanza",
    "gn:country_code":"HN",
    "gn:dem":902,
    "gn:feature_class":"P",
    "gn:feature_code":"PPL",
    "gn:name":"La Esperanza",
    "gn:population":0,
    "gn:timezone":"America/Tegucigalpa",
    "iso:country":"HN",
    "name:cat_x_preferred":[
        "La Esperanza"
    ],
    "name:ceb_x_preferred":[
        "La Esperanza"
    ],
    "name:deu_x_preferred":[
        "La Esperanza"
    ],
    "name:fra_x_preferred":[
        "La Esperanza"
    ],
    "name:ita_x_preferred":[
        "La Esperanza"
    ],
    "name:kor_x_preferred":[
        "\ub77c\uc5d0\uc2a4\ud398\ub780\uc0ac"
    ],
    "name:nld_x_preferred":[
        "La Esperanza"
    ],
    "name:por_x_preferred":[
        "La Esperanza"
    ],
    "name:spa_x_preferred":[
        "La Esperanza"
    ],
    "name:srp_x_preferred":[
        "\u041b\u0430 \u0415\u0441\u043f\u0435\u0440\u0430\u043d\u0437\u0430"
    ],
    "name:swe_x_preferred":[
        "La Esperanza"
    ],
    "name:vie_x_preferred":[
        "La Esperanza"
    ],
    "wof:name":"La Esperanza",
    "wof:placetype":"locality"
},
  "geometry": {"coordinates":[-88.62111,15.38694],"type":"Point"}
}