{
  "type": "Feature",
  "properties": {
    "gn:admin1_code":"08",
    "gn:asciiname":"Chaguites",
    "gn:country_code":"HN",
    "gn:dem":810,
    "gn:feature_class":"P",
    "gn:feature_code":"PPL",
    "gn:name":"Chag\u00fcites",
    "gn:population":0,
    "gn:timezone":"America/Tegucigalpa",
    "iso:country":"HN",
    "wof:name":"Chaguites",
    "wof:placetype":"locality"
},
  "geometry": {"coordinates":[-87.13333,13.65],"type":"Point"}
}