{
  "type": "Feature",
  "properties": {
    "gn:admin1_code":"02",
    "gn:asciiname":"Guinto",
    "gn:country_code":"HN",
    "gn:dem":244,
    "gn:feature_class":"P",
    "gn:feature_code":"PPL",
    "gn:name":"G\u00fcinto",
    "gn:population":0,
    "gn:timezone":"America/Tegucigalpa",
    "iso:country":"HN",
    "wof:name":"Guinto",
    "wof:placetype":"locality"
},
  "geometry": {"coordinates":[-87.19194,13.42694],"type":"Point"}
}