{
  "type": "Feature",
  "properties": {
    "gn:admin1_code":"18",
    "gn:asciiname":"Mejia",
    "gn:country_code":"HN",
    "gn:dem":992,
    "gn:feature_class":"P",
    "gn:feature_code":"PPL",
    "gn:name":"Mej\u00eda",
    "gn:population":0,
    "gn:timezone":"America/Tegucigalpa",
    "iso:country":"HN",
    "name:cat_x_preferred":[
        "Mej\u00eda"
    ],
    "name:ces_x_preferred":[
        "Mej\u00eda"
    ],
    "name:deu_x_preferred":[
        "Mej\u00eda"
    ],
    "name:fra_x_preferred":[
        "Mej\u00eda"
    ],
    "name:ita_x_preferred":[
        "Mej\u00eda"
    ],
    "name:jpn_x_preferred":[
        "\u30e1\u30d2\u30a2"
    ],
    "name:nds_x_preferred":[
        "Mej\u00eda"
    ],
    "name:rus_x_preferred":[
        "\u041c\u0435\u0445\u0438\u044f"
    ],
    "name:spa_x_preferred":[
        "Mej\u00eda"
    ],
    "wof:name":"Mejia",
    "wof:placetype":"locality"
},
  "geometry": {"coordinates":[-86.88333,15.21667],"type":"Point"}
}