{
  "type": "Feature",
  "properties": {
    "gn:admin1_code":"16",
    "gn:asciiname":"Jocomico",
    "gn:country_code":"HN",
    "gn:dem":233,
    "gn:feature_class":"P",
    "gn:feature_code":"PPL",
    "gn:name":"Jocomico",
    "gn:population":0,
    "gn:timezone":"America/Tegucigalpa",
    "iso:country":"HN",
    "wof:name":"Jocomico",
    "wof:placetype":"locality"
},
  "geometry": {"coordinates":[-88.23333000000002,15.31667],"type":"Point"}
}