{
  "type": "Feature",
  "properties": {
    "gn:admin1_code":"04",
    "gn:asciiname":"La Concepcion",
    "gn:country_code":"HN",
    "gn:dem":929,
    "gn:feature_class":"P",
    "gn:feature_code":"PPL",
    "gn:name":"La Concepci\u00f3n",
    "gn:population":0,
    "gn:timezone":"America/Tegucigalpa",
    "iso:country":"HN",
    "wof:name":"La Concepcion",
    "wof:placetype":"locality"
},
  "geometry": {"coordinates":[-87.78333000000001,14.71667],"type":"Point"}
}