{
  "type": "Feature",
  "properties": {
    "gn:admin1_code":"13",
    "gn:asciiname":"Suyapita",
    "gn:cc2":"HN",
    "gn:country_code":"HN",
    "gn:dem":422,
    "gn:feature_class":"P",
    "gn:feature_code":"PPL",
    "gn:name":"Suyapita",
    "gn:population":0,
    "gn:timezone":"America/Tegucigalpa",
    "iso:country":"HN",
    "name:und_x_variant":[
        "Snyapita",
        "Suyapita"
    ],
    "wof:name":"Suyapita",
    "wof:placetype":"locality"
},
  "geometry": {"coordinates":[-88.51666999999998,14.03333],"type":"Point"}
}