{
  "type": "Feature",
  "properties": {
    "gn:admin1_code":"07",
    "gn:asciiname":"La Tejera",
    "gn:country_code":"HN",
    "gn:dem":331,
    "gn:feature_class":"P",
    "gn:feature_code":"PPL",
    "gn:name":"La Tejera",
    "gn:population":0,
    "gn:timezone":"America/Tegucigalpa",
    "iso:country":"HN",
    "wof:name":"La Tejera",
    "wof:placetype":"locality"
},
  "geometry": {"coordinates":[-87.03444,13.66028],"type":"Point"}
}