{
  "type": "Feature",
  "properties": {
    "iso:country":"HN",
    "name:unk_x_variant":[
        "Sand Bay"
    ],
    "qs:gn_country":"HN",
    "qs:gn_fcode":"PPL",
    "qs:gn_pop":1072,
    "qs:name":"Sandy Bay",
    "qs:name_adm0":"Honduras",
    "qs:name_adm1":"Islas de la Bah\u00eda",
    "qs:photos":0,
    "qs:photos_1k":0,
    "qs:photos_9k":1,
    "qs:photos_9r":1,
    "qs:photos_all":7,
    "qs:photos_sr":0,
    "qs:placetype":"Town",
    "qs:pop_sr":"3",
    "qs:woe_adm0":23424841,
    "wd:wordcount":57,
    "wof:name":"Sandy Bay",
    "wof:placetype":"locality",
    "wof:population":1072
},
  "geometry": {"coordinates":[-86.56446,16.32923],"type":"Point"}
}