{
  "type": "Feature",
  "properties": {
    "gn:admin1_code":"08",
    "gn:asciiname":"El Tambor",
    "gn:country_code":"HN",
    "gn:dem":502,
    "gn:feature_class":"P",
    "gn:feature_code":"PPL",
    "gn:name":"El Tambor",
    "gn:population":0,
    "gn:timezone":"America/Tegucigalpa",
    "iso:country":"HN",
    "wof:name":"El Tambor",
    "wof:placetype":"locality"
},
  "geometry": {"coordinates":[-87.24250000000001,13.73694],"type":"Point"}
}