{
  "type": "Feature",
  "properties": {
    "gn:admin1_code":"12",
    "gn:asciiname":"El Moray",
    "gn:country_code":"HN",
    "gn:dem":806,
    "gn:feature_class":"P",
    "gn:feature_code":"PPL",
    "gn:name":"El Moray",
    "gn:population":0,
    "gn:timezone":"America/Tegucigalpa",
    "iso:country":"HN",
    "wof:name":"El Moray",
    "wof:placetype":"locality"
},
  "geometry": {"coordinates":[-87.645,13.85472],"type":"Point"}
}