{
  "type": "Feature",
  "properties": {
    "gn:admin1_code":"15",
    "gn:asciiname":"Chorrera",
    "gn:country_code":"HN",
    "gn:dem":540,
    "gn:feature_class":"P",
    "gn:feature_code":"PPL",
    "gn:name":"Chorrera",
    "gn:population":0,
    "gn:timezone":"America/Tegucigalpa",
    "iso:country":"HN",
    "wof:name":"Chorrera",
    "wof:placetype":"locality"
},
  "geometry": {"coordinates":[-86.26666999999998,14.88333],"type":"Point"}
}