{
  "type": "Feature",
  "properties": {
    "gn:admin1_code":"13",
    "gn:asciiname":"Coyolito",
    "gn:country_code":"HN",
    "gn:dem":1035,
    "gn:feature_class":"P",
    "gn:feature_code":"PPL",
    "gn:name":"Coyolito",
    "gn:population":0,
    "gn:timezone":"America/Tegucigalpa",
    "iso:country":"HN",
    "wof:name":"Coyolito",
    "wof:placetype":"locality"
},
  "geometry": {"coordinates":[-88.63333,14.21667],"type":"Point"}
}