{
  "type": "Feature",
  "properties": {
    "gn:admin1_code":"14",
    "gn:asciiname":"El Roblar",
    "gn:country_code":"HN",
    "gn:dem":1261,
    "gn:feature_class":"P",
    "gn:feature_code":"PPL",
    "gn:name":"El Roblar",
    "gn:population":0,
    "gn:timezone":"America/Tegucigalpa",
    "iso:country":"HN",
    "wof:name":"El Roblar",
    "wof:placetype":"locality"
},
  "geometry": {"coordinates":[-89.09999999999999,14.65],"type":"Point"}
}