{
  "type": "Feature",
  "properties": {
    "gn:admin1_code":"13",
    "gn:asciiname":"Arganas",
    "gn:cc2":"HN",
    "gn:country_code":"HN",
    "gn:dem":1182,
    "gn:feature_class":"P",
    "gn:feature_code":"PPL",
    "gn:name":"\u00c1rganas",
    "gn:population":0,
    "gn:timezone":"America/Tegucigalpa",
    "iso:country":"HN",
    "name:und_x_variant":[
        "Harganas",
        "\u00c1rganas"
    ],
    "wof:name":"Arganas",
    "wof:placetype":"locality"
},
  "geometry": {"coordinates":[-88.61667,14.53333],"type":"Point"}
}