{
  "type": "Feature",
  "properties": {
    "gn:admin1_code":"08",
    "gn:asciiname":"Montana Grande",
    "gn:country_code":"HN",
    "gn:dem":1522,
    "gn:feature_class":"P",
    "gn:feature_code":"PPL",
    "gn:name":"Monta\u00f1a Grande",
    "gn:population":0,
    "gn:timezone":"America/Tegucigalpa",
    "iso:country":"HN",
    "wof:name":"Montana Grande",
    "wof:placetype":"locality"
},
  "geometry": {"coordinates":[-87.09909,14.10274],"type":"Point"}
}