{
  "type": "Feature",
  "properties": {
    "gn:admin1_code":"07",
    "gn:asciiname":"Apala",
    "gn:country_code":"HN",
    "gn:dem":528,
    "gn:feature_class":"P",
    "gn:feature_code":"PPL",
    "gn:name":"Apala",
    "gn:population":0,
    "gn:timezone":"America/Tegucigalpa",
    "iso:country":"HN",
    "name:cat_x_preferred":[
        "Apala"
    ],
    "name:deu_x_preferred":[
        "Apala"
    ],
    "name:por_x_preferred":[
        "Apala"
    ],
    "name:rus_x_preferred":[
        "\u0410\u043f\u0430\u043b\u0430"
    ],
    "name:spa_x_preferred":[
        "Apala"
    ],
    "wof:name":"Apala",
    "wof:placetype":"locality"
},
  "geometry": {"coordinates":[-86.34999999999999,14.01667],"type":"Point"}
}