{
  "type": "Feature",
  "properties": {
    "gn:admin1_code":"04",
    "gn:asciiname":"El Paraiso",
    "gn:country_code":"HN",
    "gn:dem":1203,
    "gn:feature_class":"P",
    "gn:feature_code":"PPL",
    "gn:name":"El Para\u00edso",
    "gn:population":0,
    "gn:timezone":"America/Tegucigalpa",
    "iso:country":"HN",
    "wof:name":"El Paraiso",
    "wof:placetype":"locality"
},
  "geometry": {"coordinates":[-87.61667,14.15],"type":"Point"}
}