{
  "type": "Feature",
  "properties": {
    "gn:admin1_code":"13",
    "gn:asciiname":"Barrio San Matias",
    "gn:country_code":"HN",
    "gn:dem":1450,
    "gn:feature_class":"P",
    "gn:feature_code":"PPL",
    "gn:name":"Barrio San Mat\u00edas",
    "gn:population":0,
    "gn:timezone":"America/Tegucigalpa",
    "iso:country":"HN",
    "wof:name":"Barrio San Matias",
    "wof:placetype":"locality"
},
  "geometry": {"coordinates":[-88.56667,14.45],"type":"Point"}
}