{
  "type": "Feature",
  "properties": {
    "gn:admin1_code":"03",
    "gn:asciiname":"Isleta",
    "gn:cc2":"HN",
    "gn:country_code":"HN",
    "gn:dem":56,
    "gn:feature_class":"P",
    "gn:feature_code":"PPL",
    "gn:name":"Isleta",
    "gn:population":0,
    "gn:timezone":"America/Tegucigalpa",
    "iso:country":"HN",
    "name:und_x_variant":[
        "La Isleta",
        "Isleta Central",
        "Isleta"
    ],
    "wof:name":"Isleta",
    "wof:placetype":"locality"
},
  "geometry": {"coordinates":[-86.16667,15.56667],"type":"Point"}
}