{
  "type": "Feature",
  "properties": {
    "gn:admin1_code":"08",
    "gn:asciiname":"Sabana del Conejo",
    "gn:country_code":"HN",
    "gn:dem":1582,
    "gn:feature_class":"P",
    "gn:feature_code":"PPL",
    "gn:name":"Sabana del Conejo",
    "gn:population":0,
    "gn:timezone":"America/Tegucigalpa",
    "iso:country":"HN",
    "wof:name":"Sabana del Conejo",
    "wof:placetype":"locality"
},
  "geometry": {"coordinates":[-87.41667,14.03333],"type":"Point"}
}