{
  "type": "Feature",
  "properties": {
    "gn:admin1_code":"04",
    "gn:asciiname":"La Pita",
    "gn:country_code":"HN",
    "gn:dem":453,
    "gn:feature_class":"P",
    "gn:feature_code":"PPL",
    "gn:name":"La Pita",
    "gn:population":0,
    "gn:timezone":"America/Tegucigalpa",
    "iso:country":"HN",
    "wof:name":"La Pita",
    "wof:placetype":"locality"
},
  "geometry": {"coordinates":[-87.59999999999999,14.73333],"type":"Point"}
}