{
  "type": "Feature",
  "properties": {
    "gn:admin1_code":"02",
    "gn:asciiname":"Las Tres Ceibas",
    "gn:country_code":"HN",
    "gn:dem":24,
    "gn:feature_class":"P",
    "gn:feature_code":"PPL",
    "gn:name":"Las Tres Ceibas",
    "gn:population":0,
    "gn:timezone":"America/Tegucigalpa",
    "iso:country":"HN",
    "wof:name":"Las Tres Ceibas",
    "wof:placetype":"locality"
},
  "geometry": {"coordinates":[-87.31278,13.32306],"type":"Point"}
}