{
  "type": "Feature",
  "properties": {
    "gn:admin1_code":"08",
    "gn:asciiname":"Los Cedritos",
    "gn:cc2":"HN",
    "gn:country_code":"HN",
    "gn:dem":644,
    "gn:feature_class":"P",
    "gn:feature_code":"PPL",
    "gn:name":"Los Cedritos",
    "gn:population":0,
    "gn:timezone":"America/Tegucigalpa",
    "iso:country":"HN",
    "name:und_x_variant":[
        "Cedritos",
        "Los Cedritos"
    ],
    "wof:name":"Los Cedritos",
    "wof:placetype":"locality"
},
  "geometry": {"coordinates":[-87.15000000000001,13.78333],"type":"Point"}
}