{
  "type": "Feature",
  "properties": {
    "gn:admin1_code":"02",
    "gn:asciiname":"El Jicarito",
    "gn:cc2":"HN",
    "gn:country_code":"HN",
    "gn:dem":987,
    "gn:feature_class":"P",
    "gn:feature_code":"PPL",
    "gn:name":"El Jicarito",
    "gn:population":0,
    "gn:timezone":"America/Tegucigalpa",
    "iso:country":"HN",
    "name:und_x_variant":[
        "Jicarito",
        "El Jicarito"
    ],
    "wof:name":"El Jicarito",
    "wof:placetype":"locality"
},
  "geometry": {"coordinates":[-86.86667,13.38333],"type":"Point"}
}