{
  "type": "Feature",
  "properties": {
    "gn:admin1_code":"02",
    "gn:asciiname":"Tablones Arriba",
    "gn:country_code":"HN",
    "gn:dem":236,
    "gn:feature_class":"P",
    "gn:feature_code":"PPL",
    "gn:name":"Tablones Arriba",
    "gn:population":0,
    "gn:timezone":"America/Tegucigalpa",
    "iso:country":"HN",
    "wof:name":"Tablones Arriba",
    "wof:placetype":"locality"
},
  "geometry": {"coordinates":[-87.08194,13.25972],"type":"Point"}
}