{
  "type": "Feature",
  "properties": {
    "gn:admin1_code":"04",
    "gn:asciiname":"Las Minitas",
    "gn:cc2":"HN",
    "gn:country_code":"HN",
    "gn:dem":1253,
    "gn:feature_class":"P",
    "gn:feature_code":"PPL",
    "gn:name":"Las Minitas",
    "gn:population":0,
    "gn:timezone":"America/Tegucigalpa",
    "iso:country":"HN",
    "name:und_x_variant":[
        "Minitas",
        "Las Minitas"
    ],
    "wof:name":"Las Minitas",
    "wof:placetype":"locality"
},
  "geometry": {"coordinates":[-87.48333000000002,14.73333],"type":"Point"}
}