{
  "type": "Feature",
  "properties": {
    "gn:admin1_code":"08",
    "gn:asciiname":"San Francisco de Soroguara",
    "gn:cc2":"HN",
    "gn:country_code":"HN",
    "gn:dem":1482,
    "gn:feature_class":"P",
    "gn:feature_code":"PPL",
    "gn:name":"San Francisco de Soroguara",
    "gn:population":0,
    "gn:timezone":"America/Tegucigalpa",
    "iso:country":"HN",
    "name:und_x_variant":[
        "San Fracisco de Soroguara",
        "San Francisco",
        "San Francisco de Soroguara"
    ],
    "wof:name":"San Francisco de Soroguara",
    "wof:placetype":"locality"
},
  "geometry": {"coordinates":[-87.40000000000001,14.31667],"type":"Point"}
}