{
  "type": "Feature",
  "properties": {
    "gn:admin1_code":"11",
    "gn:admin2_code":"1101.0",
    "gn:asciiname":"Gravel Bay",
    "gn:country_code":"HN",
    "gn:dem":20,
    "gn:feature_class":"P",
    "gn:feature_code":"PPL",
    "gn:name":"Gravel Bay",
    "gn:population":0,
    "gn:timezone":"America/Tegucigalpa",
    "iso:country":"HN",
    "wof:name":"Gravel Bay",
    "wof:placetype":"locality"
},
  "geometry": {"coordinates":[-86.55235,16.31479],"type":"Point"}
}