{
  "type": "Feature",
  "properties": {
    "gn:admin1_code":"08",
    "gn:asciiname":"La Loma de Enmedio",
    "gn:country_code":"HN",
    "gn:dem":483,
    "gn:feature_class":"P",
    "gn:feature_code":"PPL",
    "gn:name":"La Loma de Enmedio",
    "gn:population":0,
    "gn:timezone":"America/Tegucigalpa",
    "iso:country":"HN",
    "wof:name":"La Loma de Enmedio",
    "wof:placetype":"locality"
},
  "geometry": {"coordinates":[-87.25583,13.75278],"type":"Point"}
}