{
  "type": "Feature",
  "properties": {
    "gn:admin1_code":"08",
    "gn:asciiname":"El Eden",
    "gn:country_code":"HN",
    "gn:dem":1406,
    "gn:feature_class":"P",
    "gn:feature_code":"PPL",
    "gn:name":"El Ed\u00e9n",
    "gn:population":0,
    "gn:timezone":"America/Tegucigalpa",
    "iso:country":"HN",
    "wof:name":"El Eden",
    "wof:placetype":"locality"
},
  "geometry": {"coordinates":[-87.09999999999999,14.08333],"type":"Point"}
}