{
  "type": "Feature",
  "properties": {
    "gn:admin1_code":"16",
    "gn:asciiname":"Cruz de Pacaya",
    "gn:country_code":"HN",
    "gn:dem":1290,
    "gn:feature_class":"P",
    "gn:feature_code":"PPL",
    "gn:name":"Cruz de Pacaya",
    "gn:population":0,
    "gn:timezone":"America/Tegucigalpa",
    "iso:country":"HN",
    "wof:name":"Cruz de Pacaya",
    "wof:placetype":"locality"
},
  "geometry": {"coordinates":[-88.46666999999999,14.86667],"type":"Point"}
}