{
  "type": "Feature",
  "properties": {
    "gn:admin1_code":"06",
    "gn:asciiname":"Buenos Aires",
    "gn:country_code":"HN",
    "gn:dem":784,
    "gn:feature_class":"P",
    "gn:feature_code":"PPL",
    "gn:name":"Buenos Aires",
    "gn:population":979,
    "gn:timezone":"America/Tegucigalpa",
    "iso:country":"HN",
    "wof:name":"Buenos Aires",
    "wof:placetype":"locality",
    "wof:population":979
},
  "geometry": {"coordinates":[-88.18333,15.48333],"type":"Point"}
}