{
  "type": "Feature",
  "properties": {
    "gn:admin1_code":"08",
    "gn:asciiname":"Guarabuqui",
    "gn:cc2":"HN",
    "gn:country_code":"HN",
    "gn:dem":972,
    "gn:feature_class":"P",
    "gn:feature_code":"PPL",
    "gn:name":"Guarabuqu\u00ed",
    "gn:population":0,
    "gn:timezone":"America/Tegucigalpa",
    "iso:country":"HN",
    "name:und_x_variant":[
        "Guarrabuqui",
        "Guarabuqu\u00ed"
    ],
    "wof:name":"Guarabuqui",
    "wof:placetype":"locality"
},
  "geometry": {"coordinates":[-86.95,14.76667],"type":"Point"}
}