{
  "type": "Feature",
  "properties": {
    "gn:admin1_code":"12",
    "gn:asciiname":"Agua Blanca",
    "gn:country_code":"HN",
    "gn:dem":1133,
    "gn:feature_class":"P",
    "gn:feature_code":"PPL",
    "gn:name":"Agua Blanca",
    "gn:population":0,
    "gn:timezone":"America/Tegucigalpa",
    "iso:country":"HN",
    "name:bre_x_preferred":[
        "Agua Blanca"
    ],
    "name:ceb_x_preferred":[
        "Agua Blanca"
    ],
    "name:deu_x_preferred":[
        "Agua Blanca"
    ],
    "name:fra_x_preferred":[
        "Agua Blanca"
    ],
    "name:nld_x_preferred":[
        "Agua Blanca"
    ],
    "name:por_x_preferred":[
        "Agua Blanca"
    ],
    "name:sco_x_preferred":[
        "Agua Blanca"
    ],
    "name:spa_x_preferred":[
        "Agua Blanca"
    ],
    "name:swe_x_preferred":[
        "Agua Blanca"
    ],
    "wof:name":"Agua Blanca",
    "wof:placetype":"locality"
},
  "geometry": {"coordinates":[-87.92889,13.93778],"type":"Point"}
}