{
  "type": "Feature",
  "properties": {
    "gn:admin1_code":"04",
    "gn:asciiname":"El Hobo",
    "gn:country_code":"HN",
    "gn:dem":935,
    "gn:feature_class":"P",
    "gn:feature_code":"PPL",
    "gn:name":"El Hobo",
    "gn:population":0,
    "gn:timezone":"America/Tegucigalpa",
    "iso:country":"HN",
    "wof:name":"El Hobo",
    "wof:placetype":"locality"
},
  "geometry": {"coordinates":[-88.01666999999998,14.61667],"type":"Point"}
}