{
  "type": "Feature",
  "properties": {
    "gn:admin1_code":"02",
    "gn:asciiname":"El Tropico",
    "gn:country_code":"HN",
    "gn:dem":1164,
    "gn:feature_class":"P",
    "gn:feature_code":"PPL",
    "gn:name":"El Tr\u00f3pico",
    "gn:population":0,
    "gn:timezone":"America/Tegucigalpa",
    "iso:country":"HN",
    "wof:name":"El Tropico",
    "wof:placetype":"locality"
},
  "geometry": {"coordinates":[-86.83333,13.36667],"type":"Point"}
}