{
  "type": "Feature",
  "properties": {
    "gn:admin1_code":"05",
    "gn:asciiname":"La Ruda",
    "gn:country_code":"HN",
    "gn:dem":1209,
    "gn:feature_class":"P",
    "gn:feature_code":"PPL",
    "gn:name":"La Ruda",
    "gn:population":0,
    "gn:timezone":"America/Tegucigalpa",
    "iso:country":"HN",
    "name:deu_x_preferred":[
        "La Ruda"
    ],
    "name:fra_x_preferred":[
        "La Ruda"
    ],
    "name:spa_x_preferred":[
        "La Ruda Salska"
    ],
    "wof:name":"La Ruda",
    "wof:placetype":"locality"
},
  "geometry": {"coordinates":[-88.88333,14.85],"type":"Point"}
}