{
  "type": "Feature",
  "properties": {
    "gn:admin1_code":"02",
    "gn:asciiname":"Las Estradas",
    "gn:country_code":"HN",
    "gn:dem":322,
    "gn:feature_class":"P",
    "gn:feature_code":"PPL",
    "gn:name":"Las Estradas",
    "gn:population":0,
    "gn:timezone":"America/Tegucigalpa",
    "iso:country":"HN",
    "wof:name":"Las Estradas",
    "wof:placetype":"locality"
},
  "geometry": {"coordinates":[-87.27278000000003,13.64222],"type":"Point"}
}