{
  "type": "Feature",
  "properties": {
    "gn:admin1_code":"12",
    "gn:asciiname":"El Sitio",
    "gn:country_code":"HN",
    "gn:dem":905,
    "gn:feature_class":"P",
    "gn:feature_code":"PPL",
    "gn:name":"El Sitio",
    "gn:population":0,
    "gn:timezone":"America/Tegucigalpa",
    "iso:country":"HN",
    "wof:name":"El Sitio",
    "wof:placetype":"locality"
},
  "geometry": {"coordinates":[-87.79222,13.96667],"type":"Point"}
}