{
  "type": "Feature",
  "properties": {
    "iso:country":"HN",
    "name:eng_x_preferred":[
        "San Francisco"
    ],
    "name:epo_x_preferred":[
        "San Francisco"
    ],
    "name:fra_x_preferred":[
        "San Francisco"
    ],
    "name:ita_x_preferred":[
        "San Francisco"
    ],
    "name:nan_x_preferred":[
        "San Francisco"
    ],
    "name:nld_x_preferred":[
        "San Francisco"
    ],
    "name:pol_x_preferred":[
        "San Francisco"
    ],
    "name:por_x_preferred":[
        "San Francisco"
    ],
    "name:spa_x_preferred":[
        "San Francisco"
    ],
    "name:swe_x_preferred":[
        "San Francisco"
    ],
    "name:zho_x_preferred":[
        "\u8056\u5f17\u862d\u897f\u65af\u79d1"
    ],
    "qs:gn_country":"HN",
    "qs:gn_fcode":"PPL",
    "qs:gn_pop":2806,
    "qs:name":"San Francisco",
    "qs:name_adm0":"Honduras",
    "qs:name_adm1":"Atl\u00e1ntida",
    "qs:photos":0,
    "qs:photos_1k":0,
    "qs:photos_9k":1,
    "qs:photos_9r":1,
    "qs:photos_all":1,
    "qs:photos_sr":0,
    "qs:placetype":"Town",
    "qs:pop_sr":"4",
    "qs:woe_adm0":23424841,
    "wof:name":"San Francisco",
    "wof:placetype":"locality",
    "wof:population":2806
},
  "geometry": {"coordinates":[-87.05,15.65],"type":"Point"}
}