{
  "type": "Feature",
  "properties": {
    "gn:country":"HN",
    "gn:fcode":"PPL",
    "gn:population":1250,
    "iso:country":"HN",
    "name:und_x_variant":[
        "Nombre Jes\u00fas"
    ],
    "name:zho_x_preferred":[
        "\u8036\u7a4c\u8056\u540d\u93ae"
    ],
    "qs:name":"Nombre de Jes\u00fas",
    "qs:photos_9r":0,
    "qs:photos_sr":0,
    "qs:pop_sr":"3",
    "wd:wordcount":35,
    "wof:name":"Nombre de Jes\u00fas",
    "wof:placetype":"locality",
    "wof:population":1250
},
  "geometry": {"coordinates":[-86.68333,15.35],"type":"Point"}
}