{
  "type": "Feature",
  "properties": {
    "gn:admin1_code":"13",
    "gn:asciiname":"Comapara",
    "gn:cc2":"HN",
    "gn:country_code":"HN",
    "gn:dem":521,
    "gn:feature_class":"P",
    "gn:feature_code":"PPL",
    "gn:name":"Comapara",
    "gn:population":0,
    "gn:timezone":"America/Tegucigalpa",
    "iso:country":"HN",
    "name:und_x_variant":[
        "Camapara",
        "Comapara"
    ],
    "wof:name":"Comapara",
    "wof:placetype":"locality"
},
  "geometry": {"coordinates":[-88.58333,14.06667],"type":"Point"}
}