{
  "type": "Feature",
  "properties": {
    "gn:admin1_code":"08",
    "gn:asciiname":"El Capulin",
    "gn:cc2":"HN",
    "gn:country_code":"HN",
    "gn:dem":820,
    "gn:feature_class":"P",
    "gn:feature_code":"PPL",
    "gn:name":"El Capul\u00edn",
    "gn:population":0,
    "gn:timezone":"America/Tegucigalpa",
    "iso:country":"HN",
    "name:und_x_variant":[
        "Chapulin",
        "El Capul\u00edn"
    ],
    "wof:name":"El Capulin",
    "wof:placetype":"locality"
},
  "geometry": {"coordinates":[-87.53333000000001,13.85],"type":"Point"}
}