{
  "type": "Feature",
  "properties": {
    "gn:admin1_code":"12",
    "gn:asciiname":"Guajiquirito",
    "gn:country_code":"HN",
    "gn:dem":1867,
    "gn:feature_class":"P",
    "gn:feature_code":"PPL",
    "gn:name":"Guajiquirito",
    "gn:population":0,
    "gn:timezone":"America/Tegucigalpa",
    "iso:country":"HN",
    "wof:name":"Guajiquirito",
    "wof:placetype":"locality"
},
  "geometry": {"coordinates":[-87.83333,14.11667],"type":"Point"}
}