{
  "type": "Feature",
  "properties": {
    "iso:country":"HN",
    "name:und_x_variant":[
        "Salada Barra"
    ],
    "qs:gn_country":"HN",
    "qs:gn_fcode":"PPL",
    "qs:gn_pop":0,
    "qs:name":"Salado Barra",
    "qs:name_adm0":"Honduras",
    "qs:name_adm1":"Atl\u00e1ntida",
    "qs:photos":95,
    "qs:photos_1k":19,
    "qs:photos_9k":1,
    "qs:photos_9r":3,
    "qs:photos_all":95,
    "qs:photos_sr":3,
    "qs:placetype":"Town",
    "qs:pop_sr":"0",
    "qs:woe_adm0":23424841,
    "wof:name":"Salado Barra",
    "wof:placetype":"locality"
},
  "geometry": {"coordinates":[-87.03333000000001,15.75],"type":"Point"}
}