{
  "type": "Feature",
  "properties": {
    "gn:admin1_code":"16",
    "gn:asciiname":"Laguneta",
    "gn:country_code":"HN",
    "gn:dem":628,
    "gn:feature_class":"P",
    "gn:feature_code":"PPL",
    "gn:name":"Laguneta",
    "gn:population":0,
    "gn:timezone":"America/Tegucigalpa",
    "iso:country":"HN",
    "wof:name":"Laguneta",
    "wof:placetype":"locality"
},
  "geometry": {"coordinates":[-88.43333,15.15],"type":"Point"}
}