{
  "type": "Feature",
  "properties": {
    "gn:admin1_code":"08",
    "gn:asciiname":"Cunimisca",
    "gn:cc2":"HN",
    "gn:country_code":"HN",
    "gn:dem":824,
    "gn:feature_class":"P",
    "gn:feature_code":"PPL",
    "gn:name":"Cunimisca",
    "gn:population":0,
    "gn:timezone":"America/Tegucigalpa",
    "iso:country":"HN",
    "name:und_x_variant":[
        "Cunimisaca",
        "Cunimisca"
    ],
    "wof:name":"Cunimisca",
    "wof:placetype":"locality"
},
  "geometry": {"coordinates":[-87.57083,13.87833],"type":"Point"}
}