{
  "type": "Feature",
  "properties": {
    "gn:admin1_code":"01",
    "gn:asciiname":"Casa de Alto",
    "gn:country_code":"HN",
    "gn:dem":24,
    "gn:feature_class":"P",
    "gn:feature_code":"PPL",
    "gn:name":"Casa de Alto",
    "gn:population":0,
    "gn:timezone":"America/Tegucigalpa",
    "iso:country":"HN",
    "wof:name":"Casa de Alto",
    "wof:placetype":"locality"
},
  "geometry": {"coordinates":[-87.15000000000001,15.63333],"type":"Point"}
}