{
  "type": "Feature",
  "properties": {
    "gn:admin1_code":"13",
    "gn:asciiname":"El Juncal",
    "gn:cc2":"HN",
    "gn:country_code":"HN",
    "gn:dem":1468,
    "gn:feature_class":"P",
    "gn:feature_code":"PPL",
    "gn:name":"El Juncal",
    "gn:population":0,
    "gn:timezone":"America/Tegucigalpa",
    "iso:country":"HN",
    "name:und_x_variant":[
        "Juncal",
        "El Juncal"
    ],
    "wof:name":"El Juncal",
    "wof:placetype":"locality"
},
  "geometry": {"coordinates":[-88.48333000000002,14.78333],"type":"Point"}
}