{
  "type": "Feature",
  "properties": {
    "gn:admin1_code":"15",
    "gn:asciiname":"Casas Viejas",
    "gn:country_code":"HN",
    "gn:dem":527,
    "gn:feature_class":"P",
    "gn:feature_code":"PPL",
    "gn:name":"Casas Viejas",
    "gn:population":0,
    "gn:timezone":"America/Tegucigalpa",
    "iso:country":"HN",
    "wof:name":"Casas Viejas",
    "wof:placetype":"locality"
},
  "geometry": {"coordinates":[-85.98333000000002,15.18333],"type":"Point"}
}