{
  "type": "Feature",
  "properties": {
    "gn:admin1_code":"14",
    "gn:asciiname":"La Concordia",
    "gn:cc2":"HN",
    "gn:country_code":"HN",
    "gn:dem":1154,
    "gn:feature_class":"P",
    "gn:feature_code":"PPL",
    "gn:name":"La Concordia",
    "gn:population":0,
    "gn:timezone":"America/Tegucigalpa",
    "iso:country":"HN",
    "name:und_x_variant":[
        "Concordia",
        "La Concordia"
    ],
    "wof:name":"La Concordia",
    "wof:placetype":"locality"
},
  "geometry": {"coordinates":[-88.96666999999999,14.56667],"type":"Point"}
}