{
  "type": "Feature",
  "properties": {
    "gn:admin1_code":"08",
    "gn:asciiname":"Petacones",
    "gn:country_code":"HN",
    "gn:dem":397,
    "gn:feature_class":"P",
    "gn:feature_code":"PPL",
    "gn:name":"Petacones",
    "gn:population":0,
    "gn:timezone":"America/Tegucigalpa",
    "iso:country":"HN",
    "wof:name":"Petacones",
    "wof:placetype":"locality"
},
  "geometry": {"coordinates":[-87.48333000000002,13.86667],"type":"Point"}
}