{
  "type": "Feature",
  "properties": {
    "gn:admin1_code":"08",
    "gn:asciiname":"El Tabanco",
    "gn:country_code":"HN",
    "gn:dem":1162,
    "gn:feature_class":"P",
    "gn:feature_code":"PPL",
    "gn:name":"El Tabanco",
    "gn:population":0,
    "gn:timezone":"America/Tegucigalpa",
    "iso:country":"HN",
    "wof:name":"El Tabanco",
    "wof:placetype":"locality"
},
  "geometry": {"coordinates":[-87.43416999999999,13.90778],"type":"Point"}
}