{
  "type": "Feature",
  "properties": {
    "gn:admin1_code":"04",
    "gn:asciiname":"Delicias",
    "gn:country_code":"HN",
    "gn:dem":872,
    "gn:feature_class":"P",
    "gn:feature_code":"PPL",
    "gn:name":"Delicias",
    "gn:population":0,
    "gn:timezone":"America/Tegucigalpa",
    "iso:country":"HN",
    "wof:name":"Delicias",
    "wof:placetype":"locality"
},
  "geometry": {"coordinates":[-88.05,14.68333],"type":"Point"}
}