{
  "type": "Feature",
  "properties": {
    "gn:admin1_code":"13",
    "gn:asciiname":"Los Robles",
    "gn:country_code":"HN",
    "gn:dem":453,
    "gn:feature_class":"P",
    "gn:feature_code":"PPL",
    "gn:name":"Los Robles",
    "gn:population":0,
    "gn:timezone":"America/Tegucigalpa",
    "iso:country":"HN",
    "wof:name":"Los Robles",
    "wof:placetype":"locality"
},
  "geometry": {"coordinates":[-88.86667,14.16667],"type":"Point"}
}