{
  "type": "Feature",
  "properties": {
    "gn:country":"HN",
    "gn:fcode":"PPL",
    "gn:population":2495,
    "iso:country":"HN",
    "name:ita_x_preferred":[
        "La Ermita"
    ],
    "name:spa_x_preferred":[
        "La Ermita"
    ],
    "name:und_x_variant":[
        "Hermita"
    ],
    "name:zho_x_preferred":[
        "\u62c9\u57c3\u723e\u7c73\u5854"
    ],
    "qs_pg:aaroncc":"HN",
    "qs_pg:gn_country":"HN",
    "qs_pg:gn_fcode":"PPL",
    "qs_pg:gn_pop":2495,
    "qs_pg:name":"La Ermita",
    "qs_pg:photos_9r":0,
    "qs_pg:photos_sr":0,
    "qs_pg:pop_sr":4,
    "qs_pg:qs_pg_placetype":"locality",
    "wof:name":"La Ermita",
    "wof:placetype":"locality",
    "wof:population":2495
},
  "geometry": {"coordinates":[-87.06667,14.46667],"type":"Point"}
}