{
  "type": "Feature",
  "properties": {
    "gn:admin1_code":"07",
    "gn:asciiname":"El Frijotillo",
    "gn:country_code":"HN",
    "gn:dem":336,
    "gn:feature_class":"P",
    "gn:feature_code":"PPL",
    "gn:name":"El Frijotillo",
    "gn:population":0,
    "gn:timezone":"America/Tegucigalpa",
    "iso:country":"HN",
    "wof:name":"El Frijotillo",
    "wof:placetype":"locality"
},
  "geometry": {"coordinates":[-87.16417,13.55139],"type":"Point"}
}