{
  "type": "Feature",
  "properties": {
    "gn:admin1_code":"07",
    "gn:asciiname":"El Escano",
    "gn:cc2":"HN",
    "gn:country_code":"HN",
    "gn:dem":107,
    "gn:feature_class":"P",
    "gn:feature_code":"PPL",
    "gn:name":"El Esca\u00f1o",
    "gn:population":0,
    "gn:timezone":"America/Tegucigalpa",
    "iso:country":"HN",
    "name:und_x_variant":[
        "Esca\u00f1o",
        "El Esca\u00f1o"
    ],
    "wof:name":"El Escano",
    "wof:placetype":"locality"
},
  "geometry": {"coordinates":[-87.08333,13.46667],"type":"Point"}
}