{
  "type": "Feature",
  "properties": {
    "gn:admin1_code":"01",
    "gn:asciiname":"La Belgica",
    "gn:cc2":"HN",
    "gn:country_code":"HN",
    "gn:dem":30,
    "gn:feature_class":"P",
    "gn:feature_code":"PPL",
    "gn:name":"La B\u00e9lgica",
    "gn:population":0,
    "gn:timezone":"America/Tegucigalpa",
    "iso:country":"HN",
    "name:und_x_variant":[
        "Belgica",
        "La B\u00e9lgica",
        "La Masica"
    ],
    "wof:name":"La Belgica",
    "wof:placetype":"locality"
},
  "geometry": {"coordinates":[-87.09999999999999,15.63333],"type":"Point"}
}