{
  "type": "Feature",
  "properties": {
    "gn:admin1_code":"05",
    "gn:asciiname":"Cutilca",
    "gn:cc2":"HN",
    "gn:country_code":"HN",
    "gn:dem":806,
    "gn:feature_class":"P",
    "gn:feature_code":"PPL",
    "gn:name":"Cutilca",
    "gn:population":0,
    "gn:timezone":"America/Tegucigalpa",
    "iso:country":"HN",
    "name:und_x_variant":[
        "Cutica",
        "Cutilca"
    ],
    "wof:name":"Cutilca",
    "wof:placetype":"locality"
},
  "geometry": {"coordinates":[-88.83333,14.78333],"type":"Point"}
}