{
  "type": "Feature",
  "properties": {
    "gn:admin1_code":"09",
    "gn:asciiname":"Claura",
    "gn:cc2":"HN",
    "gn:country_code":"HN",
    "gn:dem":5,
    "gn:feature_class":"P",
    "gn:feature_code":"PPL",
    "gn:name":"Claura",
    "gn:population":0,
    "gn:timezone":"America/Tegucigalpa",
    "iso:country":"HN",
    "name:und_x_variant":[
        "Clacura",
        "Claura"
    ],
    "wof:name":"Claura",
    "wof:placetype":"locality"
},
  "geometry": {"coordinates":[-84.06667,15.61667],"type":"Point"}
}