{
  "type": "Feature",
  "properties": {
    "gn:admin1_code":"16",
    "gn:asciiname":"Portillo Hondo",
    "gn:country_code":"HN",
    "gn:dem":1536,
    "gn:feature_class":"P",
    "gn:feature_code":"PPL",
    "gn:name":"Portillo Hondo",
    "gn:population":0,
    "gn:timezone":"America/Tegucigalpa",
    "iso:country":"HN",
    "wof:name":"Portillo Hondo",
    "wof:placetype":"locality"
},
  "geometry": {"coordinates":[-88.34999999999999,15.16667],"type":"Point"}
}