{
  "type": "Feature",
  "properties": {
    "gn:admin1_code":"08",
    "gn:asciiname":"Quebrada Grande",
    "gn:country_code":"HN",
    "gn:dem":2182,
    "gn:feature_class":"P",
    "gn:feature_code":"PPL",
    "gn:name":"Quebrada Grande",
    "gn:population":0,
    "gn:timezone":"America/Tegucigalpa",
    "iso:country":"HN",
    "wof:name":"Quebrada Grande",
    "wof:placetype":"locality"
},
  "geometry": {"coordinates":[-87.08333,14.96667],"type":"Point"}
}