{
  "type": "Feature",
  "properties": {
    "gn:admin1_code":"14",
    "gn:asciiname":"El Camalote",
    "gn:country_code":"HN",
    "gn:dem":1463,
    "gn:feature_class":"P",
    "gn:feature_code":"PPL",
    "gn:name":"El Camalote",
    "gn:population":0,
    "gn:timezone":"America/Tegucigalpa",
    "iso:country":"HN",
    "wof:name":"El Camalote",
    "wof:placetype":"locality"
},
  "geometry": {"coordinates":[-89.11667,14.48333],"type":"Point"}
}