{
  "type": "Feature",
  "properties": {
    "gn:admin1_code":"05",
    "gn:asciiname":"San Antonio del Norte",
    "gn:country_code":"HN",
    "gn:dem":682,
    "gn:feature_class":"P",
    "gn:feature_code":"PPL",
    "gn:name":"San Antonio del Norte",
    "gn:population":0,
    "gn:timezone":"America/Tegucigalpa",
    "iso:country":"HN",
    "wof:name":"San Antonio del Norte",
    "wof:placetype":"locality"
},
  "geometry": {"coordinates":[-89.11667,15.05],"type":"Point"}
}