{
  "type": "Feature",
  "properties": {
    "gn:admin1_code":"07",
    "gn:asciiname":"Obraje",
    "gn:country_code":"HN",
    "gn:dem":413,
    "gn:feature_class":"P",
    "gn:feature_code":"PPL",
    "gn:name":"Obraje",
    "gn:population":0,
    "gn:timezone":"America/Tegucigalpa",
    "iso:country":"HN",
    "wof:name":"Obraje",
    "wof:placetype":"locality"
},
  "geometry": {"coordinates":[-86.76666999999998,13.78333],"type":"Point"}
}