{
  "type": "Feature",
  "properties": {
    "iso:country":"HN",
    "name:ceb_x_preferred":[
        "Marcovia"
    ],
    "name:eng_x_preferred":[
        "Marcovia"
    ],
    "name:fra_x_preferred":[
        "Marcovia"
    ],
    "name:ita_x_preferred":[
        "Marcovia"
    ],
    "name:nan_x_preferred":[
        "Marcovia"
    ],
    "name:nld_x_preferred":[
        "Marcovia"
    ],
    "name:pol_x_preferred":[
        "Marcovia"
    ],
    "name:por_x_preferred":[
        "Marcovia"
    ],
    "name:spa_x_preferred":[
        "Marcovia"
    ],
    "name:swe_x_preferred":[
        "Marcovia"
    ],
    "name:zho_x_preferred":[
        "\u99ac\u723e\u79d1\u7dad\u4e9e"
    ],
    "qs:gn_country":"HN",
    "qs:gn_fcode":"PPL",
    "qs:gn_pop":1928,
    "qs:name":"Marcovia",
    "qs:name_adm0":"Honduras",
    "qs:name_adm1":"Choluteca",
    "qs:photos":0,
    "qs:photos_1k":0,
    "qs:photos_9k":0,
    "qs:photos_9r":0,
    "qs:photos_all":0,
    "qs:photos_sr":0,
    "qs:placetype":"Town",
    "qs:pop_sr":"3",
    "qs:woe_adm0":23424841,
    "wof:name":"Marcovia",
    "wof:placetype":"locality",
    "wof:population":1928
},
  "geometry": {"coordinates":[-87.30972,13.28806],"type":"Point"}
}