{
  "type": "Feature",
  "properties": {
    "gn:admin1_code":"08",
    "gn:asciiname":"El Jocomico",
    "gn:country_code":"HN",
    "gn:dem":880,
    "gn:feature_class":"P",
    "gn:feature_code":"PPL",
    "gn:name":"El Jocomico",
    "gn:population":0,
    "gn:timezone":"America/Tegucigalpa",
    "iso:country":"HN",
    "wof:name":"El Jocomico",
    "wof:placetype":"locality"
},
  "geometry": {"coordinates":[-86.91667,14.58333],"type":"Point"}
}