{
  "type": "Feature",
  "properties": {
    "gn:admin1_code":"18",
    "gn:asciiname":"La Montana",
    "gn:country_code":"HN",
    "gn:dem":867,
    "gn:feature_class":"P",
    "gn:feature_code":"PPL",
    "gn:name":"La Monta\u00f1a",
    "gn:population":0,
    "gn:timezone":"America/Tegucigalpa",
    "iso:country":"HN",
    "wof:name":"La Montana",
    "wof:placetype":"locality"
},
  "geometry": {"coordinates":[-86.78333000000001,15.46667],"type":"Point"}
}