{
  "type": "Feature",
  "properties": {
    "gn:admin1_code":"08",
    "gn:asciiname":"El Terrero Prieto",
    "gn:country_code":"HN",
    "gn:dem":1013,
    "gn:feature_class":"P",
    "gn:feature_code":"PPL",
    "gn:name":"El Terrero Prieto",
    "gn:population":0,
    "gn:timezone":"America/Tegucigalpa",
    "iso:country":"HN",
    "wof:name":"El Terrero Prieto",
    "wof:placetype":"locality"
},
  "geometry": {"coordinates":[-87.04333000000003,13.92167],"type":"Point"}
}