{
  "type": "Feature",
  "properties": {
    "gn:admin1_code":"18",
    "gn:asciiname":"Quebrada Grande",
    "gn:cc2":"HN",
    "gn:country_code":"HN",
    "gn:dem":463,
    "gn:feature_class":"P",
    "gn:feature_code":"PPL",
    "gn:name":"Quebrada Grande",
    "gn:population":0,
    "gn:timezone":"America/Tegucigalpa",
    "iso:country":"HN",
    "name:und_x_variant":[
        "Quebrada Honda",
        "Quebrada Grande"
    ],
    "wof:name":"Quebrada Grande",
    "wof:placetype":"locality"
},
  "geometry": {"coordinates":[-86.91667,15.45],"type":"Point"}
}