{
  "type": "Feature",
  "properties": {
    "gn:admin1_code":"02",
    "gn:asciiname":"Lagunillas",
    "gn:country_code":"HN",
    "gn:dem":1379,
    "gn:feature_class":"P",
    "gn:feature_code":"PPL",
    "gn:name":"Lagunillas",
    "gn:population":0,
    "gn:timezone":"America/Tegucigalpa",
    "iso:country":"HN",
    "name:ceb_x_preferred":[
        "Lagunillas"
    ],
    "name:deu_x_preferred":[
        "Lagunillas"
    ],
    "name:fra_x_preferred":[
        "Lagunillas"
    ],
    "name:ita_x_preferred":[
        "Lagunillas"
    ],
    "name:lit_x_preferred":[
        "Laguniljasas"
    ],
    "name:nld_x_preferred":[
        "Lagunillas"
    ],
    "name:sco_x_preferred":[
        "Lagunillas"
    ],
    "name:spa_x_preferred":[
        "Lagunillas"
    ],
    "name:swe_x_preferred":[
        "Lagunillas"
    ],
    "wof:name":"Lagunillas",
    "wof:placetype":"locality"
},
  "geometry": {"coordinates":[-86.75,13.36667],"type":"Point"}
}