{
  "type": "Feature",
  "properties": {
    "gn:admin1_code":"17",
    "gn:asciiname":"Cueva",
    "gn:country_code":"HN",
    "gn:dem":360,
    "gn:feature_class":"P",
    "gn:feature_code":"PPL",
    "gn:name":"Cueva",
    "gn:population":0,
    "gn:timezone":"America/Tegucigalpa",
    "iso:country":"HN",
    "wof:name":"Cueva",
    "wof:placetype":"locality"
},
  "geometry": {"coordinates":[-87.70860999999999,13.84361],"type":"Point"}
}