{
  "type": "Feature",
  "properties": {
    "gn:admin1_code":"02",
    "gn:asciiname":"El Higuito",
    "gn:country_code":"HN",
    "gn:dem":574,
    "gn:feature_class":"P",
    "gn:feature_code":"PPL",
    "gn:name":"El Higuito",
    "gn:population":0,
    "gn:timezone":"America/Tegucigalpa",
    "iso:country":"HN",
    "wof:name":"El Higuito",
    "wof:placetype":"locality"
},
  "geometry": {"coordinates":[-87.02944000000002,13.52083],"type":"Point"}
}