{
  "type": "Feature",
  "properties": {
    "gn:admin1_code":"12",
    "gn:asciiname":"San Bartolo",
    "gn:country_code":"HN",
    "gn:dem":1155,
    "gn:feature_class":"P",
    "gn:feature_code":"PPL",
    "gn:name":"San Bartolo",
    "gn:population":0,
    "gn:timezone":"America/Tegucigalpa",
    "iso:country":"HN",
    "name:ceb_x_preferred":[
        "San Bartolo"
    ],
    "name:deu_x_preferred":[
        "San Bartolo"
    ],
    "name:epo_x_preferred":[
        "San Bartolo"
    ],
    "name:fra_x_preferred":[
        "San Bartolo"
    ],
    "name:por_x_preferred":[
        "San Bartolo"
    ],
    "name:sco_x_preferred":[
        "San Bartolo"
    ],
    "name:spa_x_preferred":[
        "San Bartolo"
    ],
    "name:srp_x_preferred":[
        "San Bartolo"
    ],
    "name:swe_x_preferred":[
        "San Bartolo"
    ],
    "wof:name":"San Bartolo",
    "wof:placetype":"locality"
},
  "geometry": {"coordinates":[-87.78333000000001,14.06667],"type":"Point"}
}