{
  "type": "Feature",
  "properties": {
    "gn:admin1_code":"04",
    "gn:asciiname":"Villa Napoles",
    "gn:cc2":"HN",
    "gn:country_code":"HN",
    "gn:dem":861,
    "gn:feature_class":"P",
    "gn:feature_code":"PPL",
    "gn:name":"Villa N\u00e1poles",
    "gn:population":0,
    "gn:timezone":"America/Tegucigalpa",
    "iso:country":"HN",
    "name:und_x_variant":[
        "La Muralla",
        "Villa N\u00e1poles"
    ],
    "wof:name":"Villa Napoles",
    "wof:placetype":"locality"
},
  "geometry": {"coordinates":[-87.98333000000002,14.76667],"type":"Point"}
}