{
  "type": "Feature",
  "properties": {
    "gn:admin1_code":"08",
    "gn:asciiname":"Los Altos",
    "gn:country_code":"HN",
    "gn:dem":811,
    "gn:feature_class":"P",
    "gn:feature_code":"PPL",
    "gn:name":"Los Altos",
    "gn:population":0,
    "gn:timezone":"America/Tegucigalpa",
    "iso:country":"HN",
    "wof:name":"Los Altos",
    "wof:placetype":"locality"
},
  "geometry": {"coordinates":[-87.13333,14.51667],"type":"Point"}
}