{
  "type": "Feature",
  "properties": {
    "gn:country":"HN",
    "gn:fcode":"PPL",
    "gn:pop":976,
    "iso:country":"HN",
    "qs:name":"San Nicol\u00e1s",
    "qs:photos_9r":0,
    "qs:photos_sr":0,
    "qs:pop_sr":"2",
    "wd:wordcount":277,
    "wof:name":"San Nicol\u00e1s",
    "wof:placetype":"locality",
    "wof:population":976
},
  "geometry": {"coordinates":[-87.34999999999999,14.71667],"type":"Point"}
}