{
  "type": "Feature",
  "properties": {
    "gn:admin1_code":"16",
    "gn:asciiname":"El Mogote",
    "gn:cc2":"HN",
    "gn:country_code":"HN",
    "gn:dem":833,
    "gn:feature_class":"P",
    "gn:feature_code":"PPL",
    "gn:name":"El Mogote",
    "gn:population":0,
    "gn:timezone":"America/Tegucigalpa",
    "iso:country":"HN",
    "name:und_x_variant":[
        "Mogote",
        "El Mogote"
    ],
    "wof:name":"El Mogote",
    "wof:placetype":"locality"
},
  "geometry": {"coordinates":[-88.06667,14.76667],"type":"Point"}
}