{
  "type": "Feature",
  "properties": {
    "gn:admin1_code":"08",
    "gn:asciiname":"Monte Redondo",
    "gn:country_code":"HN",
    "gn:dem":910,
    "gn:feature_class":"P",
    "gn:feature_code":"PPL",
    "gn:name":"Monte Redondo",
    "gn:population":0,
    "gn:timezone":"America/Tegucigalpa",
    "iso:country":"HN",
    "wof:name":"Monte Redondo",
    "wof:placetype":"locality"
},
  "geometry": {"coordinates":[-87.46194,13.89806],"type":"Point"}
}