{
  "type": "Feature",
  "properties": {
    "gn:admin1_code":"07",
    "gn:asciiname":"El Tabloncito",
    "gn:country_code":"HN",
    "gn:dem":1221,
    "gn:feature_class":"P",
    "gn:feature_code":"PPL",
    "gn:name":"El Tabloncito",
    "gn:population":0,
    "gn:timezone":"America/Tegucigalpa",
    "iso:country":"HN",
    "wof:name":"El Tabloncito",
    "wof:placetype":"locality"
},
  "geometry": {"coordinates":[-86.86667,13.95],"type":"Point"}
}