{
  "type": "Feature",
  "properties": {
    "gn:admin1_code":"06",
    "gn:asciiname":"Caule",
    "gn:cc2":"HN",
    "gn:country_code":"HN",
    "gn:dem":295,
    "gn:feature_class":"P",
    "gn:feature_code":"PPL",
    "gn:name":"Caule",
    "gn:population":0,
    "gn:timezone":"America/Tegucigalpa",
    "iso:country":"HN",
    "name:und_x_variant":[
        "Coule",
        "Caule"
    ],
    "wof:name":"Caule",
    "wof:placetype":"locality"
},
  "geometry": {"coordinates":[-87.91667,15.36667],"type":"Point"}
}