{
  "type": "Feature",
  "properties": {
    "gn:country":"HN",
    "gn:fcode":"PPL",
    "gn:population":940,
    "iso:country":"HN",
    "qs:name":"Mandasta",
    "qs:photos_9r":0,
    "qs:photos_sr":0,
    "qs:pop_sr":"2",
    "wof:name":"Mandasta",
    "wof:placetype":"locality",
    "wof:population":940
},
  "geometry": {"coordinates":[-86.91667,13.73333],"type":"Point"}
}