{
  "type": "Feature",
  "properties": {
    "gn:admin1_code":"02",
    "gn:asciiname":"Coyolito",
    "gn:country_code":"HN",
    "gn:dem":213,
    "gn:feature_class":"P",
    "gn:feature_code":"PPL",
    "gn:name":"Coyolito",
    "gn:population":0,
    "gn:timezone":"America/Tegucigalpa",
    "iso:country":"HN",
    "wof:name":"Coyolito",
    "wof:placetype":"locality"
},
  "geometry": {"coordinates":[-87.24167,13.56667],"type":"Point"}
}