{
  "type": "Feature",
  "properties": {
    "gn:admin1_code":"02",
    "gn:asciiname":"Los Jutes",
    "gn:country_code":"HN",
    "gn:dem":730,
    "gn:feature_class":"P",
    "gn:feature_code":"PPL",
    "gn:name":"Los Jutes",
    "gn:population":0,
    "gn:timezone":"America/Tegucigalpa",
    "iso:country":"HN",
    "wof:name":"Los Jutes",
    "wof:placetype":"locality"
},
  "geometry": {"coordinates":[-86.25,15.25],"type":"Point"}
}