{
  "type": "Feature",
  "properties": {
    "gn:admin1_code":"12",
    "gn:asciiname":"Mal Aire",
    "gn:country_code":"HN",
    "gn:dem":331,
    "gn:feature_class":"P",
    "gn:feature_code":"PPL",
    "gn:name":"Mal Aire",
    "gn:population":0,
    "gn:timezone":"America/Tegucigalpa",
    "iso:country":"HN",
    "wof:name":"Mal Aire",
    "wof:placetype":"locality"
},
  "geometry": {"coordinates":[-87.68000000000001,13.9225],"type":"Point"}
}