{
  "type": "Feature",
  "properties": {
    "gn:admin1_code":"03",
    "gn:asciiname":"Los Leones",
    "gn:country_code":"HN",
    "gn:dem":38,
    "gn:feature_class":"P",
    "gn:feature_code":"PPL",
    "gn:name":"Los Leones",
    "gn:population":0,
    "gn:timezone":"America/Tegucigalpa",
    "iso:country":"HN",
    "wof:name":"Los Leones",
    "wof:placetype":"locality"
},
  "geometry": {"coordinates":[-85.89211,15.8402],"type":"Point"}
}