{
  "type": "Feature",
  "properties": {
    "gn:country":"HN",
    "gn:fcode":"PPL",
    "gn:population":1130,
    "iso:country":"HN",
    "name:ceb_x_preferred":[
        "San Joaqu\u00edn"
    ],
    "name:eus_x_preferred":[
        "San Joaqu\u00edn"
    ],
    "name:fas_x_preferred":[
        "\u0633\u0646 \u062e\u0648\u0622\u06a9\u06cc\u0646"
    ],
    "name:fra_x_preferred":[
        "San Joaqu\u00edn"
    ],
    "name:ita_x_preferred":[
        "San Joaqu\u00edn"
    ],
    "name:kor_x_preferred":[
        "\uc0b0\ud638\uc544\ud0a8"
    ],
    "name:nld_x_preferred":[
        "San Joaqu\u00edn"
    ],
    "name:por_x_preferred":[
        "San Joaqu\u00edn"
    ],
    "name:ron_x_preferred":[
        "San Joaqu\u00edn"
    ],
    "name:rus_x_preferred":[
        "\u0421\u0430\u043d-\u0425\u043e\u0430\u043a\u0438\u043d"
    ],
    "name:spa_x_preferred":[
        "San Joaqu\u00edn"
    ],
    "name:srp_x_preferred":[
        "\u0421\u0430\u043d \u0425\u043e\u0430\u043a\u0438\u043d"
    ],
    "name:zho_x_preferred":[
        "\u8056\u83ef\u91d1"
    ],
    "qs:name":"San Joaqu\u00edn",
    "qs:photos_9r":0,
    "qs:photos_sr":0,
    "qs:pop_sr":"3",
    "wd:wordcount":376,
    "wof:name":"San Joaqu\u00edn",
    "wof:placetype":"locality",
    "wof:population":1130
},
  "geometry": {"coordinates":[-88.90000000000001,15.05],"type":"Point"}
}