{
  "type": "Feature",
  "properties": {
    "gn:country":"HN",
    "gn:fcode":"PPL",
    "gn:pop":962,
    "iso:country":"HN",
    "qs:name":"San Antonio",
    "qs:photos_9r":0,
    "qs:photos_sr":0,
    "qs:pop_sr":"2",
    "wof:name":"San Antonio",
    "wof:placetype":"locality",
    "wof:population":962
},
  "geometry": {"coordinates":[-88.96666999999999,14.51667],"type":"Point"}
}