{
  "type": "Feature",
  "properties": {
    "gn:admin1_code":"07",
    "gn:asciiname":"Chilito",
    "gn:country_code":"HN",
    "gn:dem":1232,
    "gn:feature_class":"P",
    "gn:feature_code":"PPL",
    "gn:name":"Chilito",
    "gn:population":0,
    "gn:timezone":"America/Tegucigalpa",
    "iso:country":"HN",
    "wof:name":"Chilito",
    "wof:placetype":"locality"
},
  "geometry": {"coordinates":[-86.81667,14.25],"type":"Point"}
}