{
  "type": "Feature",
  "properties": {
    "gn:admin1_code":"15",
    "gn:asciiname":"Hacienda San Jose",
    "gn:cc2":"HN",
    "gn:country_code":"HN",
    "gn:dem":349,
    "gn:feature_class":"P",
    "gn:feature_code":"PPL",
    "gn:name":"Hacienda San Jos\u00e9",
    "gn:population":0,
    "gn:timezone":"America/Tegucigalpa",
    "iso:country":"HN",
    "name:und_x_variant":[
        "San Jose",
        "Hacienda San Jos\u00e9"
    ],
    "wof:name":"Hacienda San Jose",
    "wof:placetype":"locality"
},
  "geometry": {"coordinates":[-86.13333,14.65],"type":"Point"}
}