{
  "type": "Feature",
  "properties": {
    "iso:country":"HN",
    "name:deu_x_preferred":[
        "Zambrano"
    ],
    "name:fra_x_preferred":[
        "Zambrano"
    ],
    "name:ita_x_preferred":[
        "Zambrano"
    ],
    "name:rus_x_preferred":[
        "\u0421\u0430\u043c\u0431\u0440\u0430\u043d\u043e"
    ],
    "name:spa_x_preferred":[
        "Zambrano"
    ],
    "name:srp_x_preferred":[
        "\u0417\u0430\u043c\u0431\u0440\u0430\u043d\u043e"
    ],
    "name:ukr_x_preferred":[
        "\u0421\u0430\u043c\u0431\u0440\u0430\u043d\u043e"
    ],
    "name:vie_x_preferred":[
        "Zambrano"
    ],
    "qs:gn_country":"HN",
    "qs:gn_fcode":"PPL",
    "qs:gn_pop":3873,
    "qs:name":"Zambrano",
    "qs:name_adm0":"Honduras",
    "qs:name_adm1":"Francisco Moraz\u00e1n",
    "qs:photos":0,
    "qs:photos_1k":0,
    "qs:photos_9k":1,
    "qs:photos_9r":1,
    "qs:photos_all":4,
    "qs:photos_sr":0,
    "qs:placetype":"Town",
    "qs:pop_sr":"4",
    "qs:woe_adm0":23424841,
    "wd:wordcount":674,
    "wof:name":"Zambrano",
    "wof:placetype":"locality",
    "wof:population":3873
},
  "geometry": {"coordinates":[-87.40000000000001,14.26667],"type":"Point"}
}