{
  "type": "Feature",
  "properties": {
    "gn:admin1_code":"07",
    "gn:asciiname":"El Rio",
    "gn:country_code":"HN",
    "gn:dem":802,
    "gn:feature_class":"P",
    "gn:feature_code":"PPL",
    "gn:name":"El R\u00edo",
    "gn:population":0,
    "gn:timezone":"America/Tegucigalpa",
    "iso:country":"HN",
    "wof:name":"El Rio",
    "wof:placetype":"locality"
},
  "geometry": {"coordinates":[-86.83333,13.93333],"type":"Point"}
}