{
  "type": "Feature",
  "properties": {
    "gn:admin1_code":"13",
    "gn:asciiname":"El Aguacate",
    "gn:country_code":"HN",
    "gn:dem":1571,
    "gn:feature_class":"P",
    "gn:feature_code":"PPL",
    "gn:name":"El Aguacate",
    "gn:population":0,
    "gn:timezone":"America/Tegucigalpa",
    "iso:country":"HN",
    "wof:name":"El Aguacate",
    "wof:placetype":"locality"
},
  "geometry": {"coordinates":[-88.38333,14.78333],"type":"Point"}
}