{
  "type": "Feature",
  "properties": {
    "gn:admin1_code":"02",
    "gn:asciiname":"La Angostura",
    "gn:country_code":"HN",
    "gn:dem":425,
    "gn:feature_class":"P",
    "gn:feature_code":"PPL",
    "gn:name":"La Angostura",
    "gn:population":0,
    "gn:timezone":"America/Tegucigalpa",
    "iso:country":"HN",
    "name:ceb_x_preferred":[
        "La Angostura"
    ],
    "name:deu_x_preferred":[
        "La Angostura"
    ],
    "name:spa_x_preferred":[
        "La Angostura"
    ],
    "name:srp_x_preferred":[
        "\u041b\u0430 \u0410\u043d\u0433\u043e\u0441\u0442\u0443\u0440\u0430"
    ],
    "name:swe_x_preferred":[
        "La Angostura"
    ],
    "wof:name":"La Angostura",
    "wof:placetype":"locality"
},
  "geometry": {"coordinates":[-87.24028,13.60139],"type":"Point"}
}