{
  "type": "Feature",
  "properties": {
    "gn:admin1_code":"08",
    "gn:asciiname":"La Ceibita",
    "gn:cc2":"HN",
    "gn:country_code":"HN",
    "gn:dem":953,
    "gn:feature_class":"P",
    "gn:feature_code":"PPL",
    "gn:name":"La Ceibita",
    "gn:population":0,
    "gn:timezone":"America/Tegucigalpa",
    "iso:country":"HN",
    "name:und_x_variant":[
        "Ceibita",
        "La Ceibita"
    ],
    "wof:name":"La Ceibita",
    "wof:placetype":"locality"
},
  "geometry": {"coordinates":[-86.76666999999998,14.45],"type":"Point"}
}