{
  "type": "Feature",
  "properties": {
    "gn:admin1_code":"02",
    "gn:asciiname":"El Capulin",
    "gn:country_code":"HN",
    "gn:dem":80,
    "gn:feature_class":"P",
    "gn:feature_code":"PPL",
    "gn:name":"El Capul\u00edn",
    "gn:population":0,
    "gn:timezone":"America/Tegucigalpa",
    "iso:country":"HN",
    "wof:name":"El Capulin",
    "wof:placetype":"locality"
},
  "geometry": {"coordinates":[-87.19389,13.38028],"type":"Point"}
}