{
  "type": "Feature",
  "properties": {
    "gn:admin1_code":"12",
    "gn:asciiname":"Los Patios",
    "gn:country_code":"HN",
    "gn:dem":1899,
    "gn:feature_class":"P",
    "gn:feature_code":"PPL",
    "gn:name":"Los Patios",
    "gn:population":0,
    "gn:timezone":"America/Tegucigalpa",
    "iso:country":"HN",
    "name:deu_x_preferred":[
        "Los Patios"
    ],
    "name:fas_x_preferred":[
        "\u0644\u0648\u0633 \u067e\u0627\u062a\u06cc\u0648\u0633"
    ],
    "name:fra_x_preferred":[
        "Los Patios"
    ],
    "name:ita_x_preferred":[
        "Los Patios"
    ],
    "name:kat_x_preferred":[
        "\u10da\u10dd\u10e1-\u10de\u10d0\u10e2\u10d8\u10dd\u10e1\u10d8"
    ],
    "name:msa_x_preferred":[
        "Los Patios"
    ],
    "name:nld_x_preferred":[
        "Los Patios"
    ],
    "name:por_x_preferred":[
        "Los Patios"
    ],
    "name:spa_x_preferred":[
        "Los Patios"
    ],
    "name:tgl_x_preferred":[
        "Los Patios"
    ],
    "name:vie_x_preferred":[
        "Los Patios"
    ],
    "name:war_x_preferred":[
        "Los Patios"
    ],
    "name:zho_x_preferred":[
        "\u6d1b\u65af\u5e15\u8482\u5967\u65af"
    ],
    "wof:name":"Los Patios",
    "wof:placetype":"locality"
},
  "geometry": {"coordinates":[-88.08333,14.03333],"type":"Point"}
}