{
  "type": "Feature",
  "properties": {
    "gn:admin1_code":"17",
    "gn:asciiname":"Las Cuevitas",
    "gn:cc2":"HN",
    "gn:country_code":"HN",
    "gn:dem":137,
    "gn:feature_class":"P",
    "gn:feature_code":"PPL",
    "gn:name":"Las Cuevitas",
    "gn:population":0,
    "gn:timezone":"America/Tegucigalpa",
    "iso:country":"HN",
    "name:und_x_variant":[
        "Cuevitas",
        "Las Cuevitas"
    ],
    "wof:name":"Las Cuevitas",
    "wof:placetype":"locality"
},
  "geometry": {"coordinates":[-87.56416999999998,13.6525],"type":"Point"}
}