{
  "type": "Feature",
  "properties": {
    "gn:admin1_code":"09",
    "gn:asciiname":"Piankira",
    "gn:country_code":"HN",
    "gn:dem":8,
    "gn:feature_class":"P",
    "gn:feature_code":"PPL",
    "gn:name":"Piankira",
    "gn:population":0,
    "gn:timezone":"America/Tegucigalpa",
    "iso:country":"HN",
    "wof:name":"Piankira",
    "wof:placetype":"locality"
},
  "geometry": {"coordinates":[-83.51666999999998,14.98333],"type":"Point"}
}