{
  "type": "Feature",
  "properties": {
    "gn:admin1_code":"09",
    "gn:asciiname":"Kaski",
    "gn:cc2":"HN",
    "gn:country_code":"HN",
    "gn:dem":7,
    "gn:feature_class":"P",
    "gn:feature_code":"PPL",
    "gn:name":"Kask\u00ed",
    "gn:population":0,
    "gn:timezone":"America/Tegucigalpa",
    "iso:country":"HN",
    "name:und_x_variant":[
        "Katsk\u00ed",
        "Kask\u00ed"
    ],
    "wof:name":"Kaski",
    "wof:placetype":"locality"
},
  "geometry": {"coordinates":[-83.68333,15.36667],"type":"Point"}
}