{
  "type": "Feature",
  "properties": {
    "gn:admin1_code":"03",
    "gn:asciiname":"Rigores",
    "gn:country_code":"HN",
    "gn:dem":52,
    "gn:feature_class":"P",
    "gn:feature_code":"PPL",
    "gn:name":"Rigores",
    "gn:population":0,
    "gn:timezone":"America/Tegucigalpa",
    "iso:country":"HN",
    "wof:name":"Rigores",
    "wof:placetype":"locality"
},
  "geometry": {"coordinates":[-86.08226999999999,15.71041],"type":"Point"}
}