{
  "type": "Feature",
  "properties": {
    "gn:admin1_code":"03",
    "gn:asciiname":"Playa Domingo",
    "gn:country_code":"HN",
    "gn:dem":18,
    "gn:feature_class":"P",
    "gn:feature_code":"PPL",
    "gn:name":"Playa Domingo",
    "gn:population":0,
    "gn:timezone":"America/Tegucigalpa",
    "iso:country":"HN",
    "wof:name":"Playa Domingo",
    "wof:placetype":"locality"
},
  "geometry": {"coordinates":[-85.06667,15.86667],"type":"Point"}
}