{
  "type": "Feature",
  "properties": {
    "gn:admin1_code":"13",
    "gn:asciiname":"Motica",
    "gn:country_code":"HN",
    "gn:dem":558,
    "gn:feature_class":"P",
    "gn:feature_code":"PPL",
    "gn:name":"Motica",
    "gn:population":0,
    "gn:timezone":"America/Tegucigalpa",
    "iso:country":"HN",
    "wof:name":"Motica",
    "wof:placetype":"locality"
},
  "geometry": {"coordinates":[-88.38333,13.95],"type":"Point"}
}