{
  "type": "Feature",
  "properties": {
    "gn:admin1_code":"08",
    "gn:asciiname":"Coror",
    "gn:cc2":"HN",
    "gn:country_code":"HN",
    "gn:dem":1572,
    "gn:feature_class":"P",
    "gn:feature_code":"PPL",
    "gn:name":"Coror",
    "gn:population":0,
    "gn:timezone":"America/Tegucigalpa",
    "iso:country":"HN",
    "name:und_x_variant":[
        "Caror",
        "El Cororo",
        "Coror"
    ],
    "wof:name":"Coror",
    "wof:placetype":"locality"
},
  "geometry": {"coordinates":[-87.33194,13.94028],"type":"Point"}
}