{
  "type": "Feature",
  "properties": {
    "gn:admin1_code":"09",
    "gn:asciiname":"Leimus",
    "gn:cc2":"HN",
    "gn:country_code":"HN",
    "gn:dem":50,
    "gn:feature_class":"P",
    "gn:feature_code":"PPL",
    "gn:name":"Leimus",
    "gn:population":0,
    "gn:timezone":"America/Tegucigalpa",
    "iso:country":"HN",
    "name:und_x_variant":[
        "Laimus",
        "Lemus",
        "Leimus"
    ],
    "wof:name":"Leimus",
    "wof:placetype":"locality"
},
  "geometry": {"coordinates":[-84.08333,14.71667],"type":"Point"}
}