{
  "type": "Feature",
  "properties": {
    "gn:admin1_code":"08",
    "gn:asciiname":"El Chupadero",
    "gn:country_code":"HN",
    "gn:dem":372,
    "gn:feature_class":"P",
    "gn:feature_code":"PPL",
    "gn:name":"El Chupadero",
    "gn:population":0,
    "gn:timezone":"America/Tegucigalpa",
    "iso:country":"HN",
    "wof:name":"El Chupadero",
    "wof:placetype":"locality"
},
  "geometry": {"coordinates":[-87.55,13.78333],"type":"Point"}
}