{
  "type": "Feature",
  "properties": {
    "gn:admin1_code":"17",
    "gn:asciiname":"El Chaparral",
    "gn:country_code":"HN",
    "gn:dem":47,
    "gn:feature_class":"P",
    "gn:feature_code":"PPL",
    "gn:name":"El Chaparral",
    "gn:population":0,
    "gn:timezone":"America/Tegucigalpa",
    "iso:country":"HN",
    "name:spa_x_preferred":[
        "El Chaparral"
    ],
    "wof:name":"El Chaparral",
    "wof:placetype":"locality"
},
  "geometry": {"coordinates":[-87.43333,13.55],"type":"Point"}
}