{
  "type": "Feature",
  "properties": {
    "gn:admin1_code":"16",
    "gn:asciiname":"Las Trojes",
    "gn:country_code":"HN",
    "gn:dem":358,
    "gn:feature_class":"P",
    "gn:feature_code":"PPL",
    "gn:name":"Las Trojes",
    "gn:population":0,
    "gn:timezone":"America/Tegucigalpa",
    "iso:country":"HN",
    "wof:name":"Las Trojes",
    "wof:placetype":"locality"
},
  "geometry": {"coordinates":[-88.26666999999998,15.05],"type":"Point"}
}