{
  "type": "Feature",
  "properties": {
    "gn:admin1_code":"07",
    "gn:asciiname":"El Castillo",
    "gn:country_code":"HN",
    "gn:dem":1243,
    "gn:feature_class":"P",
    "gn:feature_code":"PPL",
    "gn:name":"El Castillo",
    "gn:population":0,
    "gn:timezone":"America/Tegucigalpa",
    "iso:country":"HN",
    "name:ceb_x_preferred":[
        "El Castillo"
    ],
    "name:deu_x_preferred":[
        "El Castillo"
    ],
    "name:ita_x_preferred":[
        "El Castillo"
    ],
    "name:nld_x_preferred":[
        "El Castillo"
    ],
    "name:pol_x_preferred":[
        "El Castillo"
    ],
    "name:spa_x_preferred":[
        "El Castillo"
    ],
    "name:swe_x_preferred":[
        "El Castillo"
    ],
    "name:vie_x_preferred":[
        "El Castillo"
    ],
    "wof:name":"El Castillo",
    "wof:placetype":"locality"
},
  "geometry": {"coordinates":[-86.51666999999998,13.81667],"type":"Point"}
}