{
  "type": "Feature",
  "properties": {
    "gn:admin1_code":"10",
    "gn:asciiname":"San Marcos",
    "gn:country_code":"HN",
    "gn:dem":320,
    "gn:feature_class":"P",
    "gn:feature_code":"PPL",
    "gn:name":"San Marcos",
    "gn:population":0,
    "gn:timezone":"America/Tegucigalpa",
    "iso:country":"HN",
    "wof:name":"San Marcos",
    "wof:placetype":"locality"
},
  "geometry": {"coordinates":[-88.23333000000002,13.88333],"type":"Point"}
}