{
  "type": "Feature",
  "properties": {
    "gn:admin1_code":"01",
    "gn:asciiname":"Lombardia",
    "gn:country_code":"HN",
    "gn:dem":691,
    "gn:feature_class":"P",
    "gn:feature_code":"PPL",
    "gn:name":"Lombardia",
    "gn:population":0,
    "gn:timezone":"America/Tegucigalpa",
    "iso:country":"HN",
    "wof:name":"Lombardia",
    "wof:placetype":"locality"
},
  "geometry": {"coordinates":[-87.28333000000001,15.56667],"type":"Point"}
}