{
  "type": "Feature",
  "properties": {
    "iso:country":"HN",
    "name:eng_x_preferred":[
        "Protecci\u00f3n"
    ],
    "name:fra_x_preferred":[
        "Protecci\u00f3n"
    ],
    "name:ita_x_preferred":[
        "Protecci\u00f3n"
    ],
    "name:nld_x_preferred":[
        "Protecci\u00f3n"
    ],
    "name:por_x_preferred":[
        "Protecci\u00f3n"
    ],
    "name:spa_x_preferred":[
        "Protecci\u00f3n"
    ],
    "name:swe_x_preferred":[
        "Protecci\u00f3n"
    ],
    "name:zho_x_preferred":[
        "\u666e\u7f85\u7279\u514b\u897f\u7fc1"
    ],
    "qs:gn_country":"HN",
    "qs:gn_fcode":"PPL",
    "qs:gn_pop":2101,
    "qs:name":"Protecci\u00f3n",
    "qs:name_adm0":"Honduras",
    "qs:name_adm1":"Santa B\u00e1rbara",
    "qs:photos":0,
    "qs:photos_1k":0,
    "qs:photos_9k":1,
    "qs:photos_9r":1,
    "qs:photos_all":1,
    "qs:photos_sr":0,
    "qs:placetype":"Town",
    "qs:pop_sr":"4",
    "qs:woe_adm0":23424841,
    "wof:name":"Protecci\u00f3n",
    "wof:placetype":"locality",
    "wof:population":2101
},
  "geometry": {"coordinates":[-88.65000000000001,15.03333],"type":"Point"}
}