{
  "type": "Feature",
  "properties": {
    "gn:admin1_code":"08",
    "gn:asciiname":"Emituca",
    "gn:country_code":"HN",
    "gn:dem":682,
    "gn:feature_class":"P",
    "gn:feature_code":"PPL",
    "gn:name":"Emituca",
    "gn:population":0,
    "gn:timezone":"America/Tegucigalpa",
    "iso:country":"HN",
    "wof:name":"Emituca",
    "wof:placetype":"locality"
},
  "geometry": {"coordinates":[-87.56555999999998,13.79611],"type":"Point"}
}