{
  "type": "Feature",
  "properties": {
    "gn:admin1_code":"12",
    "gn:asciiname":"Las Moras",
    "gn:cc2":"HN",
    "gn:country_code":"HN",
    "gn:dem":1866,
    "gn:feature_class":"P",
    "gn:feature_code":"PPL",
    "gn:name":"Las Moras",
    "gn:population":0,
    "gn:timezone":"America/Tegucigalpa",
    "iso:country":"HN",
    "name:und_x_variant":[
        "Moras",
        "Las Moras"
    ],
    "wof:name":"Las Moras",
    "wof:placetype":"locality"
},
  "geometry": {"coordinates":[-87.81667,14.13333],"type":"Point"}
}