{
  "type": "Feature",
  "properties": {
    "gn:admin1_code":"17",
    "gn:asciiname":"Campamento",
    "gn:country_code":"HN",
    "gn:dem":8,
    "gn:feature_class":"P",
    "gn:feature_code":"PPL",
    "gn:name":"Campamento",
    "gn:population":0,
    "gn:timezone":"America/Tegucigalpa",
    "iso:country":"HN",
    "name:ceb_x_preferred":[
        "Campamento"
    ],
    "name:deu_x_preferred":[
        "Campamento"
    ],
    "name:fra_x_preferred":[
        "Campamento"
    ],
    "name:ita_x_preferred":[
        "Campamento"
    ],
    "name:nld_x_preferred":[
        "Campamento"
    ],
    "name:por_x_preferred":[
        "Campamento"
    ],
    "name:spa_x_preferred":[
        "Campamento"
    ],
    "name:swe_x_preferred":[
        "Campamento"
    ],
    "wof:name":"Campamento",
    "wof:placetype":"locality"
},
  "geometry": {"coordinates":[-87.56278,13.41167],"type":"Point"}
}