{
  "type": "Feature",
  "properties": {
    "gn:country":"HN",
    "gn:fcode":"PPL",
    "gn:pop":900,
    "iso:country":"HN",
    "qs:name":"Potrerillos",
    "qs:photos_9r":0,
    "qs:photos_sr":0,
    "qs:pop_sr":"2",
    "wd:wordcount":65,
    "wof:name":"Potrerillos",
    "wof:placetype":"locality",
    "wof:population":900
},
  "geometry": {"coordinates":[-88.43333,15.26667],"type":"Point"}
}