{
  "type": "Feature",
  "properties": {
    "gn:admin1_code":"02",
    "gn:asciiname":"La Puerta",
    "gn:cc2":"HN",
    "gn:country_code":"HN",
    "gn:dem":1234,
    "gn:feature_class":"P",
    "gn:feature_code":"PPL",
    "gn:name":"La Puerta",
    "gn:population":0,
    "gn:timezone":"America/Tegucigalpa",
    "iso:country":"HN",
    "name:und_x_variant":[
        "Puerta",
        "La Puerta"
    ],
    "wof:name":"La Puerta",
    "wof:placetype":"locality"
},
  "geometry": {"coordinates":[-86.88333,13.43333],"type":"Point"}
}