{
  "type": "Feature",
  "properties": {
    "gn:admin1_code":"13",
    "gn:asciiname":"El Arrayan",
    "gn:country_code":"HN",
    "gn:dem":1218,
    "gn:feature_class":"P",
    "gn:feature_code":"PPL",
    "gn:name":"El Array\u00e1n",
    "gn:population":0,
    "gn:timezone":"America/Tegucigalpa",
    "iso:country":"HN",
    "wof:name":"El Arrayan",
    "wof:placetype":"locality"
},
  "geometry": {"coordinates":[-88.41667,14.23333],"type":"Point"}
}