{
  "type": "Feature",
  "properties": {
    "gn:admin1_code":"05",
    "gn:asciiname":"Loma Encerrada",
    "gn:country_code":"HN",
    "gn:dem":1087,
    "gn:feature_class":"P",
    "gn:feature_code":"PPL",
    "gn:name":"Loma Encerrada",
    "gn:population":0,
    "gn:timezone":"America/Tegucigalpa",
    "iso:country":"HN",
    "wof:name":"Loma Encerrada",
    "wof:placetype":"locality"
},
  "geometry": {"coordinates":[-88.78333000000001,14.78333],"type":"Point"}
}