{
  "type": "Feature",
  "properties": {
    "gn:admin1_code":"08",
    "gn:asciiname":"La Arena",
    "gn:country_code":"HN",
    "gn:dem":1544,
    "gn:feature_class":"P",
    "gn:feature_code":"PPL",
    "gn:name":"La Arena",
    "gn:population":0,
    "gn:timezone":"America/Tegucigalpa",
    "iso:country":"HN",
    "wof:name":"La Arena",
    "wof:placetype":"locality"
},
  "geometry": {"coordinates":[-87.32805999999999,13.92444],"type":"Point"}
}