{
  "type": "Feature",
  "properties": {
    "gn:admin1_code":"13",
    "gn:asciiname":"Plan del Ocotal",
    "gn:cc2":"HN",
    "gn:country_code":"HN",
    "gn:dem":898,
    "gn:feature_class":"P",
    "gn:feature_code":"PPL",
    "gn:name":"Plan del Ocotal",
    "gn:population":0,
    "gn:timezone":"America/Tegucigalpa",
    "iso:country":"HN",
    "name:und_x_variant":[
        "El Plan del Ocotal",
        "Plan del Ocotal"
    ],
    "wof:name":"Plan del Ocotal",
    "wof:placetype":"locality"
},
  "geometry": {"coordinates":[-88.63333,14.85],"type":"Point"}
}