{
  "type": "Feature",
  "properties": {
    "gn:admin1_code":"15",
    "gn:asciiname":"Quiscamote",
    "gn:country_code":"HN",
    "gn:dem":788,
    "gn:feature_class":"P",
    "gn:feature_code":"PPL",
    "gn:name":"Quiscamote",
    "gn:population":0,
    "gn:timezone":"America/Tegucigalpa",
    "iso:country":"HN",
    "wof:name":"Quiscamote",
    "wof:placetype":"locality"
},
  "geometry": {"coordinates":[-86.68333,14.93333],"type":"Point"}
}