{
  "type": "Feature",
  "properties": {
    "gn:admin1_code":"04",
    "gn:asciiname":"El Ojo de Agua",
    "gn:cc2":"HN",
    "gn:country_code":"HN",
    "gn:dem":1109,
    "gn:feature_class":"P",
    "gn:feature_code":"PPL",
    "gn:name":"El Ojo de Agua",
    "gn:population":0,
    "gn:timezone":"America/Tegucigalpa",
    "iso:country":"HN",
    "name:und_x_variant":[
        "Ojo de Agua",
        "El Ojo de Agua"
    ],
    "wof:name":"El Ojo de Agua",
    "wof:placetype":"locality"
},
  "geometry": {"coordinates":[-87.58333,14.15],"type":"Point"}
}