{
  "type": "Feature",
  "properties": {
    "gn:admin1_code":"13",
    "gn:asciiname":"Casitas",
    "gn:cc2":"HN",
    "gn:country_code":"HN",
    "gn:dem":740,
    "gn:feature_class":"P",
    "gn:feature_code":"PPL",
    "gn:name":"Casitas",
    "gn:population":0,
    "gn:timezone":"America/Tegucigalpa",
    "iso:country":"HN",
    "name:und_x_variant":[
        "Las Casitas",
        "Casitas"
    ],
    "wof:name":"Casitas",
    "wof:placetype":"locality"
},
  "geometry": {"coordinates":[-88.95,14.25],"type":"Point"}
}