{
  "type": "Feature",
  "properties": {
    "gn:admin1_code":"11",
    "gn:asciiname":"Man of War Cay",
    "gn:country_code":"HN",
    "gn:dem":1,
    "gn:feature_class":"P",
    "gn:feature_code":"PPL",
    "gn:name":"Man of War Cay",
    "gn:population":0,
    "gn:timezone":"America/Tegucigalpa",
    "iso:country":"HN",
    "wof:name":"Man of War Cay",
    "wof:placetype":"locality"
},
  "geometry": {"coordinates":[-86.56667,16.35],"type":"Point"}
}