{
  "type": "Feature",
  "properties": {
    "iso:country":"HN",
    "name:ceb_x_preferred":[
        "La S\u00e1bana"
    ],
    "name:spa_x_preferred":[
        "La Sabana"
    ],
    "name:urd_x_preferred":[
        "\u0644\u0627 \u0633\u0627\u0628\u0627\u0646\u0627"
    ],
    "qs:gn_country":"HN",
    "qs:gn_fcode":"PPL",
    "qs:gn_pop":1524,
    "qs:name":"La Sabana",
    "qs:name_adm0":"Honduras",
    "qs:name_adm1":"Santa B\u00e1rbara",
    "qs:photos":0,
    "qs:photos_1k":0,
    "qs:photos_9k":0,
    "qs:photos_9r":0,
    "qs:photos_all":0,
    "qs:photos_sr":0,
    "qs:placetype":"Town",
    "qs:pop_sr":"3",
    "qs:woe_adm0":23424841,
    "wd:wordcount":34,
    "wof:name":"La Sabana",
    "wof:placetype":"locality",
    "wof:population":1524
},
  "geometry": {"coordinates":[-87.93333,15.36667],"type":"Point"}
}