{
  "type": "Feature",
  "properties": {
    "gn:admin1_code":"07",
    "gn:asciiname":"Los Guasimos",
    "gn:country_code":"HN",
    "gn:dem":576,
    "gn:feature_class":"P",
    "gn:feature_code":"PPL",
    "gn:name":"Los Gu\u00e1simos",
    "gn:population":0,
    "gn:timezone":"America/Tegucigalpa",
    "iso:country":"HN",
    "wof:name":"Los Guasimos",
    "wof:placetype":"locality"
},
  "geometry": {"coordinates":[-86.43333,13.91667],"type":"Point"}
}