{
  "type": "Feature",
  "properties": {
    "gn:admin1_code":"17",
    "gn:asciiname":"Juancho",
    "gn:country_code":"HN",
    "gn:dem":49,
    "gn:feature_class":"P",
    "gn:feature_code":"PPL",
    "gn:name":"Juancho",
    "gn:population":0,
    "gn:timezone":"America/Tegucigalpa",
    "iso:country":"HN",
    "name:ceb_x_preferred":[
        "Juancho"
    ],
    "name:swe_x_preferred":[
        "Juancho"
    ],
    "wof:name":"Juancho",
    "wof:placetype":"locality"
},
  "geometry": {"coordinates":[-87.59,13.55389],"type":"Point"}
}