{
  "type": "Feature",
  "properties": {
    "gn:admin1_code":"12",
    "gn:asciiname":"Togola",
    "gn:country_code":"HN",
    "gn:dem":1809,
    "gn:feature_class":"P",
    "gn:feature_code":"PPL",
    "gn:name":"Togola",
    "gn:population":0,
    "gn:timezone":"America/Tegucigalpa",
    "iso:country":"HN",
    "wof:name":"Togola",
    "wof:placetype":"locality"
},
  "geometry": {"coordinates":[-88.09999999999999,14.03333],"type":"Point"}
}