{
  "type": "Feature",
  "properties": {
    "gn:admin1_code":"08",
    "gn:asciiname":"El Terrero",
    "gn:cc2":"HN",
    "gn:country_code":"HN",
    "gn:dem":1155,
    "gn:feature_class":"P",
    "gn:feature_code":"PPL",
    "gn:name":"El Terrero",
    "gn:population":0,
    "gn:timezone":"America/Tegucigalpa",
    "iso:country":"HN",
    "name:und_x_variant":[
        "El Terro",
        "El Terrero"
    ],
    "wof:name":"El Terrero",
    "wof:placetype":"locality"
},
  "geometry": {"coordinates":[-87.17806,13.83194],"type":"Point"}
}