{
  "type": "Feature",
  "properties": {
    "gn:admin1_code":"10",
    "gn:asciiname":"Cerro Coyote",
    "gn:country_code":"HN",
    "gn:dem":2084,
    "gn:feature_class":"P",
    "gn:feature_code":"PPL",
    "gn:name":"Cerro Coyote",
    "gn:population":0,
    "gn:timezone":"America/Tegucigalpa",
    "iso:country":"HN",
    "wof:name":"Cerro Coyote",
    "wof:placetype":"locality"
},
  "geometry": {"coordinates":[-88.25,14.33333],"type":"Point"}
}