{
  "type": "Feature",
  "properties": {
    "gn:admin1_code":"12",
    "gn:asciiname":"La Crucita",
    "gn:country_code":"HN",
    "gn:dem":1465,
    "gn:feature_class":"P",
    "gn:feature_code":"PPL",
    "gn:name":"La Crucita",
    "gn:population":0,
    "gn:timezone":"America/Tegucigalpa",
    "iso:country":"HN",
    "wof:name":"La Crucita",
    "wof:placetype":"locality"
},
  "geometry": {"coordinates":[-87.84999999999999,14.06667],"type":"Point"}
}