{
  "type": "Feature",
  "properties": {
    "iso:country":"HN",
    "name:eng_x_preferred":[
        "Texiguat"
    ],
    "name:fra_x_preferred":[
        "Texiguat"
    ],
    "name:ita_x_preferred":[
        "Texiguat"
    ],
    "name:nld_x_preferred":[
        "Texiguat"
    ],
    "name:pol_x_preferred":[
        "Texiguat"
    ],
    "name:por_x_preferred":[
        "Texiguat"
    ],
    "name:spa_x_preferred":[
        "Texiguat"
    ],
    "name:swe_x_preferred":[
        "Tex\u00edguat"
    ],
    "name:zho_x_preferred":[
        "\u7279\u514b\u897f\u74dc\u7279"
    ],
    "qs:gn_country":"HN",
    "qs:gn_fcode":"PPL",
    "qs:gn_pop":1012,
    "qs:name":"Tex\u00edguat",
    "qs:name_adm0":"Honduras",
    "qs:name_adm1":"El Para\u00edso",
    "qs:photos":0,
    "qs:photos_1k":0,
    "qs:photos_9k":1,
    "qs:photos_9r":1,
    "qs:photos_all":1,
    "qs:photos_sr":0,
    "qs:placetype":"Town",
    "qs:pop_sr":"3",
    "qs:woe_adm0":23424841,
    "wof:name":"Tex\u00edguat",
    "wof:placetype":"locality",
    "wof:population":1012
},
  "geometry": {"coordinates":[-87.02249999999999,13.64972],"type":"Point"}
}