{
  "type": "Feature",
  "properties": {
    "gn:admin1_code":"05",
    "gn:asciiname":"El Pinalito",
    "gn:cc2":"HN",
    "gn:country_code":"HN",
    "gn:dem":800,
    "gn:feature_class":"P",
    "gn:feature_code":"PPL",
    "gn:name":"El Pinalito",
    "gn:population":0,
    "gn:timezone":"America/Tegucigalpa",
    "iso:country":"HN",
    "name:und_x_variant":[
        "Pinalito",
        "El Pinalito"
    ],
    "wof:name":"El Pinalito",
    "wof:placetype":"locality"
},
  "geometry": {"coordinates":[-89.08333,14.81667],"type":"Point"}
}