{
  "type": "Feature",
  "properties": {
    "gn:admin1_code":"11",
    "gn:asciiname":"Arrozal",
    "gn:cc2":"HN",
    "gn:country_code":"HN",
    "gn:dem":23,
    "gn:feature_class":"P",
    "gn:feature_code":"PPL",
    "gn:name":"Arrozal",
    "gn:population":0,
    "gn:timezone":"America/Tegucigalpa",
    "iso:country":"HN",
    "name:und_x_variant":[
        "Arrosal",
        "Arrozal"
    ],
    "wof:name":"Arrozal",
    "wof:placetype":"locality"
},
  "geometry": {"coordinates":[-86.38333,16.38332999999999],"type":"Point"}
}