{
  "type": "Feature",
  "properties": {
    "gn:admin1_code":"04",
    "gn:asciiname":"Terreritos",
    "gn:cc2":"HN",
    "gn:country_code":"HN",
    "gn:dem":731,
    "gn:feature_class":"P",
    "gn:feature_code":"PPL",
    "gn:name":"Terreritos",
    "gn:population":0,
    "gn:timezone":"America/Tegucigalpa",
    "iso:country":"HN",
    "name:und_x_variant":[
        "El Terreritos",
        "Terreritos (1)",
        "Territos",
        "Terreritos"
    ],
    "wof:name":"Terreritos",
    "wof:placetype":"locality"
},
  "geometry": {"coordinates":[-87.31667,14.83333],"type":"Point"}
}