{
  "type": "Feature",
  "properties": {
    "gn:admin1_code":"13",
    "gn:asciiname":"Caiquin",
    "gn:country_code":"HN",
    "gn:dem":1326,
    "gn:feature_class":"P",
    "gn:feature_code":"PPL",
    "gn:name":"Caiqu\u00edn",
    "gn:population":0,
    "gn:timezone":"America/Tegucigalpa",
    "iso:country":"HN",
    "wof:name":"Caiquin",
    "wof:placetype":"locality"
},
  "geometry": {"coordinates":[-88.59999999999999,14.41667],"type":"Point"}
}