{
  "type": "Feature",
  "properties": {
    "gn:admin1_code":"17",
    "gn:asciiname":"Hacienda Vieja",
    "gn:country_code":"HN",
    "gn:dem":48,
    "gn:feature_class":"P",
    "gn:feature_code":"PPL",
    "gn:name":"Hacienda Vieja",
    "gn:population":0,
    "gn:timezone":"America/Tegucigalpa",
    "iso:country":"HN",
    "wof:name":"Hacienda Vieja",
    "wof:placetype":"locality"
},
  "geometry": {"coordinates":[-87.45389,13.54722],"type":"Point"}
}