{
  "type": "Feature",
  "properties": {
    "gn:admin1_code":"07",
    "gn:asciiname":"Comelias",
    "gn:country_code":"HN",
    "gn:dem":866,
    "gn:feature_class":"P",
    "gn:feature_code":"PPL",
    "gn:name":"Comelias",
    "gn:population":0,
    "gn:timezone":"America/Tegucigalpa",
    "iso:country":"HN",
    "wof:name":"Comelias",
    "wof:placetype":"locality"
},
  "geometry": {"coordinates":[-86.15000000000001,14.05],"type":"Point"}
}