{
  "type": "Feature",
  "properties": {
    "gn:admin1_code":"02",
    "gn:asciiname":"Hacienda El Jicaro",
    "gn:country_code":"HN",
    "gn:dem":10,
    "gn:feature_class":"P",
    "gn:feature_code":"PPL",
    "gn:name":"Hacienda El J\u00edcaro",
    "gn:population":0,
    "gn:timezone":"America/Tegucigalpa",
    "iso:country":"HN",
    "wof:name":"Hacienda El Jicaro",
    "wof:placetype":"locality"
},
  "geometry": {"coordinates":[-87.44360999999998,13.27139],"type":"Point"}
}