{
  "type": "Feature",
  "properties": {
    "gn:country":"HN",
    "gn:fcode":"PPL",
    "gn:pop":1075,
    "iso:country":"HN",
    "name:bre_x_preferred":[
        "Agua Caliente"
    ],
    "name:cat_x_preferred":[
        "Agua Caliente"
    ],
    "name:ceb_x_preferred":[
        "Agua Caliente"
    ],
    "name:deu_x_preferred":[
        "Agua Caliente"
    ],
    "name:eng_x_preferred":[
        "Agua Caliente"
    ],
    "name:epo_x_preferred":[
        "Agua Caliente"
    ],
    "name:fra_x_preferred":[
        "Agua Caliente"
    ],
    "name:glg_x_preferred":[
        "Agua Caliente"
    ],
    "name:ita_x_preferred":[
        "Agua Caliente"
    ],
    "name:nld_x_preferred":[
        "Agua Caliente"
    ],
    "name:por_x_preferred":[
        "Agua Caliente"
    ],
    "name:sme_x_preferred":[
        "Nueva Jalapa"
    ],
    "name:spa_x_preferred":[
        "Agua Caliente"
    ],
    "name:swe_x_preferred":[
        "Agua_Caliente"
    ],
    "qs:name":"Agua Caliente",
    "qs:photos_9r":0,
    "qs:photos_sr":0,
    "qs:pop_sr":"3",
    "wd:wordcount":218,
    "wof:name":"Agua Caliente",
    "wof:placetype":"locality",
    "wof:population":1075
},
  "geometry": {"coordinates":[-88.81667,14.88333],"type":"Point"}
}