{
  "type": "Feature",
  "properties": {
    "gn:admin1_code":"13",
    "gn:asciiname":"La Cuesta",
    "gn:country_code":"HN",
    "gn:dem":381,
    "gn:feature_class":"P",
    "gn:feature_code":"PPL",
    "gn:name":"La Cuesta",
    "gn:population":0,
    "gn:timezone":"America/Tegucigalpa",
    "iso:country":"HN",
    "wof:name":"La Cuesta",
    "wof:placetype":"locality"
},
  "geometry": {"coordinates":[-88.71666999999999,14.06667],"type":"Point"}
}