{
  "type": "Feature",
  "properties": {
    "gn:admin1_code":"15",
    "gn:asciiname":"El Tunal",
    "gn:country_code":"HN",
    "gn:dem":551,
    "gn:feature_class":"P",
    "gn:feature_code":"PPL",
    "gn:name":"El Tunal",
    "gn:population":0,
    "gn:timezone":"America/Tegucigalpa",
    "iso:country":"HN",
    "name:spa_x_preferred":[
        "El Tunal"
    ],
    "wof:name":"El Tunal",
    "wof:placetype":"locality"
},
  "geometry": {"coordinates":[-86.34999999999999,14.85],"type":"Point"}
}