{
  "type": "Feature",
  "properties": {
    "gn:admin1_code":"07",
    "gn:asciiname":"El Nacascolo",
    "gn:country_code":"HN",
    "gn:dem":458,
    "gn:feature_class":"P",
    "gn:feature_code":"PPL",
    "gn:name":"El Nacascolo",
    "gn:population":0,
    "gn:timezone":"America/Tegucigalpa",
    "iso:country":"HN",
    "wof:name":"El Nacascolo",
    "wof:placetype":"locality"
},
  "geometry": {"coordinates":[-87.10778000000001,13.5775],"type":"Point"}
}