{
  "type": "Feature",
  "properties": {
    "gn:admin1_code":"08",
    "gn:asciiname":"Las Playas",
    "gn:cc2":"HN",
    "gn:country_code":"HN",
    "gn:dem":1339,
    "gn:feature_class":"P",
    "gn:feature_code":"PPL",
    "gn:name":"Las Playas",
    "gn:population":0,
    "gn:timezone":"America/Tegucigalpa",
    "iso:country":"HN",
    "name:und_x_variant":[
        "Playas",
        "Las Playas"
    ],
    "wof:name":"Las Playas",
    "wof:placetype":"locality"
},
  "geometry": {"coordinates":[-87.03333000000001,14.08333],"type":"Point"}
}