{
  "type": "Feature",
  "properties": {
    "gn:admin1_code":"09",
    "gn:asciiname":"Tasbarraya",
    "gn:country_code":"HN",
    "gn:dem":5,
    "gn:feature_class":"P",
    "gn:feature_code":"PPL",
    "gn:name":"Tasbarraya",
    "gn:population":0,
    "gn:timezone":"America/Tegucigalpa",
    "iso:country":"HN",
    "name:und_x_variant":[
        "Tasba Raya"
    ],
    "wof:name":"Tasbarraya",
    "wof:placetype":"locality"
},
  "geometry": {"coordinates":[-83.87759,15.28838],"type":"Point"}
}