{
  "type": "Feature",
  "properties": {
    "gn:admin1_code":"01",
    "gn:asciiname":"Coco Pando",
    "gn:country_code":"HN",
    "gn:dem":6,
    "gn:feature_class":"P",
    "gn:feature_code":"PPL",
    "gn:name":"Coco Pando",
    "gn:population":0,
    "gn:timezone":"America/Tegucigalpa",
    "iso:country":"HN",
    "wof:name":"Coco Pando",
    "wof:placetype":"locality"
},
  "geometry": {"coordinates":[-86.91667,15.75],"type":"Point"}
}