{
  "type": "Feature",
  "properties": {
    "gn:admin1_code":"07",
    "gn:asciiname":"Cerro Grande",
    "gn:cc2":"HN",
    "gn:country_code":"HN",
    "gn:dem":635,
    "gn:feature_class":"P",
    "gn:feature_code":"PPL",
    "gn:name":"Cerro Grande",
    "gn:population":0,
    "gn:timezone":"America/Tegucigalpa",
    "iso:country":"HN",
    "name:ceb_x_preferred":[
        "Cerro Grande"
    ],
    "name:deu_x_preferred":[
        "Cerro Grande"
    ],
    "name:spa_x_preferred":[
        "Cerro Grande"
    ],
    "name:swe_x_preferred":[
        "Cerro Grande"
    ],
    "name:und_x_variant":[
        "Cero Grande"
    ],
    "wof:name":"Cerro Grande",
    "wof:placetype":"locality"
},
  "geometry": {"coordinates":[-87.05,13.65],"type":"Point"}
}