{
  "type": "Feature",
  "properties": {
    "gn:admin1_code":"03",
    "gn:asciiname":"Orica",
    "gn:country_code":"HN",
    "gn:dem":741,
    "gn:feature_class":"P",
    "gn:feature_code":"PPL",
    "gn:name":"Orica",
    "gn:population":0,
    "gn:timezone":"America/Tegucigalpa",
    "iso:country":"HN",
    "wof:name":"Orica",
    "wof:placetype":"locality"
},
  "geometry": {"coordinates":[-86.18333,15.48333],"type":"Point"}
}