{
  "type": "Feature",
  "properties": {
    "gn:admin1_code":"03",
    "gn:asciiname":"Orica",
    "gn:country_code":"HN",
    "gn:dem":741,
    "gn:feature_class":"P",
    "gn:feature_code":"PPL",
    "gn:name":"Orica",
    "gn:population":0,
    "gn:timezone":"America/Tegucigalpa",
    "iso:country":"HN",
    "name:azb_x_preferred":[
        "\u0627\u0648\u0631\u06cc\u06a9\u0627"
    ],
    "name:dan_x_preferred":[
        "Orica"
    ],
    "name:deu_x_preferred":[
        "Orica"
    ],
    "name:fas_x_preferred":[
        "\u0627\u0648\u0631\u06cc\u06a9\u0627"
    ],
    "name:fra_x_preferred":[
        "Orica"
    ],
    "name:nld_x_preferred":[
        "Orica"
    ],
    "name:rus_x_preferred":[
        "Orica"
    ],
    "wof:name":"Orica",
    "wof:placetype":"locality"
},
  "geometry": {"coordinates":[-86.18333,15.48333],"type":"Point"}
}