{
  "type": "Feature",
  "properties": {
    "gn:admin1_code":"06",
    "gn:asciiname":"Suich de Soto",
    "gn:cc2":"HN",
    "gn:country_code":"HN",
    "gn:dem":15,
    "gn:feature_class":"P",
    "gn:feature_code":"PPL",
    "gn:name":"Suich de Soto",
    "gn:population":0,
    "gn:timezone":"America/Tegucigalpa",
    "iso:country":"HN",
    "name:und_x_variant":[
        "Soto",
        "Suich de Soto"
    ],
    "wof:name":"Suich de Soto",
    "wof:placetype":"locality"
},
  "geometry": {"coordinates":[-87.90000000000001,15.65],"type":"Point"}
}