{
  "type": "Feature",
  "properties": {
    "gn:admin1_code":"07",
    "gn:asciiname":"El Matasano",
    "gn:cc2":"HN",
    "gn:country_code":"HN",
    "gn:dem":965,
    "gn:feature_class":"P",
    "gn:feature_code":"PPL",
    "gn:name":"El Matasano",
    "gn:population":0,
    "gn:timezone":"America/Tegucigalpa",
    "iso:country":"HN",
    "name:und_x_variant":[
        "Matazanos",
        "Los Matazanos",
        "El Matasano"
    ],
    "wof:name":"El Matasano",
    "wof:placetype":"locality"
},
  "geometry": {"coordinates":[-86.76666999999998,14.25],"type":"Point"}
}