{
  "type": "Feature",
  "properties": {
    "gn:admin1_code":"08",
    "gn:asciiname":"El Rodeo",
    "gn:country_code":"HN",
    "gn:dem":448,
    "gn:feature_class":"P",
    "gn:feature_code":"PPL",
    "gn:name":"El Rodeo",
    "gn:population":0,
    "gn:timezone":"America/Tegucigalpa",
    "iso:country":"HN",
    "wof:name":"El Rodeo",
    "wof:placetype":"locality"
},
  "geometry": {"coordinates":[-87.4875,13.8225],"type":"Point"}
}