{
  "type": "Feature",
  "properties": {
    "gn:admin1_code":"15",
    "gn:asciiname":"Puerto Delon",
    "gn:country_code":"HN",
    "gn:dem":237,
    "gn:feature_class":"P",
    "gn:feature_code":"PPL",
    "gn:name":"Puerto Del\u00f3n",
    "gn:population":0,
    "gn:timezone":"America/Tegucigalpa",
    "iso:country":"HN",
    "wof:name":"Puerto Delon",
    "wof:placetype":"locality"
},
  "geometry": {"coordinates":[-85.84999999999999,14.35],"type":"Point"}
}