{
  "type": "Feature",
  "properties": {
    "gn:admin1_code":"03",
    "gn:asciiname":"La Atascosa",
    "gn:cc2":"HN",
    "gn:country_code":"HN",
    "gn:dem":78,
    "gn:feature_class":"P",
    "gn:feature_code":"PPL",
    "gn:name":"La Atascosa",
    "gn:population":0,
    "gn:timezone":"America/Tegucigalpa",
    "iso:country":"HN",
    "name:und_x_variant":[
        "Atascosa",
        "La Atascosa"
    ],
    "wof:name":"La Atascosa",
    "wof:placetype":"locality"
},
  "geometry": {"coordinates":[-86.09999999999999,15.73333],"type":"Point"}
}