{
  "type": "Feature",
  "properties": {
    "iso:country":"HN",
    "name:ceb_x_preferred":[
        "Dolores"
    ],
    "name:eng_x_preferred":[
        "Dolores"
    ],
    "name:fra_x_preferred":[
        "Dolores"
    ],
    "name:ita_x_preferred":[
        "Dolores"
    ],
    "name:nan_x_preferred":[
        "Dolores"
    ],
    "name:nld_x_preferred":[
        "Dolores"
    ],
    "name:pol_x_preferred":[
        "Dolores"
    ],
    "name:por_x_preferred":[
        "Dolores"
    ],
    "name:spa_x_preferred":[
        "Dolores"
    ],
    "name:swe_x_preferred":[
        "Dolores"
    ],
    "name:zho_x_preferred":[
        "\u591a\u6d1b\u96f7\u65af"
    ],
    "qs:gn_country":"HN",
    "qs:gn_fcode":"PPL",
    "qs:gn_pop":1107,
    "qs:name":"Dolores",
    "qs:name_adm0":"Honduras",
    "qs:name_adm1":"Cop\u00e1n",
    "qs:photos":0,
    "qs:photos_1k":0,
    "qs:photos_9k":0,
    "qs:photos_9r":0,
    "qs:photos_all":0,
    "qs:photos_sr":0,
    "qs:placetype":"Town",
    "qs:pop_sr":"3",
    "qs:woe_adm0":23424841,
    "wd:wordcount":62,
    "wof:name":"Dolores",
    "wof:placetype":"locality",
    "wof:population":1107
},
  "geometry": {"coordinates":[-88.83333,14.86667],"type":"Point"}
}