{
  "type": "Feature",
  "properties": {
    "gn:admin1_code":"07",
    "gn:asciiname":"Las Presas",
    "gn:country_code":"HN",
    "gn:dem":581,
    "gn:feature_class":"P",
    "gn:feature_code":"PPL",
    "gn:name":"Las Presas",
    "gn:population":0,
    "gn:timezone":"America/Tegucigalpa",
    "iso:country":"HN",
    "wof:name":"Las Presas",
    "wof:placetype":"locality"
},
  "geometry": {"coordinates":[-87.03194000000001,13.52917],"type":"Point"}
}