{
  "type": "Feature",
  "properties": {
    "gn:admin1_code":"15",
    "gn:asciiname":"La Lima",
    "gn:country_code":"HN",
    "gn:dem":469,
    "gn:feature_class":"P",
    "gn:feature_code":"PPL",
    "gn:name":"La Lima",
    "gn:population":0,
    "gn:timezone":"America/Tegucigalpa",
    "iso:country":"HN",
    "name:bul_x_preferred":[
        "\u041b\u0438\u043c\u0430"
    ],
    "name:fra_x_preferred":[
        "La Lima"
    ],
    "name:ita_x_preferred":[
        "La Lima"
    ],
    "name:lit_x_preferred":[
        "La Lima"
    ],
    "name:nld_x_preferred":[
        "La Lima"
    ],
    "name:pol_x_preferred":[
        "La Lima"
    ],
    "name:por_x_preferred":[
        "La Lima"
    ],
    "name:rus_x_preferred":[
        "\u041b\u0430-\u041b\u0438\u043c\u0430"
    ],
    "name:spa_x_preferred":[
        "La Lima"
    ],
    "name:zho_x_preferred":[
        "\u62c9\u5229\u99ac"
    ],
    "wof:name":"La Lima",
    "wof:placetype":"locality"
},
  "geometry": {"coordinates":[-85.86667,15.13333],"type":"Point"}
}