{
  "type": "Feature",
  "properties": {
    "gn:admin1_code":"15",
    "gn:asciiname":"La Lima",
    "gn:country_code":"HN",
    "gn:dem":469,
    "gn:feature_class":"P",
    "gn:feature_code":"PPL",
    "gn:name":"La Lima",
    "gn:population":0,
    "gn:timezone":"America/Tegucigalpa",
    "iso:country":"HN",
    "wof:name":"La Lima",
    "wof:placetype":"locality"
},
  "geometry": {"coordinates":[-85.86667,15.13333],"type":"Point"}
}