{
  "type": "Feature",
  "properties": {
    "gn:admin1_code":"08",
    "gn:asciiname":"El Hato",
    "gn:country_code":"HN",
    "gn:dem":444,
    "gn:feature_class":"P",
    "gn:feature_code":"PPL",
    "gn:name":"El Hato",
    "gn:population":0,
    "gn:timezone":"America/Tegucigalpa",
    "iso:country":"HN",
    "name:ita_x_preferred":[
        "El Hato"
    ],
    "name:spa_x_preferred":[
        "El Hato"
    ],
    "name:zho_x_preferred":[
        "\u57c3\u723e\u963f\u6258"
    ],
    "wof:name":"El Hato",
    "wof:placetype":"locality"
},
  "geometry": {"coordinates":[-87.32139000000002,13.70806],"type":"Point"}
}