{
  "type": "Feature",
  "properties": {
    "gn:admin1_code":"08",
    "gn:asciiname":"El Hato",
    "gn:country_code":"HN",
    "gn:dem":444,
    "gn:feature_class":"P",
    "gn:feature_code":"PPL",
    "gn:name":"El Hato",
    "gn:population":0,
    "gn:timezone":"America/Tegucigalpa",
    "iso:country":"HN",
    "wof:name":"El Hato",
    "wof:placetype":"locality"
},
  "geometry": {"coordinates":[-87.32139000000002,13.70806],"type":"Point"}
}