{
  "type": "Feature",
  "properties": {
    "gn:admin1_code":"17",
    "gn:asciiname":"Portillo de La Gloria",
    "gn:country_code":"HN",
    "gn:dem":39,
    "gn:feature_class":"P",
    "gn:feature_code":"PPL",
    "gn:name":"Portillo de La Gloria",
    "gn:population":0,
    "gn:timezone":"America/Tegucigalpa",
    "iso:country":"HN",
    "wof:name":"Portillo de La Gloria",
    "wof:placetype":"locality"
},
  "geometry": {"coordinates":[-87.38778000000001,13.41833],"type":"Point"}
}