{
  "type": "Feature",
  "properties": {
    "gn:admin1_code":"05",
    "gn:asciiname":"Paso La Vaca",
    "gn:country_code":"HN",
    "gn:dem":1201,
    "gn:feature_class":"P",
    "gn:feature_code":"PPL",
    "gn:name":"Paso La Vaca",
    "gn:population":0,
    "gn:timezone":"America/Tegucigalpa",
    "iso:country":"HN",
    "wof:name":"Paso La Vaca",
    "wof:placetype":"locality"
},
  "geometry": {"coordinates":[-88.88333,14.53333],"type":"Point"}
}