{
  "type": "Feature",
  "properties": {
    "gn:admin1_code":"07",
    "gn:asciiname":"El Hatillo",
    "gn:country_code":"HN",
    "gn:dem":297,
    "gn:feature_class":"P",
    "gn:feature_code":"PPL",
    "gn:name":"El Hatillo",
    "gn:population":0,
    "gn:timezone":"America/Tegucigalpa",
    "iso:country":"HN",
    "wof:name":"El Hatillo",
    "wof:placetype":"locality"
},
  "geometry": {"coordinates":[-87.11667,13.55],"type":"Point"}
}