{
  "type": "Feature",
  "properties": {
    "gn:admin1_code":"08",
    "gn:asciiname":"Potrero Redondo",
    "gn:country_code":"HN",
    "gn:dem":960,
    "gn:feature_class":"P",
    "gn:feature_code":"PPL",
    "gn:name":"Potrero Redondo",
    "gn:population":0,
    "gn:timezone":"America/Tegucigalpa",
    "iso:country":"HN",
    "wof:name":"Potrero Redondo",
    "wof:placetype":"locality"
},
  "geometry": {"coordinates":[-87.26721999999999,13.85528],"type":"Point"}
}