{
  "type": "Feature",
  "properties": {
    "gn:admin1_code":"09",
    "gn:asciiname":"Walpata",
    "gn:country_code":"HN",
    "gn:dem":10,
    "gn:feature_class":"P",
    "gn:feature_code":"PPL",
    "gn:name":"Walpat\u00e1",
    "gn:population":0,
    "gn:timezone":"America/Tegucigalpa",
    "iso:country":"HN",
    "name:spa_x_preferred":[
        "Walpat\u00e1"
    ],
    "wof:name":"Walpata",
    "wof:placetype":"locality"
},
  "geometry": {"coordinates":[-83.84891,15.27402],"type":"Point"}
}