{
  "type": "Feature",
  "properties": {
    "gn:admin1_code":"08",
    "gn:asciiname":"El Arado",
    "gn:country_code":"HN",
    "gn:dem":1037,
    "gn:feature_class":"P",
    "gn:feature_code":"PPL",
    "gn:name":"El Arado",
    "gn:population":0,
    "gn:timezone":"America/Tegucigalpa",
    "iso:country":"HN",
    "wof:name":"El Arado",
    "wof:placetype":"locality"
},
  "geometry": {"coordinates":[-87.5175,13.89833],"type":"Point"}
}