{
  "type": "Feature",
  "properties": {
    "gn:admin1_code":"05",
    "gn:asciiname":"El Cordoncillo",
    "gn:cc2":"HN",
    "gn:country_code":"HN",
    "gn:dem":712,
    "gn:feature_class":"P",
    "gn:feature_code":"PPL",
    "gn:name":"El Cordoncillo",
    "gn:population":0,
    "gn:timezone":"America/Tegucigalpa",
    "iso:country":"HN",
    "name:und_x_variant":[
        "Cordoncillo",
        "El Cordoncillo"
    ],
    "wof:name":"El Cordoncillo",
    "wof:placetype":"locality"
},
  "geometry": {"coordinates":[-89.21666999999999,14.86667],"type":"Point"}
}