{
  "type": "Feature",
  "properties": {
    "gn:admin1_code":"15",
    "gn:asciiname":"Quebrada Arriba",
    "gn:country_code":"HN",
    "gn:dem":848,
    "gn:feature_class":"P",
    "gn:feature_code":"PPL",
    "gn:name":"Quebrada Arriba",
    "gn:population":0,
    "gn:timezone":"America/Tegucigalpa",
    "iso:country":"HN",
    "wof:name":"Quebrada Arriba",
    "wof:placetype":"locality"
},
  "geometry": {"coordinates":[-86.81667,14.95],"type":"Point"}
}