{
  "type": "Feature",
  "properties": {
    "gn:admin1_code":"12",
    "gn:asciiname":"El Junco",
    "gn:country_code":"HN",
    "gn:dem":433,
    "gn:feature_class":"P",
    "gn:feature_code":"PPL",
    "gn:name":"El Junco",
    "gn:population":0,
    "gn:timezone":"America/Tegucigalpa",
    "iso:country":"HN",
    "name:ceb_x_preferred":[
        "Laguna El Junco"
    ],
    "name:fin_x_preferred":[
        "El Junco"
    ],
    "name:fra_x_preferred":[
        "El Junco"
    ],
    "name:spa_x_preferred":[
        "Laguna El Junco"
    ],
    "name:swe_x_preferred":[
        "Laguna El Junco"
    ],
    "wof:name":"El Junco",
    "wof:placetype":"locality"
},
  "geometry": {"coordinates":[-87.66306,13.92111],"type":"Point"}
}