{
  "type": "Feature",
  "properties": {
    "gn:admin1_code":"01",
    "gn:asciiname":"Culota",
    "gn:cc2":"HN",
    "gn:country_code":"HN",
    "gn:dem":26,
    "gn:feature_class":"P",
    "gn:feature_code":"PPL",
    "gn:name":"Culota",
    "gn:population":0,
    "gn:timezone":"America/Tegucigalpa",
    "iso:country":"HN",
    "name:und_x_variant":[
        "Cullota",
        "Culotta",
        "Culota"
    ],
    "wof:name":"Culota",
    "wof:placetype":"locality"
},
  "geometry": {"coordinates":[-87.56667,15.73333],"type":"Point"}
}