{
  "type": "Feature",
  "properties": {
    "gn:admin1_code":"08",
    "gn:asciiname":"La Ilusion",
    "gn:country_code":"HN",
    "gn:dem":907,
    "gn:feature_class":"P",
    "gn:feature_code":"PPL",
    "gn:name":"La Ilusi\u00f3n",
    "gn:population":0,
    "gn:timezone":"America/Tegucigalpa",
    "iso:country":"HN",
    "wof:name":"La Ilusion",
    "wof:placetype":"locality"
},
  "geometry": {"coordinates":[-86.93333,14.68333],"type":"Point"}
}