{
  "type": "Feature",
  "properties": {
    "gn:admin1_code":"08",
    "gn:asciiname":"Comayaguela",
    "gn:country_code":"HN",
    "gn:dem":962,
    "gn:feature_class":"P",
    "gn:feature_code":"PPL",
    "gn:name":"Comayag\u00fcela",
    "gn:population":0,
    "gn:timezone":"America/Tegucigalpa",
    "iso:country":"HN",
    "name:und_x_variant":[
        "Comayag\u00fcela"
    ],
    "wof:name":"Comayaguela",
    "wof:placetype":"locality"
},
  "geometry": {"coordinates":[-87.21666999999999,14.08333],"type":"Point"}
}