{
  "type": "Feature",
  "properties": {
    "gn:admin1_code":"02",
    "gn:asciiname":"Raton",
    "gn:country_code":"HN",
    "gn:dem":11,
    "gn:feature_class":"P",
    "gn:feature_code":"PPL",
    "gn:name":"Rat\u00f3n",
    "gn:population":0,
    "gn:timezone":"America/Tegucigalpa",
    "iso:country":"HN",
    "name:ben_x_preferred":[
        "\u09b0"
    ],
    "name:ceb_x_preferred":[
        "Raton"
    ],
    "name:ell_x_preferred":[
        "\u03a1\u03ac\u03c4\u03bf\u03bd"
    ],
    "name:fra_x_preferred":[
        "Raton"
    ],
    "name:hin_x_preferred":[
        "\u0930\u0948\u091f\u0928"
    ],
    "name:ind_x_preferred":[
        "Raton"
    ],
    "name:kor_x_preferred":[
        "\ub77c\ud1a4"
    ],
    "name:por_x_preferred":[
        "Raton"
    ],
    "name:spa_x_preferred":[
        "Rat\u00f3n"
    ],
    "name:swe_x_preferred":[
        "Raton"
    ],
    "name:vie_x_preferred":[
        "Raton"
    ],
    "wof:name":"Raton",
    "wof:placetype":"locality"
},
  "geometry": {"coordinates":[-87.50667,13.28944],"type":"Point"}
}