{
  "type": "Feature",
  "properties": {
    "gn:admin1_code":"07",
    "gn:asciiname":"El Dulce Nombre",
    "gn:country_code":"HN",
    "gn:dem":870,
    "gn:feature_class":"P",
    "gn:feature_code":"PPL",
    "gn:name":"El Dulce Nombre",
    "gn:population":0,
    "gn:timezone":"America/Tegucigalpa",
    "iso:country":"HN",
    "wof:name":"El Dulce Nombre",
    "wof:placetype":"locality"
},
  "geometry": {"coordinates":[-87.18861,13.64111],"type":"Point"}
}