{
  "type": "Feature",
  "properties": {
    "gn:admin1_code":"05",
    "gn:asciiname":"Las Flores",
    "gn:cc2":"HN",
    "gn:country_code":"HN",
    "gn:dem":799,
    "gn:feature_class":"P",
    "gn:feature_code":"PPL",
    "gn:name":"Las Flores",
    "gn:population":0,
    "gn:timezone":"America/Tegucigalpa",
    "iso:country":"HN",
    "name:und_x_variant":[
        "Flores",
        "Las Flores"
    ],
    "wof:name":"Las Flores",
    "wof:placetype":"locality"
},
  "geometry": {"coordinates":[-89.15000000000001,14.73333],"type":"Point"}
}