{
  "type": "Feature",
  "properties": {
    "iso:country":"HN",
    "name:bul_x_preferred":[
        "\u041b\u0430 \u041b\u0438\u043c\u0430"
    ],
    "name:chi_x_preferred":[
        "\u62c9\u5229\u99ac"
    ],
    "name:dut_x_preferred":[
        "La Lima"
    ],
    "name:eng_x_preferred":[
        "La Lima"
    ],
    "name:fre_x_preferred":[
        "La Lima"
    ],
    "name:ita_x_preferred":[
        "La Lima"
    ],
    "name:jpn_x_preferred":[
        "\u30e9\u30fb\u30ea\u30de"
    ],
    "name:lit_x_preferred":[
        "La Lima"
    ],
    "name:nan_x_preferred":[
        "La Lima"
    ],
    "name:pol_x_preferred":[
        "La Lima"
    ],
    "name:por_x_preferred":[
        "La Lima"
    ],
    "name:rus_x_preferred":[
        "\u041b\u0430-\u041b\u0438\u043c\u0430"
    ],
    "name:spa_x_preferred":[
        "La Lima"
    ],
    "name:swe_x_preferred":[
        "La Lima"
    ],
    "name:unk_x_variant":[
        "Lima Vieja"
    ],
    "qs:gn_country":"HN",
    "qs:gn_fcode":"PPL",
    "qs:gn_pop":45955,
    "qs:name":"La Lima",
    "qs:name_adm0":"Honduras",
    "qs:name_adm1":"Cort\u00e9s",
    "qs:photos":131,
    "qs:photos_1k":27,
    "qs:photos_9k":1,
    "qs:photos_9r":3,
    "qs:photos_all":131,
    "qs:photos_sr":3,
    "qs:placetype":"Town",
    "qs:pop_sr":"7",
    "qs:woe_adm0":23424841,
    "wd:wordcount":643,
    "wof:name":"La Lima",
    "wof:placetype":"locality",
    "wof:population":45955
},
  "geometry": {"coordinates":[-87.91667,15.43333],"type":"Point"}
}