{
  "type": "Feature",
  "properties": {
    "gn:admin1_code":"17",
    "gn:asciiname":"El Coyolito",
    "gn:country_code":"HN",
    "gn:dem":686,
    "gn:feature_class":"P",
    "gn:feature_code":"PPL",
    "gn:name":"El Coyolito",
    "gn:population":0,
    "gn:timezone":"America/Tegucigalpa",
    "iso:country":"HN",
    "wof:name":"El Coyolito",
    "wof:placetype":"locality"
},
  "geometry": {"coordinates":[-87.64944,13.77806],"type":"Point"}
}