{
  "type": "Feature",
  "properties": {
    "gn:admin1_code":"12",
    "gn:asciiname":"Los Positos",
    "gn:country_code":"HN",
    "gn:dem":459,
    "gn:feature_class":"P",
    "gn:feature_code":"PPL",
    "gn:name":"Los Positos",
    "gn:population":0,
    "gn:timezone":"America/Tegucigalpa",
    "iso:country":"HN",
    "wof:name":"Los Positos",
    "wof:placetype":"locality"
},
  "geometry": {"coordinates":[-87.73889,13.87917],"type":"Point"}
}