{
  "type": "Feature",
  "properties": {
    "gn:admin1_code":"08",
    "gn:asciiname":"El Piliguin",
    "gn:cc2":"HN",
    "gn:country_code":"HN",
    "gn:dem":1363,
    "gn:feature_class":"P",
    "gn:feature_code":"PPL",
    "gn:name":"El Pilig\u00fc\u00edn",
    "gn:population":0,
    "gn:timezone":"America/Tegucigalpa",
    "iso:country":"HN",
    "name:und_x_variant":[
        "El Pelingu\u00edn",
        "El Pilig\u00fc\u00edn"
    ],
    "wof:name":"El Piliguin",
    "wof:placetype":"locality"
},
  "geometry": {"coordinates":[-87.15000000000001,14.13333],"type":"Point"}
}