{
  "type": "Feature",
  "properties": {
    "gn:admin1_code":"17",
    "gn:asciiname":"Plan del Higo",
    "gn:country_code":"HN",
    "gn:dem":372,
    "gn:feature_class":"P",
    "gn:feature_code":"PPL",
    "gn:name":"Plan del Higo",
    "gn:population":0,
    "gn:timezone":"America/Tegucigalpa",
    "iso:country":"HN",
    "wof:name":"Plan del Higo",
    "wof:placetype":"locality"
},
  "geometry": {"coordinates":[-87.53333000000001,13.68333],"type":"Point"}
}