{
  "type": "Feature",
  "properties": {
    "gn:admin1_code":"08",
    "gn:asciiname":"Paso Ganado",
    "gn:cc2":"HN",
    "gn:country_code":"HN",
    "gn:dem":655,
    "gn:feature_class":"P",
    "gn:feature_code":"PPL",
    "gn:name":"Paso Ganado",
    "gn:population":0,
    "gn:timezone":"America/Tegucigalpa",
    "iso:country":"HN",
    "name:und_x_variant":[
        "Paso del Ganado",
        "Paso Ganado"
    ],
    "wof:name":"Paso Ganado",
    "wof:placetype":"locality"
},
  "geometry": {"coordinates":[-87.11667,13.83333],"type":"Point"}
}