{
  "type": "Feature",
  "properties": {
    "gn:admin1_code":"02",
    "gn:asciiname":"Los Mescales",
    "gn:country_code":"HN",
    "gn:dem":599,
    "gn:feature_class":"P",
    "gn:feature_code":"PPL",
    "gn:name":"Los Mescales",
    "gn:population":0,
    "gn:timezone":"America/Tegucigalpa",
    "iso:country":"HN",
    "wof:name":"Los Mescales",
    "wof:placetype":"locality"
},
  "geometry": {"coordinates":[-87.20583000000001,13.6075],"type":"Point"}
}