{
  "type": "Feature",
  "properties": {
    "gn:admin1_code":"13",
    "gn:asciiname":"Fraternidad La Gloria",
    "gn:cc2":"HN",
    "gn:country_code":"HN",
    "gn:dem":1355,
    "gn:feature_class":"P",
    "gn:feature_code":"PPL",
    "gn:name":"Fraternidad La Gloria",
    "gn:population":0,
    "gn:timezone":"America/Tegucigalpa",
    "iso:country":"HN",
    "name:und_x_variant":[
        "Fraternidad",
        "Fraternidad La Gloria"
    ],
    "wof:name":"Fraternidad La Gloria",
    "wof:placetype":"locality"
},
  "geometry": {"coordinates":[-88.61667,14.45],"type":"Point"}
}