{
  "type": "Feature",
  "properties": {
    "gn:admin1_code":"08",
    "gn:asciiname":"Los Arados",
    "gn:country_code":"HN",
    "gn:dem":1726,
    "gn:feature_class":"P",
    "gn:feature_code":"PPL",
    "gn:name":"Los Arados",
    "gn:population":0,
    "gn:timezone":"America/Tegucigalpa",
    "iso:country":"HN",
    "wof:name":"Los Arados",
    "wof:placetype":"locality"
},
  "geometry": {"coordinates":[-87.09833,13.97167],"type":"Point"}
}