{
  "type": "Feature",
  "properties": {
    "gn:admin1_code":"08",
    "gn:asciiname":"Los Chaguites",
    "gn:cc2":"HN",
    "gn:country_code":"HN",
    "gn:dem":1379,
    "gn:feature_class":"P",
    "gn:feature_code":"PPL",
    "gn:name":"Los Chag\u00fcites",
    "gn:population":0,
    "gn:timezone":"America/Tegucigalpa",
    "iso:country":"HN",
    "name:und_x_variant":[
        "Chaguites",
        "Los Chag\u00fcites"
    ],
    "wof:name":"Los Chaguites",
    "wof:placetype":"locality"
},
  "geometry": {"coordinates":[-87.32333,13.97972],"type":"Point"}
}