{
  "type": "Feature",
  "properties": {
    "gn:admin1_code":"08",
    "gn:asciiname":"El Limon",
    "gn:country_code":"HN",
    "gn:dem":674,
    "gn:feature_class":"P",
    "gn:feature_code":"PPL",
    "gn:name":"El Lim\u00f3n",
    "gn:population":0,
    "gn:timezone":"America/Tegucigalpa",
    "iso:country":"HN",
    "wof:name":"El Limon",
    "wof:placetype":"locality"
},
  "geometry": {"coordinates":[-87.48555999999998,13.89667],"type":"Point"}
}