{
  "type": "Feature",
  "properties": {
    "gn:admin1_code":"07",
    "gn:asciiname":"San Marcos Abajo",
    "gn:cc2":"HN",
    "gn:country_code":"HN",
    "gn:dem":735,
    "gn:feature_class":"P",
    "gn:feature_code":"PPL",
    "gn:name":"San Marcos Abajo",
    "gn:population":0,
    "gn:timezone":"America/Tegucigalpa",
    "iso:country":"HN",
    "name:und_x_variant":[
        "Marcos Abajo",
        "San Marcos Abajo"
    ],
    "wof:name":"San Marcos Abajo",
    "wof:placetype":"locality"
},
  "geometry": {"coordinates":[-86.56667,13.95],"type":"Point"}
}