{
  "type": "Feature",
  "properties": {
    "gn:admin1_code":"06",
    "gn:asciiname":"Campana",
    "gn:cc2":"HN",
    "gn:country_code":"HN",
    "gn:dem":9,
    "gn:feature_class":"P",
    "gn:feature_code":"PPL",
    "gn:name":"Campana",
    "gn:population":0,
    "gn:timezone":"America/Tegucigalpa",
    "iso:country":"HN",
    "name:ben_x_preferred":[
        "\u0995\u09be\u09ae\u09aa\u09be\u09a8\u09be"
    ],
    "name:cat_x_preferred":[
        "Campana"
    ],
    "name:ceb_x_preferred":[
        "Campana"
    ],
    "name:deu_x_preferred":[
        "Campana"
    ],
    "name:ell_x_preferred":[
        "\u039a\u03b1\u03bc\u03c0\u03ac\u03bd\u03b9\u03b1"
    ],
    "name:epo_x_preferred":[
        "Campana"
    ],
    "name:eus_x_preferred":[
        "Campana"
    ],
    "name:fra_x_preferred":[
        "Campana"
    ],
    "name:glg_x_preferred":[
        "Camp\u00e1"
    ],
    "name:heb_x_preferred":[
        "\u05e7\u05de\u05e4\u05e0\u05d4"
    ],
    "name:hin_x_preferred":[
        "\u0915\u0948\u0902\u092a\u093e\u0928\u093e"
    ],
    "name:ind_x_preferred":[
        "Campana"
    ],
    "name:ita_x_preferred":[
        "Campana"
    ],
    "name:kor_x_preferred":[
        "\uce84\ud30c\ub098"
    ],
    "name:nds_x_preferred":[
        "Campana"
    ],
    "name:nld_x_preferred":[
        "Campana"
    ],
    "name:pol_x_preferred":[
        "Campana"
    ],
    "name:por_x_preferred":[
        "Campana"
    ],
    "name:rus_x_preferred":[
        "\u041a\u0430\u043c\u043f\u0430\u043d\u0430"
    ],
    "name:scn_x_preferred":[
        "Campana"
    ],
    "name:slk_x_preferred":[
        "Campana"
    ],
    "name:slv_x_preferred":[
        "Campana"
    ],
    "name:spa_x_preferred":[
        "Campana"
    ],
    "name:srp_x_preferred":[
        "Kampana"
    ],
    "name:swe_x_preferred":[
        "Campana"
    ],
    "name:ukr_x_preferred":[
        "\u041a\u0430\u043c\u043f\u0430\u043d\u0430"
    ],
    "name:und_x_variant":[
        "Ejidos de la Campana"
    ],
    "name:urd_x_preferred":[
        "\u06a9\u06cc\u0645\u067e\u0627\u0646\u0627"
    ],
    "name:vie_x_preferred":[
        "Campana"
    ],
    "name:vol_x_preferred":[
        "Campana"
    ],
    "name:zho_x_preferred":[
        "\u574e\u5e15\u7d0d"
    ],
    "wof:name":"Campana",
    "wof:placetype":"locality"
},
  "geometry": {"coordinates":[-87.84999999999999,15.76667],"type":"Point"}
}