{
  "type": "Feature",
  "properties": {
    "gn:admin1_code":"06",
    "gn:asciiname":"Campana",
    "gn:cc2":"HN",
    "gn:country_code":"HN",
    "gn:dem":9,
    "gn:feature_class":"P",
    "gn:feature_code":"PPL",
    "gn:name":"Campana",
    "gn:population":0,
    "gn:timezone":"America/Tegucigalpa",
    "iso:country":"HN",
    "name:und_x_variant":[
        "Ejidos de la Campana",
        "Campana"
    ],
    "wof:name":"Campana",
    "wof:placetype":"locality"
},
  "geometry": {"coordinates":[-87.84999999999999,15.76667],"type":"Point"}
}