{
  "type": "Feature",
  "properties": {
    "gn:admin1_code":"09",
    "gn:asciiname":"Siakwalaya",
    "gn:country_code":"HN",
    "gn:dem":6,
    "gn:feature_class":"P",
    "gn:feature_code":"PPL",
    "gn:name":"Siakwalaya",
    "gn:population":0,
    "gn:timezone":"America/Tegucigalpa",
    "iso:country":"HN",
    "wof:name":"Siakwalaya",
    "wof:placetype":"locality"
},
  "geometry": {"coordinates":[-83.65000000000001,15.01667],"type":"Point"}
}