{
  "type": "Feature",
  "properties": {
    "gn:admin1_code":"16",
    "gn:asciiname":"El Palmo",
    "gn:cc2":"HN",
    "gn:country_code":"HN",
    "gn:dem":1117,
    "gn:feature_class":"P",
    "gn:feature_code":"PPL",
    "gn:name":"El Palmo",
    "gn:population":0,
    "gn:timezone":"America/Tegucigalpa",
    "iso:country":"HN",
    "name:und_x_variant":[
        "Palmo",
        "El Palmo"
    ],
    "wof:name":"El Palmo",
    "wof:placetype":"locality"
},
  "geometry": {"coordinates":[-88.34999999999999,14.83333],"type":"Point"}
}