{
  "type": "Feature",
  "properties": {
    "gn:admin1_code":"04",
    "gn:asciiname":"La Aguja",
    "gn:country_code":"HN",
    "gn:dem":897,
    "gn:feature_class":"P",
    "gn:feature_code":"PPL",
    "gn:name":"La Aguja",
    "gn:population":0,
    "gn:timezone":"America/Tegucigalpa",
    "iso:country":"HN",
    "wof:name":"La Aguja",
    "wof:placetype":"locality"
},
  "geometry": {"coordinates":[-87.73333000000002,14.73333],"type":"Point"}
}