{
  "type": "Feature",
  "properties": {
    "gn:admin1_code":"10",
    "gn:asciiname":"La Caridad",
    "gn:cc2":"HN",
    "gn:country_code":"HN",
    "gn:dem":134,
    "gn:feature_class":"P",
    "gn:feature_code":"PPL",
    "gn:name":"La Caridad",
    "gn:population":0,
    "gn:timezone":"America/Tegucigalpa",
    "iso:country":"HN",
    "name:ast_x_preferred":[
        "A Carid\u00e1"
    ],
    "name:deu_x_preferred":[
        "La Caridad"
    ],
    "name:spa_x_preferred":[
        "La Caridad"
    ],
    "name:und_x_variant":[
        "Caridad",
        "La Caridad"
    ],
    "name:urd_x_preferred":[
        "\u0644\u0627 \u06a9\u0627\u0631\u06cc\u0688\u0627\u0688"
    ],
    "wof:name":"La Caridad",
    "wof:placetype":"locality"
},
  "geometry": {"coordinates":[-88.40000000000001,13.88333],"type":"Point"}
}