{
  "type": "Feature",
  "properties": {
    "gn:admin1_code":"17",
    "gn:asciiname":"Montecristo Numero Uno",
    "gn:cc2":"HN",
    "gn:country_code":"HN",
    "gn:dem":138,
    "gn:feature_class":"P",
    "gn:feature_code":"PPL",
    "gn:name":"Montecristo N\u00famero Uno",
    "gn:population":0,
    "gn:timezone":"America/Tegucigalpa",
    "iso:country":"HN",
    "name:und_x_variant":[
        "Montecristo No. 1",
        "Montecristo N\u00famero Uno"
    ],
    "wof:name":"Montecristo Numero Uno",
    "wof:placetype":"locality"
},
  "geometry": {"coordinates":[-87.56583000000001,13.66917],"type":"Point"}
}