{
  "type": "Feature",
  "properties": {
    "gn:admin1_code":"18",
    "gn:asciiname":"Nana Chumba",
    "gn:country_code":"HN",
    "gn:dem":23,
    "gn:feature_class":"P",
    "gn:feature_code":"PPL",
    "gn:name":"Nana Chumba",
    "gn:population":0,
    "gn:timezone":"America/Tegucigalpa",
    "iso:country":"HN",
    "wof:name":"Nana Chumba",
    "wof:placetype":"locality"
},
  "geometry": {"coordinates":[-87.81667,15.45],"type":"Point"}
}