{
  "type": "Feature",
  "properties": {
    "gn:admin1_code":"08",
    "gn:asciiname":"Parriguapa",
    "gn:country_code":"HN",
    "gn:dem":578,
    "gn:feature_class":"P",
    "gn:feature_code":"PPL",
    "gn:name":"Parriguapa",
    "gn:population":0,
    "gn:timezone":"America/Tegucigalpa",
    "iso:country":"HN",
    "wof:name":"Parriguapa",
    "wof:placetype":"locality"
},
  "geometry": {"coordinates":[-87.43028000000002,13.84278],"type":"Point"}
}