{
  "type": "Feature",
  "properties": {
    "gn:admin1_code":"08",
    "gn:asciiname":"Izopito",
    "gn:country_code":"HN",
    "gn:dem":1205,
    "gn:feature_class":"P",
    "gn:feature_code":"PPL",
    "gn:name":"Izopito",
    "gn:population":0,
    "gn:timezone":"America/Tegucigalpa",
    "iso:country":"HN",
    "wof:name":"Izopito",
    "wof:placetype":"locality"
},
  "geometry": {"coordinates":[-87.15889,13.86861],"type":"Point"}
}