{
  "type": "Feature",
  "properties": {
    "gn:admin1_code":"17",
    "gn:asciiname":"Puerto Soto",
    "gn:country_code":"HN",
    "gn:dem":6,
    "gn:feature_class":"P",
    "gn:feature_code":"PPL",
    "gn:name":"Puerto Soto",
    "gn:population":0,
    "gn:timezone":"America/Tegucigalpa",
    "iso:country":"HN",
    "wof:name":"Puerto Soto",
    "wof:placetype":"locality"
},
  "geometry": {"coordinates":[-87.57583000000002,13.37917],"type":"Point"}
}