{
  "type": "Feature",
  "properties": {
    "gn:admin1_code":"15",
    "gn:asciiname":"El Tizate",
    "gn:cc2":"HN",
    "gn:country_code":"HN",
    "gn:dem":602,
    "gn:feature_class":"P",
    "gn:feature_code":"PPL",
    "gn:name":"El Tizate",
    "gn:population":0,
    "gn:timezone":"America/Tegucigalpa",
    "iso:country":"HN",
    "name:und_x_variant":[
        "Tizate",
        "El Tizate"
    ],
    "wof:name":"El Tizate",
    "wof:placetype":"locality"
},
  "geometry": {"coordinates":[-86.33333,14.88333],"type":"Point"}
}