{
  "type": "Feature",
  "properties": {
    "gn:admin1_code":"13",
    "gn:asciiname":"Suncuyo",
    "gn:country_code":"HN",
    "gn:dem":607,
    "gn:feature_class":"P",
    "gn:feature_code":"PPL",
    "gn:name":"Suncuyo",
    "gn:population":0,
    "gn:timezone":"America/Tegucigalpa",
    "iso:country":"HN",
    "wof:name":"Suncuyo",
    "wof:placetype":"locality"
},
  "geometry": {"coordinates":[-88.68333,14.21667],"type":"Point"}
}