{
  "type": "Feature",
  "properties": {
    "gn:admin1_code":"17",
    "gn:asciiname":"Los Plantelitos",
    "gn:country_code":"HN",
    "gn:dem":346,
    "gn:feature_class":"P",
    "gn:feature_code":"PPL",
    "gn:name":"Los Plantelitos",
    "gn:population":0,
    "gn:timezone":"America/Tegucigalpa",
    "iso:country":"HN",
    "wof:name":"Los Plantelitos",
    "wof:placetype":"locality"
},
  "geometry": {"coordinates":[-87.65167,13.76583],"type":"Point"}
}