{
  "type": "Feature",
  "properties": {
    "gn:admin1_code":"00",
    "gn:asciiname":"Mogotes",
    "gn:country_code":"HN",
    "gn:dem":1183,
    "gn:feature_class":"P",
    "gn:feature_code":"PPL",
    "gn:name":"Mogotes",
    "gn:population":0,
    "gn:timezone":"America/Tegucigalpa",
    "iso:country":"HN",
    "name:deu_x_preferred":[
        "Mogotes"
    ],
    "name:fra_x_preferred":[
        "Mogotes"
    ],
    "name:ita_x_preferred":[
        "Mogotes"
    ],
    "name:kat_x_preferred":[
        "\u10db\u10dd\u10d2\u10dd\u10e2\u10d4\u10e1\u10d8"
    ],
    "name:msa_x_preferred":[
        "Mogotes"
    ],
    "name:nld_x_preferred":[
        "Mogotes"
    ],
    "name:spa_x_preferred":[
        "Mogotes"
    ],
    "name:tgl_x_preferred":[
        "Mogotes"
    ],
    "name:vie_x_preferred":[
        "Mogotes"
    ],
    "name:war_x_preferred":[
        "Mogotes"
    ],
    "name:zho_x_preferred":[
        "\u83ab\u6208\u7279\u65af"
    ],
    "wof:name":"Mogotes",
    "wof:placetype":"locality"
},
  "geometry": {"coordinates":[-87.18333,14.93333],"type":"Point"}
}