{
  "type": "Feature",
  "properties": {
    "gn:admin1_code":"08",
    "gn:asciiname":"La Uvilla",
    "gn:cc2":"HN",
    "gn:country_code":"HN",
    "gn:dem":839,
    "gn:feature_class":"P",
    "gn:feature_code":"PPL",
    "gn:name":"La Uvilla",
    "gn:population":0,
    "gn:timezone":"America/Tegucigalpa",
    "iso:country":"HN",
    "name:und_x_variant":[
        "Uvilla",
        "Uvillas",
        "La Uvilla"
    ],
    "wof:name":"La Uvilla",
    "wof:placetype":"locality"
},
  "geometry": {"coordinates":[-87.10861,13.88111],"type":"Point"}
}