{
  "type": "Feature",
  "properties": {
    "gn:admin1_code":"02",
    "gn:asciiname":"Paso La Angostura",
    "gn:country_code":"HN",
    "gn:dem":510,
    "gn:feature_class":"P",
    "gn:feature_code":"PPL",
    "gn:name":"Paso La Angostura",
    "gn:population":0,
    "gn:timezone":"America/Tegucigalpa",
    "iso:country":"HN",
    "wof:name":"Paso La Angostura",
    "wof:placetype":"locality"
},
  "geometry": {"coordinates":[-87.21666999999999,13.55],"type":"Point"}
}