{
  "type": "Feature",
  "properties": {
    "gn:admin1_code":"04",
    "gn:asciiname":"Los Guamiles",
    "gn:country_code":"HN",
    "gn:dem":606,
    "gn:feature_class":"P",
    "gn:feature_code":"PPL",
    "gn:name":"Los Guamiles",
    "gn:population":0,
    "gn:timezone":"America/Tegucigalpa",
    "iso:country":"HN",
    "wof:name":"Los Guamiles",
    "wof:placetype":"locality"
},
  "geometry": {"coordinates":[-87.71666999999999,14.75],"type":"Point"}
}