{
  "type": "Feature",
  "properties": {
    "gn:admin1_code":"05",
    "gn:asciiname":"El Balsamo",
    "gn:country_code":"HN",
    "gn:dem":1270,
    "gn:feature_class":"P",
    "gn:feature_code":"PPL",
    "gn:name":"El B\u00e1lsamo",
    "gn:population":0,
    "gn:timezone":"America/Tegucigalpa",
    "iso:country":"HN",
    "wof:name":"El Balsamo",
    "wof:placetype":"locality"
},
  "geometry": {"coordinates":[-88.78333000000001,14.65],"type":"Point"}
}