{
  "type": "Feature",
  "properties": {
    "gn:admin1_code":"02",
    "gn:asciiname":"Hacienda Los Patos",
    "gn:country_code":"HN",
    "gn:dem":15,
    "gn:feature_class":"P",
    "gn:feature_code":"PPL",
    "gn:name":"Hacienda Los Patos",
    "gn:population":0,
    "gn:timezone":"America/Tegucigalpa",
    "iso:country":"HN",
    "wof:name":"Hacienda Los Patos",
    "wof:placetype":"locality"
},
  "geometry": {"coordinates":[-87.31166999999998,13.24361],"type":"Point"}
}