{
  "type": "Feature",
  "properties": {
    "gn:admin1_code":"07",
    "gn:asciiname":"Banaderas",
    "gn:country_code":"HN",
    "gn:dem":879,
    "gn:feature_class":"P",
    "gn:feature_code":"PPL",
    "gn:name":"Ba\u00f1aderas",
    "gn:population":0,
    "gn:timezone":"America/Tegucigalpa",
    "iso:country":"HN",
    "wof:name":"Banaderas",
    "wof:placetype":"locality"
},
  "geometry": {"coordinates":[-86.76666999999998,14.26667],"type":"Point"}
}