{
  "type": "Feature",
  "properties": {
    "gn:admin1_code":"12",
    "gn:asciiname":"Mogola",
    "gn:country_code":"HN",
    "gn:dem":1542,
    "gn:feature_class":"P",
    "gn:feature_code":"PPL",
    "gn:name":"Mogola",
    "gn:population":0,
    "gn:timezone":"America/Tegucigalpa",
    "iso:country":"HN",
    "wof:name":"Mogola",
    "wof:placetype":"locality"
},
  "geometry": {"coordinates":[-87.98333000000002,14.11667],"type":"Point"}
}