{
  "type": "Feature",
  "properties": {
    "gn:admin1_code":"07",
    "gn:asciiname":"Apatoro",
    "gn:country_code":"HN",
    "gn:dem":552,
    "gn:feature_class":"P",
    "gn:feature_code":"PPL",
    "gn:name":"Apatoro",
    "gn:population":0,
    "gn:timezone":"America/Tegucigalpa",
    "iso:country":"HN",
    "wof:name":"Apatoro",
    "wof:placetype":"locality"
},
  "geometry": {"coordinates":[-86.88333,13.68333],"type":"Point"}
}