{
  "type": "Feature",
  "properties": {
    "gn:gn_country":"HN",
    "gn:gn_fcode":"PPL",
    "gn:gn_pop":1759,
    "gn:population":1759,
    "iso:country":"HN",
    "qs_pg:aaroncc":"HN",
    "qs_pg:gn_country":"HN",
    "qs_pg:gn_fcode":"PPL",
    "qs_pg:gn_pop":1759,
    "qs_pg:name":"Agualote",
    "qs_pg:photos_9r":0,
    "qs_pg:photos_sr":0,
    "qs_pg:pop_sr":3,
    "qs_pg:qs_pg_placetype":"locality",
    "wof:name":"Agualote",
    "wof:placetype":"locality",
    "wof:population":1759
},
  "geometry": {"coordinates":[-88.55306,15.33528],"type":"Point"}
}