{
  "type": "Feature",
  "properties": {
    "gn:admin1_code":"07",
    "gn:asciiname":"El Talpetate",
    "gn:cc2":"HN",
    "gn:country_code":"HN",
    "gn:dem":497,
    "gn:feature_class":"P",
    "gn:feature_code":"PPL",
    "gn:name":"El Talpetate",
    "gn:population":0,
    "gn:timezone":"America/Tegucigalpa",
    "iso:country":"HN",
    "name:und_x_variant":[
        "Talpetate",
        "El Talpetate"
    ],
    "wof:name":"El Talpetate",
    "wof:placetype":"locality"
},
  "geometry": {"coordinates":[-87.13249999999999,13.60722],"type":"Point"}
}