{
  "type": "Feature",
  "properties": {
    "gn:admin1_code":"09",
    "gn:asciiname":"Kahka",
    "gn:cc2":"HN",
    "gn:country_code":"HN",
    "gn:dem":110,
    "gn:feature_class":"P",
    "gn:feature_code":"PPL",
    "gn:name":"Kahka",
    "gn:population":0,
    "gn:timezone":"America/Tegucigalpa",
    "iso:country":"HN",
    "name:und_x_variant":[
        "Kaska",
        "Kahka"
    ],
    "wof:name":"Kahka",
    "wof:placetype":"locality"
},
  "geometry": {"coordinates":[-84.78333000000001,14.71667],"type":"Point"}
}