{
  "type": "Feature",
  "properties": {
    "gn:admin1_code":"08",
    "gn:asciiname":"Las Crucitas",
    "gn:cc2":"HN",
    "gn:country_code":"HN",
    "gn:dem":764,
    "gn:feature_class":"P",
    "gn:feature_code":"PPL",
    "gn:name":"Las Crucitas",
    "gn:population":0,
    "gn:timezone":"America/Tegucigalpa",
    "iso:country":"HN",
    "name:und_x_variant":[
        "Crucitas",
        "La Crucita",
        "Las Crucitas"
    ],
    "wof:name":"Las Crucitas",
    "wof:placetype":"locality"
},
  "geometry": {"coordinates":[-87.13333,14.61667],"type":"Point"}
}