{
  "type": "Feature",
  "properties": {
    "gn:admin1_code":"12",
    "gn:asciiname":"El Gramalito",
    "gn:country_code":"HN",
    "gn:dem":466,
    "gn:feature_class":"P",
    "gn:feature_code":"PPL",
    "gn:name":"El Gramalito",
    "gn:population":0,
    "gn:timezone":"America/Tegucigalpa",
    "iso:country":"HN",
    "wof:name":"El Gramalito",
    "wof:placetype":"locality"
},
  "geometry": {"coordinates":[-87.72083000000001,13.85306],"type":"Point"}
}