{
  "type": "Feature",
  "properties": {
    "gn:admin1_code":"15",
    "gn:asciiname":"El Encanto",
    "gn:country_code":"HN",
    "gn:dem":342,
    "gn:feature_class":"P",
    "gn:feature_code":"PPL",
    "gn:name":"El Encanto",
    "gn:population":0,
    "gn:timezone":"America/Tegucigalpa",
    "iso:country":"HN",
    "name:cat_x_preferred":[
        "El Encanto"
    ],
    "name:ceb_x_preferred":[
        "El Encanto"
    ],
    "name:fra_x_preferred":[
        "El Encanto"
    ],
    "name:heb_x_preferred":[
        "\u05d0\u05dc \u05d0\u05e0\u05e7\u05e0\u05d8\u05d5"
    ],
    "name:ilo_x_preferred":[
        "El Encanto"
    ],
    "name:ita_x_preferred":[
        "El Encanto"
    ],
    "name:msa_x_preferred":[
        "El Encanto"
    ],
    "name:nld_x_preferred":[
        "El Encanto"
    ],
    "name:por_x_preferred":[
        "El Encanto"
    ],
    "name:rus_x_preferred":[
        "\u042d\u043b\u044c-\u042d\u043d\u043a\u0430\u043d\u0442\u043e"
    ],
    "name:spa_x_preferred":[
        "El Encanto"
    ],
    "name:swe_x_preferred":[
        "El Encanto"
    ],
    "name:tgl_x_preferred":[
        "El Encanto"
    ],
    "name:vie_x_preferred":[
        "El Encanto"
    ],
    "name:war_x_preferred":[
        "El Encanto"
    ],
    "name:zho_x_preferred":[
        "\u57c3\u723e\u6069\u574e\u6258"
    ],
    "wof:name":"El Encanto",
    "wof:placetype":"locality"
},
  "geometry": {"coordinates":[-85.76666,14.80674],"type":"Point"}
}