{
  "type": "Feature",
  "properties": {
    "gn:admin1_code":"08",
    "gn:asciiname":"San Jose de la Mora",
    "gn:cc2":"HN",
    "gn:country_code":"HN",
    "gn:dem":1047,
    "gn:feature_class":"P",
    "gn:feature_code":"PPL",
    "gn:name":"San Jos\u00e9 de la Mora",
    "gn:population":0,
    "gn:timezone":"America/Tegucigalpa",
    "iso:country":"HN",
    "name:und_x_variant":[
        "Mora",
        "La Mora",
        "San Jos\u00e9 de la Mora"
    ],
    "wof:name":"San Jose de la Mora",
    "wof:placetype":"locality"
},
  "geometry": {"coordinates":[-87.41667,14.53333],"type":"Point"}
}