{
  "type": "Feature",
  "properties": {
    "iso:country":"HN",
    "name:unk_x_variant":[
        "San Jos\u00e9"
    ],
    "qs:gn_country":"HN",
    "qs:gn_fcode":"PPL",
    "qs:gn_pop":888,
    "qs:name":"San Jos\u00e9 de Oriente",
    "qs:name_adm0":"Honduras",
    "qs:name_adm1":"Santa B\u00e1rbara",
    "qs:photos":0,
    "qs:photos_1k":0,
    "qs:photos_9k":1,
    "qs:photos_9r":1,
    "qs:photos_all":4,
    "qs:photos_sr":0,
    "qs:placetype":"Town",
    "qs:pop_sr":"2",
    "qs:woe_adm0":23424841,
    "wof:name":"San Jos\u00e9 de Oriente",
    "wof:placetype":"locality",
    "wof:population":888
},
  "geometry": {"coordinates":[-88.11667,15.03333],"type":"Point"}
}