{
  "type": "Feature",
  "properties": {
    "gn:admin1_code":"10",
    "gn:asciiname":"Manazapa",
    "gn:country_code":"HN",
    "gn:dem":1153,
    "gn:feature_class":"P",
    "gn:feature_code":"PPL",
    "gn:name":"Manazapa",
    "gn:population":0,
    "gn:timezone":"America/Tegucigalpa",
    "iso:country":"HN",
    "wof:name":"Manazapa",
    "wof:placetype":"locality"
},
  "geometry": {"coordinates":[-88.18333,14.11667],"type":"Point"}
}