{
  "type": "Feature",
  "properties": {
    "gn:admin1_code":"01",
    "gn:asciiname":"Colonia Guillen",
    "gn:country_code":"HN",
    "gn:dem":62,
    "gn:feature_class":"P",
    "gn:feature_code":"PPL",
    "gn:name":"Colonia Guillen",
    "gn:population":0,
    "gn:timezone":"America/Tegucigalpa",
    "iso:country":"HN",
    "wof:name":"Colonia Guillen",
    "wof:placetype":"locality"
},
  "geometry": {"coordinates":[-87.65000000000001,15.73333],"type":"Point"}
}