{
  "type": "Feature",
  "properties": {
    "gn:admin1_code":"17",
    "gn:asciiname":"El Portillo",
    "gn:country_code":"HN",
    "gn:dem":56,
    "gn:feature_class":"P",
    "gn:feature_code":"PPL",
    "gn:name":"El Portillo",
    "gn:population":0,
    "gn:timezone":"America/Tegucigalpa",
    "iso:country":"HN",
    "wof:name":"El Portillo",
    "wof:placetype":"locality"
},
  "geometry": {"coordinates":[-87.74722,13.55611],"type":"Point"}
}