{
  "type": "Feature",
  "properties": {
    "gn:admin1_code":"04",
    "gn:asciiname":"Majadas",
    "gn:country_code":"HN",
    "gn:dem":939,
    "gn:feature_class":"P",
    "gn:feature_code":"PPL",
    "gn:name":"Majadas",
    "gn:population":0,
    "gn:timezone":"America/Tegucigalpa",
    "iso:country":"HN",
    "wof:name":"Majadas",
    "wof:placetype":"locality"
},
  "geometry": {"coordinates":[-87.51666999999998,14.86667],"type":"Point"}
}